Workbook
Name \0: #REF!
Name \a: #REF!
Name \b: #REF!
Name \c: #REF!
Name \d: #REF!
Name \df: #N/A
Name \e: #REF!
Name \f: #REF!
Name \i: #REF!
Name \l: #REF!
Name \PRINT_BALANCO: #REF!
Name \r: #REF!
Name \s: #REF!
Name \t: #REF!
Name _________________________________INV12: #REF!
Name _________________________________INV13: #REF!
Name _________________________________inv2: #REF!
Name _________________________________inv2: #REF!
Name _________________________________inv2: #REF!
Name ________________________________INV12: #REF!
Name ________________________________INV13: #REF!
Name ________________________________inv2: #REF!
Name ________________________________inv2: #REF!
Name ________________________________inv2: #REF!
Name _______________________________INV12: #REF!
Name _______________________________INV13: #REF!
Name _______________________________inv2: #REF!
Name _______________________________inv2: #REF!
Name _______________________________inv2: #REF!
Name ______________________________INV12: #REF!
Name ______________________________INV13: #REF!
Name ______________________________inv2: #REF!
Name ______________________________inv2: #REF!
Name ______________________________inv2: #REF!
Name _____________________________INV12: #REF!
Name _____________________________INV13: #REF!
Name _____________________________inv2: #REF!
Name _____________________________inv2: #REF!
Name _____________________________inv2: #REF!
Name ____________________________INV12: #REF!
Name ____________________________INV13: #REF!
Name ____________________________inv2: #REF!
Name ____________________________inv2: #REF!
Name ____________________________inv2: #REF!
Name ___________________________INV12: #REF!
Name ___________________________INV13: #REF!
Name ___________________________inv2: #REF!
Name ___________________________inv2: #REF!
Name ___________________________inv2: #REF!
Name __________________________INV12: #REF!
Name __________________________INV13: #REF!
Name __________________________inv2: #REF!
Name __________________________inv2: #REF!
Name __________________________inv2: #REF!
Name _________________________INV12: #REF!
Name _________________________INV13: #REF!
Name _________________________inv2: #REF!
Name _________________________inv2: #REF!
Name _________________________inv2: #REF!
Name ________________________INV12: #REF!

Sheet Meta (2)
A1: META 2026 | C1: YTD | G1: jan a jun | H1: jan a ago | I1: projeção ate dez
A2: Meta Anual | B2: 12 | C2: 1 | D2: 11 | E2: Nova meta mês | G2: 3120555 | H2: =C3 -> 444545.69 | I2: =H2+576522+85120+420000+374267+140000+(400000*3) -> 3240454.7 | K2: 576622 | L2: Nacionais
A3: 8060000 | B3: =A3/B2 -> 671666.67 | C3: ='Areas Sintetico atualizado'!C3 -> 444545.69 | D3: =A3-C3 -> 7615454.3 | E3: =D3/D2 -> 692314.03 | G3: =G2/A3 -> 0.38716563 | H3: =H2/A3 -> 0.055154552 | I3: =I2/A3 -> 0.40204152 | K3: 85120 | L3: Internacionais
K4: 420000 | L4: Pre faturas
H5: =10377407-5768380 -> 4609027 | K5: 374267 | L5: WM
H6: =(H2/H5)-1 -> -0.90354891 | K6: 140000 | L6: Tonico
A7: META 2025 | C7: YTD | I7: 6143091
A8: Meta Anual | B8: 12 | I8: =(I2/I7)-1 -> -0.4725042
A9: =A3 -> 8060000 | B9: =A9/B8 -> 671666.67 | C9: ='Areas Sintetico atualizado'!L3 -> 444545.69 | E9: =A9-C9 -> 7615454.3 | F9: =E9/D2 -> 692314.03
B13: Recebimento | C13: Faturamento | D13: Meta | E13: Despesas | F13: Despesas indiretas | G13: Custo direto
A14: Jan | B14: ='Areas Sintetico atualizado'!C4 -> 279821.07 | C14: ='Areas Sintetico atualizado'!C3 -> 444545.69 | D14: 671667 | E14: =F14+G14 -> 316604.06 | F14: ='Areas Sintetico atualizado'!C13 -> 104973.54 | G14: ='Areas Sintetico atualizado'!C6 -> 211630.52 | I14: =B14-F14-G14 -> -36782.99
A15: Fev | D15: 671667 | E15: =F15+G15 -> 0 | I15: =B15-F15-G15 -> 0
A16: Mar | D16: 671667 | E16: =F16+G16 -> 0 | I16: =B16-F16-G16 -> 0
A17: Abr | D17: 671667 | E17: =F17+G17 -> 0 | I17: =B17-F17-G17 -> 0
A18: Mai | D18: 671667 | E18: =F18+G18 -> 0 | I18: =B18-F18-G18 -> 0
A19: Jun | D19: 671667 | E19: =F19+G19 -> 0 | I19: =B19-F19-G19 -> 0
A20: Jul | D20: 671667 | E20: =F20+G20 -> 0 | I20: =B20-F20-G20 -> 0
A21: Ago | D21: 671667 | E21: =F21+G21 -> 0 | I21: =B21-F21-G21 -> 0
A22: Set | D22: 671667 | E22: =F22+G22 -> 0 | I22: =B22-F22-G22 -> 0
A23: Out | D23: 671667 | E23: =F23+G23 -> 0 | I23: =B23-F23-G23 -> 0
A24: Nov | D24: 671667 | E24: =F24+G24 -> 0 | I24: =B24-F24-G24 -> 0
A25: Dez | D25: 671667 | E25: =F25+G25 -> 0 | I25: =B25-F25-G25 -> 0
B26: =SUM(B14:B25) -> 279821.07 | C26: =SUM(C14:C25) -> 444545.69 | D26: =SUM(D14:D25) -> 8060004 | E26: =SUM(E14:E25) -> 316604.06 | F26: =SUM(F14:F25) -> 104973.54 | G26: =SUM(G14:G25) -> 211630.52 | H26: =SUM(H14:H25) -> 0 | I26: =SUM(I14:I25) -> -36782.99
A28: MÉDIA ANUAL | B28: =B26/12 -> 23318.423
D31: =C26-F26-G26 -> 127941.63 | E31: =B26-F26-G26 -> -36782.99
B35: Recebimento | C35: Despesas | E35: #
A36: Jan | B36: 316807.42 | C36: 330244.38 | D36: ='[1]Base_Resultado Mensal_V2'!D190 -> 134911.6 | E36: =B36-C36-D36 -> -148348.56
A37: Fev | B37: 216057.27 | C37: 377306.7 | D37: ='[1]Base_Resultado Mensal_V2'!F190 -> 5092.45 | E37: =B37-C37-D37 -> -166341.88
A38: Mar | B38: 613202.96 | C38: 363984.21 | D38: ='[1]Base_Resultado Mensal_V2'!H190 -> 814.99 | E38: =B38-C38-D38 -> 248403.76
A39: Abr | B39: 588260.32 | C39: 375072.46 | D39: ='[1]Base_Resultado Mensal_V2'!J190 -> 110831.76 | E39: =B39-C39-D39 -> 102356.1
A40: Mai | B40: 658171.05 | C40: 360112.8 | D40: ='[1]Base_Resultado Mensal_V2'!L190 -> 5968 | E40: =B40-C40-D40 -> 292090.25
A41: Jun | B41: 632809.49 | C41: 334821.86 | D41: ='[1]Base_Resultado Mensal_V2'!N190 -> 11928.17 | E41: =B41-C41-D41 -> 286059.46
A42: Jul | B42: 260036.93 | C42: 337422.56 | D42: ='[1]Base_Resultado Mensal_V2'!P190 -> 183171.96 | E42: =B42-C42-D42 -> -260557.59
B43: 3285345.4 | C43: 2478965 | D43: =SUM(D36:D42) -> 452718.93

Sheet Rateio Mensal
A1: JANEIRO | E1: Orçado | H1: DESPESAS RATEADAS | K1: Rateio anual
A2: =K2 -> Custo equipe - Contencioso | B2: ='Base_Resultado Mensal_V2'!C5 -> 73576.315 | C2: =+B2/B5 -> 0.34766401 | E2: ='Areas Sintetico atualizado'!B39 -> 74354.065 | F2: =E2/$E$5 -> 0.34839708 | H2: =('Base_Resultado Mensal_V2'!C194)-'Base_Resultado Mensal_V2'!C200-'Base_Resultado Mensal_V2'!C201-'Base_Resultado Mensal_V2'!C202 -> 101895.64 | I2: =$H$2*C2 -> 35425.447 | K2: ='DRE 2026'!A6 -> Custo equipe - Contencioso | L2: ='DRE 2026'!B6 -> 881797.73 | M2: =L2/$L$5 -> 0.36682229
A3: =K3 -> Custo equipe - Econômico | B3: ='Base_Resultado Mensal_V2'!C30 -> 76041.035 | C3: =+B3/B5 -> 0.35931034 | E3: ='Areas Sintetico atualizado'!B57 -> 76879.165 | F3: =E3/$E$5 -> 0.36022881 | I3: =$H$2*C3 -> 36612.157 | K3: ='DRE 2026'!A7 -> Custo equipe - Econômico | L3: ='DRE 2026'!B7 -> 914114.75 | M3: =L3/$L$5 -> 0.38026596
A4: =K4 -> Custo equipe - Arbitragem e Compliance | B4: ='Base_Resultado Mensal_V2'!C58 -> 62013.17 | C4: =B4/$B$5 -> 0.29302565 | E4: ='Areas Sintetico atualizado'!B75 -> 62184.36 | F4: =E4/$E$5 -> 0.29137411 | I4: =$H$2*C4 -> 29858.036 | K4: ='DRE 2026'!A8 -> Custo equipe - Arbitragem e Compliance | L4: ='DRE 2026'!B8 -> 607970.16 | M4: =L4/$L$5 -> 0.25291175
A5: Total das Áreas | B5: =SUM(B2:B4) -> 211630.52 | C5: =SUM(C2:C4) -> 1 | E5: =SUM(E2:E4) -> 213417.59 | K5: =A5 -> Total das Áreas | L5: =SUM(L2:L4) -> 2403882.6 | M5: =SUM(M2:M4) -> 1
A7: FEVEREIRO
A8: =K2 -> Custo equipe - Contencioso | B8: ='Base_Resultado Mensal_V2'!D5 -> 76342.345 | C8: =+B8/B11 -> 0.34953137 | E8: ='DRE 2026'!D6 -> 72754.065 | F8: =E8/$E$11 -> 0.34857659 | H8: ='Base_Resultado Mensal_V2'!D203 -> 90395.7 | I8: =$H$8*C8 -> 31596.133
A9: =K3 -> Custo equipe - Econômico | B9: ='Base_Resultado Mensal_V2'!D30 -> 80276.745 | C9: =+B9/B11 -> 0.36754491 | E9: ='DRE 2026'!D7 -> 75379.165 | F9: =E9/$E$11 -> 0.36115387 | I9: =$H$8*C9 -> 33224.48
A10: =K4 -> Custo equipe - Arbitragem e Compliance | B10: ='Base_Resultado Mensal_V2'!D58 -> 61794.34 | C10: =B10/$B$11 -> 0.28292372 | E10: ='DRE 2026'!D8 -> 60584.36 | F10: =E10/$E$11 -> 0.29026955 | I10: =$H$8*C10 -> 25575.088
A11: =K5 -> Total das Áreas | B11: =SUM(B8:B10) -> 218413.43 | C11: =SUM(C8:C10) -> 1 | E11: =SUM(E8:E10) -> 208717.59

Sheet Fluxo consolidado 
B1: 671666.67
B2: Janeiro | C2: Fevereiro | D2: Março | E2: Abril | F2: Maio | G2: Junho | H2: Julho | I2: Agosto | J2: Setembro | K2: Outubro | L2: Novembro | M2: Dezembro | N2: 1
A3: Contencioso | B3: Realizado | C3: Realizado | D3: Realizado | E3: Realizado | F3: Realizado | G3: Realizado | H3: Realizado | I3: Realizado | J3: Realizado | K3: Realizado | L3: Realizado | M3: Realizado | N3: TOTAL
A4: Recebimento | B4: ='Areas Sintetico atualizado'!C36 -> 72613.091 | N4: =B4+C4+D4+E4+F4+G4+H4+I4+J4+K4+L4+M4 -> 72613.091 | P4: Minimo de receita
A5: Equipe | B5: ='Areas Sintetico atualizado'!C39+'Areas Sintetico atualizado'!C40 -> 73576.315 | N5: =B5+C5+D5+E5+F5+G5+H5+I5+J5+K5+L5+M5 -> 73576.315 | P5: =(N5+N6+N7+N8)/$N$2 -> 123775.81
A6: Despesas | B6: ='Areas Sintetico atualizado'!C41+'Areas Sintetico atualizado'!C42 -> 36485.542 | N6: =B6+C6+D6+E6+F6+G6+H6+I6+J6+K6+L6+M6 -> 36485.542
A7: Impostos | B7: ='Areas Sintetico atualizado'!C46 -> 10891.964 | N7: =B7+C7+D7+E7+F7+G7+H7+I7+J7+K7+L7+M7 -> 10891.964 | P7: Margem Liq.
A8: Investimento amortizaçao | B8: ='Areas Sintetico atualizado'!C47 -> 2821.9888 | N8: =B8+C8+D8+E8+F8+G8+H8+I8+J8+K8+L8+M8 -> 2821.9888
A9: Margem liquida | B9: =B4-B5-B6-B7-B8 -> -51162.718 | C9: =C4-C5-C6-C7-C8 -> 0 | D9: =D4-D5-D6-D7-D8 -> 0 | E9: =E4-E5-E6-E7-E8 -> 0 | F9: =F4-F5-F6-F7-F8 -> 0 | G9: =G4-G5-G6-G7-G8 -> 0 | H9: =H4-H5-H6-H7-H8 -> 0 | I9: =I4-I5-I6-I7-I8 -> 0 | ... N9: =N4-N5-N6-N7-N8 -> -51162.718 | P9: =N9/N4 -> -0.70459359
B11: Janeiro | C11: Fevereiro | D11: Março | E11: Abril | F11: Maio | G11: Junho | H11: Julho | I11: Agosto | J11: Setembro | K11: =K2 -> Outubro | L11: =L2 -> Novembro | M11: =M2 -> Dezembro
A12: Economico | B12: Realizado | C12: Realizado | D12: Realizado | E12: Realizado | F12: Realizado | G12: Realizado | H12: Realizado | I12: Realizado | J12: Realizado | K12: Realizado | L12: Realizado | M12: Realizado | N12: TOTAL
A13: Recebimento | B13: ='Areas Sintetico atualizado'!C54 -> 120362.57 | N13: =B13+C13+D13+E13+F13+G13+H13+I13+J13+K13+L13+M13 -> 120362.57 | P13: Minimo de receita
A14: Equipe | B14: ='Areas Sintetico atualizado'!C57 -> 76041.035 | N14: =B14+C14+D14+E14+F14+G14+H14+I14+J14+K14+L14+M14 -> 76041.035 | P14: =(N14+N15+N16+N17)/$N$2 -> 135495.91
A15: Despesas | B15: ='Areas Sintetico atualizado'!C59+'Areas Sintetico atualizado'!C60 -> 38483.962 | N15: =B15+C15+D15+E15+F15+G15+H15+I15+J15+K15+L15+M15 -> 38483.962
A16: Impostos | B16: ='Areas Sintetico atualizado'!C64 -> 18054.386 | N16: =B16+C16+D16+E16+F16+G16+H16+I16+J16+K16+L16+M16 -> 18054.386 | P16: Margem Liq.
A17: Investimento amortizaçao | B17: ='Areas Sintetico atualizado'!C65 -> 2916.5221 | N17: =B17+C17+D17+E17+F17+G17+H17+I17+J17+K17+L17+M17 -> 2916.5221
A18: Margem liquida | B18: =B13-B14-B15-B16-B17 -> -15133.331 | C18: =C13-C14-C15-C16-C17 -> 0 | D18: =D13-D14-D15-D16-D17 -> 0 | E18: =E13-E14-E15-E16-E17 -> 0 | F18: =F13-F14-F15-F16-F17 -> 0 | G18: =G13-G14-G15-G16-G17 -> 0 | H18: =H13-H14-H15-H16-H17 -> 0 | I18: =I13-I14-I15-I16-I17 -> 0 | ... N18: =N13-N14-N15-N16-N17 -> -15133.331 | P18: =N18/N13 -> -0.1257312
B20: Janeiro | C20: Fevereiro | D20: Março | E20: Abril | F20: Maio | G20: Junho | H20: Julho | I20: Agosto | J20: Setembro | K20: =K2 -> Outubro | L20: =L2 -> Novembro | M20: =M2 -> Dezembro
A21: Arbitragem | B21: Realizado | C21: Realizado | D21: Realizado | E21: Realizado | F21: Realizado | G21: Realizado | H21: Realizado | I21: Realizado | J21: Realizado | K21: Realizado | L21: Realizado | M21: Realizado | N21: TOTAL
A22: Recebimento | B22: ='Areas Sintetico atualizado'!C72 -> 86846.335 | N22: =B22+C22+D22+E22+F22+G22+H22+I22+J22+K22+L22+M22 -> 86846.335 | P22: Minimo de receita
A23: Equipe | B23: ='Areas Sintetico atualizado'!C75 -> 62013.17 | N23: =B23+C23+D23+E23+F23+G23+H23+I23+J23+K23+L23+M23 -> 62013.17 | P23: =(N23+N24+N25+N26)/$N$2 -> 107422.65
A24: Despesas | B24: ='Areas Sintetico atualizado'!C77+'Areas Sintetico atualizado'!C78 -> 30004.036 | N24: =B24+C24+D24+E24+F24+G24+H24+I24+J24+K24+L24+M24 -> 30004.036
A25: Impostos | B25: ='Areas Sintetico atualizado'!C82 -> 13026.95 | N25: =B25+C25+D25+E25+F25+G25+H25+I25+J25+K25+L25+M25 -> 13026.95 | P25: Margem Liq.
A26: Investimento amortizaçao | B26: ='Areas Sintetico atualizado'!C83 -> 2378.4892 | N26: =B26+C26+D26+E26+F26+G26+H26+I26+J26+K26+L26+M26 -> 2378.4892
A27: Margem liquida | B27: =B22-B23-B24-B25-B26 -> -20576.31 | C27: =C22-C23-C24-C25-C26 -> 0 | D27: =D22-D23-D24-D25-D26 -> 0 | E27: =E22-E23-E24-E25-E26 -> 0 | F27: =F22-F23-F24-F25-F26 -> 0 | G27: =G22-G23-G24-G25-G26 -> 0 | H27: =H22-H23-H24-H25-H26 -> 0 | I27: =I22-I23-I24-I25-I26 -> 0 | ... N27: =N22-N23-N24-N25-N26 -> -20576.31 | P27: =N27/N22 -> -0.23692779
B30: =B4+B13+B22 -> 279822 | C30: =C4+C13+C22 -> 0 | D30: =D4+D13+D22 -> 0 | E30: =E4+E13+E22 -> 0 | F30: =F4+F13+F22 -> 0 | G30: =G4+G13+G22 -> 0 | H30: =H4+H13+H22 -> 0 | I30: =I4+I13+I22 -> 0 | ... M30: =M4+M13+M22 -> 0 | N30: =B30+C30+D30+E30+F30+G30+H30+I30+J30+K30+L30+M30 -> 279822

Sheet DRE 2026
A1: DRE | C1: Janeiro | D1: Fevereiro | E1: Março | F1: Abril | G1: Maio | H1: Junho | I1: Julho | J1: Agosto | K1: Setembro | L1: Outubro | M1: Novembro | N1: Dezembro
A2: Resultado Institucional | C2: Orçado | D2: Orçado | E2: Orçado | F2: Orçado | G2: Orçado | H2: Orçado | I2: Orçado | J2: Orçado | K2: Orçado | L2: Orçado | M2: Orçado | N2: Orçado
A3: Faturamento | B3: =SUM(C3:N3) -> 8060000 | C3: 671666.67 | D3: 671666.67 | E3: 671666.67 | F3: 671666.67 | G3: 671666.67 | H3: 671666.67 | I3: 671666.67 | J3: 671666.67 | K3: 671666.67 | L3: 671666.67 | M3: 671666.67 | N3: 671666.67
A4: Despesas
A5: Custos Diretos | B5: =SUM(C5:N5) -> 2403882.6 | C5: =SUM(C6:C8) -> 213417.59 | D5: =SUM(D6:D8) -> 208717.59 | E5: =SUM(E6:E8) -> 196100.61 | F5: =SUM(F6:F8) -> 200900.61 | G5: =SUM(G6:G8) -> 196100.61 | H5: =SUM(H6:H8) -> 196100.61 | I5: =SUM(I6:I8) -> 200900.61 | J5: =SUM(J6:J8) -> 196100.61 | ... N5: =SUM(N6:N8) -> 198128.67
A6: Custo equipe - Contencioso | B6: =SUM(C6:N6) -> 881797.73 | C6: ='[2]Orçamento 2026'!D5 -> 74354.065 | D6: ='[2]Orçamento 2026'!E5 -> 72754.065 | E6: ='[2]Orçamento 2026'!F5 -> 72754.065 | F6: ='[2]Orçamento 2026'!G5 -> 74354.065 | G6: ='[2]Orçamento 2026'!H5 -> 72754.065 | H6: ='[2]Orçamento 2026'!I5 -> 72754.065 | I6: ='[2]Orçamento 2026'!J5 -> 74354.065 | J6: ='[2]Orçamento 2026'!K5 -> 72754.065 | ... N6: ='[2]Orçamento 2026'!O5 -> 73451.317
A7: Custo equipe - Econômico | B7: =SUM(C7:N7) -> 914114.75 | C7: ='[2]Orçamento 2026'!D28 -> 76879.165 | D7: ='[2]Orçamento 2026'!E28 -> 75379.165 | E7: ='[2]Orçamento 2026'!F28 -> 75379.165 | F7: ='[2]Orçamento 2026'!G28 -> 76979.165 | G7: ='[2]Orçamento 2026'!H28 -> 75379.165 | H7: ='[2]Orçamento 2026'!I28 -> 75379.165 | I7: ='[2]Orçamento 2026'!J28 -> 76979.165 | J7: ='[2]Orçamento 2026'!K28 -> 75379.165 | ... N7: ='[2]Orçamento 2026'!O28 -> 76467.423
A8: Custo equipe - Arbitragem e Compliance | B8: =SUM(C8:N8) -> 607970.16 | C8: ='[2]Orçamento 2026'!D53 -> 62184.36 | D8: ='[2]Orçamento 2026'!E53 -> 60584.36 | E8: ='[2]Orçamento 2026'!F53 -> 47967.38 | F8: ='[2]Orçamento 2026'!G53 -> 49567.38 | G8: ='[2]Orçamento 2026'!H53 -> 47967.38 | H8: ='[2]Orçamento 2026'!I53 -> 47967.38 | I8: ='[2]Orçamento 2026'!J53 -> 49567.38 | J8: ='[2]Orçamento 2026'!K53 -> 47967.38 | ... N8: ='[2]Orçamento 2026'!O53 -> 48209.927
A9: Despesas Indiretas | B9: =SUM(C9:N9) -> 1331793.8 | C9: =SUM(C10:C20) -> 102906.66 | D9: =SUM(D10:D20) -> 100790.33 | E9: =SUM(E10:E20) -> 128651.12 | F9: =SUM(F10:F20) -> 118391.12 | G9: =SUM(G10:G20) -> 108896.07 | H9: =SUM(H10:H20) -> 100270.33 | I9: =SUM(I10:I20) -> 108849.44 | J9: =SUM(J10:J20) -> 102160.57 | ... N9: =SUM(N10:N20) -> 136624.19
A10: Ocupação | B10: =SUM(C10:N10) -> 410635.68 | C10: ='[2]Orçamento 2026'!D73 -> 27197.48 | D10: ='[2]Orçamento 2026'!E73 -> 34236.38 | E10: ='[2]Orçamento 2026'!F73 -> 34236.38 | F10: ='[2]Orçamento 2026'!G73 -> 34236.38 | G10: ='[2]Orçamento 2026'!H73 -> 34236.38 | H10: ='[2]Orçamento 2026'!I73 -> 35213.24 | I10: ='[2]Orçamento 2026'!J73 -> 35213.24 | J10: ='[2]Orçamento 2026'!K73 -> 35213.24 | ... N10: ='[2]Orçamento 2026'!O73 -> 35213.24
A11: Telecomunicações | B11: =SUM(C11:N11) -> 10127.402 | C11: ='[2]Orçamento 2026'!D80 -> 890 | D11: ='[2]Orçamento 2026'!E80 -> 839.7638 | E11: ='[2]Orçamento 2026'!F80 -> 839.7638 | F11: ='[2]Orçamento 2026'!G80 -> 839.7638 | G11: ='[2]Orçamento 2026'!H80 -> 839.7638 | H11: ='[2]Orçamento 2026'!I80 -> 839.7638 | I11: ='[2]Orçamento 2026'!J80 -> 839.7638 | J11: ='[2]Orçamento 2026'!K80 -> 839.7638 | ... N11: ='[2]Orçamento 2026'!O80 -> 839.7638
A12: Despesas Gerais | B12: =SUM(C12:N12) -> 74921.85 | C12: ='[2]Orçamento 2026'!D83 -> 7255 | D12: ='[2]Orçamento 2026'!E83 -> 5505 | E12: ='[2]Orçamento 2026'!F83 -> 5742.205 | F12: ='[2]Orçamento 2026'!G83 -> 7292.205 | G12: ='[2]Orçamento 2026'!H83 -> 5742.205 | H12: ='[2]Orçamento 2026'!I83 -> 5683.605 | I12: ='[2]Orçamento 2026'!J83 -> 7333.605 | J12: ='[2]Orçamento 2026'!K83 -> 5683.605 | ... N12: ='[2]Orçamento 2026'!O83 -> 5783.605
A13: Consultoria | B13: =SUM(C13:N13) -> 244264.88 | C13: ='[2]Orçamento 2026'!D97 -> 23240.8 | D13: ='[2]Orçamento 2026'!E97 -> 23035.8 | E13: ='[2]Orçamento 2026'!F97 -> 22815.8 | F13: ='[2]Orçamento 2026'!G97 -> 18355.8 | G13: ='[2]Orçamento 2026'!H97 -> 18055.8 | H13: ='[2]Orçamento 2026'!I97 -> 18705.8 | I13: ='[2]Orçamento 2026'!J97 -> 18480.8 | J13: ='[2]Orçamento 2026'!K97 -> 19255.8 | ... N13: ='[2]Orçamento 2026'!O97 -> 22772.561
A14: Salários Administração | B14: =SUM(C14:N14) -> 82659.531 | C14: ='[2]Orçamento 2026'!D103 -> 6426.58 | D14: ='[2]Orçamento 2026'!E103 -> 6776.58 | E14: ='[2]Orçamento 2026'!F103 -> 6426.58 | F14: ='[2]Orçamento 2026'!G103 -> 6426.58 | G14: ='[2]Orçamento 2026'!H103 -> 6426.58 | H14: ='[2]Orçamento 2026'!I103 -> 6426.58 | I14: ='[2]Orçamento 2026'!J103 -> 6426.58 | J14: ='[2]Orçamento 2026'!K103 -> 6426.58 | ... N14: ='[2]Orçamento 2026'!O103 -> 8923.437
A15: Administrativas | B15: =SUM(C15:N15) -> 91084.465 | C15: ='[2]Orçamento 2026'!D111 -> 2996.8033 | D15: ='[2]Orçamento 2026'!E111 -> 2996.8033 | E15: ='[2]Orçamento 2026'!F111 -> 14690.387 | F15: ='[2]Orçamento 2026'!G111 -> 14690.387 | G15: ='[2]Orçamento 2026'!H111 -> 14695.337 | H15: ='[2]Orçamento 2026'!I111 -> 3001.3367 | I15: ='[2]Orçamento 2026'!J111 -> 5655.4486 | J15: ='[2]Orçamento 2026'!K111 -> 5691.5827 | ... N15: ='[2]Orçamento 2026'!O111 -> 5691.5827
A16: Taxas / Despesas Financeiras | B16: =SUM(C16:N16) -> 0
A17: Investimentos em Prospecção | B17: =SUM(C17:N17) -> 96000 | C17: ='[2]Orçamento 2026'!D124 -> 4500 | D17: ='[2]Orçamento 2026'!E124 -> 4500 | E17: ='[2]Orçamento 2026'!F124 -> 6000 | F17: ='[2]Orçamento 2026'!G124 -> 6000 | G17: ='[2]Orçamento 2026'!H124 -> 6000 | H17: ='[2]Orçamento 2026'!I124 -> 7500 | I17: ='[2]Orçamento 2026'!J124 -> 4500 | J17: ='[2]Orçamento 2026'!K124 -> 6000 | ... N17: ='[2]Orçamento 2026'!O124 -> 34500
A18: Endomarketing | B18: =SUM(C18:N18) -> 1200 | C18: ='[2]Orçamento 2026'!D151 -> 100 | D18: ='[2]Orçamento 2026'!E151 -> 100 | E18: ='[2]Orçamento 2026'!F151 -> 100 | F18: ='[2]Orçamento 2026'!G151 -> 100 | G18: ='[2]Orçamento 2026'!H151 -> 100 | H18: ='[2]Orçamento 2026'!I151 -> 100 | I18: ='[2]Orçamento 2026'!J151 -> 100 | J18: ='[2]Orçamento 2026'!K151 -> 100 | ... N18: ='[2]Orçamento 2026'!O151 -> 100
A19: ='[3]Areas Sintetico atualizado'!A21 -> Gestão do Conhecimento | B19: =SUM(C19:N19) -> 2300 | C19: ='[2]Orçamento 2026'!D145 -> 0 | D19: ='[2]Orçamento 2026'!E145 -> 0 | E19: ='[2]Orçamento 2026'!F145 -> 0 | F19: ='[2]Orçamento 2026'!G145 -> 150 | G19: ='[2]Orçamento 2026'!H145 -> 0 | H19: ='[2]Orçamento 2026'!I145 -> 0 | I19: ='[2]Orçamento 2026'!J145 -> 0 | J19: ='[2]Orçamento 2026'!K145 -> 150 | ... N19: ='[2]Orçamento 2026'!O145 -> 0
A20: Informática | B20: =SUM(C20:N20) -> 318600 | C20: ='[2]Orçamento 2026'!D161 -> 30300 | D20: ='[2]Orçamento 2026'!E161 -> 22800 | E20: ='[2]Orçamento 2026'!F161 -> 37800 | F20: ='[2]Orçamento 2026'!G161 -> 30300 | G20: ='[2]Orçamento 2026'!H161 -> 22800 | H20: ='[2]Orçamento 2026'!I161 -> 22800 | I20: ='[2]Orçamento 2026'!J161 -> 30300 | J20: ='[2]Orçamento 2026'!K161 -> 22800 | ... N20: ='[2]Orçamento 2026'!O161 -> 22800
A21: Resultado Bruto | B21: =B3-B5-B9 -> 4324323.6 | C21: =C3-C5-C9 -> 355342.42 | D21: =D3-D5-D9 -> 362158.75 | E21: =E3-E5-E9 -> 346914.94 | F21: =F3-F5-F9 -> 352374.94 | G21: =G3-G5-G9 -> 366669.99 | H21: =H3-H5-H9 -> 375295.73 | I21: =I3-I5-I9 -> 361916.62 | ... N21: =N3-N5-N9 -> 336913.81
A22: Margem de bruta | B22: =B21/B3 -> 0.53651657 | C22: =C21/C3 -> 0.52904578 | D22: =D21/D3 -> 0.53919417 | E22: =E21/E3 -> 0.51649867 | F22: =F21/F3 -> 0.52462771 | G22: =G21/G3 -> 0.54591066 | H22: =H21/H3 -> 0.55875295 | I22: =I21/I3 -> 0.53883368 | ... N22: =N21/N3 -> 0.50160865
A23: Impostos | B23: =C23+D23+E23+F23+G23+H23+I23+J23+K23+L23+M23+N23 -> 1809000 | C23: =(C3*15%)+50000 -> 150750 | D23: =(D3*15%)+50000 -> 150750 | E23: =(E3*15%)+50000 -> 150750 | F23: =(F3*15%)+50000 -> 150750 | G23: =(G3*15%)+50000 -> 150750 | H23: =(H3*15%)+50000 -> 150750 | I23: =(I3*15%)+50000 -> 150750 | J23: =(J3*15%)+50000 -> 150750 | ... N23: =(N3*15%)+50000 -> 150750
A24: Amortização | B24: =SUM(C24:N24) -> 97404 | C24: 8117 | D24: 8117 | E24: 8117 | F24: 8117 | G24: 8117 | H24: 8117 | I24: 8117 | J24: 8117 | K24: 8117 | L24: 8117 | M24: 8117 | N24: 8117
A25: Resultado Liquido após impostos | B25: =B21-B23-B24 -> 2417919.6 | C25: =C21-C23-C24 -> 196475.42 | D25: =D21-D23-D24 -> 203291.75 | E25: =E21-E23-E24 -> 188047.94 | F25: =F21-F23-F24 -> 193507.94 | G25: =G21-G23-G24 -> 207802.99 | H25: =H21-H23-H24 -> 216428.73 | I25: =I21-I23-I24 -> 203049.62 | ... N25: =N21-N23-N24 -> 178046.81
A26: Margem liquida | B26: =B25/B3 -> 0.29999002 | C26: =C25/C3 -> 0.29251923 | D26: =D25/D3 -> 0.30266762 | E26: =E25/E3 -> 0.27997212 | F26: =F25/F3 -> 0.28810116 | G26: =G25/G3 -> 0.30938411 | H26: =H25/H3 -> 0.3222264 | I26: =I25/I3 -> 0.30230713 | ... N26: =N25/N3 -> 0.2650821
A27: Reserva bônus | B27: =B25*10% -> 241791.96 | C27: =C25*10% -> 19647.542 | D27: =D25*10% -> 20329.175 | E27: =E25*10% -> 18804.794 | F27: =F25*10% -> 19350.794 | G27: =G25*10% -> 20780.299 | H27: =H25*10% -> 21642.873 | I27: =I25*10% -> 20304.962 | ... N27: =N25*10% -> 17804.681
A29: Rentabilidade | B29: =B6+B7+B8 -> 2403882.6 | C29: =C6+C7+C8 -> 213417.59 | D29: =D6+D7+D8 -> 208717.59 | E29: =E6+E7+E8 -> 196100.61 | F29: =F6+F7+F8 -> 200900.61 | G29: =G6+G7+G8 -> 196100.61 | H29: =H6+H7+H8 -> 196100.61 | I29: =I6+I7+I8 -> 200900.61 | ... N29: =N6+N7+N8 -> 198128.67
B30: =B9 -> 1331793.8 | C30: =C9 -> 102906.66 | D30: =D9 -> 100790.33 | E30: =E9 -> 128651.12 | F30: =F9 -> 118391.12 | G30: =G9 -> 108896.07 | H30: =H9 -> 100270.33 | I30: =I9 -> 108849.44 | ... N30: =N9 -> 136624.19
B31: =B29-B30 -> 1072088.8 | C31: =C29-C30 -> 110510.93 | D31: =D29-D30 -> 107927.26 | E31: =E29-E30 -> 67449.495 | F31: =F29-F30 -> 82509.495 | G31: =G29-G30 -> 87204.545 | H31: =H29-H30 -> 95830.285 | I31: =I29-I30 -> 92051.173 | ... N31: =N29-N30 -> 61504.477
B32: =B31/B3 -> 0.1330135 | C32: =C31/C3 -> 0.1645324 | D32: =D31/D3 -> 0.16068575 | E32: =E31/E3 -> 0.10042108 | F32: =F31/F3 -> 0.12284292 | G32: =G31/G3 -> 0.12983307 | H32: =H31/H3 -> 0.14267536 | I32: =I31/I3 -> 0.13704889 | ... N32: =N31/N3 -> 0.091569941
B96: =SUM(B97:B102) -> 0 | D96: =SUM(D97:D102) -> 0 | E96: =SUM(E97:E102) -> 0 | F96: =SUM(F97:F102) -> 0 | G96: =SUM(G97:G102) -> 0 | H96: =SUM(H97:H102) -> 0 | I96: =SUM(I97:I102) -> 0 | J96: =SUM(J97:J102) -> 0 | K96: =SUM(K97:K102) -> 0 | ... N96: =SUM(N97:N102) -> 0
A103: Assinaturas
B137: =SUM(B138:B141) -> 0 | D137: =SUM(D138:D141) -> 0 | E137: =SUM(E138:E141) -> 0 | F137: =SUM(F138:F141) -> 0 | G137: =SUM(G138:G141) -> 0 | H137: =SUM(H138:H141) -> 0 | I137: =SUM(I138:I141) -> 0 | J137: =SUM(J138:J141) -> 0 | K137: =SUM(K138:K141) -> 0 | ... N137: =SUM(N138:N141) -> 0
B168: =B4+B26+B51+B67+B73+B76+B90+B96+B103+B142+B152+B116+B137 -> 0.29999002 | D168: =D4+D26+D51+D67+D73+D76+D90+D96+D103+D142+D152+D116+D137 -> 0.30266762 | E168: =E4+E26+E51+E67+E73+E76+E90+E96+E103+E142+E152+E116+E137 -> 0.27997212 | F168: =F4+F26+F51+F67+F73+F76+F90+F96+F103+F142+F152+F116+F137 -> 0.28810116 | G168: =G4+G26+G51+G67+G73+G76+G90+G96+G103+G142+G152+G116+G137 -> 0.30938411 | H168: =H4+H26+H51+H67+H73+H76+H90+H96+H103+H142+H152+H116+H137 -> 0.3222264 | I168: =I4+I26+I51+I67+I73+I76+I90+I96+I103+I142+I152+I116+I137 -> 0.30230713 | J168: =J4+J26+J51+J67+J73+J76+J90+J96+J103+J142+J152+J116+J137 -> 0.31941214 | K168: =K4+K26+K51+K67+K73+K76+K90+K96+K103+K142+K152+K116+K137 -> 0.32127318 | ... N168: =N4+N26+N51+N67+N73+N76+N90+N96+N103+N142+N152+N116+N137 -> 0.2650821

Sheet Orçamento 2026
C1: 0.045
A2: Resultado Financeiro 2025 | B2: Soma JAN. a DEZ. | D2: Janeiro | E2: Fevereiro | F2: Março | G2: Abril | H2: Maio | I2: Junho | J2: Julho | K2: Agosto | L2: Setembro | M2: Outubro | N2: Novembro | O2: Dezembro
A3: Movimentação de Entradas | B3: =SUM(C3:O3) -> 8060000 | D3: 671666.67 | E3: 671666.67 | F3: 671666.67 | G3: 671666.67 | H3: 671666.67 | I3: 671666.67 | J3: 671666.67 | K3: 671666.67 | L3: 671666.67 | M3: 671666.67 | N3: 671666.67 | O3: 671666.67
A4: Receita de honorários | B4: =SUM(D4:O4) -> 0
A5: Custo equipe - Contencioso | B5: =SUM(D5:O5) -> 881797.73 | D5: =SUM(D6:D27) -> 74354.065 | E5: =SUM(E6:E27) -> 72754.065 | F5: =SUM(F6:F27) -> 72754.065 | G5: =SUM(G6:G27) -> 74354.065 | H5: =SUM(H6:H27) -> 72754.065 | I5: =SUM(I6:I27) -> 72754.065 | J5: =SUM(J6:J27) -> 74354.065 | K5: =SUM(K6:K27) -> 72754.065 | ... O5: =SUM(O6:O27) -> 73451.317
A6: Daniel Costa Caselta - Distribuição Mensal Fixa | B6: =SUM(D6:O6) -> 280548 | D6: ='[2]Tabela 2025 2026'!Q13 -> 23379 | E6: =D6 -> 23379 | F6: =E6 -> 23379 | G6: =F6 -> 23379 | H6: =G6 -> 23379 | I6: =H6 -> 23379 | J6: =I6 -> 23379 | K6: =J6 -> 23379 | L6: =K6 -> 23379 | ... O6: =N6 -> 23379
A7: Daniel Costa Caselta - Pro labore | B7: =SUM(D7:O7) -> 19452 | D7: ='[2]Tabela 2025 2026'!M14 -> 1621 | E7: =D7 -> 1621 | F7: =E7 -> 1621 | G7: =F7 -> 1621 | H7: =G7 -> 1621 | I7: =H7 -> 1621 | J7: =I7 -> 1621 | K7: =J7 -> 1621 | L7: =K7 -> 1621 | ... O7: =N7 -> 1621
A8: Daniel Costa Caselta - Convenio Medico | B8: =SUM(D8:O8) -> 21825.998 | D8: 1794.65 | E8: =D8 -> 1794.65 | F8: =E8 -> 1794.65 | G8: =F8 -> 1794.65 | H8: =G8 -> 1794.65 | I8: =H8 -> 1794.65 | J8: =I8 -> 1794.65 | K8: =J8 -> 1794.65 | L8: =K8 -> 1794.65 | M8: =L8+(L8*[2]Premissas!B4) -> 2063.8475 | N8: 1804.65 | O8: 1805.65
A9: Aurelio Marchini Santos - Distribuição Mensal Fixa | B9: =SUM(D9:O9) -> 140274 | D9: ='[2]Tabela 2025 2026'!Q13/2 -> 11689.5 | E9: =D9 -> 11689.5 | F9: =E9 -> 11689.5 | G9: =F9 -> 11689.5 | H9: =G9 -> 11689.5 | I9: =H9 -> 11689.5 | J9: =I9 -> 11689.5 | K9: =J9 -> 11689.5 | L9: =K9 -> 11689.5 | ... O9: =N9 -> 11689.5
A10: Aurelio Marchini Santos- Pro labore | B10: =SUM(D10:O10) -> 9726 | D10: ='[2]Tabela 2025 2026'!M13/2 -> 810.5 | E10: =D10 -> 810.5 | F10: =E10 -> 810.5 | G10: =F10 -> 810.5 | H10: =G10 -> 810.5 | I10: =H10 -> 810.5 | J10: =I10 -> 810.5 | K10: =J10 -> 810.5 | L10: =K10 -> 810.5 | ... O10: =N10 -> 810.5
A11: Aurelio Marchini Santos - Convenio Medico | B11: =SUM(D11:O11) -> 20483.176 | D11: =(3290.47/2) -> 1645.235 | E11: =D11 -> 1645.235 | F11: =E11 -> 1645.235 | G11: =F11 -> 1645.235 | H11: =G11 -> 1645.235 | I11: =H11 -> 1645.235 | J11: =I11 -> 1645.235 | K11: =J11 -> 1645.235 | L11: =K11 -> 1645.235 | M11: =(3290.47/2)*[2]Premissas!B4+'Orçamento 2026'!L11 -> 1892.0202 | N11: =M11 -> 1892.0202 | O11: =N11 -> 1892.0202
A12: Beatriz Baes Xavier - Distribuição Mensal Fixa | B12: =SUM(D12:O12) -> 90448.8 | D12: ='[2]Tabela 2025 2026'!Q4 -> 7537.4 | E12: =D12 -> 7537.4 | F12: =E12 -> 7537.4 | G12: =F12 -> 7537.4 | H12: =G12 -> 7537.4 | I12: =H12 -> 7537.4 | J12: =I12 -> 7537.4 | K12: =J12 -> 7537.4 | L12: =K12 -> 7537.4 | ... O12: =N12 -> 7537.4
A13: Beatriz Baes Xavier - Pro Labore | B13: =SUM(D13:O13) -> 19452 | D13: ='[2]Tabela 2025 2026'!M4 -> 1621 | E13: =D13 -> 1621 | F13: =E13 -> 1621 | G13: =F13 -> 1621 | H13: =G13 -> 1621 | I13: =H13 -> 1621 | J13: =I13 -> 1621 | K13: =J13 -> 1621 | L13: =K13 -> 1621 | ... O13: =N13 -> 1621
A14: Beatriz Baes Xavier - Convenio Medico | B14: =SUM(D14:O14) -> 16344.36 | D14: 1312.8 | E14: =D14 -> 1312.8 | F14: =E14 -> 1312.8 | G14: =F14 -> 1312.8 | H14: =G14 -> 1312.8 | I14: =H14 -> 1312.8 | J14: =I14 -> 1312.8 | K14: =J14 -> 1312.8 | L14: =K14 -> 1312.8 | M14: =1312.8*[2]Premissas!B4+'Orçamento 2026'!L14 -> 1509.72 | N14: =M14 -> 1509.72 | O14: =N14 -> 1509.72
A15: Beatriz Baes Xavier - Despesas Extras - Cartao Predio | B15: =SUM(D15:O15) -> 0
A16: Beatriz Baes Xavier - Reajuste de Distribuição Mensal Fixa | B16: =SUM(D16:O16) -> 0
A17: Isabel de Almeida Rego Campinho - Distribuição Mensal Fixa | B17: =SUM(D17:O17) -> 187260 | D17: ='[2]Tabela 2025 2026'!Q9 -> 15605 | E17: =D17 -> 15605 | F17: =E17 -> 15605 | G17: =F17 -> 15605 | H17: =G17 -> 15605 | I17: =H17 -> 15605 | J17: =I17 -> 15605 | K17: =J17 -> 15605 | L17: =K17 -> 15605 | ... O17: =N17 -> 15605
A18: Isabel de Almeida Rego Campinho - Pro Labore | B18: =SUM(D18:O18) -> 19452 | D18: ='[2]Tabela 2025 2026'!M9 -> 1621 | E18: =D18 -> 1621 | F18: =E18 -> 1621 | G18: =F18 -> 1621 | H18: =G18 -> 1621 | I18: =H18 -> 1621 | J18: =I18 -> 1621 | K18: =J18 -> 1621 | L18: =K18 -> 1621 | ... O18: =N18 -> 1621
A19: Isabel de Almeida Rego Campinho - Convenio Medico | B19: =SUM(D19:O19) -> 20131.401 | D19: 1616.98 | E19: 1616.98 | F19: 1616.98 | G19: 1616.98 | H19: 1616.98 | I19: 1616.98 | J19: 1616.98 | K19: 1616.98 | L19: 1616.98 | M19: =1616.98*[2]Premissas!B4+'Orçamento 2026'!L19 -> 1859.527 | N19: =M19 -> 1859.527 | O19: =N19 -> 1859.527
A20: Isabel de Almeida Rego Campinho - Reajuste de Distribuição Mensal Fixa | B20: =SUM(D20:O20) -> 0
A21: Joao Victor estagiario | B21: =SUM(D21:O21) -> 26400 | D21: 2200 | E21: 2200 | F21: 2200 | G21: 2200 | H21: 2200 | I21: 2200 | J21: 2200 | K21: 2200 | L21: 2200 | M21: 2200 | N21: 2200 | O21: 2200
A22: Joao Victor VT | B22: =SUM(D22:O22) -> 3600 | D22: 300 | E22: 300 | F22: 300 | G22: 300 | H22: 300 | I22: 300 | J22: 300 | K22: 300 | L22: 300 | M22: 300 | N22: 300 | O22: 300
A23: ISS Trimestral | B23: =SUM(D23:O23) -> 6400 | D23: 1600 | G23: 1600 | J23: 1600 | M23: 1600
A24: Seguro de vida | B24: =SUM(D24:O24) -> 0
A25: Vale Refeição | B25: =SUM(D25:O25) -> 0
A26: Amortização | B26: =SUM(D26:O26) -> 0
A27: Participação/comissão/repasse - Contencioso | B27: =SUM(D27:O27) -> 0
A28: Custo equipe - Econômico | B28: =SUM(D28:O28) -> 914114.75 | D28: =SUM(D29:D51) -> 76879.165 | E28: =SUM(E29:E51) -> 75379.165 | F28: =SUM(F29:F51) -> 75379.165 | G28: =SUM(G29:G51) -> 76979.165 | H28: =SUM(H29:H51) -> 75379.165 | I28: =SUM(I29:I51) -> 75379.165 | J28: =SUM(J29:J51) -> 76979.165 | K28: =SUM(K29:K51) -> 75379.165 | ... O28: =SUM(O29:O51) -> 76467.423
A29: Ricardo Franco Botelho - Distribuição Mensal Fixa | B29: =SUM(D29:O29) -> 280548 | D29: ='[2]Tabela 2025 2026'!Q16 -> 23379 | E29: =D29 -> 23379 | F29: =E29 -> 23379 | G29: =F29 -> 23379 | H29: =G29 -> 23379 | I29: =H29 -> 23379 | J29: =I29 -> 23379 | K29: =J29 -> 23379 | L29: =K29 -> 23379 | ... O29: =N29 -> 23379
A30: Ricardo Franco Botelho - Pro labore | B30: =SUM(D30:O30) -> 19452 | D30: ='[2]Tabela 2025 2026'!M16 -> 1621 | E30: =D30 -> 1621 | F30: =E30 -> 1621 | G30: =F30 -> 1621 | H30: =G30 -> 1621 | I30: =H30 -> 1621 | J30: =I30 -> 1621 | K30: =J30 -> 1621 | L30: =K30 -> 1621 | ... O30: =N30 -> 1621
A31: Ricardo Franco Botelho - Convenio Medico | B31: =SUM(D31:O31) -> 30320.481 | D31: 2435.38 | E31: 2435.38 | F31: 2435.38 | G31: 2435.38 | H31: 2435.38 | I31: 2435.38 | J31: 2435.38 | K31: 2435.38 | L31: 2435.38 | M31: =2435.38*[2]Premissas!B4+'Orçamento 2026'!L31 -> 2800.687 | N31: =M31 -> 2800.687 | O31: =N31 -> 2800.687
A32: Aurelio Marchini Santos - Distribuição Mensal Fixa | B32: =SUM(D32:O32) -> 140274 | D32: ='[2]Tabela 2025 2026'!Q13/2 -> 11689.5 | E32: =D32 -> 11689.5 | F32: =E32 -> 11689.5 | G32: =F32 -> 11689.5 | H32: =G32 -> 11689.5 | I32: =H32 -> 11689.5 | J32: =I32 -> 11689.5 | K32: =J32 -> 11689.5 | L32: =K32 -> 11689.5 | ... O32: =N32 -> 11689.5
A33: Aurelio Marchini Santos- Pro labore | B33: =SUM(D33:O33) -> 9726 | D33: ='[2]Tabela 2025 2026'!M13/2 -> 810.5 | E33: =D33 -> 810.5 | F33: =E33 -> 810.5 | G33: =F33 -> 810.5 | H33: =G33 -> 810.5 | I33: =H33 -> 810.5 | J33: =I33 -> 810.5 | K33: =J33 -> 810.5 | L33: =K33 -> 810.5 | ... O33: =N33 -> 810.5
A34: Aurelio Marchini Santos - Convenio Medico | B34: =SUM(D34:O34) -> 19742.82 | D34: =(3290.47/2) -> 1645.235 | E34: =(3290.47/2) -> 1645.235 | F34: =(3290.47/2) -> 1645.235 | G34: =(3290.47/2) -> 1645.235 | H34: =(3290.47/2) -> 1645.235 | I34: =(3290.47/2) -> 1645.235 | J34: =(3290.47/2) -> 1645.235 | K34: =(3290.47/2) -> 1645.235 | L34: =(3290.47/2) -> 1645.235 | M34: =(3290.47/2)*[2]Premissas!B30+'Orçamento 2026'!L34 -> 1645.235 | N34: =M34 -> 1645.235 | O34: =N34 -> 1645.235
A35: Aurelio Marchini Santos - AASP | B35: =SUM(D35:O35) -> 1100 | E35: 100 | F35: 100 | G35: 100 | H35: 100 | I35: 100 | J35: 100 | K35: 100 | L35: 100 | M35: 100 | N35: 100 | O35: 100
A36: Bruno Micalli Pedrinelli - Distribuição Mensal Fixa | B36: =SUM(D36:O36) -> 96454.56 | D36: ='[2]Tabela 2025 2026'!Q5 -> 8037.88 | E36: =D36 -> 8037.88 | F36: =E36 -> 8037.88 | G36: =F36 -> 8037.88 | H36: =G36 -> 8037.88 | I36: =H36 -> 8037.88 | J36: =I36 -> 8037.88 | K36: =J36 -> 8037.88 | L36: =K36 -> 8037.88 | ... O36: =N36 -> 8037.88
A37: Bruno Micalli Pedrinelli - Pro Labore | B37: =SUM(D37:O37) -> 19452 | D37: ='[2]Tabela 2025 2026'!M5 -> 1621 | E37: =D37 -> 1621 | F37: =E37 -> 1621 | G37: =F37 -> 1621 | H37: =G37 -> 1621 | I37: =H37 -> 1621 | J37: =I37 -> 1621 | K37: =J37 -> 1621 | L37: =K37 -> 1621 | ... O37: =N37 -> 1621
A38: Bruno Micalli Pedrinelli - Convenio Medico | B38: =SUM(D38:O38) -> 16344.36 | D38: 1312.8 | E38: 1312.8 | F38: 1312.8 | G38: 1312.8 | H38: 1312.8 | I38: 1312.8 | J38: 1312.8 | K38: 1312.8 | L38: 1312.8 | M38: =1312.8*[2]Premissas!$B$4+'Orçamento 2026'!L38 -> 1509.72 | N38: =M38 -> 1509.72 | O38: =N38 -> 1509.72
A39: Bruno Micalli Pedrinelli - Reajuste de Distribuição Mensal Fixa | B39: =SUM(D39:O39) -> 0
A40: Elisa Hime Funari - Distribuição Mensal Fixa | B40: =SUM(D40:O40) -> 142548 | D40: ='[2]Tabela 2025 2026'!Q7 -> 11879 | E40: =D40 -> 11879 | F40: =E40 -> 11879 | G40: =F40 -> 11879 | H40: =G40 -> 11879 | I40: =H40 -> 11879 | J40: =I40 -> 11879 | K40: =J40 -> 11879 | L40: =K40 -> 11879 | ... O40: =N40 -> 11879
A41: Elisa Hime Funari - Pro Labore | B41: =SUM(D41:O41) -> 19452 | D41: ='[2]Tabela 2025 2026'!M7 -> 1621 | E41: =D41 -> 1621 | F41: =E41 -> 1621 | G41: =F41 -> 1621 | H41: =G41 -> 1621 | I41: =H41 -> 1621 | J41: =I41 -> 1621 | K41: =J41 -> 1621 | L41: =K41 -> 1621 | ... O41: =N41 -> 1621
A42: Elisa Hime Funari - Convenio Medico | B42: =SUM(D42:O42) -> 27316.172 | D42: =2194.07 -> 2194.07 | E42: =2194.07 -> 2194.07 | F42: =2194.07 -> 2194.07 | G42: =2194.07 -> 2194.07 | H42: =2194.07 -> 2194.07 | I42: =2194.07 -> 2194.07 | J42: =2194.07 -> 2194.07 | K42: =2194.07 -> 2194.07 | L42: =2194.07 -> 2194.07 | M42: =2194.07*[2]Premissas!B4+'Orçamento 2026'!L42 -> 2523.1805 | N42: =M42 -> 2523.1805 | O42: =N42 -> 2523.1805
A43: Elisa Hime Funari - Reajuste de Distribuição Mensal Fixa | B43: =SUM(D43:O43) -> 0
A44: Elisa Hime Funari - Convenio Medico | B44: =SUM(D44:O44) -> 0
A45: Andrielly da Silva Gonsalves - Distribuição Mensal Fixa | B45: =SUM(D45:O45) -> 49188 | D45: ='[2]Tabela 2025 2026'!Q3 -> 4099 | E45: =D45 -> 4099 | F45: =E45 -> 4099 | G45: =F45 -> 4099 | H45: =G45 -> 4099 | I45: =H45 -> 4099 | J45: =I45 -> 4099 | K45: =J45 -> 4099 | L45: =K45 -> 4099 | ... O45: =N45 -> 4099
A46: Andrielly da Silva Gonsalves - Pro Labore | B46: =SUM(D46:O46) -> 19452 | D46: ='[2]Tabela 2025 2026'!M3 -> 1621 | E46: =D46 -> 1621 | F46: =E46 -> 1621 | G46: =F46 -> 1621 | H46: =G46 -> 1621 | I46: =H46 -> 1621 | J46: =I46 -> 1621 | K46: =J46 -> 1621 | L46: =K46 -> 1621 | ... O46: =N46 -> 1621
A47: Andrielly da Silva Gonsalves - Convenio Medico | B47: =SUM(D47:O47) -> 16344.36 | D47: 1312.8 | E47: 1312.8 | F47: 1312.8 | G47: 1312.8 | H47: 1312.8 | I47: 1312.8 | J47: 1312.8 | K47: 1312.8 | L47: 1312.8 | M47: =1312.8*[2]Premissas!B4+'Orçamento 2026'!L47 -> 1509.72 | N47: =M47 -> 1509.72 | O47: =N47 -> 1509.72
A48: ISS Trimestral | B48: =SUM(D48:O48) -> 6400 | D48: 1600 | G48: 1600 | J48: 1600 | M48: 1600
A49: Seguro de vida | B49: =SUM(D49:O49) -> 0
A50: Vale Refeição | B50: =SUM(D50:O50) -> 0
A51: Vale Transporte | B51: =SUM(D51:O51) -> 0
A52: Participação/comissão/repasse - Economico | B52: =SUM(D52:O52) -> 0
A53: Custo equipe - Arbitragem e Compliance | B53: =D53+E53+F53+G53+H53+I53+J53+K53+L53+M53+N53+O53 -> 607970.16 | D53: =SUM(D54:D68) -> 62184.36 | E53: =SUM(E54:E68) -> 60584.36 | F53: =SUM(F54:F68) -> 47967.38 | G53: =SUM(G54:G68) -> 49567.38 | H53: =SUM(H54:H68) -> 47967.38 | I53: =SUM(I54:I68) -> 47967.38 | J53: =SUM(J54:J68) -> 49567.38 | K53: =SUM(K54:K68) -> 47967.38 | ... O53: =SUM(O54:O68) -> 48209.927
A54: Martim Della Valle - Distribuição Mensal Fixa | B54: =SUM(D54:O54) -> 280548 | D54: ='[2]Tabela 2025 2026'!Q15 -> 23379 | E54: =D54 -> 23379 | F54: =E54 -> 23379 | G54: =F54 -> 23379 | H54: =G54 -> 23379 | I54: =H54 -> 23379 | J54: =I54 -> 23379 | K54: =J54 -> 23379 | L54: =K54 -> 23379 | ... O54: =N54 -> 23379
A55: Martim Della Valle - Pro labore | B55: =SUM(D55:O55) -> 19452 | D55: ='[2]Tabela 2025 2026'!M15 -> 1621 | E55: =D55 -> 1621 | F55: =E55 -> 1621 | G55: =F55 -> 1621 | H55: =G55 -> 1621 | I55: =H55 -> 1621 | J55: =I55 -> 1621 | K55: =J55 -> 1621 | L55: =K55 -> 1621 | ... O55: =N55 -> 1621
A56: Felipe Sartório de Melo - Distribuição Mensal Fixa | B56: =SUM(D56:O56) -> 160912.8 | D56: ='[2]Tabela 2025 2026'!Q8 -> 13409.4 | E56: =D56 -> 13409.4 | F56: =E56 -> 13409.4 | G56: =F56 -> 13409.4 | H56: =G56 -> 13409.4 | I56: =H56 -> 13409.4 | J56: =I56 -> 13409.4 | K56: =J56 -> 13409.4 | L56: =K56 -> 13409.4 | ... O56: =N56 -> 13409.4
A57: Felipe Sartório de Melo - Pro Labore | B57: =SUM(D57:O57) -> 19452 | D57: ='[2]Tabela 2025 2026'!M8 -> 1621 | E57: =D57 -> 1621 | F57: =E57 -> 1621 | G57: =F57 -> 1621 | H57: =G57 -> 1621 | I57: =H57 -> 1621 | J57: =I57 -> 1621 | K57: =J57 -> 1621 | L57: =K57 -> 1621 | ... O57: =N57 -> 1621
A58: Felipe Sartório de Melo - Convenio Medico | B58: =SUM(D58:O58) -> 20131.401 | D58: 1616.98 | E58: 1616.98 | F58: 1616.98 | G58: 1616.98 | H58: 1616.98 | I58: 1616.98 | J58: 1616.98 | K58: 1616.98 | L58: 1616.98 | M58: =1616.98*[2]Premissas!B4+'Orçamento 2026'!L58 -> 1859.527 | N58: =M58 -> 1859.527 | O58: =N58 -> 1859.527
A59: Felipe Sartório de Melo - Reajuste de Distribuição Mensal Fixa | B59: =SUM(D59:O59) -> 0
A60: Joao | B60: =SUM(D60:O60) -> 18758 | D60: =11000-D61 -> 9379 | E60: =D60 -> 9379
A61: Joao | B61: =SUM(D61:O61) -> 3242 | D61: 1621 | E61: =D61 -> 1621
A62: Joao | B62: =SUM(D62:O62) -> 3233.96 | D62: 1616.98 | E62: 1616.98
A63: Emillly | B63: =SUM(D63:O63) -> 56322 | D63: =6320-D64 -> 4699 | E63: =6320-E64 -> 4698 | F63: =6320-F64 -> 4697 | G63: =6320-G64 -> 4696 | H63: =6320-H64 -> 4695 | I63: =6320-I64 -> 4694 | J63: =6320-J64 -> 4693 | K63: =6320-K64 -> 4692 | ... O63: =6320-O64 -> 4688
A64: Emillly | B64: =SUM(D64:O64) -> 19518 | D64: 1621 | E64: 1622 | F64: 1623 | G64: 1624 | H64: 1625 | I64: 1626 | J64: 1627 | K64: 1628 | L64: 1629 | M64: 1630 | N64: 1631 | O64: 1632
A65: ISS Trimestral | B65: =SUM(D65:O65) -> 6400 | D65: 1600 | G65: 1600 | J65: 1600 | M65: 1600
A66: Seguro de vida | B66: =SUM(D66:O66) -> 0
A67: Vale Refeição | B67: =SUM(D67:O67) -> 0
A68: Vale Transporte | B68: =SUM(D68:O68) -> 0
A69: Participação/comissão/repasse - Arbitragem | B69: =SUM(D69:O69) -> 0
A70: Despesas para Clientes | B70: =D70+E70+F70+G70+H70+I70+J70+K70+L70+M70+N70+O70 -> 0 | D70: =SUM(D71:D72) -> 0 | E70: =SUM(E71:E72) -> 0 | F70: =SUM(F71:F72) -> 0 | G70: =SUM(G71:G72) -> 0 | H70: =SUM(H71:H72) -> 0 | I70: =SUM(I71:I72) -> 0 | J70: =SUM(J71:J72) -> 0 | K70: =SUM(K71:K72) -> 0 | ... O70: =SUM(O71:O72) -> 0
A71: Não Reembolsáveis | B71: =SUM(D71:O71) -> 0
A72: Reembolsáveis | B72: =SUM(D72:O72) -> 0
A73: Ocupação | B73: =D73+E73+F73+G73+H73+I73+J73+K73+L73+M73+N73+O73 -> 410635.68 | D73: =SUM(D74:D79) -> 27197.48 | E73: =SUM(E74:E79) -> 34236.38 | F73: =SUM(F74:F79) -> 34236.38 | G73: =SUM(G74:G79) -> 34236.38 | H73: =SUM(H74:H79) -> 34236.38 | I73: =SUM(I74:I79) -> 35213.24 | J73: =SUM(J74:J79) -> 35213.24 | K73: =SUM(K74:K79) -> 35213.24 | ... O73: =SUM(O74:O79) -> 35213.24
A74: Aluguel | B74: =SUM(D74:O74) -> 267334.02 | D74: =26385-4677 -> 21708 | E74: =26385-4677 -> 21708 | F74: =26385-4677 -> 21708 | G74: =26385-4677 -> 21708 | H74: =26385-4677 -> 21708 | I74: =H74*[2]Premissas!B3+H74 -> 22684.86 | J74: =I74 -> 22684.86 | K74: =I74 -> 22684.86 | L74: =K74 -> 22684.86 | M74: =L74 -> 22684.86 | N74: =M74 -> 22684.86 | O74: =N74 -> 22684.86
A75: Condomínio | B75: =SUM(D75:O75) -> 54473.76 | D75: =4344*[2]Premissas!B3+4344 -> 4539.48 | E75: =D75 -> 4539.48 | F75: =E75 -> 4539.48 | G75: =F75 -> 4539.48 | H75: =G75 -> 4539.48 | I75: =H75 -> 4539.48 | J75: =I75 -> 4539.48 | K75: =J75 -> 4539.48 | L75: =K75 -> 4539.48 | ... O75: =N75 -> 4539.48
A76: Cameras Ed. Lacerda | B76: =SUM(D76:O76) -> 0
A77: Energia | B77: =SUM(D77:O77) -> 11400 | D77: 950 | E77: 950 | F77: 950 | G77: 950 | H77: 950 | I77: 950 | J77: 950 | K77: 950 | L77: 950 | M77: 950 | N77: 950 | O77: 950
A78: IPTU | B78: =SUM(D78:O78) -> 77427.9 | E78: =6399*[2]Premissas!B5+6399 -> 7038.9 | F78: =E78 -> 7038.9 | G78: =F78 -> 7038.9 | H78: =G78 -> 7038.9 | I78: =H78 -> 7038.9 | J78: =I78 -> 7038.9 | K78: =J78 -> 7038.9 | L78: =K78 -> 7038.9 | M78: =L78 -> 7038.9 | ... O78: =N78 -> 7038.9
A79: Seguro Locação | B79: =SUM(D79:O79) -> 0
A80: Telecomunicações | B80: =D80+E80+F80+G80+H80+I80+J80+K80+L80+M80+N80+O80 -> 10127.402 | D80: =SUM(D81:D82) -> 890 | E80: =SUM(E81:E82) -> 839.7638 | F80: =SUM(F81:F82) -> 839.7638 | G80: =SUM(G81:G82) -> 839.7638 | H80: =SUM(H81:H82) -> 839.7638 | I80: =SUM(I81:I82) -> 839.7638 | J80: =SUM(J81:J82) -> 839.7638 | K80: =SUM(K81:K82) -> 839.7638 | ... O80: =SUM(O81:O82) -> 839.7638
A81: Internet | B81: =SUM(D81:O81) -> 9286.1204 | D81: 810 | E81: 770.5564 | F81: 770.5564 | G81: 770.5564 | H81: 770.5564 | I81: 770.5564 | J81: 770.5564 | K81: 770.5564 | L81: 770.5564 | M81: 770.5564 | N81: 770.5564 | O81: 770.5564
A82: Telefonia Fixa | B82: =SUM(D82:O82) -> 841.2814 | D82: 80 | E82: 69.2074 | F82: 69.2074 | G82: 69.2074 | H82: 69.2074 | I82: 69.2074 | J82: 69.2074 | K82: 69.2074 | L82: 69.2074 | M82: 69.2074 | N82: 69.2074 | O82: 69.2074
A83: Despesas Gerais | B83: =D83+E83+F83+G83+H83+I83+J83+K83+L83+M83+N83+O83 -> 74921.85 | D83: =SUM(D84:D96) -> 7255 | E83: =SUM(E84:E96) -> 5505 | F83: =SUM(F84:F96) -> 5742.205 | G83: =SUM(G84:G96) -> 7292.205 | H83: =SUM(H84:H96) -> 5742.205 | I83: =SUM(I84:I96) -> 5683.605 | J83: =SUM(J84:J96) -> 7333.605 | K83: =SUM(K84:K96) -> 5683.605 | ... O83: =SUM(O84:O96) -> 5783.605
A84: Alteração Contrato Social | B84: =SUM(D84:O84) -> 3200 | D84: 800 | G84: 800 | J84: 800 | M84: 800
A85: Cartório | B85: =SUM(D85:O85) -> 0
A86: Cópias / Gráfica | B86: =SUM(D86:O86) -> 1200 | D86: 100 | E86: 100 | F86: 100 | G86: 100 | H86: 100 | I86: 100 | J86: 100 | K86: 100 | L86: 100 | M86: 100 | N86: 100 | O86: 100
A87: Correio | B87: =SUM(D87:O87) -> 1200 | D87: 100 | E87: 100 | F87: 100 | G87: 100 | H87: 100 | I87: 100 | J87: 100 | K87: 100 | L87: 100 | M87: 100 | N87: 100 | O87: 100
A88: Estacionamento (clientes) | B88: =SUM(D88:O88) -> 200 | D88: 50 | G88: 50 | J88: 50 | M88: 50
A89: Higiene e Copa | B89: =SUM(D89:O89) -> 6000 | D89: 500 | E89: 500 | F89: 500 | G89: 500 | H89: 500 | I89: 500 | J89: 500 | K89: 500 | L89: 500 | M89: 500 | N89: 500 | O89: 500
A90: Limpeza e Copeira | B90: =SUM(D90:O90) -> 37960.05 | D90: 3049 | E90: 3049 | F90: =E90*[2]Premissas!B3+'Orçamento 2026'!D90 -> 3186.205 | G90: =F90 -> 3186.205 | H90: =G90 -> 3186.205 | I90: =H90 -> 3186.205 | J90: =I90 -> 3186.205 | K90: =J90 -> 3186.205 | L90: =K90 -> 3186.205 | M90: =L90 -> 3186.205 | N90: =M90 -> 3186.205 | O90: =N90 -> 3186.205
A91: Manutenção ar condicionado | B91: =SUM(D91:O91) -> 11329.8 | D91: 920 | E91: 920 | F91: 920 | G91: 920 | H91: 920 | I91: =H91*[2]Premissas!B3+'Orçamento 2026'!H91 -> 961.4 | J91: =I91 -> 961.4 | K91: =J91 -> 961.4 | L91: =K91 -> 961.4 | M91: =L91 -> 961.4 | N91: =M91 -> 961.4 | O91: =N91 -> 961.4
A92: Manutenção do Escritório | B92: =SUM(D92:O92) -> 2000 | D92: 500 | G92: 500 | J92: 500 | M92: 500
A93: Manutenção do Jardim | B93: =SUM(D93:O93) -> 10032 | D93: 836 | E93: 836 | F93: 836 | G93: 836 | H93: 836 | I93: 836 | J93: 836 | K93: 836 | L93: 836 | M93: 836 | N93: 836 | O93: 836
A94: Material de Escritório | B94: =SUM(D94:O94) -> 1200 | D94: 300 | G94: 300 | J94: 300 | M94: 300
A95: Motoboy | B95: =SUM(D95:O95) -> 600 | D95: 100 | F95: 100 | H95: 100 | L95: 100 | N95: 100 | O95: 100
A96: Táxi | B96: =SUM(D96:O96) -> 0
A97: Consultoria | B97: =SUM(B98:B102) -> 244264.88 | D97: =SUM(D98:D102) -> 23240.8 | E97: =SUM(E98:E102) -> 23035.8 | F97: =SUM(F98:F102) -> 22815.8 | G97: =SUM(G98:G102) -> 18355.8 | H97: =SUM(H98:H102) -> 18055.8 | I97: =SUM(I98:I102) -> 18705.8 | J97: =SUM(J98:J102) -> 18480.8 | K97: =SUM(K98:K102) -> 19255.8 | ... O97: =SUM(O98:O102) -> 22772.561
A98: Consultoria Adm. e Financeira | B98: =SUM(D98:O98) -> 178454.88 | D98: 14705.8 | E98: 14705.8 | F98: 14705.8 | G98: 14705.8 | H98: 14705.8 | I98: 14705.8 | J98: 14705.8 | K98: 14705.8 | L98: 14705.8 | M98: =L98*[2]Premissas!B3+'Orçamento 2026'!L98 -> 15367.561 | N98: =M98 -> 15367.561 | O98: =N98 -> 15367.561
A99: Contabilidade BPO | B99: =SUM(D99:O99) -> 14280 | D99: 4760 | E99: 4760 | F99: 4760
A100: Contabilidade | Taxas e Obrigações Fiscais | B100: =SUM(D100:O100) -> 40200 | D100: 3350 | E100: 3350 | F100: 3350 | G100: 3350 | H100: 3350 | I100: 3350 | J100: 3350 | K100: 3350 | L100: 3350 | M100: 3350 | N100: 3350 | O100: 3350
...

Sheet Base_Resultado Mensal_V2
A2: Resultado Financeiro 2025 | B2: ANUAL | C2: Janeiro | D2: Fevereiro | E2: Março | F2: Abril | G2: Maio | H2: Junho | I2: Julho | J2: Agosto | K2: Setembro | L2: Outubro | M2: Novembro | N2: Dezembro
A3: Movimentação de Entradas | C3: =SUM(C4:C4) -> 279821.07 | D3: =SUM(D4:D4) -> 319233.58 | E3: =SUM(E4:E4) -> 0 | F3: =SUM(F4:F4) -> 0 | G3: =SUM(G4:G4) -> 0 | H3: =SUM(H4:H4) -> 0 | I3: =SUM(I4:I4) -> 0 | J3: =SUM(J4:J4) -> 0 | ... N3: =SUM(N4:N4) -> 0
A4: Receita de honorários | B4: =SUM(C4:N4) -> 599054.65 | C4: 279821.07 | D4: 319233.58 | O4: =C4+D4+E4+F4+G4+H4+I4+J4+K4+L4+M4+N4 -> 599054.65
A5: Custo equipe - Contencioso | B5: =SUM(C5:N5) -> 149918.66 | C5: =SUM(C6:C27) -> 73576.315 | D5: =SUM(D6:D27) -> 76342.345 | E5: =SUM(E6:E27) -> 0 | F5: =SUM(F6:F27) -> 0 | G5: =SUM(G6:G27) -> 0 | H5: =SUM(H6:H27) -> 0 | I5: =SUM(I6:I27) -> 0 | J5: =SUM(J6:J27) -> 0 | ... N5: =SUM(N6:N27) -> 0 | O5: =C5+D5+E5+F5+G5+H5+I5+J5+K5+L5+M5+N5 -> 149918.66
A6: Aurelio Marchini Santos - Convenio Medico | B6: =SUM(C6:N6) -> 3182.83 | C6: =3182.83/2 -> 1591.415 | D6: =3182.83/2 -> 1591.415 | O6: =C6+D6+E6+F6+G6+H6+I6+J6+K6+L6+M6+N6 -> 3182.83
A7: Aurelio Marchini Santos - Distribuição Mensal Fixa | B7: =SUM(C7:N7) -> 23379 | C7: =12500-C8 -> 11689.5 | D7: =12500-D8 -> 11689.5 | O7: =C7+D7+E7+F7+G7+H7+I7+J7+K7+L7+M7+N7 -> 23379
A8: Aurelio Marchini Santos- Pro labore | B8: =SUM(C8:N8) -> 1621 | C8: 810.5 | D8: 810.5 | O8: =C8+D8+E8+F8+G8+H8+I8+J8+K8+L8+M8+N8 -> 1621
A9: Aurelio Marchini Santos- AASP | B9: =SUM(C9:N9) -> 54.35 | D9: =108.7/2 -> 54.35
A10: Beatriz Baes Xavier - Convenio Medico | B10: =SUM(C10:N10) -> 2538.92 | C10: 1269.46 | D10: 1269.46 | O10: =C10+D10+E10+F10+G10+H10+I10+J10+K10+L10+M10+N10 -> 2538.92
A11: Beatriz Baes Xavier - Despesas Extras - Cartao Predio | B11: =SUM(C11:N11) -> 0 | O11: =C11+D11+E11+F11+G11+H11+I11+J11+K11+L11+M11+N11 -> 0
A12: Beatriz Baes Xavier - Distribuição Mensal Fixa | B12: =SUM(C12:N12) -> 14556.4 | C12: =8640-C13 -> 7019 | D12: =9158.4-D13 -> 7537.4 | O12: =C12+D12+E12+F12+G12+H12+I12+J12+K12+L12+M12+N12 -> 14556.4
A13: Beatriz Baes Xavier - Pro Labore | B13: =SUM(C13:N13) -> 3242 | C13: 1621 | D13: 1621 | O13: =C13+D13+E13+F13+G13+H13+I13+J13+K13+L13+M13+N13 -> 3242
A14: Beatriz Baes Xavier - Reajuste de Distribuição Mensal Fixa | B14: =SUM(C14:N14) -> 518.4 | D14: 518.4 | O14: =C14+D14+E14+F14+G14+H14+I14+J14+K14+L14+M14+N14 -> 518.4
A15: Daniel Costa Caselta - Convenio Medico | B15: =SUM(C15:N15) -> 3472.28 | C15: 1736.14 | D15: 1736.14 | O15: =C15+D15+E15+F15+G15+H15+I15+J15+K15+L15+M15+N15 -> 3472.28
A16: Daniel Costa Caselta - Distribuição Mensal Fixa | B16: =SUM(C16:N16) -> 46758 | C16: =25000-C17 -> 23379 | D16: =25000-D17 -> 23379 | O16: =C16+D16+E16+F16+G16+H16+I16+J16+K16+L16+M16+N16 -> 46758
A17: Daniel Costa Caselta - Pro labore | B17: =SUM(C17:N17) -> 3242 | C17: 1621 | D17: 1621 | O17: =C17+D17+E17+F17+G17+H17+I17+J17+K17+L17+M17+N17 -> 3242
A18: Daniel Costa Caselta - AASP | B18: =SUM(C18:N18) -> 206.4 | C18: 97.7 | D18: 108.7 | O18: =C18+D18+E18+F18+G18+H18+I18+J18+K18+L18+M18+N18 -> 206.4
A19: Isabel de Almeida Rego Campinho - Convenio Medico | B19: =SUM(C19:N19) -> 3128.16 | C19: 1564.08 | D19: 1564.08 | O19: =C19+D19+E19+F19+G19+H19+I19+J19+K19+L19+M19+N19 -> 3128.16
A20: Isabel de Almeida Rego Campinho - Distribuição Mensal Fixa | B20: =SUM(C20:N20) -> 29644 | C20: =15660-C21 -> 14039 | D20: =17226-D21 -> 15605 | O20: =C20+D20+E20+F20+G20+H20+I20+J20+K20+L20+M20+N20 -> 29644
A21: Isabel de Almeida Rego Campinho - Pro Labore | B21: =SUM(C21:N21) -> 3242 | C21: 1621 | D21: 1621 | O21: =C21+D21+E21+F21+G21+H21+I21+J21+K21+L21+M21+N21 -> 3242
A22: Isabel de Almeida Rego Campinho - Reajuste de Distribuição Mensal Fixa | B22: =SUM(C22:N22) -> 1566 | D22: 1566 | O22: =C22+D22+E22+F22+G22+H22+I22+J22+K22+L22+M22+N22 -> 1566
A23: João Victor Santos de Oliveira - Bolsa auxilio / IR Estagiários | B23: =SUM(C23:N23) -> 5600 | C23: 2800 | D23: 2800 | O23: =C23+D23+E23+F23+G23+H23+I23+J23+K23+L23+M23+N23 -> 5600
A24: João Victor Santos de Oliveira - Seguro de Vida | B24: =SUM(C24:N24) -> 0 | O24: =C24+D24+E24+F24+G24+H24+I24+J24+K24+L24+M24+N24 -> 0
A25: ISS Trimestral | B25: =SUM(C25:N25) -> 1719.72 | C25: =382.16*4+191.08 -> 1719.72 | O25: =C25+D25+E25+F25+G25+H25+I25+J25+K25+L25+M25+N25 -> 1719.72
A26: Vale Refeição | B26: =SUM(C26:N26) -> 1844 | C26: 829.8 | D26: 1014.2 | O26: =C26+D26+E26+F26+G26+H26+I26+J26+K26+L26+M26+N26 -> 1844
A27: Vale Transporte | B27: =SUM(C27:N27) -> 403.2 | C27: 168 | D27: 235.2 | O27: =C27+D27+E27+F27+G27+H27+I27+J27+K27+L27+M27+N27 -> 403.2
A28: Participação/Comissão - Contencioso | B28: =SUM(C28:N28) -> 0 | O28: =C28+D28+E28+F28+G28+H28+I28+J28+K28+L28+M28+N28 -> 0
A29: Repasse - Contencioso | B29: =SUM(C29:N29) -> 0 | O29: =C29+D29+E29+F29+G29+H29+I29+J29+K29+L29+M29+N29 -> 0
A30: Custo equipe - Econômico | B30: =SUM(B31:B56) -> 157817.78 | C30: =SUM(C31:C55) -> 76041.035 | D30: =SUM(D31:D55) -> 80276.745 | E30: =SUM(E31:E55) -> 0 | F30: =SUM(F31:F55) -> 0 | G30: =SUM(G31:G55) -> 0 | H30: =SUM(H31:H55) -> 0 | I30: =SUM(I31:I55) -> 0 | J30: =SUM(J31:J55) -> 0 | ... N30: =SUM(N31:N55) -> 0 | O30: =C30+D30+E30+F30+G30+H30+I30+J30+K30+L30+M30+N30 -> 156317.78
A31: Andrielly da Silva Gonsalves - Convenio Medico | B31: =SUM(C31:N31) -> 1834.38 | C31: 1269.46 | D31: 564.92 | O31: =C31+D31+E31+F31+G31+H31+I31+J31+K31+L31+M31+N31 -> 1834.38
A32: Andrielly da Silva Gonsalves - Distribuição Mensal Fixa | B32: =SUM(C32:N32) -> 7678 | C32: =5200-C33 -> 3579 | D32: =5720-D33 -> 4099 | O32: =C32+D32+E32+F32+G32+H32+I32+J32+K32+L32+M32+N32 -> 7678
A33: Andrielly da Silva Gonsalves - Pro Labore | B33: =SUM(C33:N33) -> 3242 | C33: 1621 | D33: 1621 | O33: =C33+D33+E33+F33+G33+H33+I33+J33+K33+L33+M33+N33 -> 3242
A34: Andrielly da Silva Gonsalves - Subsidio de Pós | B34: =SUM(C34:N34) -> 3018 | D34: =1509+1509 -> 3018 | O34: =C34+D34+E34+F34+G34+H34+I34+J34+K34+L34+M34+N34 -> 3018
A35: Andrielly da Silva Gonsalves - Reajuste de Distribuição Mensal Fixa | B35: =SUM(C35:N35) -> 520 | D35: 520 | O35: =C35+D35+E35+F35+G35+H35+I35+J35+K35+L35+M35+N35 -> 520
A36: Aurelio Marchini Santos - AASP | B36: =SUM(C36:N36) -> 152.05 | C36: 97.7 | D36: =108.7/2 -> 54.35 | O36: =C36+D36+E36+F36+G36+H36+I36+J36+K36+L36+M36+N36 -> 152.05
A37: Aurelio Marchini Santos - Convenio Medico | B37: =SUM(C37:N37) -> 3182.83 | C37: =3182.83/2 -> 1591.415 | D37: =3182.83/2 -> 1591.415 | O37: =C37+D37+E37+F37+G37+H37+I37+J37+K37+L37+M37+N37 -> 3182.83
A38: Aurelio Marchini Santos - Distribuição Mensal Fixa | B38: =SUM(C38:N38) -> 23379 | C38: =12500-C39 -> 11689.5 | D38: =12500-D39 -> 11689.5 | O38: =C38+D38+E38+F38+G38+H38+I38+J38+K38+L38+M38+N38 -> 23379
A39: Aurelio Marchini Santos- Pro labore | B39: =SUM(C39:N39) -> 1621 | C39: 810.5 | D39: 810.5 | O39: =C39+D39+E39+F39+G39+H39+I39+J39+K39+L39+M39+N39 -> 1621
A40: Bruno Micalli Pedrinelli - Convenio Medico | B40: =SUM(C40:N40) -> 1834.38 | C40: 1269.46 | D40: 564.92 | O40: =C40+D40+E40+F40+G40+H40+I40+J40+K40+L40+M40+N40 -> 1834.38
A41: Bruno Micalli Pedrinelli - Distribuição Mensal Fixa | B41: =SUM(C41:N41) -> 15040.88 | C41: =8624-C42 -> 7003 | D41: =9658.88-D42 -> 8037.88 | O41: =C41+D41+E41+F41+G41+H41+I41+J41+K41+L41+M41+N41 -> 15040.88
A42: Bruno Micalli Pedrinelli - Pro Labore | B42: =SUM(C42:N42) -> 3242 | C42: 1621 | D42: 1621 | O42: =C42+D42+E42+F42+G42+H42+I42+J42+K42+L42+M42+N42 -> 3242
A43: Bruno Micalli Pedrinelli - Reajuste de Distribuição Mensal Fixa | B43: =SUM(C43:N43) -> 1034.38 | D43: 1034.38 | O43: =C43+D43+E43+F43+G43+H43+I43+J43+K43+L43+M43+N43 -> 1034.38
A44: Elisa Hime Funari - Convenio Medico | B44: =SUM(C44:N44) -> 4244.6 | C44: 2122.3 | D44: 2122.3 | O44: =C44+D44+E44+F44+G44+H44+I44+J44+K44+L44+M44+N44 -> 4244.6
A45: Elisa Hime Funari - Distribuição Mensal Fixa | B45: =SUM(C45:N45) -> 22758 | C45: =12500-C46 -> 10879 | D45: =13500-D46 -> 11879 | O45: =C45+D45+E45+F45+G45+H45+I45+J45+K45+L45+M45+N45 -> 22758
A46: Elisa Hime Funari - Pro Labore | B46: =SUM(C46:N46) -> 3242 | C46: 1621 | D46: 1621 | O46: =C46+D46+E46+F46+G46+H46+I46+J46+K46+L46+M46+N46 -> 3242
A47: Elisa Hime Funari - Reajuste de Distribuição Mensal Fixa | B47: =SUM(C47:N47) -> 1000 | D47: 1000 | O47: =C47+D47+E47+F47+G47+H47+I47+J47+K47+L47+M47+N47 -> 1000
A48: Ricardo Franco Botelho - Convenio Medico | B48: =SUM(C48:N48) -> 5783.31 | C48: 2355.73 | D48: 3427.58 | O48: =C48+D48+E48+F48+G48+H48+I48+J48+K48+L48+M48+N48 -> 5783.31
A49: Ricardo Franco Botelho - Distribuição Mensal Fixa | B49: =SUM(C49:N49) -> 46758 | C49: =25000-C50 -> 23379 | D49: =25000-D50 -> 23379 | O49: =C49+D49+E49+F49+G49+H49+I49+J49+K49+L49+M49+N49 -> 46758
A50: Ricardo Franco Botelho - Pro labore | B50: =SUM(C50:N50) -> 3242 | C50: 1621 | D50: 1621 | O50: =C50+D50+E50+F50+G50+H50+I50+J50+K50+L50+M50+N50 -> 3242
A51: Victoria Malta Corradini - Convenio Medico | B51: =SUM(C51:N51) -> 1409.09 | C51: 1409.09 | O51: =C51+D51+E51+F51+G51+H51+I51+J51+K51+L51+M51+N51 -> 1409.09
A52: ISS - Trimestral | B52: =SUM(C52:N52) -> 2101.88 | C52: =382.16*5+191.08 -> 2101.88 | O52: =C52+D52+E52+F52+G52+H52+I52+J52+K52+L52+M52+N52 -> 2101.88
A53: Seguro de Vida | B53: =SUM(C53:N53) -> 0 | O53: =C53+D53+E53+F53+G53+H53+I53+J53+K53+L53+M53+N53 -> 0
A54: Vale Refeição | B54: =SUM(C54:N54) -> 0 | O54: =C54+D54+E54+F54+G54+H54+I54+J54+K54+L54+M54+N54 -> 0
A55: Vale Transporte | B55: =SUM(C55:N55) -> 0 | O55: =C55+D55+E55+F55+G55+H55+I55+J55+K55+L55+M55+N55 -> 0
A56: Participação/comissão - Economico | B56: =SUM(C56:N56) -> 1500 | D56: 1500 | O56: =C56+D56+E56+F56+G56+H56+I56+J56+K56+L56+M56+N56 -> 1500
A57: Repasse - Economico | B57: =SUM(C57:N57) -> 0 | O57: =C57+D57+E57+F57+G57+H57+I57+J57+K57+L57+M57+N57 -> 0
A58: Custo equipe - Arbitragem e Compliance | B58: =SUM(C58:N58) -> 123807.51 | C58: =SUM(C59:C74) -> 62013.17 | D58: =SUM(D59:D74) -> 61794.34 | E58: =SUM(E59:E74) -> 0 | F58: =SUM(F59:F74) -> 0 | G58: =SUM(G59:G74) -> 0 | H58: =SUM(H59:H74) -> 0 | I58: =SUM(I59:I74) -> 0 | J58: =SUM(J59:J74) -> 0 | ... M58: =SUM(M59:M74) -> 0 | N58: =SUM(N59:N76) -> 0 | O58: =C58+D58+E58+F58+G58+H58+I58+J58+K58+L58+M58+N58 -> 123807.51
A59: Emilly Kauany Martins Calixto - Ajuda de Custo VR | B59: =SUM(C59:N59) -> 0
A60: Emilly Kauany Martins Calixto - Convenio medico | B60: =SUM(C60:N60) -> 2538.46 | C60: 1269 | D60: 1269.46
A61: Emilly Kauany Martins Calixto - Distribuição Mensal Fixa | B61: =SUM(C61:N61) -> 9398 | C61: =6320-C62 -> 4699 | D61: =6320-D62 -> 4699
A62: Emilly Kauany Martins Calixto - Pro Labore | B62: =SUM(C62:N62) -> 3242 | C62: 1621 | D62: 1621
A63: Felipe Sartório de Melo - Convenio Medico | B63: =SUM(C63:N63) -> 3128.16 | C63: 1564.08 | D63: 1564.08 | O63: =C63+D63+E63+F63+G63+H63+I63+J63+K63+L63+M63+N63 -> 3128.16
A64: Felipe Sartório de Melo - Distribuição Mensal Fixa | B64: =SUM(C64:N64) -> 25208.4 | C64: =13420-C65 -> 11799 | D64: =15030.4-D65 -> 13409.4 | O64: =C64+D64+E64+F64+G64+H64+I64+J64+K64+L64+M64+N64 -> 25208.4
A65: Felipe Sartório de Melo - Pro Labore | B65: =SUM(C65:N65) -> 3242 | C65: 1621 | D65: 1621 | O65: =C65+D65+E65+F65+G65+H65+I65+J65+K65+L65+M65+N65 -> 3242
A66: Felipe Sartório de Melo - Reajuste de Distribuição Mensal Fixa | B66: =SUM(C66:N66) -> 1610.4 | D66: 1610.4 | O66: =C66+D66+E66+F66+G66+H66+I66+J66+K66+L66+M66+N66 -> 1610.4
A67: Joao Gabriel Previero de Arruda Sampaio - Convenio Medico | B67: =SUM(C67:N67) -> 1911.45 | C67: 1911.45
A68: Joao Gabriel Previero de Arruda Sampaio - Distribuição Mensal Fixa | B68: =SUM(C68:N68) -> 18758 | C68: =11000-C69 -> 9379 | D68: =11000-D69 -> 9379
A69: Joao Gabriel Previero de Arruda Sampaio - | B69: =SUM(C69:N69) -> 3242 | C69: 1621 | D69: 1621
A70: Martim Della Valle - Distribuição Mensal Fixa | B70: =SUM(C70:N70) -> 46758 | C70: =25000-C71 -> 23379 | D70: =25000-D71 -> 23379 | O70: =C70+D70+E70+F70+G70+H70+I70+J70+K70+L70+M70+N70 -> 46758
A71: Martim Della Valle - Pro labore | B71: =SUM(C71:N71) -> 3242 | C71: 1621 | D71: 1621 | O71: =C71+D71+E71+F71+G71+H71+I71+J71+K71+L71+M71+N71 -> 3242
A72: Seguro de Vida | B72: =SUM(C72:N72) -> 0 | O72: =C72+D72+E72+F72+G72+H72+I72+J72+K72+L72+M72+N72 -> 0
A73: Vale Refeição | B73: =SUM(C73:N73) -> 0 | O73: =C73+D73+E73+F73+G73+H73+I73+J73+K73+L73+M73+N73 -> 0
A74: ISS Trimestral | B74: =SUM(C74:N74) -> 1528.64 | C74: =382.16*4 -> 1528.64 | O74: =C74+D74+E74+F74+G74+H74+I74+J74+K74+L74+M74+N74 -> 1528.64
A75: Participação/comissão - Arbitragem | B75: =SUM(C75:N75) -> 0 | O75: =C75+D75+E75+F75+G75+H75+I75+J75+K75+L75+M75+N75 -> 0
A76: Repasse - Arbitragem | B76: =SUM(C76:N76) -> 0 | O76: =C76+D76+E76+F76+G76+H76+I76+J76+K76+L76+M76+N76 -> 0
A77: Despesas para Clientes | B77: =SUM(C77:N77) -> 9762.54 | C77: =SUM(C78:C79) -> 8549.81 | D77: =SUM(D78:D79) -> 1212.73 | E77: =SUM(E78:E79) -> 0 | F77: =SUM(F78:F79) -> 0 | G77: =SUM(G78:G79) -> 0 | H77: =SUM(H78:H79) -> 0 | I77: =SUM(I78:I79) -> 0 | J77: =SUM(J78:J79) -> 0 | ... N77: =SUM(N78:N79) -> 0 | O77: =C77+D77+E77+F77+G77+H77+I77+J77+K77+L77+M77+N77 -> 9762.54
A78: Não Reembolsáveis | B78: =SUM(C78:N78) -> 0 | O78: =C78+D78+E78+F78+G78+H78+I78+J78+K78+L78+M78+N78 -> 0
A79: Reembolsáveis | B79: =SUM(C79:N79) -> 9762.54 | C79: =86.06+3916.04+250.06+3947.65+350 -> 8549.81 | D79: =374.31+800+38.42 -> 1212.73 | O79: =C79+D79+E79+F79+G79+H79+I79+J79+K79+L79+M79+N79 -> 9762.54
A80: Ocupação | B80: =SUM(C80:N80) -> 71743.81 | C80: =SUM(C81:C86) -> 32337.05 | D80: =SUM(D81:D86) -> 39406.76 | E80: =SUM(E81:E86) -> 0 | F80: =SUM(F81:F86) -> 0 | G80: =SUM(G81:G86) -> 0 | H80: =SUM(H81:H86) -> 0 | I80: =SUM(I81:I86) -> 0 | J80: =SUM(J81:J86) -> 0 | ... N80: =SUM(N81:N86) -> 0 | O80: =C80+D80+E80+F80+G80+H80+I80+J80+K80+L80+M80+N80 -> 71743.81
A81: Aluguel | B81: =SUM(C81:N81) -> 52769.26 | C81: 26384.63 | D81: 26384.63 | O81: =C81+D81+E81+F81+G81+H81+I81+J81+K81+L81+M81+N81 -> 52769.26
A82: Condomínio | B82: =SUM(C82:N82) -> 9992 | C82: 4996 | D82: 4996 | O82: =C82+D82+E82+F82+G82+H82+I82+J82+K82+L82+M82+N82 -> 9992
A83: Camera Ed. Lacerda | B83: =SUM(C83:N83) -> 0 | O83: =C83+D83+E83+F83+G83+H83+I83+J83+K83+L83+M83+N83 -> 0
A84: Energia | B84: =SUM(C84:N84) -> 1699.87 | C84: 773.71 | D84: 926.16 | O84: =C84+D84+E84+F84+G84+H84+I84+J84+K84+L84+M84+N84 -> 1699.87
A85: IPTU | B85: =SUM(C85:N85) -> 6916.97 | D85: 6916.97 | O85: =C85+D85+E85+F85+G85+H85+I85+J85+K85+L85+M85+N85 -> 6916.97
A86: Seguro Locação | B86: =SUM(C86:N86) -> 365.71 | C86: 182.71 | D86: 183 | O86: =C86+D86+E86+F86+G86+H86+I86+J86+K86+L86+M86+N86 -> 365.71
A87: Telecomunicações | B87: =SUM(C87:N87) -> 1614.32 | C87: =SUM(C88:C89) -> 807.16 | D87: =SUM(D88:D89) -> 807.16 | E87: =SUM(E88:E89) -> 0 | F87: =SUM(F88:F89) -> 0 | G87: =SUM(G88:G89) -> 0 | H87: =SUM(H88:H89) -> 0 | I87: =SUM(I88:I89) -> 0 | J87: =SUM(J88:J89) -> 0 | ... N87: =SUM(N88:N89) -> 0 | O87: =C87+D87+E87+F87+G87+H87+I87+J87+K87+L87+M87+N87 -> 1614.32
A88: Internet | B88: =SUM(C88:N88) -> 1483.74 | C88: =399.9+184.92+157.05 -> 741.87 | D88: =399.9+184.92+157.05 -> 741.87 | O88: =C88+D88+E88+F88+G88+H88+I88+J88+K88+L88+M88+N88 -> 1483.74
A89: Telefonia Fixa | B89: =SUM(C89:N89) -> 130.58 | C89: 65.29 | D89: 65.29 | O89: =C89+D89+E89+F89+G89+H89+I89+J89+K89+L89+M89+N89 -> 130.58
A90: Despesas Gerais | B90: =SUM(C90:N90) -> 12017.12 | C90: =SUM(C91:C104) -> 6773.44 | D90: =SUM(D91:D104) -> 5243.68 | E90: =SUM(E91:E104) -> 0 | F90: =SUM(F91:F104) -> 0 | G90: =SUM(G91:G104) -> 0 | H90: =SUM(H91:H104) -> 0 | I90: =SUM(I91:I104) -> 0 | J90: =SUM(J91:J104) -> 0 | ... N90: =SUM(N91:N104) -> 0 | O90: =C90+D90+E90+F90+G90+H90+I90+J90+K90+L90+M90+N90 -> 12017.12
A91: Alteração Contrato Social | B91: =SUM(C91:N91) -> 0 | O91: =C91+D91+E91+F91+G91+H91+I91+J91+K91+L91+M91+N91 -> 0
A92: Cartório | B92: =SUM(C92:N92) -> 0 | O92: =C92+D92+E92+F92+G92+H92+I92+J92+K92+L92+M92+N92 -> 0
A93: Cópias / Gráfica | B93: =SUM(C93:N93) -> 0 | O93: =C93+D93+E93+F93+G93+H93+I93+J93+K93+L93+M93+N93 -> 0
A94: Correio | B94: =SUM(C94:N94) -> 0 | O94: =C94+D94+E94+F94+G94+H94+I94+J94+K94+L94+M94+N94 -> 0
A95: Estacionamento (clientes) | B95: =SUM(C95:N95) -> 0 | O95: =C95+D95+E95+F95+G95+H95+I95+J95+K95+L95+M95+N95 -> 0
A96: Limpeza e Copeira - Serviço Terceirizado | B96: =SUM(C96:N96) -> 6098.46 | C96: 3049.23 | D96: 3049.23 | O96: =C96+D96+E96+F96+G96+H96+I96+J96+K96+L96+M96+N96 -> 6098.46
A97: Manutenção ar condicionado | B97: =SUM(C97:N97) -> 1839.52 | C97: 919.76 | D97: 919.76 | O97: =C97+D97+E97+F97+G97+H97+I97+J97+K97+L97+M97+N97 -> 1839.52
A98: Manutenção do Escritório | B98: =SUM(C98:N98) -> 50 | D98: 50 | O98: =C98+D98+E98+F98+G98+H98+I98+J98+K98+L98+M98+N98 -> 50
A99: Manutenção do Jardim | B99: =SUM(C99:N99) -> 1755.6 | C99: 836 | D99: 919.6 | O99: =C99+D99+E99+F99+G99+H99+I99+J99+K99+L99+M99+N99 -> 1755.6
A100: Material de Escritório | B100: =SUM(C100:N100) -> 41.2 | D100: 41.2 | O100: =C100+D100+E100+F100+G100+H100+I100+J100+K100+L100+M100+N100 -> 41.2
A101: Material de Higiene e Copa | B101: =SUM(C101:N101) -> 1259.38 | C101: =216.9+443.9+142.95+191.74 -> 995.49 | D101: =67.3+196.59 -> 263.89 | O101: =C101+D101+E101+F101+G101+H101+I101+J101+K101+L101+M101+N101 -> 1259.38
...

Sheet Areas Sintetico atualizado
A1: DRE 2025 | B1: Janeiro | F1: Fevereiro | O1: 11 | Q1: CHECK
A2: Resultado Institucional | B2: Orçado | C2: Realizado | D2: Variação Mensal | E2: Desvio% | F2: Orçado | G2: Realizado | H2: Variação Mensal | I2: Desvio% | J2: Orçado YTG | K2: Orçado YTD | L2: Realizado | M2: Variação | N2: Variação Mensal | O2: YTG
A3: Faturamento | B3: ='DRE 2026'!C3 -> 671666.67 | C3: 444545.69 | D3: =+C3-B3 -> -227120.98 | E3: =C3/B3 -> 0.66185462 | F3: ='DRE 2026'!D3 -> 671666.67 | G3: 534752.84 | H3: =+G3-F3 -> -136913.83 | I3: =G3/F3 -> 0.79615807 | J3: ='DRE 2026'!B3 -> 8060000 | K3: ='DRE 2026'!C3+'DRE 2026'!D3 -> 1343333.3 | L3: =C3 -> 444545.69 | M3: =L3-K3 -> -898787.65 | N3: =L3/K3 -> 0.33092731 | O3: =J3-L3 -> 7615454.3 | Q3: =C3 -> 444545.69 | R3: =L3-Q3 -> 0
A4: Receita | C4: ='Base_Resultado Mensal_V2'!C4 -> 279821.07 | G4: ='Base_Resultado Mensal_V2'!D4 -> 319233.58 | K4: ='DRE 2026'!C3+'DRE 2026'!D3 -> 1343333.3 | L4: ='Base_Resultado Mensal_V2'!C4+'Base_Resultado Mensal_V2'!D4+'Base_Resultado Mensal_V2'!E4+'Base_Resultado Mensal_V2'!F4+'Base_Resultado Mensal_V2'!G4+'Base_Resultado Mensal_V2'!H4+'Base_Resultado Mensal_V2'!I4+'Base_Resultado Mensal_V2'!J4+'Base_Resultado Mensal_V2'!K4+'Base_Resultado Mensal_V2'!L4+'Base_Resultado Mensal_V2'!M4+'Base_Resultado Mensal_V2'!N4 -> 599054.65 | M4: =L4-K3 -> -744278.69 | Q4: ='Base_Resultado Mensal_V2'!O4 -> 599054.65 | R4: =L4-Q4 -> 0
A5: Despesas | B5: Orçado | C5: Realizado | D5: Variação Mensal | E5: Variação Mensal | F5: Orçado | G5: Realizado | H5: Variação Mensal | I5: Variação Mensal | N5: Variação Mensal
A6: Custos Diretos | B6: =SUM(B7:B11) -> 213417.59 | C6: =SUM(C7:C12) -> 211630.52 | D6: =+B6-C6 -> 1787.07 | F6: =SUM(F7:F11) -> 208717.59 | G6: =SUM(G7:G12) -> 219913.43 | H6: =+F6-G6 -> -11195.84 | J6: =SUM(J7:J11) -> 2403882.6 | K6: =SUM(K7:K11) -> 213417.59 | L6: =L7+L8+L9+L10+L11+L12 -> 211630.52 | M6: =K6-L6 -> 1787.07 | N6: =L6/K6 -> 0.99162642 | O6: =J6-L6 -> 2192252.1 | Q6: =SUM(Q7:Q12) -> 431543.95 | R6: =L6-Q6 -> -219913.43
A7: =+'Base_Resultado Mensal_V2'!A5 -> Custo equipe - Contencioso | B7: ='DRE 2026'!C6 -> 74354.065 | C7: ='Base_Resultado Mensal_V2'!C5 -> 73576.315 | D7: =+B7-C7 -> 777.75 | E7: =C7/B7 -> 0.98953991 | F7: ='DRE 2026'!D6 -> 72754.065 | G7: ='Base_Resultado Mensal_V2'!D5 -> 76342.345 | H7: =+F7-G7 -> -3588.28 | I7: =G7/F7 -> 1.0493207 | J7: ='DRE 2026'!B6 -> 881797.73 | K7: ='DRE 2026'!C6 -> 74354.065 | L7: =C7 -> 73576.315 | M7: =K7-L7 -> 777.75 | N7: =L7/K7 -> 0.98953991 | O7: =J7-L7 -> 808221.42 | Q7: ='Base_Resultado Mensal_V2'!O5 -> 149918.66 | R7: =L7-Q7 -> -76342.345
A8: ='Base_Resultado Mensal_V2'!A28 -> Participação/Comissão - Contencioso | C8: ='Base_Resultado Mensal_V2'!C28+'Base_Resultado Mensal_V2'!C29 -> 0 | G8: ='Base_Resultado Mensal_V2'!D28+'Base_Resultado Mensal_V2'!D29 -> 0 | L8: =C8 -> 0 | Q8: ='Base_Resultado Mensal_V2'!O28+'Base_Resultado Mensal_V2'!O29 -> 0 | R8: =L8-Q8 -> 0
A9: =+'Base_Resultado Mensal_V2'!A30 -> Custo equipe - Econômico | B9: ='DRE 2026'!C7 -> 76879.165 | C9: ='Base_Resultado Mensal_V2'!C30 -> 76041.035 | D9: =+B9-C9 -> 838.13 | E9: =C9/B9 -> 0.98909809 | F9: ='DRE 2026'!D7 -> 75379.165 | G9: ='Base_Resultado Mensal_V2'!D30 -> 80276.745 | H9: =+F9-G9 -> -4897.58 | I9: =G9/F9 -> 1.0649726 | J9: ='DRE 2026'!B7 -> 914114.75 | K9: ='DRE 2026'!C7 -> 76879.165 | L9: =C9 -> 76041.035 | M9: =K9-L9 -> 838.13 | N9: =L9/K9 -> 0.98909809 | O9: =J9-L9 -> 838073.72 | Q9: ='Base_Resultado Mensal_V2'!O30 -> 156317.78 | R9: =L9-Q9 -> -80276.745
A10: ='Base_Resultado Mensal_V2'!A56 -> Participação/comissão - Economico | C10: ='Base_Resultado Mensal_V2'!C28+'Base_Resultado Mensal_V2'!C29 -> 0 | G10: ='Base_Resultado Mensal_V2'!D56+'Base_Resultado Mensal_V2'!D57 -> 1500 | L10: =C10 -> 0 | Q10: ='Base_Resultado Mensal_V2'!O56+'Base_Resultado Mensal_V2'!O57 -> 1500 | R10: =L10-Q10 -> -1500
A11: =+'Base_Resultado Mensal_V2'!A58 -> Custo equipe - Arbitragem e Compliance | B11: ='DRE 2026'!C8 -> 62184.36 | C11: ='Base_Resultado Mensal_V2'!C58 -> 62013.17 | D11: =+B11-C11 -> 171.19 | E11: =C11/B11 -> 0.99724706 | F11: ='DRE 2026'!D8 -> 60584.36 | G11: ='Base_Resultado Mensal_V2'!D58 -> 61794.34 | H11: =+F11-G11 -> -1209.98 | I11: =G11/F11 -> 1.0199718 | J11: ='DRE 2026'!B8 -> 607970.16 | K11: ='DRE 2026'!C8 -> 62184.36 | L11: =C11 -> 62013.17 | M11: =K11-L11 -> 171.19 | N11: =L11/K11 -> 0.99724706 | O11: =J11-L11 -> 545956.99 | Q11: ='Base_Resultado Mensal_V2'!O58 -> 123807.51 | R11: =L11-Q11 -> -61794.34
A12: ='Base_Resultado Mensal_V2'!A75 -> Participação/comissão - Arbitragem | C12: ='Base_Resultado Mensal_V2'!C75+'Base_Resultado Mensal_V2'!C76 -> 0 | G12: ='Base_Resultado Mensal_V2'!D75+'Base_Resultado Mensal_V2'!D76 -> 0 | L12: =C12 -> 0 | Q12: ='Base_Resultado Mensal_V2'!O75+'Base_Resultado Mensal_V2'!O76 -> 0 | R12: =L12-Q12 -> 0
A13: Despesas Indiretas | B13: =SUM(B14:B24) -> 102906.66 | C13: =SUM(C14:C24) -> 104973.54 | D13: =(B13-C13) -> -2066.8767 | F13: =SUM(F14:F24) -> 100790.33 | G13: =SUM(G14:G24) -> 98454.78 | H13: =(F13-G13) -> 2335.5471 | J13: =SUM(J14:J24) -> 1331793.8 | K13: =SUM(K14:K24) -> 102906.66 | L13: =SUM(L14:L24) -> 104973.54 | M13: =K13-L13 -> -2066.8767 | N13: =L13/K13 -> 1.020085 | O13: =J13-L13 -> 1226820.3 | Q13: =SUM(Q14:Q24) -> 202043.58 | R13: =L13-Q13 -> -97070.04
A14: =+'Base_Resultado Mensal_V2'!A80 -> Ocupação | B14: ='DRE 2026'!C10 -> 27197.48 | C14: ='Base_Resultado Mensal_V2'!C80 -> 32337.05 | D14: =+B14-C14 -> -5139.57 | E14: =(C14/B14) -> 1.1889723 | F14: ='DRE 2026'!D10 -> 34236.38 | G14: ='Base_Resultado Mensal_V2'!D80 -> 39406.76 | H14: =+F14-G14 -> -5170.38 | I14: =(G14/F14) -> 1.1510201 | J14: ='DRE 2026'!B10 -> 410635.68 | K14: ='DRE 2026'!C10 -> 27197.48 | L14: =C14 -> 32337.05 | M14: =K14-L14 -> -5139.57 | N14: =L14/K14 -> 1.1889723 | O14: =J14-L14 -> 378298.63 | Q14: ='Base_Resultado Mensal_V2'!B80 -> 71743.81 | R14: =L14-Q14 -> -39406.76
A15: =+'Base_Resultado Mensal_V2'!A87 -> Telecomunicações | B15: ='DRE 2026'!C11 -> 890 | C15: ='Base_Resultado Mensal_V2'!C87 -> 807.16 | D15: =+B15-C15 -> 82.84 | E15: =(C15/B15) -> 0.90692135 | F15: ='DRE 2026'!D11 -> 839.7638 | G15: ='Base_Resultado Mensal_V2'!D87 -> 807.16 | H15: =+F15-G15 -> 32.6038 | I15: =(G15/F15) -> 0.96117504 | J15: ='DRE 2026'!B11 -> 10127.402 | K15: ='DRE 2026'!C11 -> 890 | L15: =C15 -> 807.16 | M15: =K15-L15 -> 82.84 | N15: =L15/K15 -> 0.90692135 | O15: =J15-L15 -> 9320.2418 | Q15: ='Base_Resultado Mensal_V2'!B87 -> 1614.32 | R15: =L15-Q15 -> -807.16
A16: =+'Base_Resultado Mensal_V2'!A90 -> Despesas Gerais | B16: ='DRE 2026'!C12 -> 7255 | C16: ='Base_Resultado Mensal_V2'!C90 -> 6773.44 | D16: =+B16-C16 -> 481.56 | E16: =(C16/B16) -> 0.93362371 | F16: ='DRE 2026'!D12 -> 5505 | G16: ='Base_Resultado Mensal_V2'!D90 -> 5243.68 | H16: =+F16-G16 -> 261.32 | I16: =(G16/F16) -> 0.95253043 | J16: ='DRE 2026'!B12 -> 74921.85 | K16: ='DRE 2026'!C12 -> 7255 | L16: =C16 -> 6773.44 | M16: =K16-L16 -> 481.56 | N16: =L16/K16 -> 0.93362371 | O16: =J16-L16 -> 68148.41 | Q16: ='Base_Resultado Mensal_V2'!B90 -> 12017.12 | R16: =L16-Q16 -> -5243.68
A17: =+'Base_Resultado Mensal_V2'!A105 -> Consultoria | B17: ='DRE 2026'!C13 -> 23240.8 | C17: ='Base_Resultado Mensal_V2'!C105 -> 30035.14 | D17: =+B17-C17 -> -6794.34 | E17: =(C17/B17) -> 1.2923454 | F17: ='DRE 2026'!D13 -> 23035.8 | G17: ='Base_Resultado Mensal_V2'!D105 -> 22509.85 | H17: =+F17-G17 -> 525.95 | I17: =(G17/F17) -> 0.97716815 | J17: ='DRE 2026'!B13 -> 244264.88 | K17: ='DRE 2026'!C13 -> 23240.8 | L17: =C17 -> 30035.14 | M17: =K17-L17 -> -6794.34 | N17: =L17/K17 -> 1.2923454 | O17: =J17-L17 -> 214229.74 | Q17: ='Base_Resultado Mensal_V2'!B105 -> 52544.99 | R17: =L17-Q17 -> -22509.85
A18: =+'Base_Resultado Mensal_V2'!A111 -> Salários Administração | B18: ='DRE 2026'!C14 -> 6426.58 | C18: ='Base_Resultado Mensal_V2'!C111 -> 5139.13 | D18: =+B18-C18 -> 1287.45 | E18: =(C18/B18) -> 0.79966794 | F18: ='DRE 2026'!D14 -> 6776.58 | G18: ='Base_Resultado Mensal_V2'!D111 -> 4807.3 | H18: =+F18-G18 -> 1969.28 | I18: =(G18/F18) -> 0.70939914 | J18: ='DRE 2026'!B14 -> 82659.531 | K18: ='DRE 2026'!C14 -> 6426.58 | L18: =C18 -> 5139.13 | M18: =K18-L18 -> 1287.45 | N18: =L18/K18 -> 0.79966794 | O18: =J18-L18 -> 77520.401 | Q18: ='Base_Resultado Mensal_V2'!B111 -> 9946.43 | R18: =L18-Q18 -> -4807.3
A19: =+'Base_Resultado Mensal_V2'!A119 -> Administrativas | B19: ='DRE 2026'!C15 -> 2996.8033 | C19: ='Base_Resultado Mensal_V2'!C119 -> 4300.03 | D19: =+B19-C19 -> -1303.2267 | E19: =(C19/B19) -> 1.4348723 | F19: ='DRE 2026'!D15 -> 2996.8033 | G19: ='Base_Resultado Mensal_V2'!D119 -> 6892.33 | H19: =+F19-G19 -> -3895.5267 | I19: =(G19/F19) -> 2.299894 | J19: ='DRE 2026'!B15 -> 91084.465 | K19: ='DRE 2026'!C15 -> 2996.8033 | L19: =C19 -> 4300.03 | M19: =K19-L19 -> -1303.2267 | N19: =L19/K19 -> 1.4348723 | O19: =J19-L19 -> 86784.435 | Q19: ='Base_Resultado Mensal_V2'!B119 -> 11192.36 | R19: =L19-Q19 -> -6892.33
A20: ='Base_Resultado Mensal_V2'!A129 -> Taxas / Despesas Financeiras | B20: ='DRE 2026'!C16 -> 0 | C20: ='Base_Resultado Mensal_V2'!C129 -> 0 | D20: =+B20-C20 -> 0 | F20: ='DRE 2026'!D16 -> 0 | G20: ='Base_Resultado Mensal_V2'!D129 -> 0 | H20: =+F20-G20 -> 0 | J20: ='DRE 2026'!B16 -> 0 | K20: ='DRE 2026'!C16 -> 0 | L20: =C20 -> 0 | M20: =K20-L20 -> 0 | O20: =J20-L20 -> 0 | Q20: ='Base_Resultado Mensal_V2'!B129 -> 0 | R20: =L20-Q20 -> 0
A21: =+'Base_Resultado Mensal_V2'!A132 -> Investimentos em Prospecção | B21: ='DRE 2026'!C17 -> 4500 | C21: ='Base_Resultado Mensal_V2'!C132 -> 2702.45 | D21: =+B21-C21 -> 1797.55 | E21: =(C21/B21) -> 0.60054444 | F21: ='DRE 2026'!D17 -> 4500 | G21: ='Base_Resultado Mensal_V2'!D132 -> 1166.75 | H21: =+F21-G21 -> 3333.25 | I21: =(G21/F21) -> 0.25927778 | J21: ='DRE 2026'!B17 -> 96000 | K21: ='DRE 2026'!C17 -> 4500 | L21: =C21 -> 2702.45 | M21: =K21-L21 -> 1797.55 | N21: =L21/K21 -> 0.60054444 | O21: =J21-L21 -> 93297.55 | Q21: ='Base_Resultado Mensal_V2'!B132 -> 2484.46 | R21: =L21-Q21 -> 217.99
A22: ='Base_Resultado Mensal_V2'!A159 -> Endomarketing | B22: ='DRE 2026'!C18 -> 100 | C22: ='Base_Resultado Mensal_V2'!C159 -> 0 | D22: =+B22-C22 -> 100 | E22: =(C22/B22) -> 0 | F22: ='DRE 2026'!D18 -> 100 | G22: ='Base_Resultado Mensal_V2'!D159 -> 0 | H22: =+F22-G22 -> 100 | I22: =(G22/F22) -> 0 | J22: ='DRE 2026'!B18 -> 1200 | K22: ='DRE 2026'!C18 -> 100 | L22: =C22 -> 0 | M22: =K22-L22 -> 100 | N22: =L22/K22 -> 0 | O22: =J22-L22 -> 1200 | Q22: ='Base_Resultado Mensal_V2'!B159 -> 0 | R22: =L22-Q22 -> 0
A23: ='Base_Resultado Mensal_V2'!A153 -> Gestão do Conhecimento | B23: ='DRE 2026'!C19 -> 0 | C23: ='Base_Resultado Mensal_V2'!C153 -> 692.37 | D23: =+B23-C23 -> -692.37 | F23: ='DRE 2026'!D19 -> 0 | G23: ='Base_Resultado Mensal_V2'!D153 -> 0 | H23: =+F23-G23 -> 0 | J23: ='DRE 2026'!B19 -> 2300 | K23: ='DRE 2026'!C19 -> 0 | L23: =C23 -> 692.37 | M23: =K23-L23 -> -692.37 | N23: =L23/K23 -> #DIV/0! | O23: =J23-L23 -> 1607.63 | Q23: ='Base_Resultado Mensal_V2'!B153 -> 692.37 | R23: =L23-Q23 -> 0
A24: =+'Base_Resultado Mensal_V2'!A175 -> Informática | B24: ='DRE 2026'!C20 -> 30300 | C24: ='Base_Resultado Mensal_V2'!C175 -> 22186.77 | D24: =+B24-C24 -> 8113.23 | E24: =(C24/B24) -> 0.73223663 | F24: ='DRE 2026'!D20 -> 22800 | G24: ='Base_Resultado Mensal_V2'!D175 -> 17620.95 | H24: =+F24-G24 -> 5179.05 | I24: =(G24/F24) -> 0.77284868 | J24: ='DRE 2026'!B20 -> 318600 | K24: ='DRE 2026'!C20 -> 30300 | L24: =C24 -> 22186.77 | M24: =K24-L24 -> 8113.23 | N24: =L24/K24 -> 0.73223663 | O24: =J24-L24 -> 296413.23 | Q24: ='Base_Resultado Mensal_V2'!B175 -> 39807.72 | R24: =L24-Q24 -> -17620.95
A25: Resultado Bruto | B25: =B3-B6-B13 -> 355342.42 | C25: =C4-C6-C13 -> -36782.99 | F25: =F3-F6-F13 -> 362158.75 | G25: =G4-G6-G13 -> 865.37 | J25: =J3-J6-J13 -> 4324323.6 | K25: =K3-K6-K13 -> 1027009.1 | L25: =L4-L6-L13 -> 282450.59 | Q25: =Q4-Q6-Q13 -> -34532.88
A26: Margem de bruta | B26: =B25/B3 -> 0.52904578 | C26: =C25/C4 -> -0.13145182 | F26: =F25/F3 -> 0.53919417 | G26: =G25/G4 -> 0.0027107737 | J26: =J25/J3 -> 0.53651657 | K26: =K25/K3 -> 0.76452289 | L26: =L25/L4 -> 0.47149386 | Q26: =Q25/Q4 -> -0.057645625
A27: 0.15
A28: Impostos | B28: ='DRE 2026'!C23 -> 150750 | C28: =C4*$A$27 -> 41973.16 | F28: ='DRE 2026'!D23 -> 150750 | G28: ='Base_Resultado Mensal_V2'!D163 -> 5641.82 | H28: =+F28-G28 -> 145108.18 | J28: ='DRE 2026'!B23 -> 1809000 | K28: ='DRE 2026'!C23 -> 150750 | L28: =C28 -> 41973.16 | R28: =L28-Q28 -> 41973.16
A29: Investimento amortização | B29: ='DRE 2026'!C24 -> 8117 | C29: 8117 | F29: 8117 | G29: =F29 -> 8117 | H29: =+F29-G29 -> 0 | J29: ='DRE 2026'!B24 -> 97404 | K29: ='DRE 2026'!C24 -> 8117 | L29: =C29 -> 8117 | R29: =L29-Q29 -> 8117
A30: Resultado Liquido após impostos | B30: =B25-B28-B29 -> 196475.42 | C30: =C25-C28-C29 -> -86873.151 | F30: =F25-F28-F29 -> 203291.75 | G30: =G25-G28-G29 -> -12893.45 | J30: =J25-J28-J29 -> 2417919.6 | K30: =K25-K28-K29 -> 868142.09 | L30: =L25-L28-L29 -> 232360.43 | R30: =L30-Q30 -> 232360.43
A31: Margem liquida | B31: =B30/B3 -> 0.29251923 | C31: =C30/C4 -> -0.31045965 | F31: =F30/F3 -> 0.30266762 | G31: =G30/G4 -> -0.040388765 | J31: =J30/J3 -> 0.29999002 | K31: =K30/K3 -> 0.64625961 | L31: =L30/L4 -> 0.38787852
A32: Bonus | B32: =B30*10% -> 19647.542 | C32: =C30*10% -> -8687.3151 | F32: =F30*10% -> 20329.175 | G32: =G30*10% -> -1289.345 | J32: =J30*10% -> 241791.96 | K32: =K30*10% -> 86814.209 | L32: =L30*10%-9.9 -> 23226.143 | R32: =L32-Q32 -> 23226.143
A34: 0.15 | B34: Janeiro | F34: Fevereiro
A35: Resultado Contencioso | B35: Orçado | C35: Realizado | D35: Variação Mensal | E35: Desvio% | F35: Orçado | G35: Realizado | H35: Variação Mensal | I35: Desvio% | J35: Orçado YTG | K35: Orçado YTD | L35: Realizado | M35: Variação | N35: Desvio% | O35: YTG
A36: Receita | B36: =($B$3-($B$3/4))/2 -> 251875 | C36: =57491+'Resumo_Recebidas 2025_2026'!M142+'Resumo_Recebidas 2025_2026'!O153 -> 72613.091 | D36: =C36-B36 -> -179261.91 | E36: =C36/B36 -> 0.28829018 | F36: =B36 -> 251875 | G36: =133203+'Resumo_Recebidas 2025_2026'!M144+'Resumo_Recebidas 2025_2026'!O155 -> 138600.13 | H36: =G36-F36 -> -113274.87 | I36: =G36/F36 -> 0.55027346 | J36: =($J$3-($J$3/4))/2 -> 3022500 | K36: =B36 -> 251875 | L36: =C36 -> 72613.091 | M36: =L36-K36 -> -179261.91 | N36: =L36/K36 -> 0.28829018 | O36: =J36-L36 -> 2949886.9 | Q36: =L36 -> 72613.091 | R36: =L36-Q36 -> 0
A38: Despesas | B38: Orçado | C38: Realizado | D38: Variação Mensal | E38: Desvio% | F38: Orçado | G38: Realizado | H38: Variação Mensal | I38: Desvio% | J38: Orçado YTG | K38: Orçado YTD | L38: Realizado | M38: Variação | N38: Desvio% | O38: YTG
A39: Custo Equipe | B39: =+B7 -> 74354.065 | C39: =+'Base_Resultado Mensal_V2'!C5 -> 73576.315 | D39: =+B39-C39 -> 777.75 | E39: =C39/B39 -> 0.98953991 | F39: =+F7 -> 72754.065 | G39: ='Base_Resultado Mensal_V2'!D5 -> 76342.345 | H39: =+F39-G39 -> -3588.28 | I39: =G39/F39 -> 1.0493207 | J39: ='Base_Resultado Mensal_V2'!B5 -> 149918.66 | K39: =B39 -> 74354.065 | L39: =C39 -> 73576.315 | M39: =K39-L39 -> 777.75 | N39: =L39/K39 -> 0.98953991 | O39: =J39-L39 -> 76342.345 | Q39: ='Base_Resultado Mensal_V2'!B5 -> 149918.66 | R39: =L39-Q39 -> -76342.345
A40: =A8 -> Participação/Comissão - Contencioso | C40: =C8 -> 0 | G40: ='Base_Resultado Mensal_V2'!D28 -> 0 | L40: =C40 -> 0 | Q40: =L40 -> 0
A41: Despesas Equipe | B41: ='Orçamento 2026'!D191 -> 2110.49 | C41: =+'Base_Resultado Mensal_V2'!C200 -> 1060.095 | D41: =(B41-C41) -> 1050.395 | E41: =C41/B41 -> 0.50229804 | F41: ='Orçamento 2026'!E191 -> 2110.49 | H41: =(F41-G41) -> 2110.49 | I41: =G41/F41 -> 0 | J41: ='Base_Resultado Mensal_V2'!B200 -> 3791.6483 | K41: =B41 -> 2110.49 | L41: =C41 -> 1060.095 | M41: =K41-L41 -> 1050.395 | N41: =L41/K41 -> 0.50229804 | O41: =J41-L41 -> 2731.5533 | Q41: ='Base_Resultado Mensal_V2'!O200 -> 3791.6483 | R41: =L41-Q41 -> -2731.5533
A42: Despesas Institucional | B42: =(B13-B41)*'Rateio Mensal'!M2 -> 36974.283 | C42: ='Rateio Mensal'!I2 -> 35425.447 | D42: =B42-C42 -> 1548.8363 | E42: =C42/B42 -> 0.95811044 | F42: =(F13-F41)*'Rateio Mensal'!M2 -> 36197.964 | H42: =F42-G42 -> 36197.964 | I42: =G42/F42 -> 0 | J42: =(J13-J21)*'Rateio Mensal'!M3 -> 469930.32 | K42: =B42 -> 36974.283 | L42: =C42 -> 35425.447 | M42: =K42-L42 -> 1548.8363 | N42: =L42/K42 -> 0.95811044 | O42: =J42-L42 -> 434504.88 | Q42: =L42 -> 35425.447 | R42: =L42-Q42 -> 0
A43: Resultado Bruto | B43: =B36-B39-B41-B42 -> 138436.16 | C43: =C36-C39-C41-C42-C40 -> -37448.766 | F43: =F36-F39-F41-F42 -> 140812.48 | J43: =+J36-(J39+J41+J42) -> 2398859.4 | K43: =+K36-(K39+K41+K42) -> 138436.16 | L43: =L36-L39-L41-L42-L40 -> -37448.766 | Q43: =Q36-Q39-Q41-Q42-Q40 -> -116522.66 | R43: =L43-Q43 -> 79073.898
A44: Margem de bruta | B44: =B43/B36 -> 0.54962248 | C44: =C43/C36 -> -0.51573023 | F44: =F43/F36 -> 0.559057 | J44: =J43/J36 -> 0.79366729 | K44: =K43/K36 -> 0.54962248 | L44: =L43/L36 -> -0.51573023 | Q44: =Q43/Q36 -> -1.604706
A46: Impostos | B46: =B36*$A$34 -> 37781.25 | C46: =C36*$A$34 -> 10891.964 | D46: =(B46-C46) -> 26889.287 | E46: =C46/B46 -> 0.28829018 | F46: =F36*$A$34 -> 37781.25 | J46: =J36*$A$34 -> 453375 | K46: =B46 -> 37781.25 | L46: =+L36*$A$34 -> 10891.964
A47: Investimento amortização | B47: =B29*'Rateio Mensal'!M2 -> 2977.4965 | C47: =C29*'Rateio Mensal'!C2 -> 2821.9888 | D47: =B47-C47 -> 155.50776 | E47: =C47/B47 -> 0.94777231 | F47: =F29*'Rateio Mensal'!M2 -> 2977.4965 | J47: =J29*'Rateio Mensal'!M3 -> 37039.426 | K47: =B47 -> 2977.4965 | L47: =C47 -> 2821.9888
A48: Resultado Liquido após impostos | B48: =B43-B46-B47 -> 97677.417 | C48: =C43-C46-C47 -> -51162.718 | F48: =F43-F46-F47 -> 100053.74 | G48: =G43-G46-G47 -> 0 | J48: =J43-J46-J47 -> 1908445 | K48: =K43-K46-K47 -> 97677.417 | L48: =L43-L46-L47 -> -51162.718
A49: Margem liquida | B49: =B48/B36 -> 0.38780116 | C49: =C48/C36 -> -0.70459359 | F49: =F48/F36 -> 0.39723567 | G49: =G48/G36 -> 0 | J49: =J48/J36 -> 0.63141272 | K49: =K48/K36 -> 0.38780116 | L49: =L48/L36 -> -0.70459359
A50: Reserva bônus | B50: =B48*10% -> 9767.7417 | C50: =C48*10% -> -5116.2718 | F50: =F48*10% -> 10005.374 | G50: =G48*10% -> 0 | J50: =J48*10% -> 190844.5 | K50: =K48*10% -> 9767.7417 | L50: =L48*10% -> -5116.2718
B52: Janeiro | F52: Fevereiro
A53: Resultado Econômico | B53: Orçado | C53: Realizado | D53: Variação Mensal | E53: Desvio% | F53: Orçado | G53: Realizado | H53: Variação Mensal | I53: Desvio% | J53: Orçado YTG | K53: Orçado YTD | L53: Realizado | M53: Variação | N53: Desvio% | O53: YTG
A54: Receita | B54: =($B$3-($B$3/4))/2 -> 251875 | C54: =105769+'Resumo_Recebidas 2025_2026'!M143+'Resumo_Recebidas 2025_2026'!O154 -> 120362.57 | D54: =C54-B54 -> -131512.43 | E54: =C54/B54 -> 0.4778663 | F54: =B54 -> 251875 | G54: =117627+'Resumo_Recebidas 2025_2026'!O156 -> 118661.55 | H54: =G54-F54 -> -133213.45 | I54: =G54/F54 -> 0.47111287 | J54: =($J$3-($J$3/4))/2 -> 3022500 | K54: =B54 -> 251875 | L54: =C54 -> 120362.57 | M54: =L54-K54 -> -131512.43 | N54: =L54/K54 -> 0.4778663 | O54: =J54-L54 -> 2902137.4 | Q54: =L54 -> 120362.57 | R54: =L54-Q54 -> 0
A56: Despesas | B56: Orçado | C56: Realizado | D56: Variação Mensal | E56: Desvio% | H56: Variação Mensal | I56: Desvio% | J56: Orçado YTG | K56: Orçado YTD | L56: Realizado | M56: Variação | N56: Desvio% | O56: YTG
A57: Custo Equipe | B57: =+B9 -> 76879.165 | C57: ='Base_Resultado Mensal_V2'!C30 -> 76041.035 | D57: =+B57-C57 -> 838.13 | E57: =C57/B57 -> 0.98909809 | F57: =+F9 -> 75379.165 | G57: ='Base_Resultado Mensal_V2'!D30 -> 80276.745 | H57: =+F57-G57 -> -4897.58 | I57: =G57/F57 -> 1.0649726 | J57: =J9 -> 914114.75 | K57: =B57 -> 76879.165 | L57: =C57 -> 76041.035 | M57: =K57-L57 -> 838.13 | N57: =L57/K57 -> 0.98909809 | O57: =J57-L57 -> 838073.72 | Q57: =L57 -> 76041.035 | R57: =L57-Q57 -> 0
A58: =A10 -> Participação/comissão - Economico | C58: =C10 -> 0 | G58: ='Base_Resultado Mensal_V2'!D56 -> 1500 | L58: =C58 -> 0 | Q58: ='Base_Resultado Mensal_V2'!O56+'Base_Resultado Mensal_V2'!O57 -> 1500
A59: Despesas Equipe | B59: ='Orçamento 2026'!D192 -> 3174.8233 | C59: =+'Base_Resultado Mensal_V2'!C201 -> 1871.805 | D59: =+B59-C59 -> 1303.0183 | E59: =C59/B59 -> 0.58957769 | F59: ='Orçamento 2026'!E192 -> 3174.8233 | H59: =+F59-G59 -> 3174.8233 | I59: =G59/F59 -> 0 | J59: ='Base_Resultado Mensal_V2'!B201 -> 5770.1083 | K59: =B59 -> 3174.8233 | L59: =C59 -> 1871.805 | M59: =K59-L59 -> 1303.0183 | N59: =L59/K59 -> 0.58957769 | O59: =J59-L59 -> 3898.3033 | Q59: =L59 -> 1871.805 | R59: =L59-Q59 -> 0
A60: Despesas Institucional | B60: =(B13-B59)*'Rateio Mensal'!M3 -> 37924.624 | C60: ='Rateio Mensal'!I3 -> 36612.157 | D60: =+B60-C60 -> 1312.4668 | E60: =C60/B60 -> 0.96539275 | F60: =(F13-F59)*'Rateio Mensal'!M3 -> 37119.854 | H60: =+F60-G60 -> 37119.854 | I60: =G60/F60 -> 0 | J60: =(J13-J21)*'Rateio Mensal'!M4 -> 312546.77 | K60: =B60 -> 37924.624 | L60: =C60 -> 36612.157 | M60: =K60-L60 -> 1312.4668 | N60: =L60/K60 -> 0.96539275 | O60: =J60-L60 -> 275934.61 | Q60: =L60 -> 36612.157 | R60: =L60-Q60 -> 0
A61: Resultado Bruto | B61: =B54-B57-B59-B60 -> 133896.39 | C61: =C54-C57-C59-C60-C58 -> 5837.5769 | F61: =F54-F57-F59-F60 -> 136201.16 | J61: =+J54-(J57+J59+J60) -> 1790068.4 | K61: =K54-K57-K59-K60-K58 -> 133896.39 | L61: =L54-L57-L59-L60-L58 -> 5837.5769
A62: Margem de bruta | B62: =B61/B54 -> 0.53159856 | C62: =C61/C54 -> 0.048499934 | F62: =F61/F54 -> 0.54074902 | J62: =J61/J54 -> 0.5922476 | K62: =K61/K54 -> 0.53159856 | L62: =L61/L54 -> 0.048499934
A64: Impostos | B64: =B54*$A$34 -> 37781.25 | C64: =C54*$A$34 -> 18054.386 | D64: =(B64-C64) -> 19726.864 | E64: =C64/B64 -> 0.4778663 | F64: =F54*$A$34 -> 37781.25 | J64: =J54*$A$34 -> 453375 | K64: =B64 -> 37781.25 | L64: =C64 -> 18054.386
A65: Investimento amortização | B65: =B29*'Rateio Mensal'!M3 -> 3086.6188 | C65: =C29*'Rateio Mensal'!C3 -> 2916.5221 | D65: =B65-C65 -> 170.09677 | E65: =C65/B65 -> 0.9448922 | F65: =F29*'Rateio Mensal'!M3 -> 3086.6188 | G65: =G29*'Rateio Mensal'!G3 -> 0 | J65: =J29*'Rateio Mensal'!M4 -> 24634.616 | K65: =B65 -> 3086.6188 | L65: =C65 -> 2916.5221
A66: Resultado Liquido após impostos | B66: =B61-B64-B65 -> 93028.52 | C66: =C61-C64-C65 -> -15133.331 | F66: =F61-F64-F65 -> 95333.29 | G66: =G61-G64-G65 -> 0 | J66: =J61-J64-J65 -> 1312058.8 | K66: =K61-K64-K65 -> 93028.52 | L66: =L61-L64-L65 -> -15133.331
A67: Margem liquida | B67: =B66/B54 -> 0.369344 | C67: =C66/C54 -> -0.1257312 | F67: =F66/F54 -> 0.37849445 | G67: =G66/G54 -> 0 | J67: =J66/J54 -> 0.43409719 | K67: =K66/K54 -> 0.369344 | L67: =L66/L54 -> -0.1257312
A68: Reserva bônus | B68: =B66*10% -> 9302.852 | C68: =C66*10% -> -1513.3331 | F68: =F66*10% -> 9533.329 | G68: =G66*10% -> 0 | J68: =J66*10% -> 131205.88 | K68: =K66*10% -> 9302.852 | L68: =L66*10% -> -1513.3331
B70: Janeiro | F70: Fevereiro
A71: Resultado Arbitragem | B71: Orçado | C71: Realizado | D71: Variação Mensal | E71: Desvio% | F71: Orçado | G71: Realizado | H71: Variação Mensal | I71: Desvio% | J71: Orçado YTG | K71: Orçado YTD | L71: Realizado | M71: Variação | N71: Desvio% | O71: YTG
A72: Receita | B72: =($B$3/4) -> 167916.67 | C72: =116562-('Resumo_Recebidas 2025_2026'!M136+'Resumo_Recebidas 2025_2026'!M153) -> 86846.335 | D72: =C72-B72 -> -81070.333 | E72: =C72/B72 -> 0.51719901 | F72: =B72 -> 167916.67 | G72: =68404-('Resumo_Recebidas 2025_2026'!M144+'Resumo_Recebidas 2025_2026'!M155) -> 61972.318 | H72: =G72-F72 -> -105944.35 | I72: =G72/F72 -> 0.36906591 | J72: =($J$3/4) -> 2015000 | K72: =B72 -> 167916.67 | L72: =C72 -> 86846.335 | M72: =L72-K72 -> -81070.333 | N72: =L72/K72 -> 0.51719901 | O72: =J72-L72 -> 1928153.7
A74: Despesas | B74: Orçado | C74: Realizado | D74: Variação Mensal | E74: Desvio% | F74: Orçado | G74: Realizado | H74: Variação Mensal | I74: Desvio% | J74: Orçado YTG | K74: Orçado YTD | L74: Realizado | M74: Variação | N74: Desvio% | O74: YTG
A75: Custo Equipe | B75: =+B11 -> 62184.36 | C75: ='Base_Resultado Mensal_V2'!C58 -> 62013.17 | D75: =+B75-C75 -> 171.19 | E75: =(C75/B75)-1 -> -0.002752943 | F75: =+F11 -> 60584.36 | H75: =+F75-G75 -> 60584.36 | I75: =(G75/F75)-1 -> -1 | J75: ='Base_Resultado Mensal_V2'!B58 -> 123807.51 | K75: =B75 -> 62184.36 | L75: =C75 -> 62013.17 | M75: =K75-L75 -> 171.19 | N75: =L75/K75 -> 0.99724706 | O75: =J75-L75 -> 61794.34 | Q75: =L75 -> 62013.17 | R75: =L75-Q75 -> 0
A76: =A12 -> Participação/comissão - Arbitragem | C76: =C12 -> 0 | L76: =C76 -> 0
A77: Despesas Equipe | B77: ='Orçamento 2026'!D193 -> 1901.49 | C77: =+'Base_Resultado Mensal_V2'!C202 -> 146 | D77: =+B77-C77 -> 1755.49 | E77: =(C77/B77)-1 -> -0.92321811 | F77: ='Base_Resultado Mensal_V2'!D202 -> 1429.2233 | H77: =+F77-G77 -> 1429.2233 | I77: =(G77/F77)-1 -> -1 | J77: ='Base_Resultado Mensal_V2'!B202 -> 1575.2233 | K77: =B77 -> 1901.49 | L77: =C77 -> 146 | M77: =K77-L77 -> 1755.49 | N77: =L77/K77 -> 0.076781892 | O77: =J77-L77 -> 1429.2233 | Q77: =L77 -> 146 | R77: =L77-Q77 -> 0
A78: Despesas Institucional | B78: =(B13-B59)*'Rateio Mensal'!M4 -> 25223.354 | C78: ='Rateio Mensal'!I4 -> 29858.036 | D78: =+B78-C78 -> -4634.6819 | E78: =(C78/B78)-1 -> 0.18374566 | F78: =(F13-F59)*'Rateio Mensal'!M4 -> 24688.108 | H78: =+F78-G78 -> 24688.108 | I78: =(G78/F78)-1 -> -1 | J78: =(J13-J21)*'Rateio Mensal'!M2 -> 453316.71 | K78: =B78 -> 25223.354 | L78: =C78 -> 29858.036 | M78: =K78-L78 -> -4634.6819 | N78: =L78/K78 -> 1.1837457 | O78: =J78-L78 -> 423458.68 | Q78: =L78 -> 29858.036 | R78: =L78-Q78 -> 0
A79: Resultado Bruto | B79: =B72-B75-B77-B78 -> 78607.464 | C79: =C72-C75-C77-C78-C76 -> -5170.8709 | F79: =F72-F75-F77-F78 -> 81214.977 | G79: =G72-G75-G77-G78-G76 -> 61972.318 | J79: =+J72-(J75+J77+J78) -> 1436300.6 | K79: =+K72-(K75+K77+K78) -> 78607.464 | L79: =L72-L75-L77-L78-L76 -> -5170.8709 | Q79: =C79+#REF!+#REF!+#REF!+#REF!+#REF!+#REF!+#REF!+#REF!+#REF!+#REF!+#REF! -> #REF! | R79: =L79-Q79 -> #REF!
A80: Margem de bruta | B80: =B79/B72 -> 0.46813378 | C80: =C79/C72 -> -0.059540462 | F80: =F79/F72 -> 0.48366239 | G80: =G79/G72 -> 1 | J80: =J79/J72 -> 0.71280425 | K80: =K79/K72 -> 0.46813378 | L80: =L79/L72 -> -0.059540462
A82: Impostos | B82: =B72*$A$34 -> 25187.5 | C82: =C72*$A$34 -> 13026.95 | D82: =(B82-C82) -> 12160.55 | E82: =C82/B82 -> 0.51719901 | F82: =F72*$A$34 -> 25187.5 | G82: =G72*$A$34 -> 9295.8477 | J82: =J72*$A$34 -> 302250 | K82: =B82 -> 25187.5 | L82: =L72*$A$34 -> 13026.95 | Q82: =C82+#REF!+#REF!+#REF!+#REF!+#REF! -> #REF!
A83: Investimento amortização | B83: =B29*'Rateio Mensal'!M4 -> 2052.8847 | C83: =C29*'Rateio Mensal'!C4 -> 2378.4892 | D83: =B83-C83 -> -325.60452 | E83: =C83/B83 -> 1.1586083 | F83: =F29*'Rateio Mensal'!M4 -> 2052.8847 | G83: =G29*'Rateio Mensal'!G4 -> 0 | J83: =J29*'Rateio Mensal'!M2 -> 35729.958 | K83: =B83 -> 2052.8847 | L83: =C83 -> 2378.4892
A84: Resultado Liquido após impostos | B84: =B79-B82-B83 -> 51367.079 | C84: =C79-C82-C83 -> -20576.31 | F84: =F79-F82-F83 -> 53974.592 | G84: =G79-G82-G83 -> 52676.47 | J84: =J79-J82-J83 -> 1098320.6 | K84: =K79-K82-K83 -> 51367.079 | L84: =L79-L82-L83 -> -20576.31
A85: Margem liquida | B85: =B84/B72 -> 0.30590816 | C85: =C84/C72 -> -0.23692779 | F85: =F84/F72 -> 0.32143677 | G85: =G84/G72 -> 0.85 | J85: =J84/J72 -> 0.54507226 | K85: =K84/K72 -> 0.30590816 | L85: =L84/L72 -> -0.23692779
A86: Reserva bônus | B86: =B84*10% -> 5136.7079 | C86: =C84*10% -> -2057.631 | F86: =F84*10% -> 5397.4592 | G86: =G84*10% -> 5267.647 | J86: =J84*10% -> 109832.06 | K86: =K84*10% -> 5136.7079 | L86: =L84*10% -> -2057.631
L88: =L86+L68+L50 -> -8687.236 | Q88: =Q86+Q68+Q50 -> 0

Sheet Institucional
B1: Orçado | C1: Realizado
A2: Recebimento | B2: ='Areas Sintetico atualizado'!K3 -> 1343333.3 | C2: ='Areas Sintetico atualizado'!L4 -> 599054.65
A3: Custo equipe | B3: ='[1]Areas Sintetico atualizado'!AI7 -> 1806527.7 | C3: ='Areas Sintetico atualizado'!L6 -> 211630.52 | D3: =C3/$C$2 -> 0.35327415
A4: Despesas | B4: ='[1]Areas Sintetico atualizado'!AI11 -> 1228915.9 | C4: ='Areas Sintetico atualizado'!L13 -> 104973.54 | D4: =C4/$C$2 -> 0.17523199
A5: Resultado Bruto | B5: =B2-B3-B4 -> -1692110.3 | C5: =C2-C3-C4 -> 282450.59 | D5: =C5/$C$2 -> 0.47149386
A6: Imposto | B6: =B2*14.53% -> 195186.33 | C6: ='Areas Sintetico atualizado'!L28 -> 41973.16
A7: Amortização | C7: ='Areas Sintetico atualizado'!L29 -> 8117
A8: Resultado Liquido | B8: =B5-B6 -> -1887296.7 | C8: =C5-C6-C7 -> 232360.43
A11: Recebimento
A12: Custo equipe | C12: =D3 -> 0.35327415
A13: Despesas | C13: =D4 -> 0.17523199
A14: Resultado Bruto | C14: =D5 -> 0.47149386
A15: Imposto
A16: Resultado Liquido
A20: =A2 -> Recebimento | B20: =C2 -> 599054.65
A21: ='Areas Sintetico atualizado'!A14 -> Ocupação | B21: ='Areas Sintetico atualizado'!L14 -> 32337.05 | C21: =B21/$B$20 -> 0.053980134
A22: ='Areas Sintetico atualizado'!A15 -> Telecomunicações | B22: ='Areas Sintetico atualizado'!L15 -> 807.16 | C22: =B22/$B$20 -> 0.0013473896
A23: ='Areas Sintetico atualizado'!A16 -> Despesas Gerais | B23: ='Areas Sintetico atualizado'!L16 -> 6773.44 | C23: =B23/$B$20 -> 0.011306882
A24: ='Areas Sintetico atualizado'!A17 -> Consultoria | B24: ='Areas Sintetico atualizado'!L17 -> 30035.14 | C24: =B24/$B$20 -> 0.050137563
A25: ='Areas Sintetico atualizado'!A18 -> Salários Administração | B25: ='Areas Sintetico atualizado'!L18 -> 5139.13 | C25: =B25/$B$20 -> 0.0085787332
A26: ='Areas Sintetico atualizado'!A19 -> Administrativas | B26: ='Areas Sintetico atualizado'!L19 -> 4300.03 | C26: =B26/$B$20 -> 0.0071780262
A27: ='Areas Sintetico atualizado'!A21 -> Investimentos em Prospecção | B27: ='Areas Sintetico atualizado'!L21 -> 2702.45 | C27: =B27/$B$20 -> 0.0045111911
A28: ='Areas Sintetico atualizado'!A22 -> Endomarketing | B28: ='Areas Sintetico atualizado'!L22 -> 0 | C28: =B28/$B$20 -> 0
A29: ='Areas Sintetico atualizado'!A23 -> Gestão do Conhecimento | B29: ='Areas Sintetico atualizado'!L23 -> 692.37 | C29: =B29/$B$20 -> 0.001155771
A30: ='Areas Sintetico atualizado'!A24 -> Informática | B30: ='Areas Sintetico atualizado'!L24 -> 22186.77 | C30: =B30/$B$20 -> 0.037036304
A31: ='Areas Sintetico atualizado'!A25 -> Resultado Bruto

Sheet Institucional ano
B1: Orçado
A2: Recebimento | B2: ='Areas Sintetico atualizado'!K3 -> 1343333.3
A3: Custo equipe | B3: ='[1]Areas Sintetico atualizado'!AI7 -> 1806527.7
A4: Despesas | B4: ='[1]Areas Sintetico atualizado'!AI11 -> 1228915.9
A5: Resultado Bruto | B5: =B2-B3-B4 -> -1692110.3
A6: Imposto | B6: =B2*14.53% -> 195186.33
A7: Amortização
A8: Resultado Liquido | B8: =B5-B6 -> -1887296.7
A11: Recebimento
A12: Custo equipe
A13: Despesas
A14: Resultado Bruto
A15: Imposto
A16: Resultado Liquido
A20: =A2 -> Recebimento | B20: ='DRE 2026'!B3 -> 8060000
A21: ='DRE 2026'!A5 -> Custos Diretos | B21: ='DRE 2026'!B5 -> 2403882.6 | C21: =B21/$B$32 -> 0.64349327
A22: ='DRE 2026'!A10 -> Ocupação | B22: ='DRE 2026'!B10 -> 410635.68 | C22: =B22/$B$32 -> 0.10992271
A23: ='DRE 2026'!A11 -> Telecomunicações | B23: ='DRE 2026'!B11 -> 10127.402 | C23: =B23/$B$32 -> 0.0027109954
A24: ='DRE 2026'!A12 -> Despesas Gerais | B24: ='DRE 2026'!B12 -> 74921.85 | C24: =B24/$B$32 -> 0.020055765
A25: ='DRE 2026'!A13 -> Consultoria | B25: ='DRE 2026'!B13 -> 244264.88 | C25: =B25/$B$32 -> 0.065387055
A26: ='DRE 2026'!A14 -> Salários Administração | B26: ='DRE 2026'!B14 -> 82659.531 | C26: =B26/$B$32 -> 0.022127058
A27: ='DRE 2026'!A15 -> Administrativas | B27: ='DRE 2026'!B15 -> 91084.465 | C27: =B27/$B$32 -> 0.024382322
A28: Prospecção | B28: ='DRE 2026'!B17 -> 96000 | C28: =B28/$B$32 -> 0.025698157
A29: ='DRE 2026'!A18 -> Endomarketing | B29: ='DRE 2026'!B18 -> 1200 | C29: =B29/$B$32 -> 0.00032122696
A30: ='DRE 2026'!A19 -> Gestão do Conhecimento | B30: ='DRE 2026'!B19 -> 2300 | C30: =B30/$B$32 -> 0.00061568501
A31: ='DRE 2026'!A20 -> Informática | B31: ='DRE 2026'!B20 -> 318600 | C31: =B31/$B$32 -> 0.085285758
B32: =SUM(B21:B31) -> 3735676.5
A35: =A21 -> Custos Diretos | B35: =C21 -> 0.64349327
A36: =A22 -> Ocupação | B36: =C22 -> 0.10992271
A37: =A25 -> Consultoria | B37: =C25 -> 0.065387055
A38: =A27 -> Administrativas | B38: =C24+C29+C30+C27 -> 0.045374999
A39: Pessoal | B39: =C26 -> 0.022127058
A40: TI | B40: =C31+C23 -> 0.087996754
A41: =A28 -> Prospecção | B41: =C28 -> 0.025698157

Sheet Contencioso
B1: Orçado | C1: Realizado
A2: Recebimento | B2: ='Areas Sintetico atualizado'!B36 -> 251875 | C2: ='Areas Sintetico atualizado'!L36 -> 72613.091
A3: Custo equipe | B3: ='Areas Sintetico atualizado'!K39 -> 74354.065 | C3: ='Areas Sintetico atualizado'!L39 -> 73576.315 | D3: =C3/$C$2 -> 1.0132652
A4: Comissão | B4: ='Areas Sintetico atualizado'!K40 -> 0 | C4: ='Areas Sintetico atualizado'!L40 -> 0 | D4: =C4/$C$2 -> 0
A5: Despesas Equipe | B5: ='Areas Sintetico atualizado'!K41 -> 2110.49 | C5: ='Areas Sintetico atualizado'!L41 -> 1060.095 | D5: =C5/$C$2 -> 0.014599227
A6: Despesa Institucional | B6: ='Areas Sintetico atualizado'!K42 -> 36974.283 | C6: ='Areas Sintetico atualizado'!L42 -> 35425.447 | D6: =C6/$C$2 -> 0.48786584
A7: Resultado Bruto | B7: =B2-B3-B5-B6 -> 138436.16 | C7: =C2-C3-C5-C6-C4 -> -37448.766 | D7: =C7/$C$2 -> -0.51573023
A13: Recebimento
A14: Custo equipe | B14: =D3 -> 1.0132652
A15: =A4 -> Comissão | B15: =D4 -> 0
A16: Despesas Equipe | B16: =D5 -> 0.014599227
A17: Despesa Institucional | B17: =D6 -> 0.48786584
A18: =A7 -> Resultado Bruto | B18: =D7 -> -0.51573023

Sheet Econômico
B1: Orçado | C1: Realizado
A2: Recebimento | B2: ='Areas Sintetico atualizado'!K54 -> 251875 | C2: ='Areas Sintetico atualizado'!L54 -> 120362.57
A3: Custo equipe | B3: ='Areas Sintetico atualizado'!K57 -> 76879.165 | C3: ='Areas Sintetico atualizado'!L57 -> 76041.035 | D3: =C3/$C$2 -> 0.63176644
A4: =Contencioso!A4 -> Comissão | B4: ='Areas Sintetico atualizado'!K58 -> 0 | C4: ='Areas Sintetico atualizado'!L58 -> 0 | D4: =C4/$C$2 -> 0
A5: Despesas Equipe | B5: ='Areas Sintetico atualizado'!K59 -> 3174.8233 | C5: ='Areas Sintetico atualizado'!L59 -> 1871.805 | D5: =C5/$C$2 -> 0.015551387
A6: Despesa Institucional | B6: ='Areas Sintetico atualizado'!K60 -> 37924.624 | C6: ='Areas Sintetico atualizado'!L60 -> 36612.157 | D6: =C6/$C$2 -> 0.30418224
A7: Resultado Bruto | B7: =B2-B3-B5-B6 -> 133896.39 | C7: =C2-C3-C5-C6-C4 -> 5837.5769 | D7: =C7/$C$2 -> 0.048499934
A13: Recebimento
A14: Custo equipe | B14: =D3 -> 0.63176644
A15: =A4 -> Comissão | B15: =D4 -> 0
A16: Despesas Equipe | B16: =D5 -> 0.015551387
A17: Despesa Institucional | B17: =D6 -> 0.30418224
A18: Resultado Bruto | B18: =D7 -> 0.048499934

Sheet Arbitragem
B1: Orçado | C1: Realizado
A2: Recebimento | B2: ='Areas Sintetico atualizado'!K72 -> 167916.67 | C2: ='Areas Sintetico atualizado'!L72 -> 86846.335
A3: Custo equipe | B3: ='Areas Sintetico atualizado'!K75 -> 62184.36 | C3: ='Areas Sintetico atualizado'!L75 -> 62013.17 | D3: =C3/$C$2 -> 0.71405627
A4: =Econômico!A4 -> Comissão | C4: ='Areas Sintetico atualizado'!L76 -> 0 | D4: =C4/$C$2 -> 0
A5: Despesas Equipe | B5: ='Areas Sintetico atualizado'!K77 -> 1901.49 | C5: ='Areas Sintetico atualizado'!L77 -> 146 | D5: =C5/$C$2 -> 0.0016811302
A6: Despesa Institucional | B6: ='Areas Sintetico atualizado'!K78 -> 25223.354 | C6: ='Areas Sintetico atualizado'!L78 -> 29858.036 | D6: =C6/$C$2 -> 0.34380306
A7: Resultado Bruto | B7: =B2-B3-B5-B6 -> 78607.464 | C7: =C2-C3-C5-C6-C4 -> -5170.8709 | D7: =C7/$C$2 -> -0.059540462
A13: Recebimento
A14: Custo equipe | B14: =D3 -> 0.71405627
A15: =A4 -> Comissão | B15: =D4 -> 0
A16: Despesas Equipe | B16: =D5 -> 0.0016811302
A17: Despesa Institucional | B17: =D6 -> 0.34380306
A18: Resultado Bruto | B18: =D7 -> -0.059540462

Sheet Resumo_Recebidas 2025_2026
A1: Fatura | B1: Nº | C1: Cliente | D1: Nº | E1: Caso | F1: Advogado | G1: Valor | H1: Area Originador | I1: DT Receb | J1: Valor a Creditar | K1: Area Destino | M1: saida | O1: entrada
A2: 3465 | B2: 61 | C2: Atems | D2: 10 | E2: Ream - Trabalhos Adicionais | F2: ASG | G2: 474.09 | H2: Econômico | I2: 45717 | J2: =+G3 -> 7395.61 | K2: Contencioso | M2: Consolidado | N2: Area Origem (saida) | O2: Consolidado | P2: Area Destino (Entrada)
F3: BBX | G3: 7395.61 | J3: =+G5 -> 7822.38 | K3: Contencioso | M3: =+M31+M32+M33 -> 54452.933 | N3: Arbitragem | O3: =+M8+M9+M11+M10 -> 10285.68 | P3: Arbitragem
F4: BMP | G4: 2560.02 | M4: =+M34+M35+M36+M37+M38+M39+M42+M40+M41 -> 46372.07 | N4: Contencioso | O4: =+M12+M13+M14+M15+M16+M17+M18 -> 106691.1 | P4: Contencioso
F5: DC | G5: 7822.38 | M5: =+M43+M44+M45+M46 -> 53095.31 | N5: Econômico | O5: =+M19+M20+M21+M22+M23+M24+M25 -> 36943.53 | P5: Econômico
F6: RB | G6: 9718.71
F7: VC | G7: 10429.76 | M7: Consolidado | N7: Area Origem | O7: Area Destino | P7: MÊS
F8: Total Fatura | G8: =SUM(G2:G7) -> 38400.57 | M8: =+J72 -> 857.14 | N8: Econômico | O8: Arbitragem | P8: Agosto
F9: Recebido | G9: 60000 | M9: =+J75 -> 5714.27 | N9: Contencioso | O9: Arbitragem | P9: Agosto
A10: 3480 | B10: 5 | C10: White Martins | D10: 1 | E10: Ato de Concentração - Projeto CSA | F10: ASG | G10: 350 | H10: Contencioso | I10: 45733 | J10: =+G12 -> 700 | K10: Econômico | M10: =+J89 -> 2571.42 | N10: Contencioso | O10: Arbitragem | P10: Setembro
F11: DC | G11: 525 | J11: =+G10 -> 350 | K11: Econômico | M11: =+J116 -> 1142.85 | N11: Contencioso | O11: Arbitragem | P11: Outubro
F12: VC | G12: 700 | M12: =+J2+J3 -> 15217.99 | N12: Econômico | O12: Contencioso | P12: Março
F13: Total Fatura | G13: =SUM(G10:G12) -> 1575 | M13: =+J15+J16+J17+J37 -> 34919.89 | N13: Econômico | O13: Contencioso | P13: Abril
F14: Recebido | G14: =+G13 -> 1575 | M14: =+J24+J43 -> 32348.373 | N14: Arbitragem | O14: Contencioso | P14: Junho
A15: 3522 | B15: 61 | C15: Atems | D15: 10 | E15: Ream - Trabalhos Adicionais | F15: ASG | G15: 711.12 | H15: Econômico | I15: 45748 | J15: 12843.81 | K15: Contencioso | M15: =+J96+J101 -> 1799.42 | N15: Econômico | O15: Contencioso | P15: Junho
F16: BBX | G16: 14364.56 | J16: 12721.81 | K16: Contencioso | M16: =+J29 -> 14038.968 | N16: Arbitragem | O16: Contencioso | P16: Agosto
F17: BMP | G17: 995.56 | J17: 9047.73 | K17: Contencioso | M17: =+J69 -> 300.87 | N17: Econômico | O17: Contencioso | P17: Agosto
F18: DC | G18: 14222.5 | M18: =+J82+I109+I114 -> 8065.592 | N18: Arbitragem | O18: Contencioso | P18: Setembro
F19: IAC | G19: 10113.71 | M19: =+J10+J11 -> 1050 | N19: Contencioso | O19: Econômico | P19: Março
F20: RB | G20: 7348.29 | M20: =+J34 -> 525 | N20: Contencioso | O20: Econômico | P20: Abril
F21: VC | G21: 19279.25 | M21: =+J40 -> 525 | N21: Contencioso | O21: Econômico | P21: Maio
F22: Total Fatura | G22: =SUM(G15:G21) -> 67034.99 | M22: =+J54+J48 -> 30525 | N22: Contencioso | O22: Econômico | P22: Junho
F23: Recebido | G23: 60000 | M23: =+J66+J57+J58 -> 3268.53 | N23: Contencioso | O23: Econômico | P23: Julho
A24: 3535 | B24: 136 | C24: Deere | D24: 1 | E24: Projeto Santos | F24: IAC | G24: 5833.33 | H24: Arbitragem | I24: 45809 | J24: =+G24*5.187 -> 30257.483 | K24: Contencioso | M24: =+J86 -> 525 | N24: Contencioso | O24: Econômico | P24: Agosto
F25: JGS | G25: 6250 | M25: =+J122 -> 525 | N25: Contencioso | O25: Econômico | P25: Outubro
F26: MV | G26: 5500 | H26: 10% Comiss | I26: =+G28*10% -> 9120.4733 | M26: =+J127 -> 11025 | N26: Arbitragem | O26: Contencioso | P26: Dezembro
F27: Total Fatura | G27: =SUM(G24:G26) -> 17583.33
F28: Recebido | G28: =+G27*5.187 -> 91204.733
A29: 3536 | B29: 136 | C29: Deere | D29: 1 | E29: Projeto Santos | F29: IAC | G29: 2741.67 | H29: Arbitragem | I29: 45870 | J29: =+G29*5.12059 -> 14038.968 | K29: Contencioso
F30: JGS | G30: 8100 | M30: Consolidado | N30: Area Origem | O30: Area Destino | P30: MÊS
F31: MV | G31: 8525 | H31: 10% Comiss | I31: =+G33*10% -> 9916.8777 | M31: =+J24+J43 -> 32348.373 | N31: Arbitragem | O31: Contencioso | P31: Junho
F32: Total Fatura | G32: =SUM(G29:G31) -> 19366.67 | M32: =+J29 -> 14038.968 | N32: Arbitragem | O32: Contencioso | P32: Agosto
F33: Recebido | G33: =+G32*5.12059 -> 99168.777 | M33: =+J82+I109+I114 -> 8065.592 | N33: Arbitragem | O33: Contencioso | P33: Setembro
A34: 3537 | B34: 5 | C34: White Martins | D34: 1 | E34: Ato de Concentração - Projeto CSA | F34: ASG | G34: 525 | H34: Contencioso | I34: 45748 | J34: =+G34 -> 525 | K34: Econômico | M34: =+J10+J11 -> 1050 | N34: Contencioso | O34: Econômico | P34: Março
F35: Total Fatura | G35: =+G34 -> 525 | M35: =+J34 -> 525 | N35: Contencioso | O35: Econômico | P35: Abril
F36: Recebido | G36: =+G35 -> 525 | M36: =+J40 -> 525 | N36: Contencioso | O36: Econômico | P36: Maio
A37: 3573 | B37: 20 | C37: Dascher | D37: 1 | E37: Administrative Proceeding nº 08012.001183/2009-08 - Freight Forwarding | F37: FMF | G37: 50 | H37: Econômico | I37: 45748 | J37: =+G39 -> 306.54 | K37: Contencioso | M37: =+J54+J48 -> 30525 | N37: Contencioso | O37: Econômico | P37: Junho
F38: Total Fatura | G38: =+G37 -> 50 | M38: =+J66+J57+J58 -> 3268.53 | N38: Contencioso | O38: Econômico | P38: Julho
F39: Recebido | G39: =+G38*6.1308 -> 306.54 | M39: =+J75+J86 -> 6239.27 | N39: Contencioso | O39: Econômico | P39: Agosto
A40: 3595 | B40: 5 | C40: White Martins | D40: 1 | E40: Ato de Concentração - Projeto CSA | F40: ASG | G40: 525 | H40: Contencioso | I40: 45778 | J40: =+G40 -> 525 | K40: Econômico | M40: =+J89 -> 2571.42 | N40: Contencioso | O40: Arbitragem | P40: Setembro
F41: Total Fatura | G41: =+G40 -> 525 | M41: =+J116 -> 1142.85 | N41: Contencioso | O41: Arbitragem | P41: Outubro
F42: Recebido | G42: =+G41 -> 525 | M42: =+J122 -> 525 | N42: Contencioso | O42: Econômico | P42: Outubro
A43: 3605 | B43: 136 | C43: Deere | D43: 1 | E43: Projeto Santos | F43: IAC | G43: 408.33 | H43: Arbitragem | I43: 45809 | J43: =+G43*5.12059 -> 2090.8905 | K43: Contencioso | M43: =+J2+J3 -> 15217.99 | N43: Econômico | O43: Contencioso | P43: Março
F44: JGS | G44: 100 | M44: =+J15+J16+J17+J37 -> 34919.89 | N44: Econômico | O44: Contencioso | P44: Abril
F45: MV | G45: 825 | H45: 10% Comiss | I45: =+G47*10% -> 682.74363 | M45: =+J96+J101 -> 1799.42 | N45: Econômico | O45: Contencioso | P45: Junho
F46: Total Fatura | G46: =SUM(G43:G45) -> 1333.33 | M46: =+J69+J72 -> 1158.01 | N46: Econômico | O46: Arbitragem | P46: Agosto
F47: Recebido | G47: =+G46*5.12059 -> 6827.4363
A48: 3614 | B48: 140 | C48: Meu Financiamento Solar | D48: 1 | E48: Notificação de operação ao CADE | Projeto Parker | F48: ASG | G48: 2000 | H48: Contencioso | I48: 45809 | J48: =+G53 -> 30000 | K48: Econômico
F49: AM | G49: 24150
F50: BMP | G50: 16200
F51: VC | G51: 38733.33 | M51: Consolidado | N51: Area Origem | O51: Valor Comissao | P51: Area Destino | Q51: MÊS
F52: Total Fatura | G52: =SUM(G48:G51) -> 81083.33 | M52: =+I26+I45 -> 9803.2169 | N52: Arbitragem | O52: =+M52/2 -> 4901.6084 | P52: Contencioso | Q52: Junho
F53: Recebido | G53: 30000 | O53: =+M52/2 -> 4901.6084 | P53: Economico | Q53: Junho
A54: 3640 | B54: 5 | C54: White Martins | D54: 1 | E54: Ato de Concentração - Projeto CSA | F54: ASG | G54: 525 | H54: Contencioso | I54: 45809 | J54: =+G54 -> 525 | K54: Econômico | M54: =+I31+I73+I79 -> 12528.309 | N54: Arbitragem | O54: =+$M$54/2 -> 6264.1543 | P54: Contencioso | Q54: Agosto
F55: Total Fatura | G55: =+G54 -> 525 | O55: =+$M$54/2 -> 6264.1543 | P55: Economico | Q55: Agosto
F56: Recebido | G56: =+G55 -> 525 | M56: =+I84+I92+I109+I114 -> 10268.013 | N56: Arbitragem | O56: =+$M$56/2 -> 5134.0065 | P56: Contencioso | Q56: Setembro
A57: 3687 | B57: 61 | C57: Atems | D57: 18 | E57: MS ANP - Cessão de Bases | F57: AM | G57: 9244.63 | H57: Contencioso | I57: 45839 | J57: 1021.31 | K57: Econômico | O57: =+$M$56/2 -> 5134.0065 | P57: Economico | Q57: Setembro
F58: BBX | G58: 3697.81 | J58: 1722.22 | K58: Econômico | M58: =+I120 -> 1142.85 | N58: Arbitragem | O58: =+M58/2 -> 571.425 | P58: Contencioso | Q58: Outubro
F59: DC | G59: 24889.38 | O59: =+M58/2 -> 571.425 | P59: Economico | Q59: Outubro
F60: IAC | G60: 27654.67 | M60: =+I126 -> 2500 | N60: Contencioso | O60: =+M60 -> 2500 | P60: Arbitragem | Q60: Outubro
F61: JCT | G61: 22329.06 | M61: =+I130 -> 5722.5 | N61: Arbitragem | O61: =+M61/2 -> 2861.25 | P61: Contencioso | Q61: Dezembro
F62: RB | G62: 4029.71 | O62: =+M61/2 -> 2861.25 | P62: Economico | Q62: Dezembro
F63: VC | G63: 6795.15
F64: Total Fatura | G64: =SUM(G57:G63) -> 98640.41
F65: Recebido | G65: 25000
A66: 3690 | B66: 5 | C66: White Martins | D66: 1 | E66: Ato de Concentração - Projeto CSA | F66: ASG | G66: 525 | H66: Contencioso | I66: 45839 | J66: =+G66 -> 525 | K66: Econômico
F67: Total Fatura | G67: =+G66 -> 525
F68: Recebido | G68: =+G67 -> 525
A69: 3712 | B69: 20 | C69: Dascher | D69: 1 | E69: Administrative Proceeding nº 08012.001183/2009-08 - Freight Forwarding | F69: FMF | G69: 50 | H69: Econômico | I69: 45870 | J69: =+G69*6.0174 -> 300.87 | K69: Contencioso
F70: Total Fatura | G70: =+G69 -> 50
F71: Recebido | G71: =+G70*6.0174 -> 300.87
A72: 3717 | B72: 7 | C72: John Deere Brasil | D72: 1 | E72: Consultas Diversas | F72: MV | G72: 857.14 | H72: Econômico | I72: 45870 | J72: =+G72 -> 857.14 | K72: Arbitragem
F73: Total Fatura | G73: =+G72 -> 857.14 | H73: 10% Comiss | I73: =+G74*10% -> 85.714
F74: Recebido | G74: =+G73 -> 857.14
A75: 3718 | B75: 7 | C75: John Deere Brasil | D75: 16 | E75: Pré-contencioso - Contrato de Distribuição Rota Oeste | F75: AM | G75: 8571.4 | H75: Contencioso | I75: 45870 | J75: =+G79 -> 5714.27 | K75: Arbitragem
F76: BBX | G76: 3942.89
F77: DC | G77: 1285.71
F78: IAC | G78: 5742.9
F79: MV | G79: 5714.27 | H79: 10% Comiss | I79: =+G81*10% -> 2525.717
F80: Total Fatura | G80: =SUM(G75:G79) -> 25257.17
F81: Recebido | G81: =+G80 -> 25257.17
A82: 3736 | B82: 136 | C82: Deere | D82: 2 | E82: Project South | F82: IAC | G82: 233.33 | H82: Arbitragem | I82: 45901 | J82: =+G82*5.004 -> 1167.5833 | K82: Contencioso
F83: MV | G83: 2750
F84: Total Fatura | G84: =SUM(G82:G83) -> 2983.33 | H84: 10% Comiss | I84: =+G85*10% -> 1492.8583
F85: Recebido | G85: =+G84*5.004 -> 14928.583
A86: 3746 | B86: 5 | C86: White Martins | D86: 1 | E86: Ato de Concentração - Projeto CSA | F86: ASG | G86: 525 | H86: Contencioso | I86: 45870 | J86: =+G86 -> 525 | K86: Econômico
F87: Total Fatura | G87: =+G86 -> 525
F88: Recebido | G88: =+G87 -> 525
A89: 3767 | B89: 7 | C89: John Deere Brasil | D89: 16 | E89: Pré-contencioso - Contrato de Distribuição Rota Oeste | F89: AM | G89: 7714.26 | H89: Contencioso | I89: 45901 | J89: =+G93 -> 2571.42 | K89: Arbitragem
F90: BBX | G90: 771.44
F91: DC | G91: 1285.71
F92: IAC | G92: 6428.63 | H92: 10% Comiss | I92: =+G95*10% -> 1877.146
F93: MV | G93: 2571.42
F94: Total Fatura | G94: =SUM(G89:G93) -> 18771.46
F95: Recebido | G95: =+G94 -> 18771.46
A96: 3630 | B96: 142 | C96: Engelog | D96: 1 | E96: Elaboração de Protocolo Antitruste | F96: ASG | G96: 3149.04 | H96: Econômico | I96: 45809 | J96: 899.71 | K96: Contencioso
F97: DC | G97: 899.71
F98: EHF | G98: 7966.74
F99: Total Fatura | G99: =SUM(G96:G98) -> 12015.49
F100: Recebido | G100: =+G99 -> 12015.49
...

Sheet FATURAS Analitico CENTRO CUSTO 
A1: Núm. Fat. | B1: Cód. Cliente | C1: Razão Social Cliente | D1: Caso | E1: Nome do caso | F1: Data Pagto/Canc. | G1: Valor Original Hon. | H1: Valor Líquido | I1: Sócio Responsável
A2: 3339 | B2: 5 | C2: White Martins Gases Industriais Ltda. | D2: 1 | E2: Ato de Concentração - Projeto CSA | F2: 45298 | G2: 350 | H2: 333.73 | I2: Contencioso
A3: 3295 | B3: 3 | C3: Ambev S.A. | D3: 16 | E3: Arbitragem Projeto Morgan | F3: 45658 | G3: 20400 | H3: 19145.4 | I3: Arbitragem
A4: 3296 | B4: 3 | C4: Ambev S.A. | D4: 16 | E4: Arbitragem Projeto Morgan | F4: 45659 | G4: 6800 | H4: 6381.8 | I4: Arbitragem
A5: 3297 | B5: 3 | C5: Ambev S.A. | D5: 16 | E5: Arbitragem Projeto Morgan | F5: 45659 | G5: 12183.33 | H5: 11434.08 | I5: Arbitragem
A6: 3328 | B6: 133 | C6: Arcos Dourados Comercio de Alimentos Ltda | D6: 1 | E6: Representação da Arcos Dourados em dois Inquéritos Administrativos em curso no Cade | F6: 45659 | G6: 40000 | H6: 37540 | I6: Econômico
A7: 3300 | B7: 5 | C7: White Martins Gases Industriais Ltda. | D7: 3 | E7: (Contrato Fixo) - Mandados de Segurança - TRF1 | F7: 45660 | G7: 500 | H7: 476.75 | I7: Contencioso
A8: 3342 | B8: 5 | C8: White Martins Gases Industriais Ltda. | D8: 3 | E8: (Contrato Fixo) - Mandados de Segurança - TRF1 | F8: 45660 | G8: 500 | H8: 476.75 | I8: Contencioso
A9: 3383 | B9: 5 | C9: White Martins Gases Industriais Ltda. | D9: 1 | E9: Ato de Concentração - Projeto CSA | F9: 45660 | G9: 350 | H9: 333.73 | I9: Contencioso
A10: 3337 | B10: 2 | C10: VLI Multimodal S.A | E10: 6 - (Contrato Fixo) Cautelar Dragagem MPF e MPSP / 8 - (Contrato Fixo) - Ação Ordinária ANTAQ / 12 - (Contrato Fixo) - Ação Judicial - Cobrança Multa Contratual Valec / 50 - Ação Civil Pública - Cava | F10: 45663 | G10: 2600 | H10: 2440.1 | I10: Contencioso
A11: 3952 | B11: 114 | C11: Companhia Ultragaz S.A. | D11: 1 | E11: Trustee AC Ultragaz Supergasbras | F11: 46027 | G11: 12570.97 | H11: 5898.95 | I11: Econômico
A12: 3376 | B12: 81 | C12: KCI Brazil Holdings LLC | E12: 1 - PA Mercado de Trabalho - Ferreira / 2-PA Mercado de Trabalho - Garcia / 3 - PA Mercado de Trabalho - Silva | F12: 45672 | G12: 3033.32 | H12: 2846.8 | I12: Econômico
A13: 3346 | B13: 130 | C13: Renewal Pharma Brasil Royalties Ltda. | D13: 1 | E13: Farmacia Artesanal - Injunction and Arbitration | F13: 45663 | G13: 7800 | H13: 3660.15 | I13: Arbitragem
A14: 3351 | B14: 97 | C14: Transocean Brasil Ltda. | D14: 1 | E14: Ação Civil Pública FUP | F14: 45667 | G14: 30000 | H14: 28155 | I14: Arbitragem
A15: 3379 | B15: 61 | C15: Atem's Distribuidora De Petróleo S.A. | D15: 9 | E15: Cade - Cumprimento ACC | F15: 45672 | G15: 42730.54 | H15: 40102.63 | I15: Econômico
A16: 3378 | B16: 61 | C16: Atem's Distribuidora De Petróleo S.A. | D16: 10 | E16: Ream - Trabalhos Adicionais | F16: 45672 | G16: 2702.27 | H16: 2536.1 | I16: Econômico
A17: 3381 | B17: 61 | C17: Atem's Distribuidora De Petróleo S.A. | D17: 16 | E17: Questionamentos MME | F17: 45672 | G17: 3097.33 | H17: 2906.86 | I17: Econômico
A18: 3388 | B18: 81 | C18: KCI Brazil Holdings LLC | E18: 1 - PA Mercado de Trabalho - Ferreira / 2-PA Mercado de Trabalho - Garcia / 3 - PA Mercado de Trabalho - Silva | F18: 45698 | G18: 699.99 | H18: 656.98 | I18: Econômico
A19: 3385 | B19: 61 | C19: Atem's Distribuidora De Petróleo S.A. | D19: 12 | E19: Consultas diversas - Navemazônia Navegação Ltda | F19: 45677 | G19: 2275.57 | H19: 2135.64 | I19: Econômico
A20: 3343 | B20: 61 | C20: Atem's Distribuidora De Petróleo S.A. | D20: 17 | E20: Notificação de Operação ao CADE | Operação WPL | F20: 45677 | G20: 30000 | H20: 14077.5 | I20: Econômico
A21: 3468 | B21: 68 | C21: Casa Blanca Agropecuária e Imobiliária Ltda | D21: 1 | E21: [Casa Blanca] Ação judicial - Corretores de Imóvel | F21: 45723 | G21: 345 | H21: 328.96 | I21: Contencioso
A22: 3526 | B22: 68 | C22: Casa Blanca Agropecuária e Imobiliária Ltda | D22: 1 | E22: [Casa Blanca] Ação judicial - Corretores de Imóvel | F22: 45748 | G22: 1380 | H22: 1295.13 | I22: Contencioso
A23: 3344 | B23: 61 | C23: Atem's Distribuidora De Petróleo S.A. | D23: 17 | E23: Notificação de Operação ao CADE | Operação WPL | F23: 45679 | G23: 30000 | H23: 14077.5 | I23: Econômico
A24: 3586 | B24: 68 | C24: Casa Blanca Agropecuária e Imobiliária Ltda | D24: 1 | E24: [Casa Blanca] Ação judicial - Corretores de Imóvel | F24: 45776 | G24: 5230 | H24: 4908.36 | I24: Contencioso
A25: 3623 | B25: 68 | C25: Casa Blanca Agropecuária e Imobiliária Ltda | D25: 1 | E25: [Casa Blanca] Ação judicial - Corretores de Imóvel | F25: 45792 | G25: 1900 | H25: 1783.15 | I25: Contencioso
A26: 3401 | B26: 123 | C26: Paulo Kopenhagen Goldfinger | D26: 1 | E26: Contrato Padrão Judicial - Fixo acompanhamento mensal (Brascan Allpark) | F26: 45684 | G26: 1000 | H26: 1000 | I26: Contencioso
A27: 3426 | B27: 28 | C27: Solange Queiroz Ramiro Costa | D27: 5 | E27: Consultas Gerais | F27: 45685 | G27: 2090 | H27: 2090 | I27: Contencioso
A28: 3427 | B28: 28 | C28: Solange Queiroz Ramiro Costa | D28: 10 | E28: Dionatan Meira | F28: 45685 | G28: 81290.83 | H28: 81290.83 | I28: Contencioso
A29: 3428 | B29: 137 | C29: Sol Da Costa Gestão Patrimonial S.A | D29: 1 | E29: Locação Comercial Pinheiros - SCGP | F29: 45685 | G29: 1167.5 | H29: 1095.72 | I29: Contencioso
A30: 3302 | B30: 6 | C30: Sherwin-Williams do Brasil Indústria e Comércio Ltda. | E30: 4 - (Contrato Fixo) - Ação de Cobrança - Renato Vaz de Mello - Acompanhamento Processual / 7-(Contrato Fixo) - Ação de Cobrança - ARG Representações - Acompanhamento Processual /9-(Contrato Fixo) - Ação de Cobrança - Matos & Alves Representações Ltda. ME - Acompanhamento Processual /11-(Contrato Fixo) - Ação de Cobrança - CRB Representações Ltda. - Acompanhamento Processual / 13 - (Contrato Fixo) - Ação de Cobrança - Uelton Antonio Benfica e Cia Ltda. ME - Acompanhamento Processual / 16 - (Contrato Fixo) Ação de Cobrança - Wellington Aparecido de Carvalho - Acompanhamento | F30: 45686 | G30: 3870 | H30: 3632 | I30: Contencioso
A31: 3341 | B31: 6 | C31: Sherwin-Williams do Brasil Indústria e Comércio Ltda. | E31: 4 - (Contrato Fixo) - Ação de Cobrança - Renato Vaz de Mello - Acompanhamento Processual / 7-(Contrato Fixo) - Ação de Cobrança - ARG Representações - Acompanhamento Processual /9-(Contrato Fixo) - Ação de Cobrança - Matos & Alves Representações Ltda. ME - Acompanhamento Processual /11-(Contrato Fixo) - Ação de Cobrança - CRB Representações Ltda. - Acompanhamento Processual / 13 - (Contrato Fixo) - Ação de Cobrança - Uelton Antonio Benfica e Cia Ltda. ME - Acompanhamento Processual / 16 - (Contrato Fixo) Ação de Cobrança - Wellington Aparecido de Carvalho - Acompanhamento | F31: 45686 | G31: 3870 | H31: 3632 | I31: Contencioso
A32: 3447 | B32: 32 | C32: Rodrigo Cantusio Segurado | D32: 2 | E32: Sobrepartilha | F32: 45686 | G32: 2192.48 | H32: 2192.48 | I32: Contencioso
A33: 3333 | B33: 3 | C33: Ambev S.A. | D33: 16 | E33: Arbitragem Projeto Morgan | F33: 45691 | G33: 34569 | H33: 32443.02 | I33: Arbitragem
A34: 3345 | B34: 130 | C34: Renewal Pharma Brasil Royalties Ltda. | D34: 1 | E34: Farmacia Artesanal - Injunction and Arbitration | F34: 45664 | G34: 7800 | H34: 3660.15 | I34: Arbitragem
A35: 3364 | B35: 133 | C35: Arcos Dourados Comercio de Alimentos Ltda | D35: 1 | E35: Representação da Arcos Dourados em dois Inquéritos Administrativos em curso no Cade | F35: 45691 | G35: 40000 | H35: 37540 | I35: Econômico
A36: 3392 | B36: 5 | C36: White Martins Gases Industriais Ltda. | D36: 3 | E36: (Contrato Fixo) - Mandados de Segurança - TRF1 | F36: 45692 | G36: 500 | H36: 476.75 | I36: Contencioso
A37: 3421 | B37: 5 | C37: White Martins Gases Industriais Ltda. | D37: 1 | E37: Ato de Concentração - Projeto CSA | F37: 45692 | G37: 350 | H37: 333.73 | I37: Contencioso
A38: 3390 | B38: 130 | C38: Renewal Pharma Brasil Royalties Ltda. | D38: 1 | E38: Farmacia Artesanal - Injunction and Arbitration | F38: 45691 | G38: 10233.33 | H38: 4802.03 | I38: Arbitragem
A39: 3386 | B39: 97 | C39: Transocean Brasil Ltda. | D39: 1 | E39: Ação Civil Pública FUP | F39: 45695 | G39: 14450 | H39: 13561.33 | I39: Arbitragem
A40: 3387 | B40: 61 | C40: Atem's Distribuidora De Petróleo S.A. | D40: 4 | E40: Ação judicial (Powertech/Sabbá) - Trabalhos adicionais | F40: 45698 | G40: 853.34 | H40: 800.87 | I40: Contencioso
A41: 3407 | B41: 61 | C41: Atem's Distribuidora De Petróleo S.A. | D41: 17 | E41: Notificação de Operação ao CADE | Operação WPL | F41: 45698 | G41: 30000 | H41: 14077.5 | I41: Econômico
A42: 3455 | B42: 81 | C42: KCI Brazil Holdings LLC | E42: 1 - PA Mercado de Trabalho - Ferreira / 2-PA Mercado de Trabalho - Garcia / 3 - PA Mercado de Trabalho - Silva | F42: 45701 | G42: 699.99 | H42: 656.98 | I42: Econômico
A43: 3680 | B43: 68 | C43: Casa Blanca Agropecuária e Imobiliária Ltda | D43: 1 | E43: [Casa Blanca] Ação judicial - Corretores de Imóvel | F43: 45831 | G43: 20140 | H43: 18901.39 | I43: Contencioso
A44: 3730 | B44: 68 | C44: Casa Blanca Agropecuária e Imobiliária Ltda | D44: 1 | E44: [Casa Blanca] Ação judicial - Corretores de Imóvel | F44: 45856 | G44: 405 | H44: 386.17 | I44: Contencioso
A45: 3409 | B45: 116 | C45: Alexandre Gossn Barreto | D45: 03 | E45: JusInvest - produção antecipada de provas | F45: 45698 | G45: 6000 | H45: 3000 | I45: Contencioso
A46: 3411 | B46: 116 | C46: Alexandre Gossn Barreto | D46: 03 | E46: JusInvest - produção antecipada de provas | F46: 45698 | G46: 1000 | H46: 500 | I46: Contencioso
A47: 3413 | B47: 116 | C47: Alexandre Gossn Barreto | D47: 03 | E47: JusInvest - produção antecipada de provas | F47: 45698 | G47: 1000 | H47: 500 | I47: Contencioso
A48: 3391 | B48: 130 | C48: Renewal Pharma Brasil Royalties Ltda. | D48: 1 | E48: Farmacia Artesanal - Injunction and Arbitration | F48: 45698 | G48: 10233.33 | H48: 4802.03 | I48: Arbitragem
A49: 3405 | B49: 6 | C49: Sherwin-Williams do Brasil Indústria e Comércio Ltda. | E49: 4 - (Contrato Fixo) - Ação de Cobrança - Renato Vaz de Mello - Acompanhamento Processual / 7-(Contrato Fixo) - Ação de Cobrança - ARG Representações - Acompanhamento Processual /9-(Contrato Fixo) - Ação de Cobrança - Matos & Alves Representações Ltda. ME - Acompanhamento Processual /11-(Contrato Fixo) - Ação de Cobrança - CRB Representações Ltda. - Acompanhamento Processual / 13 - (Contrato Fixo) - Ação de Cobrança - Uelton Antonio Benfica e Cia Ltda. ME - Acompanhamento Processual / 16 - (Contrato Fixo) Ação de Cobrança - Wellington Aparecido de Carvalho - Acompanhamento | F49: 45700 | G49: 3870 | H49: 3632 | I49: Contencioso
A50: 3508 | B50: 81 | C50: KCI Brazil Holdings LLC | E50: 1 - PA Mercado de Trabalho - Ferreira / 2-PA Mercado de Trabalho - Garcia / 3 - PA Mercado de Trabalho - Silva | F50: 45758 | G50: 999.99 | H50: 938.53 | I50: Econômico
A51: 3424 | B51: 61 | C51: Atem's Distribuidora De Petróleo S.A. | D51: 12 | E51: Consultas diversas - Navemazônia Navegação Ltda | F51: 45707 | G51: 2702.24 | H51: 2536.07 | I51: Econômico
A52: 3406 | B52: 61 | C52: Atem's Distribuidora De Petróleo S.A. | D52: 17 | E52: Notificação de Operação ao CADE | Operação WPL | F52: 45707 | G52: 30000 | H52: 14077.5 | I52: Econômico
A53: 3769 | B53: 68 | C53: Casa Blanca Agropecuária e Imobiliária Ltda | D53: 1 | E53: [Casa Blanca] Ação judicial - Corretores de Imóvel | F53: 45887 | G53: 290 | H53: 272.17 | I53: Contencioso
A54: 3384 | B54: 2 | C54: VLI Multimodal S.A | E54: 6 - (Contrato Fixo) Cautelar Dragagem MPF e MPSP / 8 - (Contrato Fixo) - Ação Ordinária ANTAQ / 50 - Ação Civil Pública - Cava | F54: 45708 | G54: 1950 | H54: 1830.08 | I54: Contencioso
A55: 3772 | B55: 68 | C55: Casa Blanca Agropecuária e Imobiliária Ltda | D55: 2 | E55: [Casa Blanca] -Consultas Gerais | F55: 45887 | G55: 750 | H55: 703.88 | I55: Contencioso
A56: 3796 | B56: 68 | C56: Casa Blanca Agropecuária e Imobiliária Ltda | D56: 1 | E56: [Casa Blanca] Ação judicial - Corretores de Imóvel | F56: 45909 | G56: 580 | H56: 544.33 | I56: Contencioso
A57: 3408 | B57: 116 | C57: Alexandre Gossn Barreto | D57: 04 | E57: Jusinvest - Ação ordinária | F57: 45708 | G57: 6000 | H57: 3000 | I57: Contencioso
A58: 3410 | B58: 116 | C58: Alexandre Gossn Barreto | D58: 04 | E58: Jusinvest - Ação ordinária | F58: 45708 | G58: 1000 | H58: 500 | I58: Contencioso
A59: 3412 | B59: 116 | C59: Alexandre Gossn Barreto | D59: 04 | E59: Jusinvest - Ação ordinária | F59: 45708 | G59: 1000 | H59: 500 | I59: Contencioso
A60: 3423 | B60: 61 | C60: Atem's Distribuidora De Petróleo S.A. | D60: 9 | E60: Cade - Cumprimento ACC | F60: 45709 | G60: 9860.87 | H60: 9247.34 | I60: Econômico
A61: 3422 | B61: 61 | C61: Atem's Distribuidora De Petróleo S.A. | D61: 10 | E61: Ream - Trabalhos Adicionais | F61: 45709 | G61: 474.09 | H61: 452.05 | I61: Econômico
A62: 3912 | B62: 68 | C62: Nova Mata Agropecuária e Imobiliária Ltda. | D62: 1 | E62: [Casa Blanca] Ação judicial - Corretores de Imóvel | F62: 45988 | G62: 875 | H62: 821.2 | I62: Contencioso
A63: 3454 | B63: 20 | C63: Dachser SE | D63: 2 | E63: Appeal Brazilian Court | F63: 45713 | G63: 116.67 | H63: 116.67 | I63: Contencioso
A64: 3369 | B64: 87 | C64: Spotify Technology S.A | D64: 2 | E64: CADE – Mercado Livre Complaint | F64: 45713 | G64: 5695.83 | H64: 5695.83 | I64: Econômico
A65: 3404 | B65: 91 | C65: Boehringer Ingelheim Corporate Center GmbH | D65: 1 | E65: Hellmuth Spoennemann - Boehringer Ingelheim | F65: 45713 | G65: 506.67 | H65: 506.67 | I65: Econômico
A66: 3435 | B66: 123 | C66: Paulo Kopenhagen Goldfinger | D66: 1 | E66: Contrato Padrão Judicial - Fixo acompanhamento mensal (Brascan Allpark) | F66: 45713 | G66: 1000 | H66: 1000 | I66: Contencioso
... A74: 3414 | B74: 133 | C74: Arcos Dourados Comercio de Alimentos Ltda | D74: 1 | E74: Representação da Arcos Dourados em dois Inquéritos Administrativos em curso no Cade | F74: 45721 | G74: 40000 | H74: 37540 | I74: Econômico
A75: 3572 | B75: 81 | C75: KCI Brazil Holdings LLC | E75: 1 - PA Mercado de Trabalho - Ferreira / 2-PA Mercado de Trabalho - Garcia / 3 - PA Mercado de Trabalho - Silva | F75: 45791 | G75: 999.99 | H75: 928.68 | I75: Econômico
A76: 3476 | B76: 137 | C76: Sol Da Costa Gestão Patrimonial S.A | D76: 1 | E76: Locação Comercial Pinheiros - SCGP | F76: 45721 | G76: 3735 | H76: 3505.31 | I76: Contencioso
A77: 3942 | B77: 68 | C77: Nova Mata Agropecuária e Imobiliária Ltda. | D77: 1 | E77: [Casa Blanca] Ação judicial - Corretores de Imóvel | F77: 45992 | G77: 920 | H77: 818 | I77: Contencioso
A78: 3436 | B78: 6 | C78: Sherwin-Williams do Brasil Indústria e Comércio Ltda. | E78: 4 - (Contrato Fixo) - Ação de Cobrança - Renato Vaz de Mello - Acompanhamento Processual / 7-(Contrato Fixo) - Ação de Cobrança - ARG Representações - Acompanhamento Processual /9-(Contrato Fixo) - Ação de Cobrança - Matos & Alves Representações Ltda. ME - Acompanhamento Processual /11-(Contrato Fixo) - Ação de Cobrança - CRB Representações Ltda. - Acompanhamento Processual / 13 - (Contrato Fixo) - Ação de Cobrança - Uelton Antonio Benfica e Cia Ltda. ME - Acompanhamento Processual / 16 - (Contrato Fixo) Ação de Cobrança - Wellington Aparecido de Carvalho - Acompanhamento | F78: 45726 | G78: 3870 | H78: 3632 | I78: Contencioso
A79: 3429 | B79: 56 | C79: Itaú Unibanco S.A. | D79: 9 | E79: Notificação de Operação ao CADE | Cambur - Rua das Palmeiras | F79: 45726 | G79: 22700 | H79: 21303.95 | I79: Econômico
A80: 3456 | B80: 56 | C80: Itaú Unibanco S.A. | D80: 9 | E80: Notificação de Operação ao CADE | Cambur - Rua das Palmeiras | F80: 45726 | G80: 2300 | H80: 2158.55 | I80: Econômico
A81: 3919 | B81: 2 | C81: VLI Multimodal S.A | D81: 8,50 | E81: 8 - (Contrato Fixo) - Ação Ordinária ANTAQ / 50 - Ação Civil Pública - Cava | F81: 46028 | G81: 1332.56 | H81: 1250.63 | I81: Contencioso
A82: 3932 | B82: 139 | C82: Zetta | D82: 2 | E82: Assessoria e Monitoramento (Etapa 3) - Cade | F82: 46029 | G82: 10000 | H82: 9385 | I82: Econômico
A83: 3419 | B83: 101 | C83: Antonio Jose Pereira Lyra | D83: 1 | E83: Assuntos pessoais Antonio Lyra | F83: 45708 | G83: 5747.5 | H83: 5747.5 | I83: Contencioso
A84: 3527 | B84: 101 | C84: Antonio Jose Pereira Lyra | D84: 1 | E84: Assuntos pessoais Antonio Lyra | F84: 45742 | G84: 9915 | H84: 9915 | I84: Contencioso
A85: 3488 | B85: 130 | C85: Renewal Pharma Brasil Royalties Ltda. | D85: 1 | E85: Farmacia Artesanal - Injunction and Arbitration | F85: 45741 | G85: 8966.67 | H85: 4207.62 | I85: Arbitragem
A86: 3431 | B86: 5 | C86: White Martins Gases Industriais Ltda. | D86: 3 | E86: (Contrato Fixo) - Mandados de Segurança - TRF1 | F86: 45733 | G86: 500 | H86: 476.75 | I86: Contencioso
A87: 3480 | B87: 5 | C87: White Martins Gases Industriais Ltda. | D87: 1 | E87: Ato de Concentração - Projeto CSA | F87: 45733 | G87: 1575 | H87: 1478.15 | I87: Contencioso
A88: 3367 | B88: 119 | C88: Rafael Pullen Parente | D88: 1 | E88: Ação de Cobrança | F88: 45733 | G88: 12000 | H88: 12000 | I88: Contencioso
A89: 3587 | B89: 101 | C89: Antonio Jose Pereira Lyra | D89: 1 | E89: Assuntos pessoais Antonio Lyra | F89: 45777 | G89: 1935 | H89: 1935 | I89: Contencioso
A90: 3624 | B90: 101 | C90: Antonio Jose Pereira Lyra | D90: 1 | E90: Assuntos pessoais Antonio Lyra | F90: 45792 | G90: 3390 | H90: 3390 | I90: Contencioso
... A116: 3487 | B116: 84 | C116: Orizon Valorização de Resíduos S.A | D116: 2 | E116: Consultas Gerais | F116: 45751 | G116: 2950 | H116: 2768.58 | I116: Econômico
A117: 3474 | B117: 2 | C117: VLI Multimodal S.A | E117: 6 - (Contrato Fixo) Cautelar Dragagem MPF e MPSP / 8 - (Contrato Fixo) - Ação Ordinária ANTAQ / 50 - Ação Civil Pública - Cava | F117: 45754 | G117: 1982.56 | H117: 1860.66 | I117: Contencioso
A118: 3425 | B118: 2 | C118: VLI Multimodal S.A | E118: 6 - (Contrato Fixo) Cautelar Dragagem MPF e MPSP / 8 - (Contrato Fixo) - Ação Ordinária ANTAQ / 50 - Ação Civil Pública - Cava | F118: 45754 | G118: 1982.56 | H118: 1860.66 | I118: Contencioso
A119: 3629 | B119: 81 | C119: KCI Brazil Holdings LLC | E119: 1 - PA Mercado de Trabalho - Ferreira / 2-PA Mercado de Trabalho - Garcia / 3 - PA Mercado de Trabalho - Silva | F119: 45821 | G119: 6733.32 | H119: 6319.25 | I119: Econômico
A120: 3548 | B120: 130 | C120: Renewal Pharma Brasil Royalties Ltda. | D120: 1 | E120: Farmacia Artesanal - Injunction and Arbitration | F120: 45779 | G120: 46283.33 | H120: 21718.48 | I120: Arbitragem
A121: 3496 | B121: 5 | C121: White Martins Gases Industriais Ltda. | D121: 3 | E121: (Contrato Fixo) - Mandados de Segurança - TRF1 | F121: 45757 | G121: 500 | H121: 469.25 | I121: Contencioso
A122: 3537 | B122: 5 | C122: White Martins Gases Industriais Ltda. | D122: 1 | E122: Ato de Concentração - Projeto CSA | F122: 45757 | G122: 525 | H122: 492.72 | I122: Contencioso
A123: 3510 | B123: 107 | C123: Wald, Antunes, Vita e Blattner Advogados | D123: 5 | E123: Operação Cade - Projeto Onda - Por horas | F123: 45757 | G123: 35000 | H123: 32847.5 | I123: Econômico
A124: 3957 | B124: 136 | C124: Deere & Company | D124: 3 | E124: Project North | F124: 46031 | G124: 3316.66 | H124: 3316.66 | I124: Arbitragem
A125: 3549 | B125: 130 | C125: Renewal Pharma Brasil Royalties Ltda. | D125: 1 | E125: Farmacia Artesanal - Injunction and Arbitration | F125: 45782 | G125: 46283.33 | H125: 21718.48 | I125: Arbitragem
A126: 3670 | B126: 81 | C126: KCI Brazil Holdings LLC | E126: 1 - PA Mercado de Trabalho - Ferreira / 2-PA Mercado de Trabalho - Garcia / 3 - PA Mercado de Trabalho - Silva | F126: 45852 | G126: 13166.68 | H126: 12356.94 | I126: Econômico
A127: 3491 | B127: 97 | C127: Transocean Brasil Ltda. | D127: 1 | E127: Ação Civil Pública FUP | F127: 45758 | G127: 8450 | H127: 7930.33 | I127: Arbitragem
A128: 3359 | B128: 114 | C128: Companhia Ultragaz S.A. | D128: 1 | E128: Trustee AC Ultragaz Supergasbras | F128: 45679 | G128: 12570.97 | H128: 5898.95 | I128: Econômico
A129: 3393 | B129: 114 | C129: Companhia Ultragaz S.A. | D129: 1 | E129: Trustee AC Ultragaz Supergasbras | F129: 45681 | G129: 12570.97 | H129: 5898.95 | I129: Econômico
A130: 3515 | B130: 61 | C130: Atem's Distribuidora De Petróleo S.A. | D130: 4 | E130: Ação judicial (Powertech/Sabbá) - Trabalhos adicionais | F130: 45761 | G130: 50000 | H130: 46925 | I130: Contencioso
A131: 3514 | B131: 61 | C131: Atem's Distribuidora De Petróleo S.A. | D131: 4 | E131: Ação judicial (Powertech/Sabbá) - Trabalhos adicionais | F131: 45761 | G131: 1422.23 | H131: 1334.78 | I131: Contencioso
A132: 3512 | B132: 61 | C132: Atem's Distribuidora De Petróleo S.A. | D132: 17 | E132: Notificação de Operação ao CADE | Operação WPL | F132: 45761 | G132: 30000 | H132: 14077.5 | I132: Econômico
...

Sheet Amortização
A1: 44682 | D1: Acumulado Maio
A2: Total | B2: 78409
A3: Mensal | B3: =B2/60 -> 1306.8167 | C3: parcela 1/60 | D3: =B3 -> 1306.8167
A5: 44713 | D5: Acumulado Junho
A6: Total | B6: ='[4]Orçamento 2022'!R189 -> 154730.96
A7: Mensal | B7: =B6/60 -> 2578.8493 | C7: parcela 2/60 | D7: =B3+B7 -> 3885.666
A9: 44743 | D9: Acumulado Julho
A10: Total | B10: 116368.83
A11: Mensal | B11: =B10/60 -> 1939.4805 | C11: parcela 3/60 | D11: =D7+B11 -> 5825.1465
A13: 44774 | D13: Acumulado Agosto
A14: Total | B14: ='[4]Orçamento 2022'!X189 -> 43795.59
A15: Mensal | B15: =B14/60 -> 729.9265 | C15: parcela 4/60 | D15: =D11+B15 -> 6555.073
A17: 44805 | D17: Acumulado Setembro
A18: Total | B18: ='[4]Orçamento 2022'!AA186 -> 20140
A19: Mensal | B19: =B18/60 -> 335.66667 | C19: parcela 5/60 | D19: =D15+B19 -> 6890.7397
A21: 44835 | D21: Acumulado Outubro
A22: Total | B22: ='[4]Orçamento 2022'!AD189 -> 41551
A23: Mensal | B23: =B22/60 -> 692.51667 | C23: parcela 6/60 | D23: =D19+B23 -> 7583.2563
A25: 44866 | D25: Acumulado Novembro
A26: Total | B26: ='[4]Orçamento 2022'!AG189 -> 21722
A27: Mensal | B27: =B26/60 -> 362.03333 | C27: parcela 7/60 | D27: =D23+B27 -> 7945.2897
A29: 44896 | D29: Acumulado Dezembro
A30: Total | B30: ='[4]Orçamento 2022'!AJ189 -> 10321
A31: Mensal | B31: =B30/60 -> 172.01667 | C31: parcela 8/60 | D31: =D27+B31 -> 8117.3063
A33: 44927 | D33: Acumulado Janeiro
A34: Total | B34: -
A35: Mensal | B35: - | C35: parcela 09/60 | D35: 8117.31
A37: Mês | B37: Parcela | C37: Valor Institucional
A38: 44682 | B38: 1 | C38: 1306.82
A39: 44713 | B39: 2 | C39: 3885.67
A40: 44743 | B40: 3 | C40: 5825.15
A41: 44774 | B41: 4 | C41: 6555.07
A42: 44805 | B42: 5 | C42: 6890.74
A43: 44835 | B43: 6 | C43: 7583.26
A44: 44866 | B44: 7 | C44: 7945.29
A45: 44896 | B45: 8 | C45: 8117.31
A46: 44927 | B46: 9 | C46: 8117.31
A47: 44958 | B47: 10 | C47: 8117.31
A48: 44986 | B48: 11 | C48: 8117.31
A49: 45017 | B49: 12 | C49: 8117.31
... A93: 46357 | B93: 56 | C93: 8117.31
A94: 46388 | B94: 57
A95: 46419 | B95: 58
A96: 46447 | B96: 59
A97: 46478 | B97: 60
B98: Total | C98: =SUM(C38:C97) -> 437740.19
