Workbook
Name \0: #REF!
Name \a: #REF!
Name \b: #REF!
Name \c: #REF!
Name \d: #REF!
Name \df: #N/A
Name \e: #REF!
Name \f: #REF!
Name \i: #REF!
Name \l: #REF!
Name \PRINT_BALANCO: #REF!
Name \r: #REF!
Name \s: #REF!
Name \t: #REF!
Name _________________________________INV12: #REF!
Name _________________________________INV13: #REF!
Name _________________________________inv2: #REF!
Name _________________________________inv2: #REF!
Name _________________________________inv2: #REF!
Name ________________________________INV12: #REF!
Name ________________________________INV13: #REF!
Name ________________________________inv2: #REF!
Name ________________________________inv2: #REF!
Name ________________________________inv2: #REF!
Name _______________________________INV12: #REF!
Name _______________________________INV13: #REF!
Name _______________________________inv2: #REF!
Name _______________________________inv2: #REF!
Name _______________________________inv2: #REF!
Name ______________________________INV12: #REF!
Name ______________________________INV13: #REF!
Name ______________________________inv2: #REF!
Name ______________________________inv2: #REF!
Name ______________________________inv2: #REF!
Name _____________________________INV12: #REF!
Name _____________________________INV13: #REF!
Name _____________________________inv2: #REF!
Name _____________________________inv2: #REF!
Name _____________________________inv2: #REF!
Name ____________________________INV12: #REF!
Name ____________________________INV13: #REF!
Name ____________________________inv2: #REF!
Name ____________________________inv2: #REF!
Name ____________________________inv2: #REF!
Name ___________________________INV12: #REF!
Name ___________________________INV13: #REF!
Name ___________________________inv2: #REF!
Name ___________________________inv2: #REF!
Name ___________________________inv2: #REF!
Name __________________________INV12: #REF!
Name __________________________INV13: #REF!
Name __________________________inv2: #REF!
Name __________________________inv2: #REF!
Name __________________________inv2: #REF!
Name _________________________INV12: #REF!
Name _________________________INV13: #REF!
Name _________________________inv2: #REF!
Name _________________________inv2: #REF!
Name _________________________inv2: #REF!
Name ________________________INV12: #REF!

Sheet Meta (2)
A1: META 2026 | D1: YTD | H1: jan a jun | I1: jan a ago | J1: projeção ate dez
A2: Meta Anual | C2: 12 | D2: 1 | E2: 11 | F2: Nova meta mês | H2: 3120555 | I2: =D3 -> 444545.69 | J2: =I2+576522+85120+420000+374267+140000+(400000*3) -> 3240454.7 | L2: 576622 | M2: Nacionais
A3: 8060000 | C3: =A3/C2 -> 671666.67 | D3: ='Areas Sintetico atualizado'!C3 -> 444545.69 | E3: =A3-D3 -> 7615454.3 | F3: =E3/E2 -> 692314.03 | H3: =H2/A3 -> 0.38716563 | I3: =I2/A3 -> 0.055154552 | J3: =J2/A3 -> 0.40204152 | L3: 85120 | M3: Internacionais
L4: 420000 | M4: Pre faturas
I5: =10377407-5768380 -> 4609027 | L5: 374267 | M5: WM
I6: =(I2/I5)-1 -> -0.90354891 | L6: 140000 | M6: Tonico
A7: META 2025 | D7: YTD | J7: 6143091
A8: Meta Anual | C8: 12 | J8: =(J2/J7)-1 -> -0.4725042
A9: =A3 -> 8060000 | C9: =A9/C8 -> 671666.67 | D9: ='Areas Sintetico atualizado'!X3 -> 2372506.6 | F9: =A9-D9 -> 5687493.4 | G9: =F9/E2 -> 517044.85
B13: Faturamento | C13: Recebimento | D13: Faturamento | E13: Meta | F13: Despesas | G13: Despesas indiretas | H13: Custo direto
A14: Jan | B14: ='Areas Sintetico atualizado'!C3 -> 444545.69 | C14: ='Areas Sintetico atualizado'!C4 -> 279821.07 | D14: ='Areas Sintetico atualizado'!C3 -> 444545.69 | E14: 671667 | F14: =G14+H14 -> 311424.09 | G14: ='Areas Sintetico atualizado'!C13 -> 100181.41 | H14: ='Areas Sintetico atualizado'!C6 -> 211242.68 | J14: =C14-G14-H14 -> -31603.02
A15: Fev | B15: ='Areas Sintetico atualizado'!G3 -> 534752.84 | C15: ='Areas Sintetico atualizado'!G4 -> 319233.58 | E15: 671667 | F15: =G15+H15 -> 313501.13 | G15: ='Areas Sintetico atualizado'!G13 -> 95047.39 | H15: ='Areas Sintetico atualizado'!G6 -> 218453.74 | J15: =C15-G15-H15 -> 5732.45
A16: Mar | E16: 671667 | F16: =G16+H16 -> 0 | J16: =C16-G16-H16 -> 0
A17: Abr | E17: 671667 | F17: =G17+H17 -> 0 | J17: =C17-G17-H17 -> 0
A18: Mai | E18: 671667 | F18: =G18+H18 -> 0 | J18: =C18-G18-H18 -> 0
A19: Jun | E19: 671667 | F19: =G19+H19 -> 0 | J19: =C19-G19-H19 -> 0
A20: Jul | E20: 671667 | F20: =G20+H20 -> 0 | J20: =C20-G20-H20 -> 0
A21: Ago | E21: 671667 | F21: =G21+H21 -> 0 | J21: =C21-G21-H21 -> 0
A22: Set | E22: 671667 | F22: =G22+H22 -> 0 | J22: =C22-G22-H22 -> 0
A23: Out | E23: 671667 | F23: =G23+H23 -> 0 | J23: =C23-G23-H23 -> 0
A24: Nov | E24: 671667 | F24: =G24+H24 -> 0 | J24: =C24-G24-H24 -> 0
A25: Dez | E25: 671667 | F25: =G25+H25 -> 0 | J25: =C25-G25-H25 -> 0
C26: =SUM(C14:C25) -> 599054.65 | D26: =SUM(D14:D25) -> 444545.69 | E26: =SUM(E14:E25) -> 8060004 | F26: =SUM(F14:F25) -> 624925.22 | G26: =SUM(G14:G25) -> 195228.8 | H26: =SUM(H14:H25) -> 429696.42 | I26: =SUM(I14:I25) -> 0 | J26: =SUM(J14:J25) -> -25870.57
A28: MÉDIA ANUAL | C28: =C26/12 -> 49921.221
E31: =D26-G26-H26 -> -180379.53 | F31: =C26-G26-H26 -> -25870.57
C35: Recebimento | D35: Despesas | F35: #
A36: Jan | C36: 316807.42 | D36: 330244.38 | E36: ='[1]Base_Resultado Mensal_V2'!D190 -> 134911.6 | F36: =C36-D36-E36 -> -148348.56
A37: Fev | C37: 216057.27 | D37: 377306.7 | E37: ='[1]Base_Resultado Mensal_V2'!F190 -> 5092.45 | F37: =C37-D37-E37 -> -166341.88
A38: Mar | C38: 613202.96 | D38: 363984.21 | E38: ='[1]Base_Resultado Mensal_V2'!H190 -> 814.99 | F38: =C38-D38-E38 -> 248403.76
A39: Abr | C39: 588260.32 | D39: 375072.46 | E39: ='[1]Base_Resultado Mensal_V2'!J190 -> 110831.76 | F39: =C39-D39-E39 -> 102356.1
A40: Mai | C40: 658171.05 | D40: 360112.8 | E40: ='[1]Base_Resultado Mensal_V2'!L190 -> 5968 | F40: =C40-D40-E40 -> 292090.25
A41: Jun | C41: 632809.49 | D41: 334821.86 | E41: ='[1]Base_Resultado Mensal_V2'!N190 -> 11928.17 | F41: =C41-D41-E41 -> 286059.46
A42: Jul | C42: 260036.93 | D42: 337422.56 | E42: ='[1]Base_Resultado Mensal_V2'!P190 -> 183171.96 | F42: =C42-D42-E42 -> -260557.59
C43: 3285345.4 | D43: 2478965 | E43: =SUM(E36:E42) -> 452718.93

Sheet DRE 2026
A1: DRE | C1: Janeiro | D1: Fevereiro | E1: Março | F1: Abril | G1: Maio | H1: Junho | I1: Julho | J1: Agosto | K1: Setembro | L1: Outubro | M1: Novembro | N1: Dezembro
A2: Resultado Institucional | C2: Orçado | D2: Orçado | E2: Orçado | F2: Orçado | G2: Orçado | H2: Orçado | I2: Orçado | J2: Orçado | K2: Orçado | L2: Orçado | M2: Orçado | N2: Orçado
A3: Faturamento | B3: =SUM(C3:N3) -> 8060000 | C3: 671666.67 | D3: 671666.67 | E3: 671666.67 | F3: 671666.67 | G3: 671666.67 | H3: 671666.67 | I3: 671666.67 | J3: 671666.67 | K3: 671666.67 | L3: 671666.67 | M3: 671666.67 | N3: 671666.67
A4: Despesas
A5: Custos Diretos | B5: =SUM(C5:N5) -> 2438910.6 | C5: =SUM(C6:C8) -> 215786.59 | D5: =SUM(D6:D8) -> 211686.59 | E5: =SUM(E6:E8) -> 199069.61 | F5: =SUM(F6:F8) -> 203869.61 | G5: =SUM(G6:G8) -> 199069.61 | H5: =SUM(H6:H8) -> 199069.61 | I5: =SUM(I6:I8) -> 203869.61 | J5: =SUM(J6:J8) -> 199069.61 | ... N5: =SUM(N6:N8) -> 201097.67
A6: Custo equipe - Contencioso | B6: =SUM(C6:N6) -> 901597.73 | C6: ='[2]Orçamento 2026'!D5 -> 75454.065 | D6: ='[2]Orçamento 2026'!E5 -> 74454.065 | E6: ='[2]Orçamento 2026'!F5 -> 74454.065 | F6: ='[2]Orçamento 2026'!G5 -> 76054.065 | G6: ='[2]Orçamento 2026'!H5 -> 74454.065 | H6: ='[2]Orçamento 2026'!I5 -> 74454.065 | I6: ='[2]Orçamento 2026'!J5 -> 76054.065 | J6: ='[2]Orçamento 2026'!K5 -> 74454.065 | ... N6: ='[2]Orçamento 2026'!O5 -> 75151.317
A7: Custo equipe - Econômico | B7: =SUM(C7:N7) -> 914114.75 | C7: ='[2]Orçamento 2026'!D28 -> 76879.165 | D7: ='[2]Orçamento 2026'!E28 -> 75379.165 | E7: ='[2]Orçamento 2026'!F28 -> 75379.165 | F7: ='[2]Orçamento 2026'!G28 -> 76979.165 | G7: ='[2]Orçamento 2026'!H28 -> 75379.165 | H7: ='[2]Orçamento 2026'!I28 -> 75379.165 | I7: ='[2]Orçamento 2026'!J28 -> 76979.165 | J7: ='[2]Orçamento 2026'!K28 -> 75379.165 | ... N7: ='[2]Orçamento 2026'!O28 -> 76467.423
A8: Custo equipe - Arbitragem e Compliance | B8: =SUM(C8:N8) -> 623198.16 | C8: ='[2]Orçamento 2026'!D53 -> 63453.36 | D8: ='[2]Orçamento 2026'!E53 -> 61853.36 | E8: ='[2]Orçamento 2026'!F53 -> 49236.38 | F8: ='[2]Orçamento 2026'!G53 -> 50836.38 | G8: ='[2]Orçamento 2026'!H53 -> 49236.38 | H8: ='[2]Orçamento 2026'!I53 -> 49236.38 | I8: ='[2]Orçamento 2026'!J53 -> 50836.38 | J8: ='[2]Orçamento 2026'!K53 -> 49236.38 | ... N8: ='[2]Orçamento 2026'!O53 -> 49478.927
A9: Despesas Indiretas | B9: =SUM(C9:N9) -> 1386633.4 | C9: =SUM(C10:C20) -> 102906.66 | D9: =SUM(D10:D20) -> 112483.91 | E9: =SUM(E10:E20) -> 129851.12 | F9: =SUM(F10:F20) -> 124351.12 | G9: =SUM(G10:G20) -> 103162.07 | H9: =SUM(H10:H20) -> 106230.33 | I9: =SUM(I10:I20) -> 114809.44 | J9: =SUM(J10:J20) -> 108120.57 | ... N9: =SUM(N10:N20) -> 142584.19
A10: Ocupação | B10: =SUM(C10:N10) -> 410635.68 | C10: ='[2]Orçamento 2026'!D74 -> 27197.48 | D10: ='[2]Orçamento 2026'!E74 -> 34236.38 | E10: ='[2]Orçamento 2026'!F74 -> 34236.38 | F10: ='[2]Orçamento 2026'!G74 -> 34236.38 | G10: ='[2]Orçamento 2026'!H74 -> 34236.38 | H10: ='[2]Orçamento 2026'!I74 -> 35213.24 | I10: ='[2]Orçamento 2026'!J74 -> 35213.24 | J10: ='[2]Orçamento 2026'!K74 -> 35213.24 | ... N10: ='[2]Orçamento 2026'!O74 -> 35213.24
A11: Telecomunicações | B11: =SUM(C11:N11) -> 10127.402 | C11: ='[2]Orçamento 2026'!D81 -> 890 | D11: ='[2]Orçamento 2026'!E81 -> 839.7638 | E11: ='[2]Orçamento 2026'!F81 -> 839.7638 | F11: ='[2]Orçamento 2026'!G81 -> 839.7638 | G11: ='[2]Orçamento 2026'!H81 -> 839.7638 | H11: ='[2]Orçamento 2026'!I81 -> 839.7638 | I11: ='[2]Orçamento 2026'!J81 -> 839.7638 | J11: ='[2]Orçamento 2026'!K81 -> 839.7638 | ... N11: ='[2]Orçamento 2026'!O81 -> 839.7638
A12: Despesas Gerais | B12: =SUM(C12:N12) -> 74921.85 | C12: ='[2]Orçamento 2026'!D84 -> 7255 | D12: ='[2]Orçamento 2026'!E84 -> 5505 | E12: ='[2]Orçamento 2026'!F84 -> 5742.205 | F12: ='[2]Orçamento 2026'!G84 -> 7292.205 | G12: ='[2]Orçamento 2026'!H84 -> 5742.205 | H12: ='[2]Orçamento 2026'!I84 -> 5683.605 | I12: ='[2]Orçamento 2026'!J84 -> 7333.605 | J12: ='[2]Orçamento 2026'!K84 -> 5683.605 | ... N12: ='[2]Orçamento 2026'!O84 -> 5783.605
A13: Consultoria | B13: =SUM(C13:N13) -> 287104.88 | C13: ='Orçamento 2026'!D98 -> 23240.8 | D13: ='Orçamento 2026'!E98 -> 23035.8 | E13: ='Orçamento 2026'!F98 -> 22815.8 | F13: ='Orçamento 2026'!G98 -> 23115.8 | G13: ='Orçamento 2026'!H98 -> 22815.8 | H13: ='Orçamento 2026'!I98 -> 23465.8 | I13: ='Orçamento 2026'!J98 -> 23240.8 | J13: ='Orçamento 2026'!K98 -> 24015.8 | ... N13: ='Orçamento 2026'!O98 -> 27532.561
A14: Salários Administração | B14: =SUM(C14:N14) -> 94659.531 | C14: ='[2]Orçamento 2026'!D104 -> 6426.58 | D14: ='[2]Orçamento 2026'!E104 -> 6776.58 | E14: ='Orçamento 2026'!F104 -> 7626.58 | F14: ='Orçamento 2026'!G104 -> 7626.58 | G14: ='Orçamento 2026'!H104 -> 7626.58 | H14: ='Orçamento 2026'!I104 -> 7626.58 | I14: ='Orçamento 2026'!J104 -> 7626.58 | J14: ='Orçamento 2026'!K104 -> 7626.58 | K14: ='Orçamento 2026'!L104 -> 7626.58 | L14: ='Orçamento 2026'!M104 -> 7823.437 | ... N14: ='Orçamento 2026'!O104 -> 10123.437
A15: Administrativas | B15: =SUM(C15:N15) -> 91084.049 | C15: ='[2]Orçamento 2026'!D112 -> 2996.8033 | D15: ='[2]Orçamento 2026'!E112 -> 14690.387 | E15: ='[2]Orçamento 2026'!F112 -> 14690.387 | F15: ='[2]Orçamento 2026'!G112 -> 14690.387 | G15: ='[2]Orçamento 2026'!H112 -> 3001.3367 | H15: ='[2]Orçamento 2026'!I112 -> 3001.3367 | I15: ='[2]Orçamento 2026'!J112 -> 5655.4486 | J15: ='[2]Orçamento 2026'!K112 -> 5691.5827 | ... N15: ='[2]Orçamento 2026'!O112 -> 5691.5827
A16: Taxas / Despesas Financeiras | B16: =SUM(C16:N16) -> 0
A17: Investimentos em Prospecção | B17: =SUM(C17:N17) -> 96000 | C17: ='[2]Orçamento 2026'!D125 -> 4500 | D17: ='[2]Orçamento 2026'!E125 -> 4500 | E17: ='[2]Orçamento 2026'!F125 -> 6000 | F17: ='[2]Orçamento 2026'!G125 -> 6000 | G17: ='[2]Orçamento 2026'!H125 -> 6000 | H17: ='[2]Orçamento 2026'!I125 -> 7500 | I17: ='[2]Orçamento 2026'!J125 -> 4500 | J17: ='[2]Orçamento 2026'!K125 -> 6000 | ... N17: ='[2]Orçamento 2026'!O125 -> 34500
A18: Endomarketing | B18: =SUM(C18:N18) -> 1200 | C18: ='[2]Orçamento 2026'!D152 -> 100 | D18: ='[2]Orçamento 2026'!E152 -> 100 | E18: ='[2]Orçamento 2026'!F152 -> 100 | F18: ='[2]Orçamento 2026'!G152 -> 100 | G18: ='[2]Orçamento 2026'!H152 -> 100 | H18: ='[2]Orçamento 2026'!I152 -> 100 | I18: ='[2]Orçamento 2026'!J152 -> 100 | J18: ='[2]Orçamento 2026'!K152 -> 100 | ... N18: ='[2]Orçamento 2026'!O152 -> 100
A19: ='[3]Areas Sintetico atualizado'!A21 -> Gestão do Conhecimento | B19: =SUM(C19:N19) -> 2300 | C19: ='[2]Orçamento 2026'!D146 -> 0 | D19: ='[2]Orçamento 2026'!E146 -> 0 | E19: ='[2]Orçamento 2026'!F146 -> 0 | F19: ='[2]Orçamento 2026'!G146 -> 150 | G19: ='[2]Orçamento 2026'!H146 -> 0 | H19: ='[2]Orçamento 2026'!I146 -> 0 | I19: ='[2]Orçamento 2026'!J146 -> 0 | J19: ='[2]Orçamento 2026'!K146 -> 150 | ... N19: ='[2]Orçamento 2026'!O146 -> 0
A20: Informática | B20: =SUM(C20:N20) -> 318600 | C20: ='[2]Orçamento 2026'!D162 -> 30300 | D20: ='[2]Orçamento 2026'!E162 -> 22800 | E20: ='[2]Orçamento 2026'!F162 -> 37800 | F20: ='[2]Orçamento 2026'!G162 -> 30300 | G20: ='[2]Orçamento 2026'!H162 -> 22800 | H20: ='[2]Orçamento 2026'!I162 -> 22800 | I20: ='[2]Orçamento 2026'!J162 -> 30300 | J20: ='[2]Orçamento 2026'!K162 -> 22800 | ... N20: ='[2]Orçamento 2026'!O162 -> 22800
A21: Resultado Bruto | B21: =B3-B5-B9 -> 4234456 | C21: =C3-C5-C9 -> 352973.42 | D21: =D3-D5-D9 -> 347496.17 | E21: =E3-E5-E9 -> 342745.94 | F21: =F3-F5-F9 -> 343445.94 | G21: =G3-G5-G9 -> 369434.99 | H21: =H3-H5-H9 -> 366366.73 | I21: =I3-I5-I9 -> 352987.62 | ... N21: =N3-N5-N9 -> 327984.81
A22: Margem de bruta | B22: =B21/B3 -> 0.52536675 | C22: =C21/C3 -> 0.52551873 | D22: =D21/D3 -> 0.51736402 | E22: =E21/E3 -> 0.51029173 | F22: =F21/F3 -> 0.51133391 | G22: =G21/G3 -> 0.55002728 | H22: =H21/H3 -> 0.54545916 | I22: =I21/I3 -> 0.52553988 | ... N22: =N21/N3 -> 0.48831486
A23: Impostos | B23: =C23+D23+E23+F23+G23+H23+I23+J23+K23+L23+M23+N23 -> 1209000 | C23: =(C3*15%) -> 100750 | D23: =(D3*15%) -> 100750 | E23: =(E3*15%) -> 100750 | F23: =(F3*15%) -> 100750 | G23: =(G3*15%) -> 100750 | H23: =(H3*15%) -> 100750 | I23: =(I3*15%) -> 100750 | J23: =(J3*15%) -> 100750 | ... N23: =(N3*15%) -> 100750
A24: Amortização | B24: =SUM(C24:N24) -> 97404 | C24: 8117 | D24: 8117 | E24: 8117 | F24: 8117 | G24: 8117 | H24: 8117 | I24: 8117 | J24: 8117 | K24: 8117 | L24: 8117 | M24: 8117 | N24: 8117
A25: Resultado Liquido após impostos | B25: =B21-B23-B24 -> 2928052 | C25: =C21-C23-C24 -> 244106.42 | D25: =D21-D23-D24 -> 238629.17 | E25: =E21-E23-E24 -> 233878.94 | F25: =F21-F23-F24 -> 234578.94 | G25: =G21-G23-G24 -> 260567.99 | H25: =H21-H23-H24 -> 257499.73 | I25: =I21-I23-I24 -> 244120.62 | ... N25: =N21-N23-N24 -> 219117.81
A26: Margem liquida | B26: =B25/B3 -> 0.36328188 | C26: =C25/C3 -> 0.36343387 | D26: =D25/D3 -> 0.35527916 | E26: =E25/E3 -> 0.34820686 | F26: =F25/F3 -> 0.34924905 | G26: =G25/G3 -> 0.38794242 | H26: =H25/H3 -> 0.38337429 | I26: =I25/I3 -> 0.36345502 | ... N26: =N25/N3 -> 0.32622999
A27: Reserva bônus | B27: =B25*10% -> 292805.2 | C27: =C25*10% -> 24410.642 | D27: =D25*10% -> 23862.917 | E27: =E25*10% -> 23387.894 | F27: =F25*10% -> 23457.894 | G27: =G25*10% -> 26056.799 | H27: =H25*10% -> 25749.973 | I27: =I25*10% -> 24412.062 | ... N27: =N25*10% -> 21911.781
B96: =SUM(B97:B102) -> 0 | D96: =SUM(D97:D102) -> 0 | E96: =SUM(E97:E102) -> 0 | F96: =SUM(F97:F102) -> 0 | G96: =SUM(G97:G102) -> 0 | H96: =SUM(H97:H102) -> 0 | I96: =SUM(I97:I102) -> 0 | J96: =SUM(J97:J102) -> 0 | K96: =SUM(K97:K102) -> 0 | ... N96: =SUM(N97:N102) -> 0
A103: Assinaturas
B137: =SUM(B138:B141) -> 0 | D137: =SUM(D138:D141) -> 0 | E137: =SUM(E138:E141) -> 0 | F137: =SUM(F138:F141) -> 0 | G137: =SUM(G138:G141) -> 0 | H137: =SUM(H138:H141) -> 0 | I137: =SUM(I138:I141) -> 0 | J137: =SUM(J138:J141) -> 0 | K137: =SUM(K138:K141) -> 0 | ... N137: =SUM(N138:N141) -> 0
B168: =B4+B26+B51+B67+B73+B76+B90+B96+B103+B142+B152+B116+B137 -> 0.36328188 | D168: =D4+D26+D51+D67+D73+D76+D90+D96+D103+D142+D152+D116+D137 -> 0.35527916 | E168: =E4+E26+E51+E67+E73+E76+E90+E96+E103+E142+E152+E116+E137 -> 0.34820686 | F168: =F4+F26+F51+F67+F73+F76+F90+F96+F103+F142+F152+F116+F137 -> 0.34924905 | G168: =G4+G26+G51+G67+G73+G76+G90+G96+G103+G142+G152+G116+G137 -> 0.38794242 | H168: =H4+H26+H51+H67+H73+H76+H90+H96+H103+H142+H152+H116+H137 -> 0.38337429 | I168: =I4+I26+I51+I67+I73+I76+I90+I96+I103+I142+I152+I116+I137 -> 0.36345502 | J168: =J4+J26+J51+J67+J73+J76+J90+J96+J103+J142+J152+J116+J137 -> 0.38056003 | K168: =K4+K26+K51+K67+K73+K76+K90+K96+K103+K142+K152+K116+K137 -> 0.38242107 | ... N168: =N4+N26+N51+N67+N73+N76+N90+N96+N103+N142+N152+N116+N137 -> 0.32622999

Sheet Orçamento 2026
C1: 0.045
A2: Resultado Financeiro 2026 | B2: Soma JAN. a DEZ. | D2: Janeiro | E2: Fevereiro | F2: Março | G2: Abril | H2: Maio | I2: Junho | J2: Julho | K2: Agosto | L2: Setembro | M2: Outubro | N2: Novembro | O2: Dezembro
A3: Movimentação de Entradas | B3: =SUM(C3:O3) -> 8060000 | D3: 671666.67 | E3: 671666.67 | F3: 671666.67 | G3: 671666.67 | H3: 671666.67 | I3: 671666.67 | J3: 671666.67 | K3: 671666.67 | L3: 671666.67 | M3: 671666.67 | N3: 671666.67 | O3: 671666.67
A4: Receita de honorários | B4: =SUM(D4:O4) -> 0
A5: Custo equipe - Contencioso | B5: =SUM(D5:O5) -> 901597.73 | D5: =SUM(D6:D27) -> 75454.065 | E5: =SUM(E6:E27) -> 74454.065 | F5: =SUM(F6:F27) -> 74454.065 | G5: =SUM(G6:G27) -> 76054.065 | H5: =SUM(H6:H27) -> 74454.065 | I5: =SUM(I6:I27) -> 74454.065 | J5: =SUM(J6:J27) -> 76054.065 | K5: =SUM(K6:K27) -> 74454.065 | ... O5: =SUM(O6:O27) -> 75151.317
A6: Daniel Costa Caselta - Distribuição Mensal Fixa | B6: =SUM(D6:O6) -> 280548 | D6: ='[2]Tabela 2025 2026'!Q13 -> 23379 | E6: =D6 -> 23379 | F6: =E6 -> 23379 | G6: =F6 -> 23379 | H6: =G6 -> 23379 | I6: =H6 -> 23379 | J6: =I6 -> 23379 | K6: =J6 -> 23379 | L6: =K6 -> 23379 | ... O6: =N6 -> 23379
A7: Daniel Costa Caselta - Pro labore | B7: =SUM(D7:O7) -> 19452 | D7: ='[2]Tabela 2025 2026'!M14 -> 1621 | E7: =D7 -> 1621 | F7: =E7 -> 1621 | G7: =F7 -> 1621 | H7: =G7 -> 1621 | I7: =H7 -> 1621 | J7: =I7 -> 1621 | K7: =J7 -> 1621 | L7: =K7 -> 1621 | ... O7: =N7 -> 1621
A8: Daniel Costa Caselta - Convenio Medico | B8: =SUM(D8:O8) -> 21825.998 | D8: 1794.65 | E8: =D8 -> 1794.65 | F8: =E8 -> 1794.65 | G8: =F8 -> 1794.65 | H8: =G8 -> 1794.65 | I8: =H8 -> 1794.65 | J8: =I8 -> 1794.65 | K8: =J8 -> 1794.65 | L8: =K8 -> 1794.65 | M8: =L8+(L8*[2]Premissas!B4) -> 2063.8475 | N8: 1804.65 | O8: 1805.65
A9: Aurelio Marchini Santos - Distribuição Mensal Fixa | B9: =SUM(D9:O9) -> 140274 | D9: ='[2]Tabela 2025 2026'!Q13/2 -> 11689.5 | E9: =D9 -> 11689.5 | F9: =E9 -> 11689.5 | G9: =F9 -> 11689.5 | H9: =G9 -> 11689.5 | I9: =H9 -> 11689.5 | J9: =I9 -> 11689.5 | K9: =J9 -> 11689.5 | L9: =K9 -> 11689.5 | ... O9: =N9 -> 11689.5
A10: Aurelio Marchini Santos- Pro labore | B10: =SUM(D10:O10) -> 9726 | D10: ='[2]Tabela 2025 2026'!M13/2 -> 810.5 | E10: =D10 -> 810.5 | F10: =E10 -> 810.5 | G10: =F10 -> 810.5 | H10: =G10 -> 810.5 | I10: =H10 -> 810.5 | J10: =I10 -> 810.5 | K10: =J10 -> 810.5 | L10: =K10 -> 810.5 | ... O10: =N10 -> 810.5
A11: Aurelio Marchini Santos - Convenio Medico | B11: =SUM(D11:O11) -> 20483.176 | D11: =(3290.47/2) -> 1645.235 | E11: =D11 -> 1645.235 | F11: =E11 -> 1645.235 | G11: =F11 -> 1645.235 | H11: =G11 -> 1645.235 | I11: =H11 -> 1645.235 | J11: =I11 -> 1645.235 | K11: =J11 -> 1645.235 | L11: =K11 -> 1645.235 | M11: =(3290.47/2)*[2]Premissas!B4+'Orçamento 2026'!L11 -> 1892.0202 | N11: =M11 -> 1892.0202 | O11: =N11 -> 1892.0202
A12: Beatriz Baes Xavier - Distribuição Mensal Fixa | B12: =SUM(D12:O12) -> 90448.8 | D12: ='[2]Tabela 2025 2026'!Q4 -> 7537.4 | E12: =D12 -> 7537.4 | F12: =E12 -> 7537.4 | G12: =F12 -> 7537.4 | H12: =G12 -> 7537.4 | I12: =H12 -> 7537.4 | J12: =I12 -> 7537.4 | K12: =J12 -> 7537.4 | L12: =K12 -> 7537.4 | ... O12: =N12 -> 7537.4
A13: Beatriz Baes Xavier - Pro Labore | B13: =SUM(D13:O13) -> 19452 | D13: ='[2]Tabela 2025 2026'!M4 -> 1621 | E13: =D13 -> 1621 | F13: =E13 -> 1621 | G13: =F13 -> 1621 | H13: =G13 -> 1621 | I13: =H13 -> 1621 | J13: =I13 -> 1621 | K13: =J13 -> 1621 | L13: =K13 -> 1621 | ... O13: =N13 -> 1621
A14: Beatriz Baes Xavier - Convenio Medico | B14: =SUM(D14:O14) -> 16344.36 | D14: 1312.8 | E14: =D14 -> 1312.8 | F14: =E14 -> 1312.8 | G14: =F14 -> 1312.8 | H14: =G14 -> 1312.8 | I14: =H14 -> 1312.8 | J14: =I14 -> 1312.8 | K14: =J14 -> 1312.8 | L14: =K14 -> 1312.8 | M14: =1312.8*[2]Premissas!B4+'Orçamento 2026'!L14 -> 1509.72 | N14: =M14 -> 1509.72 | O14: =N14 -> 1509.72
A15: Beatriz Baes Xavier - Despesas Extras - Cartao Predio | B15: =SUM(D15:O15) -> 0
A16: Beatriz Baes Xavier - Reajuste de Distribuição Mensal Fixa | B16: =SUM(D16:O16) -> 0
A17: Isabel de Almeida Rego Campinho - Distribuição Mensal Fixa | B17: =SUM(D17:O17) -> 187260 | D17: ='[2]Tabela 2025 2026'!Q9 -> 15605 | E17: =D17 -> 15605 | F17: =E17 -> 15605 | G17: =F17 -> 15605 | H17: =G17 -> 15605 | I17: =H17 -> 15605 | J17: =I17 -> 15605 | K17: =J17 -> 15605 | L17: =K17 -> 15605 | ... O17: =N17 -> 15605
A18: Isabel de Almeida Rego Campinho - Pro Labore | B18: =SUM(D18:O18) -> 19452 | D18: ='[2]Tabela 2025 2026'!M9 -> 1621 | E18: =D18 -> 1621 | F18: =E18 -> 1621 | G18: =F18 -> 1621 | H18: =G18 -> 1621 | I18: =H18 -> 1621 | J18: =I18 -> 1621 | K18: =J18 -> 1621 | L18: =K18 -> 1621 | ... O18: =N18 -> 1621
A19: Isabel de Almeida Rego Campinho - Convenio Medico | B19: =SUM(D19:O19) -> 20131.401 | D19: 1616.98 | E19: 1616.98 | F19: 1616.98 | G19: 1616.98 | H19: 1616.98 | I19: 1616.98 | J19: 1616.98 | K19: 1616.98 | L19: 1616.98 | M19: =1616.98*[2]Premissas!B4+'Orçamento 2026'!L19 -> 1859.527 | N19: =M19 -> 1859.527 | O19: =N19 -> 1859.527
A20: Isabel de Almeida Rego Campinho - Reajuste de Distribuição Mensal Fixa | B20: =SUM(D20:O20) -> 0
A21: Joao Victor estagiario | B21: =SUM(D21:O21) -> 33000 | D21: 2200 | E21: 2800 | F21: 2800 | G21: 2800 | H21: 2800 | I21: 2800 | J21: 2800 | K21: 2800 | L21: 2800 | M21: 2800 | N21: 2800 | O21: 2800
A22: Joao Victor VT | B22: =SUM(D22:O22) -> 3600 | D22: 300 | E22: 300 | F22: 300 | G22: 300 | H22: 300 | I22: 300 | J22: 300 | K22: 300 | L22: 300 | M22: 300 | N22: 300 | O22: 300
A23: ISS Trimestral | B23: =SUM(D23:O23) -> 6400 | D23: 1600 | G23: 1600 | J23: 1600 | M23: 1600
A24: Seguro de vida | B24: =SUM(D24:O24) -> 0
A25: Vale Refeição | B25: =SUM(D25:O25) -> 13200 | D25: 1100 | E25: 1100 | F25: 1100 | G25: 1100 | H25: 1100 | I25: 1100 | J25: 1100 | K25: 1100 | L25: 1100 | M25: 1100 | N25: 1100 | O25: 1100
A26: Amortização | B26: =SUM(D26:O26) -> 0
A27: Participação/comissão/repasse - Contencioso | B27: =SUM(D27:O27) -> 0
A28: Custo equipe - Econômico | B28: =SUM(D28:O28) -> 914114.75 | D28: =SUM(D29:D51) -> 76879.165 | E28: =SUM(E29:E51) -> 75379.165 | F28: =SUM(F29:F51) -> 75379.165 | G28: =SUM(G29:G51) -> 76979.165 | H28: =SUM(H29:H51) -> 75379.165 | I28: =SUM(I29:I51) -> 75379.165 | J28: =SUM(J29:J51) -> 76979.165 | K28: =SUM(K29:K51) -> 75379.165 | ... O28: =SUM(O29:O51) -> 76467.423
A29: Ricardo Franco Botelho - Distribuição Mensal Fixa | B29: =SUM(D29:O29) -> 280548 | D29: ='[2]Tabela 2025 2026'!Q16 -> 23379 | E29: =D29 -> 23379 | F29: =E29 -> 23379 | G29: =F29 -> 23379 | H29: =G29 -> 23379 | I29: =H29 -> 23379 | J29: =I29 -> 23379 | K29: =J29 -> 23379 | L29: =K29 -> 23379 | ... O29: =N29 -> 23379
A30: Ricardo Franco Botelho - Pro labore | B30: =SUM(D30:O30) -> 19452 | D30: ='[2]Tabela 2025 2026'!M16 -> 1621 | E30: =D30 -> 1621 | F30: =E30 -> 1621 | G30: =F30 -> 1621 | H30: =G30 -> 1621 | I30: =H30 -> 1621 | J30: =I30 -> 1621 | K30: =J30 -> 1621 | L30: =K30 -> 1621 | ... O30: =N30 -> 1621
A31: Ricardo Franco Botelho - Convenio Medico | B31: =SUM(D31:O31) -> 30320.481 | D31: 2435.38 | E31: 2435.38 | F31: 2435.38 | G31: 2435.38 | H31: 2435.38 | I31: 2435.38 | J31: 2435.38 | K31: 2435.38 | L31: 2435.38 | M31: =2435.38*[2]Premissas!B4+'Orçamento 2026'!L31 -> 2800.687 | N31: =M31 -> 2800.687 | O31: =N31 -> 2800.687
A32: Aurelio Marchini Santos - Distribuição Mensal Fixa | B32: =SUM(D32:O32) -> 140274 | D32: ='[2]Tabela 2025 2026'!Q13/2 -> 11689.5 | E32: =D32 -> 11689.5 | F32: =E32 -> 11689.5 | G32: =F32 -> 11689.5 | H32: =G32 -> 11689.5 | I32: =H32 -> 11689.5 | J32: =I32 -> 11689.5 | K32: =J32 -> 11689.5 | L32: =K32 -> 11689.5 | ... O32: =N32 -> 11689.5
A33: Aurelio Marchini Santos- Pro labore | B33: =SUM(D33:O33) -> 9726 | D33: ='[2]Tabela 2025 2026'!M13/2 -> 810.5 | E33: =D33 -> 810.5 | F33: =E33 -> 810.5 | G33: =F33 -> 810.5 | H33: =G33 -> 810.5 | I33: =H33 -> 810.5 | J33: =I33 -> 810.5 | K33: =J33 -> 810.5 | L33: =K33 -> 810.5 | ... O33: =N33 -> 810.5
A34: Aurelio Marchini Santos - Convenio Medico | B34: =SUM(D34:O34) -> 19742.82 | D34: =(3290.47/2) -> 1645.235 | E34: =(3290.47/2) -> 1645.235 | F34: =(3290.47/2) -> 1645.235 | G34: =(3290.47/2) -> 1645.235 | H34: =(3290.47/2) -> 1645.235 | I34: =(3290.47/2) -> 1645.235 | J34: =(3290.47/2) -> 1645.235 | K34: =(3290.47/2) -> 1645.235 | L34: =(3290.47/2) -> 1645.235 | M34: =(3290.47/2)*[2]Premissas!B30+'Orçamento 2026'!L34 -> 1645.235 | N34: =M34 -> 1645.235 | O34: =N34 -> 1645.235
A35: Aurelio Marchini Santos - AASP | B35: =SUM(D35:O35) -> 1100 | E35: 100 | F35: 100 | G35: 100 | H35: 100 | I35: 100 | J35: 100 | K35: 100 | L35: 100 | M35: 100 | N35: 100 | O35: 100
A36: Bruno Micalli Pedrinelli - Distribuição Mensal Fixa | B36: =SUM(D36:O36) -> 96454.56 | D36: ='[2]Tabela 2025 2026'!Q5 -> 8037.88 | E36: =D36 -> 8037.88 | F36: =E36 -> 8037.88 | G36: =F36 -> 8037.88 | H36: =G36 -> 8037.88 | I36: =H36 -> 8037.88 | J36: =I36 -> 8037.88 | K36: =J36 -> 8037.88 | L36: =K36 -> 8037.88 | ... O36: =N36 -> 8037.88
A37: Bruno Micalli Pedrinelli - Pro Labore | B37: =SUM(D37:O37) -> 19452 | D37: ='[2]Tabela 2025 2026'!M5 -> 1621 | E37: =D37 -> 1621 | F37: =E37 -> 1621 | G37: =F37 -> 1621 | H37: =G37 -> 1621 | I37: =H37 -> 1621 | J37: =I37 -> 1621 | K37: =J37 -> 1621 | L37: =K37 -> 1621 | ... O37: =N37 -> 1621
A38: Bruno Micalli Pedrinelli - Convenio Medico | B38: =SUM(D38:O38) -> 16344.36 | D38: 1312.8 | E38: 1312.8 | F38: 1312.8 | G38: 1312.8 | H38: 1312.8 | I38: 1312.8 | J38: 1312.8 | K38: 1312.8 | L38: 1312.8 | M38: =1312.8*[2]Premissas!$B$4+'Orçamento 2026'!L38 -> 1509.72 | N38: =M38 -> 1509.72 | O38: =N38 -> 1509.72
A39: Bruno Micalli Pedrinelli - Reajuste de Distribuição Mensal Fixa | B39: =SUM(D39:O39) -> 0
A40: Elisa Hime Funari - Distribuição Mensal Fixa | B40: =SUM(D40:O40) -> 142548 | D40: ='[2]Tabela 2025 2026'!Q7 -> 11879 | E40: =D40 -> 11879 | F40: =E40 -> 11879 | G40: =F40 -> 11879 | H40: =G40 -> 11879 | I40: =H40 -> 11879 | J40: =I40 -> 11879 | K40: =J40 -> 11879 | L40: =K40 -> 11879 | ... O40: =N40 -> 11879
A41: Elisa Hime Funari - Pro Labore | B41: =SUM(D41:O41) -> 19452 | D41: ='[2]Tabela 2025 2026'!M7 -> 1621 | E41: =D41 -> 1621 | F41: =E41 -> 1621 | G41: =F41 -> 1621 | H41: =G41 -> 1621 | I41: =H41 -> 1621 | J41: =I41 -> 1621 | K41: =J41 -> 1621 | L41: =K41 -> 1621 | ... O41: =N41 -> 1621
A42: Elisa Hime Funari - Convenio Medico | B42: =SUM(D42:O42) -> 27316.172 | D42: =2194.07 -> 2194.07 | E42: =2194.07 -> 2194.07 | F42: =2194.07 -> 2194.07 | G42: =2194.07 -> 2194.07 | H42: =2194.07 -> 2194.07 | I42: =2194.07 -> 2194.07 | J42: =2194.07 -> 2194.07 | K42: =2194.07 -> 2194.07 | L42: =2194.07 -> 2194.07 | M42: =2194.07*[2]Premissas!B4+'Orçamento 2026'!L42 -> 2523.1805 | N42: =M42 -> 2523.1805 | O42: =N42 -> 2523.1805
A43: Elisa Hime Funari - Reajuste de Distribuição Mensal Fixa | B43: =SUM(D43:O43) -> 0
A44: Elisa Hime Funari - Convenio Medico | B44: =SUM(D44:O44) -> 0
A45: Andrielly da Silva Gonsalves - Distribuição Mensal Fixa | B45: =SUM(D45:O45) -> 49188 | D45: ='[2]Tabela 2025 2026'!Q3 -> 4099 | E45: =D45 -> 4099 | F45: =E45 -> 4099 | G45: =F45 -> 4099 | H45: =G45 -> 4099 | I45: =H45 -> 4099 | J45: =I45 -> 4099 | K45: =J45 -> 4099 | L45: =K45 -> 4099 | ... O45: =N45 -> 4099
A46: Andrielly da Silva Gonsalves - Pro Labore | B46: =SUM(D46:O46) -> 19452 | D46: ='[2]Tabela 2025 2026'!M3 -> 1621 | E46: =D46 -> 1621 | F46: =E46 -> 1621 | G46: =F46 -> 1621 | H46: =G46 -> 1621 | I46: =H46 -> 1621 | J46: =I46 -> 1621 | K46: =J46 -> 1621 | L46: =K46 -> 1621 | ... O46: =N46 -> 1621
A47: Andrielly da Silva Gonsalves - Convenio Medico | B47: =SUM(D47:O47) -> 16344.36 | D47: 1312.8 | E47: 1312.8 | F47: 1312.8 | G47: 1312.8 | H47: 1312.8 | I47: 1312.8 | J47: 1312.8 | K47: 1312.8 | L47: 1312.8 | M47: =1312.8*[2]Premissas!B4+'Orçamento 2026'!L47 -> 1509.72 | N47: =M47 -> 1509.72 | O47: =N47 -> 1509.72
A48: ISS Trimestral | B48: =SUM(D48:O48) -> 6400 | D48: 1600 | G48: 1600 | J48: 1600 | M48: 1600
A49: Seguro de vida | B49: =SUM(D49:O49) -> 0
A50: Vale Refeição | B50: =SUM(D50:O50) -> 0
A51: Vale Transporte | B51: =SUM(D51:O51) -> 0
A52: Participação/comissão/repasse - Economico | B52: =SUM(D52:O52) -> 0
A53: Custo equipe - Arbitragem e Compliance | B53: =D53+E53+F53+G53+H53+I53+J53+K53+L53+M53+N53+O53 -> 623198.16 | D53: =SUM(D54:D69) -> 63453.36 | E53: =SUM(E54:E69) -> 61853.36 | F53: =SUM(F54:F69) -> 49236.38 | G53: =SUM(G54:G69) -> 50836.38 | H53: =SUM(H54:H69) -> 49236.38 | I53: =SUM(I54:I69) -> 49236.38 | J53: =SUM(J54:J69) -> 50836.38 | K53: =SUM(K54:K69) -> 49236.38 | ... O53: =SUM(O54:O69) -> 49478.927
A54: Martim Della Valle - Distribuição Mensal Fixa | B54: =SUM(D54:O54) -> 280548 | D54: ='[2]Tabela 2025 2026'!Q15 -> 23379 | E54: =D54 -> 23379 | F54: =E54 -> 23379 | G54: =F54 -> 23379 | H54: =G54 -> 23379 | I54: =H54 -> 23379 | J54: =I54 -> 23379 | K54: =J54 -> 23379 | L54: =K54 -> 23379 | ... O54: =N54 -> 23379
A55: Martim Della Valle - Pro labore | B55: =SUM(D55:O55) -> 19452 | D55: ='[2]Tabela 2025 2026'!M15 -> 1621 | E55: =D55 -> 1621 | F55: =E55 -> 1621 | G55: =F55 -> 1621 | H55: =G55 -> 1621 | I55: =H55 -> 1621 | J55: =I55 -> 1621 | K55: =J55 -> 1621 | L55: =K55 -> 1621 | ... O55: =N55 -> 1621
A56: Felipe Sartório de Melo - Distribuição Mensal Fixa | B56: =SUM(D56:O56) -> 160912.8 | D56: ='[2]Tabela 2025 2026'!Q8 -> 13409.4 | E56: =D56 -> 13409.4 | F56: =E56 -> 13409.4 | G56: =F56 -> 13409.4 | H56: =G56 -> 13409.4 | I56: =H56 -> 13409.4 | J56: =I56 -> 13409.4 | K56: =J56 -> 13409.4 | L56: =K56 -> 13409.4 | ... O56: =N56 -> 13409.4
A57: Felipe Sartório de Melo - Pro Labore | B57: =SUM(D57:O57) -> 19452 | D57: ='[2]Tabela 2025 2026'!M8 -> 1621 | E57: =D57 -> 1621 | F57: =E57 -> 1621 | G57: =F57 -> 1621 | H57: =G57 -> 1621 | I57: =H57 -> 1621 | J57: =I57 -> 1621 | K57: =J57 -> 1621 | L57: =K57 -> 1621 | ... O57: =N57 -> 1621
A58: Felipe Sartório de Melo - Convenio Medico | B58: =SUM(D58:O58) -> 20131.401 | D58: 1616.98 | E58: 1616.98 | F58: 1616.98 | G58: 1616.98 | H58: 1616.98 | I58: 1616.98 | J58: 1616.98 | K58: 1616.98 | L58: 1616.98 | M58: =1616.98*[2]Premissas!B4+'Orçamento 2026'!L58 -> 1859.527 | N58: =M58 -> 1859.527 | O58: =N58 -> 1859.527
A59: Felipe Sartório de Melo - Reajuste de Distribuição Mensal Fixa | B59: =SUM(D59:O59) -> 0
A60: Joao | B60: =SUM(D60:O60) -> 18758 | D60: =11000-D61 -> 9379 | E60: =D60 -> 9379
A61: Joao | B61: =SUM(D61:O61) -> 3242 | D61: 1621 | E61: =D61 -> 1621
A62: Joao | B62: =SUM(D62:O62) -> 3233.96 | D62: 1616.98 | E62: 1616.98
A63: Emillly | B63: =SUM(D63:O63) -> 56322 | D63: =6320-D64 -> 4699 | E63: =6320-E64 -> 4698 | F63: =6320-F64 -> 4697 | G63: =6320-G64 -> 4696 | H63: =6320-H64 -> 4695 | I63: =6320-I64 -> 4694 | J63: =6320-J64 -> 4693 | K63: =6320-K64 -> 4692 | ... O63: =6320-O64 -> 4688
A64: Emillly | B64: =SUM(D64:O64) -> 19518 | D64: 1621 | E64: 1622 | F64: 1623 | G64: 1624 | H64: 1625 | I64: 1626 | J64: 1627 | K64: 1628 | L64: 1629 | M64: 1630 | N64: 1631 | O64: 1632
A65: Emillly | B65: =SUM(D65:O65) -> 15228 | D65: 1269 | E65: 1269 | F65: 1269 | G65: 1269 | H65: 1269 | I65: 1269 | J65: 1269 | K65: 1269 | L65: 1269 | M65: 1269 | N65: 1269 | O65: 1269
A66: ISS Trimestral | B66: =SUM(D66:O66) -> 6400 | D66: 1600 | G66: 1600 | J66: 1600 | M66: 1600
A67: Seguro de vida | B67: =SUM(D67:O67) -> 0
A68: Vale Refeição | B68: =SUM(D68:O68) -> 0
A69: Vale Transporte | B69: =SUM(D69:O69) -> 0
A70: Participação/comissão/repasse - Arbitragem | B70: =SUM(D70:O70) -> 0
A71: Despesas para Clientes | B71: =D71+E71+F71+G71+H71+I71+J71+K71+L71+M71+N71+O71 -> 0 | D71: =SUM(D72:D73) -> 0 | E71: =SUM(E72:E73) -> 0 | F71: =SUM(F72:F73) -> 0 | G71: =SUM(G72:G73) -> 0 | H71: =SUM(H72:H73) -> 0 | I71: =SUM(I72:I73) -> 0 | J71: =SUM(J72:J73) -> 0 | K71: =SUM(K72:K73) -> 0 | ... O71: =SUM(O72:O73) -> 0
A72: Não Reembolsáveis | B72: =SUM(D72:O72) -> 0
A73: Reembolsáveis | B73: =SUM(D73:O73) -> 0
A74: Ocupação | B74: =D74+E74+F74+G74+H74+I74+J74+K74+L74+M74+N74+O74 -> 410635.68 | D74: =SUM(D75:D80) -> 27197.48 | E74: =SUM(E75:E80) -> 34236.38 | F74: =SUM(F75:F80) -> 34236.38 | G74: =SUM(G75:G80) -> 34236.38 | H74: =SUM(H75:H80) -> 34236.38 | I74: =SUM(I75:I80) -> 35213.24 | J74: =SUM(J75:J80) -> 35213.24 | K74: =SUM(K75:K80) -> 35213.24 | ... O74: =SUM(O75:O80) -> 35213.24
A75: Aluguel | B75: =SUM(D75:O75) -> 267334.02 | D75: =26385-4677 -> 21708 | E75: =26385-4677 -> 21708 | F75: =26385-4677 -> 21708 | G75: =26385-4677 -> 21708 | H75: =26385-4677 -> 21708 | I75: =H75*[2]Premissas!B3+H75 -> 22684.86 | J75: =I75 -> 22684.86 | K75: =I75 -> 22684.86 | L75: =K75 -> 22684.86 | M75: =L75 -> 22684.86 | N75: =M75 -> 22684.86 | O75: =N75 -> 22684.86
A76: Condomínio | B76: =SUM(D76:O76) -> 54473.76 | D76: =4344*[2]Premissas!B3+4344 -> 4539.48 | E76: =D76 -> 4539.48 | F76: =E76 -> 4539.48 | G76: =F76 -> 4539.48 | H76: =G76 -> 4539.48 | I76: =H76 -> 4539.48 | J76: =I76 -> 4539.48 | K76: =J76 -> 4539.48 | L76: =K76 -> 4539.48 | ... O76: =N76 -> 4539.48
A77: Cameras Ed. Lacerda | B77: =SUM(D77:O77) -> 0
A78: Energia | B78: =SUM(D78:O78) -> 11400 | D78: 950 | E78: 950 | F78: 950 | G78: 950 | H78: 950 | I78: 950 | J78: 950 | K78: 950 | L78: 950 | M78: 950 | N78: 950 | O78: 950
A79: IPTU | B79: =SUM(D79:O79) -> 77427.9 | E79: =6399*[2]Premissas!B5+6399 -> 7038.9 | F79: =E79 -> 7038.9 | G79: =F79 -> 7038.9 | H79: =G79 -> 7038.9 | I79: =H79 -> 7038.9 | J79: =I79 -> 7038.9 | K79: =J79 -> 7038.9 | L79: =K79 -> 7038.9 | M79: =L79 -> 7038.9 | ... O79: =N79 -> 7038.9
A80: Seguro Locação | B80: =SUM(D80:O80) -> 0
A81: Telecomunicações | B81: =D81+E81+F81+G81+H81+I81+J81+K81+L81+M81+N81+O81 -> 10127.402 | D81: =SUM(D82:D83) -> 890 | E81: =SUM(E82:E83) -> 839.7638 | F81: =SUM(F82:F83) -> 839.7638 | G81: =SUM(G82:G83) -> 839.7638 | H81: =SUM(H82:H83) -> 839.7638 | I81: =SUM(I82:I83) -> 839.7638 | J81: =SUM(J82:J83) -> 839.7638 | K81: =SUM(K82:K83) -> 839.7638 | ... O81: =SUM(O82:O83) -> 839.7638
A82: Internet | B82: =SUM(D82:O82) -> 9286.1204 | D82: 810 | E82: 770.5564 | F82: 770.5564 | G82: 770.5564 | H82: 770.5564 | I82: 770.5564 | J82: 770.5564 | K82: 770.5564 | L82: 770.5564 | M82: 770.5564 | N82: 770.5564 | O82: 770.5564
A83: Telefonia Fixa | B83: =SUM(D83:O83) -> 841.2814 | D83: 80 | E83: 69.2074 | F83: 69.2074 | G83: 69.2074 | H83: 69.2074 | I83: 69.2074 | J83: 69.2074 | K83: 69.2074 | L83: 69.2074 | M83: 69.2074 | N83: 69.2074 | O83: 69.2074
A84: Despesas Gerais | B84: =D84+E84+F84+G84+H84+I84+J84+K84+L84+M84+N84+O84 -> 74921.85 | D84: =SUM(D85:D97) -> 7255 | E84: =SUM(E85:E97) -> 5505 | F84: =SUM(F85:F97) -> 5742.205 | G84: =SUM(G85:G97) -> 7292.205 | H84: =SUM(H85:H97) -> 5742.205 | I84: =SUM(I85:I97) -> 5683.605 | J84: =SUM(J85:J97) -> 7333.605 | K84: =SUM(K85:K97) -> 5683.605 | ... O84: =SUM(O85:O97) -> 5783.605
A85: Alteração Contrato Social | B85: =SUM(D85:O85) -> 3200 | D85: 800 | G85: 800 | J85: 800 | M85: 800
A86: Cartório | B86: =SUM(D86:O86) -> 0
A87: Cópias / Gráfica | B87: =SUM(D87:O87) -> 1200 | D87: 100 | E87: 100 | F87: 100 | G87: 100 | H87: 100 | I87: 100 | J87: 100 | K87: 100 | L87: 100 | M87: 100 | N87: 100 | O87: 100
A88: Correio | B88: =SUM(D88:O88) -> 1200 | D88: 100 | E88: 100 | F88: 100 | G88: 100 | H88: 100 | I88: 100 | J88: 100 | K88: 100 | L88: 100 | M88: 100 | N88: 100 | O88: 100
A89: Estacionamento (clientes) | B89: =SUM(D89:O89) -> 200 | D89: 50 | G89: 50 | J89: 50 | M89: 50
A90: Higiene e Copa | B90: =SUM(D90:O90) -> 6000 | D90: 500 | E90: 500 | F90: 500 | G90: 500 | H90: 500 | I90: 500 | J90: 500 | K90: 500 | L90: 500 | M90: 500 | N90: 500 | O90: 500
A91: Limpeza e Copeira | B91: =SUM(D91:O91) -> 37960.05 | D91: 3049 | E91: 3049 | F91: =E91*[2]Premissas!B3+'Orçamento 2026'!D91 -> 3186.205 | G91: =F91 -> 3186.205 | H91: =G91 -> 3186.205 | I91: =H91 -> 3186.205 | J91: =I91 -> 3186.205 | K91: =J91 -> 3186.205 | L91: =K91 -> 3186.205 | M91: =L91 -> 3186.205 | N91: =M91 -> 3186.205 | O91: =N91 -> 3186.205
A92: Manutenção ar condicionado | B92: =SUM(D92:O92) -> 11329.8 | D92: 920 | E92: 920 | F92: 920 | G92: 920 | H92: 920 | I92: =H92*[2]Premissas!B3+'Orçamento 2026'!H92 -> 961.4 | J92: =I92 -> 961.4 | K92: =J92 -> 961.4 | L92: =K92 -> 961.4 | M92: =L92 -> 961.4 | N92: =M92 -> 961.4 | O92: =N92 -> 961.4
A93: Manutenção do Escritório | B93: =SUM(D93:O93) -> 2000 | D93: 500 | G93: 500 | J93: 500 | M93: 500
A94: Manutenção do Jardim | B94: =SUM(D94:O94) -> 10032 | D94: 836 | E94: 836 | F94: 836 | G94: 836 | H94: 836 | I94: 836 | J94: 836 | K94: 836 | L94: 836 | M94: 836 | N94: 836 | O94: 836
A95: Material de Escritório | B95: =SUM(D95:O95) -> 1200 | D95: 300 | G95: 300 | J95: 300 | M95: 300
A96: Motoboy | B96: =SUM(D96:O96) -> 600 | D96: 100 | F96: 100 | H96: 100 | L96: 100 | N96: 100 | O96: 100
A97: Táxi | B97: =SUM(D97:O97) -> 0
A98: Consultoria | B98: =SUM(B99:B103) -> 287104.88 | D98: =SUM(D99:D103) -> 23240.8 | E98: =SUM(E99:E103) -> 23035.8 | F98: =SUM(F99:F103) -> 22815.8 | G98: =SUM(G99:G103) -> 23115.8 | H98: =SUM(H99:H103) -> 22815.8 | I98: =SUM(I99:I103) -> 23465.8 | J98: =SUM(J99:J103) -> 23240.8 | K98: =SUM(K99:K103) -> 24015.8 | ... O98: =SUM(O99:O103) -> 27532.561
A99: Consultoria Adm. e Financeira | B99: =SUM(D99:O99) -> 178454.88 | D99: 14705.8 | E99: 14705.8 | F99: 14705.8 | G99: 14705.8 | H99: 14705.8 | I99: 14705.8 | J99: 14705.8 | K99: 14705.8 | L99: 14705.8 | M99: =L99*[2]Premissas!B3+'Orçamento 2026'!L99 -> 15367.561 | N99: =M99 -> 15367.561 | O99: =N99 -> 15367.561
A100: Contabilidade BPO | B100: =SUM(D100:O100) -> 57120 | D100: 4760 | E100: 4760 | F100: 4760 | G100: 4760 | H100: 4760 | I100: 4760 | J100: 4760 | K100: 4760 | L100: 4760 | M100: 4760 | N100: 4760 | O100: 4760
...

Sheet Rateio Mensal
A1: JANEIRO | E1: Orçado | H1: DESPESAS RATEADAS | K1: Rateio anual
A2: =K2 -> Custo equipe - Contencioso | B2: ='Base_Resultado Mensal_V2'!C5 -> 73576.315 | C2: =+B2/B5 -> 0.34830232 | E2: ='Areas Sintetico atualizado'!B39 -> 75454.065 | F2: =E2/$E$5 -> 0.34966985 | H2: =('Base_Resultado Mensal_V2'!C198)-'Base_Resultado Mensal_V2'!C204-'Base_Resultado Mensal_V2'!C205-'Base_Resultado Mensal_V2'!C206 -> 97103.51 | I2: =$H$2*C2 -> 33821.378 | K2: ='DRE 2026'!A6 -> Custo equipe - Contencioso | L2: ='DRE 2026'!B6 -> 901597.73 | M2: =L2/$L$5 -> 0.36967231
A3: =K3 -> Custo equipe - Econômico | B3: ='Base_Resultado Mensal_V2'!C30 -> 75653.195 | C3: =+B3/B5 -> 0.35813404 | E3: ='Areas Sintetico atualizado'!B57 -> 76879.165 | F3: =E3/$E$5 -> 0.35627406 | I3: =$H$2*C3 -> 34776.073 | K3: ='DRE 2026'!A7 -> Custo equipe - Econômico | L3: ='DRE 2026'!B7 -> 914114.75 | M3: =L3/$L$5 -> 0.37480453
A4: =K4 -> Custo equipe - Arbitragem e Compliance | B4: ='Base_Resultado Mensal_V2'!C60 -> 62013.17 | C4: =B4/$B$5 -> 0.29356364 | E4: ='Areas Sintetico atualizado'!B75 -> 63453.36 | F4: =E4/$E$5 -> 0.29405609 | I4: =$H$2*C4 -> 28506.06 | K4: ='DRE 2026'!A8 -> Custo equipe - Arbitragem e Compliance | L4: ='DRE 2026'!B8 -> 623198.16 | M4: =L4/$L$5 -> 0.25552316
A5: Total das Áreas | B5: =SUM(B2:B4) -> 211242.68 | C5: =SUM(C2:C4) -> 1 | E5: =SUM(E2:E4) -> 215786.59 | K5: =A5 -> Total das Áreas | L5: =SUM(L2:L4) -> 2438910.6 | M5: =SUM(M2:M4) -> 1
A7: FEVEREIRO | L7: 12
A8: =K2 -> Custo equipe - Contencioso | B8: ='Base_Resultado Mensal_V2'!D5 -> 76342.345 | C8: =+B8/B11 -> 0.35188306 | E8: ='DRE 2026'!D6 -> 74454.065 | F8: =E8/$E$11 -> 0.35171838 | H8: ='Base_Resultado Mensal_V2'!D207 -> 86988.31 | I8: =$H$8*C8 -> 30609.712 | L8: =L2/$L$7 -> 75133.145 | M8: =L8-B8 -> -1209.2005
A9: =K3 -> Custo equipe - Econômico | B9: ='Base_Resultado Mensal_V2'!D30 -> 78817.055 | C9: =+B9/B11 -> 0.36328968 | E9: ='DRE 2026'!D7 -> 75379.165 | F9: =E9/$E$11 -> 0.35608852 | I9: =$H$8*C9 -> 31601.955 | L9: =L3/$L$7 -> 76176.229 | M9: =L9-B9 -> -2640.8256
A10: =K4 -> Custo equipe - Arbitragem e Compliance | B10: ='Base_Resultado Mensal_V2'!D60 -> 61794.34 | C10: =B10/$B$11 -> 0.28482726 | E10: ='DRE 2026'!D8 -> 61853.36 | F10: =E10/$E$11 -> 0.2921931 | I10: =$H$8*C10 -> 24776.642 | L10: =L4/$L$7 -> 51933.18 | M10: =L10-B10 -> -9861.1599
A11: =K5 -> Total das Áreas | B11: =SUM(B8:B10) -> 216953.74 | C11: =SUM(C8:C10) -> 1 | E11: =SUM(E8:E10) -> 211686.59
A13: MARÇO
A14: =A2 -> Custo equipe - Contencioso | B14: ='Base_Resultado Mensal_V2'!E5 -> 72845.495 | C14: =+B14/B17 -> 0.36775905 | E14: ='DRE 2026'!E6 -> 74454.065 | F14: =E14/$E$17 -> 0.3740102 | H14: ='Base_Resultado Mensal_V2'!E207 -> 93764.68 | I14: =$H$14*C14 -> 34482.809
A15: =A3 -> Custo equipe - Econômico | B15: ='Base_Resultado Mensal_V2'!E30 -> 76049.975 | C15: =+B15/B17 -> 0.3839368 | E15: ='DRE 2026'!E7 -> 75379.165 | F15: =E15/$E$17 -> 0.37865732 | I15: =$H$14*C15 -> 35999.711
A16: =A4 -> Custo equipe - Arbitragem e Compliance | B16: ='Base_Resultado Mensal_V2'!E60 -> 49183.94 | C16: =B16/$B$17 -> 0.24830415 | E16: ='DRE 2026'!E8 -> 49236.38 | F16: =E16/$E$17 -> 0.24733248 | I16: =$H$14*C16 -> 23282.159
A17: =A5 -> Total das Áreas | B17: =SUM(B14:B16) -> 198079.41 | C17: =SUM(C14:C16) -> 1 | E17: =SUM(E14:E16) -> 199069.61
A19: ABRIL
A20: =A8 -> Custo equipe - Contencioso | B20: ='Base_Resultado Mensal_V2'!F5 -> 75374.055 | C20: =+B20/B23 -> 0.35965566 | E20: ='DRE 2026'!F6 -> 76054.065 | F20: =E20/$E$23 -> 0.37305249 | H20: ='Base_Resultado Mensal_V2'!F207 -> 101209.18 | I20: =$H$20*C20 -> 36400.455
A21: =A9 -> Custo equipe - Econômico | B21: ='Base_Resultado Mensal_V2'!F30 -> 79160.085 | C21: =+B21/B23 -> 0.37772112 | E21: ='DRE 2026'!F7 -> 76979.165 | F21: =E21/$E$23 -> 0.37759019 | I21: =$H$20*C21 -> 38228.845
A22: =A10 -> Custo equipe - Arbitragem e Compliance | B22: ='Base_Resultado Mensal_V2'!F60 -> 55038.69 | C22: =B22/$B$23 -> 0.26262321 | E22: ='DRE 2026'!F8 -> 50836.38 | F22: =E22/$E$23 -> 0.24935732 | I22: =$H$20*C22 -> 26579.88
A23: =A11 -> Total das Áreas | B23: =SUM(B20:B22) -> 209572.83 | C23: =SUM(C20:C22) -> 1 | E23: =SUM(E20:E22) -> 203869.61
A25: MAIO
A26: =A14 -> Custo equipe - Contencioso | B26: ='Base_Resultado Mensal_V2'!G5 -> 74141.215 | C26: =+B26/B29 -> 0.35651431 | E26: ='DRE 2026'!G6 -> 74454.065 | F26: =E26/$E$23 -> 0.36520433 | H26: ='Base_Resultado Mensal_V2'!G207 -> 99730.65 | I26: =$H$26*C26 -> 35555.404
A27: =A15 -> Custo equipe - Econômico | B27: ='Base_Resultado Mensal_V2'!G30 -> 79436.245 | C27: =+B27/B29 -> 0.38197591 | E27: ='DRE 2026'!G7 -> 75379.165 | F27: =E27/$E$23 -> 0.36974204 | I27: =$H$26*C27 -> 38094.706
A28: =A16 -> Custo equipe - Arbitragem e Compliance | B28: ='Base_Resultado Mensal_V2'!G60 -> 54383.94 | C28: =B28/$B$29 -> 0.26150978 | E28: ='DRE 2026'!G8 -> 49236.38 | F28: =E28/$E$23 -> 0.24150917 | I28: =$H$26*C28 -> 26080.54
A29: =A17 -> Total das Áreas | B29: =SUM(B26:B28) -> 207961.4 | C29: =SUM(C26:C28) -> 1 | E29: =SUM(E26:E28) -> 199069.61

Sheet Fluxo consolidado 
B1: 671666.67
B2: Janeiro | C2: Fevereiro | D2: Março | E2: Abril | F2: Maio | G2: Junho | H2: Julho | I2: Agosto | J2: Setembro | K2: Outubro | L2: Novembro | M2: Dezembro | N2: 1
A3: Contencioso | B3: Realizado | C3: Realizado | D3: Realizado | E3: Realizado | F3: Realizado | G3: Realizado | H3: Realizado | I3: Realizado | J3: Realizado | K3: Realizado | L3: Realizado | M3: Realizado | N3: TOTAL
A4: Recebimento | B4: ='Areas Sintetico atualizado'!C36 -> 38071 | C4: ='Areas Sintetico atualizado'!G36 -> 159539 | D4: ='Areas Sintetico atualizado'!K36 -> 159925 | E4: ='Areas Sintetico atualizado'!O36 -> 56461 | N4: =B4+C4+D4+E4+F4+G4+H4+I4+J4+K4+L4+M4 -> 413996 | P4: Minimo de receita
A5: Equipe | B5: ='Areas Sintetico atualizado'!C39+'Areas Sintetico atualizado'!C40 -> 73576.315 | C5: ='Areas Sintetico atualizado'!G39 -> 76342.345 | D5: ='Areas Sintetico atualizado'!K39 -> 72845.495 | E5: ='Areas Sintetico atualizado'!O39 -> 75374.055 | N5: =B5+C5+D5+E5+F5+G5+H5+I5+J5+K5+L5+M5 -> 298138.21 | P5: =(N5+N6+N7+N8)/$N$2 -> 516667.89
A6: Despesas | B6: ='Areas Sintetico atualizado'!C41+'Areas Sintetico atualizado'!C42 -> 34881.473 | C6: ='Areas Sintetico atualizado'!G41+'Areas Sintetico atualizado'!G42+'Areas Sintetico atualizado'!G40 -> 32739.031 | D6: ='Areas Sintetico atualizado'!K41+'Areas Sintetico atualizado'!K42 -> 36829.528 | E6: ='Areas Sintetico atualizado'!O40+'Areas Sintetico atualizado'!O41+'Areas Sintetico atualizado'!O42 -> 40584.373 | N6: =B6+C6+D6+E6+F6+G6+H6+I6+J6+K6+L6+M6 -> 145034.4
A7: Impostos | B7: ='Areas Sintetico atualizado'!C46 -> 5710.65 | C7: ='Areas Sintetico atualizado'!G46 -> 23930.85 | D7: ='Areas Sintetico atualizado'!K46 -> 23988.75 | E7: ='Areas Sintetico atualizado'!O46 -> 8469.15 | N7: =B7+C7+D7+E7+F7+G7+H7+I7+J7+K7+L7+M7 -> 62099.4 | P7: Margem Liq.
A8: Investimento amortizaçao | B8: ='Areas Sintetico atualizado'!C47 -> 2827.1699 | C8: ='Areas Sintetico atualizado'!G47 -> 2856.2348 | D8: ='Areas Sintetico atualizado'!K47 -> 2856.2348 | E8: ='Areas Sintetico atualizado'!O47 -> 2856.2348 | N8: =B8+C8+D8+E8+F8+G8+H8+I8+J8+K8+L8+M8 -> 11395.874
A9: Margem liquida | B9: =B4-B5-B6-B7-B8 -> -78924.607 | C9: =C4-C5-C6-C7-C8 -> 23670.54 | D9: =D4-D5-D6-D7-D8 -> 23404.993 | E9: =E4-E5-E6-E7-E8 -> -70822.813 | F9: =F4-F5-F6-F7-F8 -> 0 | G9: =G4-G5-G6-G7-G8 -> 0 | H9: =H4-H5-H6-H7-H8 -> 0 | I9: =I4-I5-I6-I7-I8 -> 0 | ... N9: =N4-N5-N6-N7-N8 -> -102671.89 | P9: =N9/N4 -> -0.24800213
B11: Janeiro | C11: Fevereiro | D11: Março | E11: Abril | F11: Maio | G11: Junho | H11: Julho | I11: Agosto | J11: Setembro | K11: =K2 -> Outubro | L11: =L2 -> Novembro | M11: =M2 -> Dezembro
A12: Economico | B12: Realizado | C12: Realizado | D12: Realizado | E12: Realizado | F12: Realizado | G12: Realizado | H12: Realizado | I12: Realizado | J12: Realizado | K12: Realizado | L12: Realizado | M12: Realizado | N12: TOTAL
A13: Recebimento | B13: ='Areas Sintetico atualizado'!C54 -> 61844 | C13: ='Areas Sintetico atualizado'!G54 -> 119667 | D13: ='Areas Sintetico atualizado'!K54 -> 343893 | E13: ='Areas Sintetico atualizado'!O54 -> 159921 | N13: =B13+C13+D13+E13+F13+G13+H13+I13+J13+K13+L13+M13 -> 685325 | P13: Minimo de receita
A14: Equipe | B14: ='Areas Sintetico atualizado'!C57 -> 75653.195 | C14: ='Areas Sintetico atualizado'!G57 -> 78817.055 | D14: ='Areas Sintetico atualizado'!K57 -> 76049.975 | E14: ='Areas Sintetico atualizado'!O57 -> 79160.085 | N14: =B14+C14+D14+E14+F14+G14+H14+I14+J14+K14+L14+M14 -> 309680.31 | P14: =(N14+N15+N16+N17)/$N$2 -> 575765.6
A15: Despesas | B15: ='Areas Sintetico atualizado'!C59+'Areas Sintetico atualizado'!C60 -> 36647.878 | C15: ='Areas Sintetico atualizado'!G58+'Areas Sintetico atualizado'!G59+'Areas Sintetico atualizado'!G60 -> 36398.024 | D15: ='Areas Sintetico atualizado'!K59+'Areas Sintetico atualizado'!K60 -> 38129.03 | E15: ='Areas Sintetico atualizado'!O58+'Areas Sintetico atualizado'!O59+'Areas Sintetico atualizado'!O60 -> 40358.164 | N15: =B15+C15+D15+E15+F15+G15+H15+I15+J15+K15+L15+M15 -> 151533.09
A16: Impostos | B16: ='Areas Sintetico atualizado'!C64 -> 9276.6 | C16: ='Areas Sintetico atualizado'!G64 -> 17950.05 | D16: ='Areas Sintetico atualizado'!K64 -> 51583.95 | E16: ='Areas Sintetico atualizado'!O64 -> 23988.15 | N16: =B16+C16+D16+E16+F16+G16+H16+I16+J16+K16+L16+M16 -> 102798.75 | P16: Margem Liq.
A17: Investimento amortizaçao | B17: ='Areas Sintetico atualizado'!C65 -> 2906.974 | C17: ='Areas Sintetico atualizado'!G65 -> 2948.8223 | D17: ='Areas Sintetico atualizado'!K65 -> 2948.8223 | E17: ='Areas Sintetico atualizado'!O65 -> 2948.8223 | N17: =B17+C17+D17+E17+F17+G17+H17+I17+J17+K17+L17+M17 -> 11753.441
A18: Margem liquida | B18: =B13-B14-B15-B16-B17 -> -62640.647 | C18: =C13-C14-C15-C16-C17 -> -16446.951 | D18: =D13-D14-D15-D16-D17 -> 175181.22 | E18: =E13-E14-E15-E16-E17 -> 13465.779 | F18: =F13-F14-F15-F16-F17 -> 0 | G18: =G13-G14-G15-G16-G17 -> 0 | H18: =H13-H14-H15-H16-H17 -> 0 | I18: =I13-I14-I15-I16-I17 -> 0 | ... N18: =N13-N14-N15-N16-N17 -> 109559.4 | P18: =N18/N13 -> 0.15986489
B20: Janeiro | C20: Fevereiro | D20: Março | E20: Abril | F20: Maio | G20: Junho | H20: Julho | I20: Agosto | J20: Setembro | K20: =K2 -> Outubro | L20: =L2 -> Novembro | M20: =M2 -> Dezembro
A21: Arbitragem | B21: Realizado | C21: Realizado | D21: Realizado | E21: Realizado | F21: Realizado | G21: Realizado | H21: Realizado | I21: Realizado | J21: Realizado | K21: Realizado | L21: Realizado | M21: Realizado | N21: TOTAL
A22: Recebimento | B22: ='Areas Sintetico atualizado'!C72 -> 133169 | C22: ='Areas Sintetico atualizado'!G72 -> 62506 | D22: ='Areas Sintetico atualizado'!K72 -> 113444 | E22: ='Areas Sintetico atualizado'!O72 -> 3476 | N22: =B22+C22+D22+E22+F22+G22+H22+I22+J22+K22+L22+M22 -> 312595 | P22: Minimo de receita
A23: Equipe | B23: ='Areas Sintetico atualizado'!C75 -> 62013.17 | C23: ='Areas Sintetico atualizado'!G75 -> 61794.34 | D23: ='Areas Sintetico atualizado'!K75 -> 49183.94 | E23: ='Areas Sintetico atualizado'!O75 -> 55038.69 | N23: =B23+C23+D23+E23+F23+G23+H23+I23+J23+K23+L23+M23 -> 228030.14 | P23: =(N23+N24+N25+N26)/$N$2 -> 396524.39
A24: Despesas | B24: ='Areas Sintetico atualizado'!C77+'Areas Sintetico atualizado'!C78 -> 28652.06 | C24: ='Areas Sintetico atualizado'!G76+'Areas Sintetico atualizado'!G77+'Areas Sintetico atualizado'!G78 -> 27410.336 | D24: ='Areas Sintetico atualizado'!K77+'Areas Sintetico atualizado'!K78 -> 27010.343 | E24: ='Areas Sintetico atualizado'!O76+'Areas Sintetico atualizado'!O77+'Areas Sintetico atualizado'!O78 -> 29213.573 | N24: =B24+C24+D24+E24+F24+G24+H24+I24+J24+K24+L24+M24 -> 112286.31
A25: Impostos | B25: ='Areas Sintetico atualizado'!C82 -> 19975.35 | C25: ='Areas Sintetico atualizado'!G82 -> 9375.9 | D25: ='Areas Sintetico atualizado'!K82 -> 17016.6 | E25: ='Areas Sintetico atualizado'!O82 -> 521.4 | N25: =B25+C25+D25+E25+F25+G25+H25+I25+J25+K25+L25+M25 -> 46889.25 | P25: Margem Liq.
A26: Investimento amortizaçao | B26: ='Areas Sintetico atualizado'!C83 -> 2382.8561 | C26: ='Areas Sintetico atualizado'!G83 -> 2311.9429 | D26: ='Areas Sintetico atualizado'!K83 -> 2311.9429 | E26: ='Areas Sintetico atualizado'!O83 -> 2311.9429 | N26: =B26+C26+D26+E26+F26+G26+H26+I26+J26+K26+L26+M26 -> 9318.6847
A27: Margem liquida | B27: =B22-B23-B24-B25-B26 -> 20145.564 | C27: =C22-C23-C24-C25-C26 -> -38386.518 | D27: =D22-D23-D24-D25-D26 -> 17921.174 | E27: =E22-E23-E24-E25-E26 -> -83609.606 | F27: =F22-F23-F24-F25-F26 -> 0 | G27: =G22-G23-G24-G25-G26 -> 0 | H27: =H22-H23-H24-H25-H26 -> 0 | I27: =I22-I23-I24-I25-I26 -> 0 | ... N27: =N22-N23-N24-N25-N26 -> -83929.386 | P27: =N27/N22 -> -0.26849241
B30: =B4+B13+B22 -> 233084 | C30: =C4+C13+C22 -> 341712 | D30: =D4+D13+D22 -> 617262 | E30: =E4+E13+E22 -> 219858 | F30: =F4+F13+F22 -> 0 | G30: =G4+G13+G22 -> 0 | H30: =H4+H13+H22 -> 0 | I30: =I4+I13+I22 -> 0 | ... M30: =M4+M13+M22 -> 0 | N30: =B30+C30+D30+E30+F30+G30+H30+I30+J30+K30+L30+M30 -> 1411916
N31: =N5+N14+N23 -> 835848.66

Sheet Base_Resultado Mensal_V2
A2: Resultado Financeiro 2026 | B2: ANUAL | C2: Janeiro | D2: Fevereiro | E2: Março | F2: Abril | G2: Maio | H2: Junho | I2: Julho | J2: Agosto | K2: Setembro | L2: Outubro | M2: Novembro | N2: Dezembro
A3: Movimentação de Entradas | C3: =SUM(C4:C4) -> 279821.07 | D3: =SUM(D4:D4) -> 319233.58 | E3: =SUM(E4:E4) -> 612501.76 | F3: =SUM(F4:F4) -> 238327.46 | G3: =SUM(G4:G4) -> 415928 | H3: =SUM(H4:H4) -> 0 | I3: =SUM(I4:I4) -> 0 | J3: =SUM(J4:J4) -> 0 | ... N3: =SUM(N4:N4) -> 0
A4: Receita de honorários | B4: =SUM(C4:N4) -> 1865811.9 | C4: 279821.07 | D4: 319233.58 | E4: 612501.76 | F4: 238327.46 | G4: 415928 | O4: =C4+D4+E4+F4+G4+H4+I4+J4+K4+L4+M4+N4 -> 1865811.9
A5: Custo equipe - Contencioso | B5: =SUM(C5:N5) -> 372279.42 | C5: =SUM(C6:C27) -> 73576.315 | D5: =SUM(D6:D27) -> 76342.345 | E5: =SUM(E6:E27) -> 72845.495 | F5: =SUM(F6:F27) -> 75374.055 | G5: =SUM(G6:G27) -> 74141.215 | H5: =SUM(H6:H27) -> 0 | I5: =SUM(I6:I27) -> 0 | J5: =SUM(J6:J27) -> 0 | ... N5: =SUM(N6:N27) -> 0 | O5: =C5+D5+E5+F5+G5+H5+I5+J5+K5+L5+M5+N5 -> 372279.42
A6: Aurelio Marchini Santos - Convenio Medico | B6: =SUM(C6:N6) -> 8752.795 | C6: =3182.83/2 -> 1591.415 | D6: =3182.83/2 -> 1591.415 | E6: =3182.83/2 -> 1591.415 | F6: =3182.83/2 -> 1591.415 | G6: =4774.27/2 -> 2387.135 | O6: =C6+D6+E6+F6+G6+H6+I6+J6+K6+L6+M6+N6 -> 8752.795
A7: Aurelio Marchini Santos - Distribuição Mensal Fixa | B7: =SUM(C7:N7) -> 58447.5 | C7: =12500-C8 -> 11689.5 | D7: =12500-D8 -> 11689.5 | E7: =12500-E8 -> 11689.5 | F7: =12500-F8 -> 11689.5 | G7: =12500-G8 -> 11689.5 | O7: =C7+D7+E7+F7+G7+H7+I7+J7+K7+L7+M7+N7 -> 58447.5
A8: Aurelio Marchini Santos- Pro labore | B8: =SUM(C8:N8) -> 4052.5 | C8: 810.5 | D8: 810.5 | E8: =1621/2 -> 810.5 | F8: =1621/2 -> 810.5 | G8: =1621/2 -> 810.5 | O8: =C8+D8+E8+F8+G8+H8+I8+J8+K8+L8+M8+N8 -> 4052.5
A9: Aurelio Marchini Santos- AASP | B9: =SUM(C9:N9) -> 54.35 | D9: =108.7/2 -> 54.35
A10: Beatriz Baes Xavier - Convenio Medico | B10: =SUM(C10:N10) -> 6347.3 | C10: 1269.46 | D10: 1269.46 | E10: 1269.46 | F10: 1269.46 | G10: 1269.46 | O10: =C10+D10+E10+F10+G10+H10+I10+J10+K10+L10+M10+N10 -> 6347.3
A11: Beatriz Baes Xavier - Despesas Extras - Cartao Predio | B11: =SUM(C11:N11) -> 0 | O11: =C11+D11+E11+F11+G11+H11+I11+J11+K11+L11+M11+N11 -> 0
A12: Beatriz Baes Xavier - Distribuição Mensal Fixa | B12: =SUM(C12:N12) -> 38168.6 | C12: =8640-C13 -> 7019 | D12: =9158.4-D13 -> 7537.4 | E12: =9158.4-E13 -> 7537.4 | F12: =9158.4-F13+500 -> 8037.4 | G12: =9158.4-G13+500 -> 8037.4 | O12: =C12+D12+E12+F12+G12+H12+I12+J12+K12+L12+M12+N12 -> 38168.6
A13: Beatriz Baes Xavier - Pro Labore | B13: =SUM(C13:N13) -> 8105 | C13: 1621 | D13: 1621 | E13: 1621 | F13: 1621 | G13: 1621 | O13: =C13+D13+E13+F13+G13+H13+I13+J13+K13+L13+M13+N13 -> 8105
A14: Beatriz Baes Xavier - Reajuste de Distribuição Mensal Fixa | B14: =SUM(C14:N14) -> 518.4 | D14: 518.4 | O14: =C14+D14+E14+F14+G14+H14+I14+J14+K14+L14+M14+N14 -> 518.4
A15: Daniel Costa Caselta - Convenio Medico | B15: =SUM(C15:N15) -> 8680.7 | C15: 1736.14 | D15: 1736.14 | E15: 1736.14 | F15: 1736.14 | G15: 1736.14 | O15: =C15+D15+E15+F15+G15+H15+I15+J15+K15+L15+M15+N15 -> 8680.7
A16: Daniel Costa Caselta - Distribuição Mensal Fixa | B16: =SUM(C16:N16) -> 116895 | C16: =25000-C17 -> 23379 | D16: =25000-D17 -> 23379 | E16: =25000-E17 -> 23379 | F16: =25000-F17 -> 23379 | G16: =25000-G17 -> 23379 | O16: =C16+D16+E16+F16+G16+H16+I16+J16+K16+L16+M16+N16 -> 116895
A17: Daniel Costa Caselta - Pro labore | B17: =SUM(C17:N17) -> 8105 | C17: 1621 | D17: 1621 | E17: 1621 | F17: 1621 | G17: 1621 | O17: =C17+D17+E17+F17+G17+H17+I17+J17+K17+L17+M17+N17 -> 8105
A18: Daniel Costa Caselta - AASP | B18: =SUM(C18:N18) -> 206.4 | C18: 97.7 | D18: 108.7 | O18: =C18+D18+E18+F18+G18+H18+I18+J18+K18+L18+M18+N18 -> 206.4
A19: Isabel de Almeida Rego Campinho - Convenio Medico | B19: =SUM(C19:N19) -> 7820.4 | C19: 1564.08 | D19: 1564.08 | E19: 1564.08 | F19: 1564.08 | G19: 1564.08 | O19: =C19+D19+E19+F19+G19+H19+I19+J19+K19+L19+M19+N19 -> 7820.4
A20: Isabel de Almeida Rego Campinho - Distribuição Mensal Fixa | B20: =SUM(C20:N20) -> 76459 | C20: =15660-C21 -> 14039 | D20: =17226-D21 -> 15605 | E20: =17226-E21 -> 15605 | F20: =17226-F21 -> 15605 | G20: =17226-G21 -> 15605 | O20: =C20+D20+E20+F20+G20+H20+I20+J20+K20+L20+M20+N20 -> 76459
A21: Isabel de Almeida Rego Campinho - Pro Labore | B21: =SUM(C21:N21) -> 8105 | C21: 1621 | D21: 1621 | E21: 1621 | F21: 1621 | G21: 1621 | O21: =C21+D21+E21+F21+G21+H21+I21+J21+K21+L21+M21+N21 -> 8105
A22: Isabel de Almeida Rego Campinho - Reajuste de Distribuição Mensal Fixa | B22: =SUM(C22:N22) -> 1566 | D22: 1566 | O22: =C22+D22+E22+F22+G22+H22+I22+J22+K22+L22+M22+N22 -> 1566
A23: João Victor Santos de Oliveira - Bolsa auxilio / IR Estagiários | B23: =SUM(C23:N23) -> 14000 | C23: 2800 | D23: 2800 | E23: 2800 | F23: 2800 | G23: 2800 | O23: =C23+D23+E23+F23+G23+H23+I23+J23+K23+L23+M23+N23 -> 14000
A24: João Victor Santos de Oliveira - Seguro de Vida | B24: =SUM(C24:N24) -> 0 | O24: =C24+D24+E24+F24+G24+H24+I24+J24+K24+L24+M24+N24 -> 0
A25: ISS Trimestral | B25: =SUM(C25:N25) -> 3748.28 | C25: =382.16*4+191.08 -> 1719.72 | F25: =507.14*4 -> 2028.56 | O25: =C25+D25+E25+F25+G25+H25+I25+J25+K25+L25+M25+N25 -> 3748.28
A26: Vale Refeição | B26: =SUM(C26:N26) -> 1844 | C26: 829.8 | D26: 1014.2 | O26: =C26+D26+E26+F26+G26+H26+I26+J26+K26+L26+M26+N26 -> 1844
A27: Vale Transporte | B27: =SUM(C27:N27) -> 403.2 | C27: 168 | D27: 235.2 | O27: =C27+D27+E27+F27+G27+H27+I27+J27+K27+L27+M27+N27 -> 403.2
A28: Participação/Comissão - Contencioso | B28: =SUM(C28:N28) -> 0 | O28: =C28+D28+E28+F28+G28+H28+I28+J28+K28+L28+M28+N28 -> 0
A29: Repasse - Contencioso | B29: =SUM(C29:N29) -> 0 | O29: =C29+D29+E29+F29+G29+H29+I29+J29+K29+L29+M29+N29 -> 0
A30: Custo equipe - Econômico | B30: =SUM(B31:B57) -> 389116.56 | C30: =SUM(C31:C57) -> 75653.195 | D30: =SUM(D31:D57) -> 78817.055 | E30: =SUM(E31:E57) -> 76049.975 | F30: =SUM(F31:F57) -> 79160.085 | G30: =SUM(G31:G57) -> 79436.245 | H30: =SUM(H31:H57) -> 0 | I30: =SUM(I31:I57) -> 0 | ... N30: =SUM(N31:N57) -> 0 | O30: =C30+D30+E30+F30+G30+H30+I30+J30+K30+L30+M30+N30 -> 389116.55
A31: Andrielly da Silva Gonsalves - Convenio Medico | B31: =SUM(C31:N31) -> 5642.76 | C31: 1269.46 | D31: 564.92 | E31: 1269.46 | F31: 1269.46 | G31: 1269.46 | O31: =C31+D31+E31+F31+G31+H31+I31+J31+K31+L31+M31+N31 -> 5642.76
A32: Andrielly da Silva Gonsalves - Distribuição Mensal Fixa | B32: =SUM(C32:N32) -> 18457 | C32: =5200-C33 -> 3579 | D32: =5720-D33 -> 4099 | E32: =6220-E33-1509 -> 3090 | F32: =6220-F33-1509 -> 3090 | G32: =6220-G33 -> 4599 | O32: =C32+D32+E32+F32+G32+H32+I32+J32+K32+L32+M32+N32 -> 18457
A33: Andrielly da Silva Gonsalves - Pro Labore | B33: =SUM(C33:N33) -> 8105 | C33: 1621 | D33: 1621 | E33: 1621 | F33: 1621 | G33: 1621 | O33: =C33+D33+E33+F33+G33+H33+I33+J33+K33+L33+M33+N33 -> 8105
A34: Andrielly da Silva Gonsalves - Subsidio de Pós | B34: =SUM(C34:N34) -> 3018 | D34: =1509+1509 -> 3018 | O34: =C34+D34+E34+F34+G34+H34+I34+J34+K34+L34+M34+N34 -> 3018
A35: Andrielly da Silva Gonsalves - Reajuste de Distribuição Mensal Fixa | B35: =SUM(C35:N35) -> 520 | D35: 520 | O35: =C35+D35+E35+F35+G35+H35+I35+J35+K35+L35+M35+N35 -> 520
A36: Aurelio Marchini Santos - AASP | B36: =SUM(C36:N36) -> 152.05 | C36: 97.7 | D36: =108.7/2 -> 54.35 | O36: =C36+D36+E36+F36+G36+H36+I36+J36+K36+L36+M36+N36 -> 152.05
A37: Aurelio Marchini Santos - Convenio Medico | B37: =SUM(C37:N37) -> 8752.795 | C37: =3182.83/2 -> 1591.415 | D37: =3182.83/2 -> 1591.415 | E37: =3182.83/2 -> 1591.415 | F37: =3182.83/2 -> 1591.415 | G37: =4774.27/2 -> 2387.135 | O37: =C37+D37+E37+F37+G37+H37+I37+J37+K37+L37+M37+N37 -> 8752.795
A38: Aurelio Marchini Santos - Distribuição Mensal Fixa | B38: =SUM(C38:N38) -> 58447.5 | C38: =12500-C39 -> 11689.5 | D38: =12500-D39 -> 11689.5 | E38: =12500-E39 -> 11689.5 | F38: =12500-F39 -> 11689.5 | G38: =12500-G39 -> 11689.5 | O38: =C38+D38+E38+F38+G38+H38+I38+J38+K38+L38+M38+N38 -> 58447.5
A39: Aurelio Marchini Santos- Pro labore | B39: =SUM(C39:N39) -> 4052.5 | C39: 810.5 | D39: 810.5 | E39: =1621/2 -> 810.5 | F39: =1621/2 -> 810.5 | G39: =1621/2 -> 810.5 | O39: =C39+D39+E39+F39+G39+H39+I39+J39+K39+L39+M39+N39 -> 4052.5
A40: Bruno Micalli Pedrinelli - Convenio Medico | B40: =SUM(C40:N40) -> 5642.76 | C40: 1269.46 | D40: 564.92 | E40: 1269.46 | F40: 1269.46 | G40: 1269.46 | O40: =C40+D40+E40+F40+G40+H40+I40+J40+K40+L40+M40+N40 -> 5642.76
A41: Bruno Micalli Pedrinelli - Distribuição Mensal Fixa | B41: =SUM(C41:N41) -> 43177.88 | C41: =8624-C42 -> 7003 | D41: =9658.88-D42 -> 8037.88 | E41: =11000-E42 -> 9379 | F41: =11000-F42 -> 9379 | G41: =11000-G42 -> 9379 | O41: =C41+D41+E41+F41+G41+H41+I41+J41+K41+L41+M41+N41 -> 43177.88
A42: Bruno Micalli Pedrinelli - Pro Labore | B42: =SUM(C42:N42) -> 8105 | C42: 1621 | D42: 1621 | E42: 1621 | F42: 1621 | G42: 1621 | O42: =C42+D42+E42+F42+G42+H42+I42+J42+K42+L42+M42+N42 -> 8105
A43: Bruno Micalli Pedrinelli - Reajuste de Distribuição Mensal Fixa | B43: =SUM(C43:N43) -> 1034.38 | D43: 1034.38 | O43: =C43+D43+E43+F43+G43+H43+I43+J43+K43+L43+M43+N43 -> 1034.38
A44: Elisa Hime Funari - Convenio Medico | B44: =SUM(C44:N44) -> 7820.5 | C44: 1564.1 | D44: 1564.1 | E44: 1564.1 | F44: 1564.1 | G44: 1564.1 | O44: =C44+D44+E44+F44+G44+H44+I44+J44+K44+L44+M44+N44 -> 7820.5
A45: Elisa Hime Funari - Distribuição Mensal Fixa | B45: =SUM(C45:N45) -> 58395 | C45: =12500-C46 -> 10879 | D45: =13500-D46 -> 11879 | E45: =13500-E46 -> 11879 | F45: =13500-F46 -> 11879 | G45: =13500-G46 -> 11879 | O45: =C45+D45+E45+F45+G45+H45+I45+J45+K45+L45+M45+N45 -> 58395
A46: Elisa Hime Funari - Pro Labore | B46: =SUM(C46:N46) -> 8105 | C46: 1621 | D46: 1621 | E46: 1621 | F46: 1621 | G46: 1621 | O46: =C46+D46+E46+F46+G46+H46+I46+J46+K46+L46+M46+N46 -> 8105
A47: Elisa Hime Funari - Reajuste de Distribuição Mensal Fixa | B47: =SUM(C47:N47) -> 1000 | D47: 1000 | O47: =C47+D47+E47+F47+G47+H47+I47+J47+K47+L47+M47+N47 -> 1000
A48: Ricardo Franco Botelho - Convenio Medico | B48: =SUM(C48:N48) -> 12630.45 | C48: 2526.09 | D48: 2526.09 | E48: 2526.09 | F48: 2526.09 | G48: 2526.09 | O48: =C48+D48+E48+F48+G48+H48+I48+J48+K48+L48+M48+N48 -> 12630.45
A49: Ricardo Franco Botelho - Distribuição Mensal Fixa | B49: =SUM(C49:N49) -> 116895 | C49: =25000-C50 -> 23379 | D49: =25000-D50 -> 23379 | E49: =25000-E50 -> 23379 | F49: =25000-F50 -> 23379 | G49: =25000-G50 -> 23379 | O49: =C49+D49+E49+F49+G49+H49+I49+J49+K49+L49+M49+N49 -> 116895
A50: Ricardo Franco Botelho - Pro labore | B50: =SUM(C50:N50) -> 8105 | C50: 1621 | D50: 1621 | E50: 1621 | F50: 1621 | G50: 1621 | O50: =C50+D50+E50+F50+G50+H50+I50+J50+K50+L50+M50+N50 -> 8105
A51: Victoria Malta Corradini - Convenio Medico | B51: =SUM(C51:N51) -> 1409.09 | C51: 1409.09 | O51: =C51+D51+E51+F51+G51+H51+I51+J51+K51+L51+M51+N51 -> 1409.09
A52: Vitoria Santos de Rezende Bolsa auxilio / IR Estagiários | B52: =SUM(C52:N52) -> 5426 | E52: 1026 | F52: 2200 | G52: 2200 | O52: =C52+D52+E52+F52+G52+H52+I52+J52+K52+L52+M52+N52 -> 5426
A53: Vitoria Santos de Rezende Seguro de vida | B53: =SUM(C53:N53) -> 0 | O53: =C53+D53+E53+F53+G53+H53+I53+J53+K53+L53+M53+N53 -> 0
A54: ISS - Trimestral | B54: =SUM(C54:N54) -> 4130.44 | C54: =382.16*5+191.08 -> 2101.88 | F54: =507.14*4 -> 2028.56 | O54: =C54+D54+E54+F54+G54+H54+I54+J54+K54+L54+M54+N54 -> 4130.44
A55: Seguro de Vida | B55: =SUM(C55:N55) -> 92.45 | E55: 92.45 | O55: =C55+D55+E55+F55+G55+H55+I55+J55+K55+L55+M55+N55 -> 92.45
A56: Vale Refeição | B56: =SUM(C56:N56) -> 0 | O56: =C56+D56+E56+F56+G56+H56+I56+J56+K56+L56+M56+N56 -> 0
A57: Vale Transporte | B57: =SUM(C57:N57) -> 0 | O57: =C57+D57+E57+F57+G57+H57+I57+J57+K57+L57+M57+N57 -> 0
A58: Participação/comissão - Economico | B58: =SUM(C58:N58) -> 3628.06 | D58: 1500 | G58: 2128.06 | O58: =C58+D58+E58+F58+G58+H58+I58+J58+K58+L58+M58+N58 -> 3628.06
A59: Repasse - Economico | B59: =SUM(C59:N59) -> 0 | O59: =C59+D59+E59+F59+G59+H59+I59+J59+K59+L59+M59+N59 -> 0
A60: Custo equipe - Arbitragem e Compliance | B60: =SUM(C60:N60) -> 282414.08 | C60: =SUM(C61:C79) -> 62013.17 | D60: =SUM(D61:D79) -> 61794.34 | E60: =SUM(E61:E79) -> 49183.94 | F60: =SUM(F61:F79) -> 55038.69 | G60: =SUM(G61:G79) -> 54383.94 | H60: =SUM(H61:H79) -> 0 | I60: =SUM(I61:I79) -> 0 | J60: =SUM(J61:J79) -> 0 | ... M60: =SUM(M61:M79) -> 0 | N60: =SUM(N61:N81) -> 0 | O60: =C60+D60+E60+F60+G60+H60+I60+J60+K60+L60+M60+N60 -> 282414.08
A61: Emilly Kauany Martins Calixto - Ajuda de Custo VR | B61: =SUM(C61:N61) -> 0
A62: Emilly Kauany Martins Calixto - Convenio medico | B62: =SUM(C62:N62) -> 6346.84 | C62: 1269 | D62: 1269.46 | E62: 1269.46 | F62: 1269.46 | G62: 1269.46
A63: Emilly Kauany Martins Calixto - Distribuição Mensal Fixa | B63: =SUM(C63:N63) -> 23495 | C63: =6320-C64 -> 4699 | D63: =6320-D64 -> 4699 | E63: =6320-E64 -> 4699 | F63: =6320-F64 -> 4699 | G63: =6320-G64 -> 4699
A64: Emilly Kauany Martins Calixto - Pro Labore | B64: =SUM(C64:N64) -> 8105 | C64: 1621 | D64: 1621 | E64: 1621 | F64: 1621 | G64: 1621
A65: Felipe Sartório de Melo - Convenio Medico | B65: =SUM(C65:N65) -> 7820.4 | C65: 1564.08 | D65: 1564.08 | E65: 1564.08 | F65: 1564.08 | G65: 1564.08 | O65: =C65+D65+E65+F65+G65+H65+I65+J65+K65+L65+M65+N65 -> 7820.4
A66: Felipe Sartório de Melo - Distribuição Mensal Fixa | B66: =SUM(C66:N66) -> 65436.6 | C66: =13420-C67 -> 11799 | D66: =15030.4-D67 -> 13409.4 | E66: =15030.4-E67 -> 13409.4 | F66: =15030.4-F67 -> 13409.4 | G66: =15030.4-G67 -> 13409.4 | O66: =C66+D66+E66+F66+G66+H66+I66+J66+K66+L66+M66+N66 -> 65436.6
A67: Felipe Sartório de Melo - Pro Labore | B67: =SUM(C67:N67) -> 8105 | C67: 1621 | D67: 1621 | E67: 1621 | F67: 1621 | G67: 1621 | O67: =C67+D67+E67+F67+G67+H67+I67+J67+K67+L67+M67+N67 -> 8105
A68: Felipe Sartório de Melo - Reajuste de Distribuição Mensal Fixa | B68: =SUM(C68:N68) -> 1610.4 | D68: 1610.4 | O68: =C68+D68+E68+F68+G68+H68+I68+J68+K68+L68+M68+N68 -> 1610.4
A69: Joao Gabriel Previero de Arruda Sampaio - Convenio Medico | B69: =SUM(C69:N69) -> 1911.45 | C69: 1911.45
A70: Joao Gabriel Previero de Arruda Sampaio - Distribuição Mensal Fixa | B70: =SUM(C70:N70) -> 18758 | C70: =11000-C71 -> 9379 | D70: =11000-D71 -> 9379
A71: Joao Gabriel Previero de Arruda Sampaio - | B71: =SUM(C71:N71) -> 3242 | C71: 1621 | D71: 1621
A72: Martim Della Valle - Distribuição Mensal Fixa | B72: =SUM(C72:N72) -> 116895 | C72: =25000-C73 -> 23379 | D72: =25000-D73 -> 23379 | E72: =25000-E73 -> 23379 | F72: =25000-F73 -> 23379 | G72: =25000-G73 -> 23379 | O72: =C72+D72+E72+F72+G72+H72+I72+J72+K72+L72+M72+N72 -> 116895
A73: Martim Della Valle - Pro labore | B73: =SUM(C73:N73) -> 8105 | C73: 1621 | D73: 1621 | E73: 1621 | F73: 1621 | G73: 1621 | O73: =C73+D73+E73+F73+G73+H73+I73+J73+K73+L73+M73+N73 -> 8105
A74: Angelina Vitoria Barbosa Teixeira das Neves - Convenio Medico
A75: Angelina Vitoria Barbosa Teixeira das Neves - Distribuição Mensal Fixa | F75: 4333.33 | G75: 5200
A76: Angelina Vitoria Barbosa Teixeira das Neves - Pro Labore
A77: Seguro de Vida | B77: =SUM(C77:N77) -> 0 | O77: =C77+D77+E77+F77+G77+H77+I77+J77+K77+L77+M77+N77 -> 0
A78: Vale Refeição | B78: =SUM(C78:N78) -> 0 | O78: =C78+D78+E78+F78+G78+H78+I78+J78+K78+L78+M78+N78 -> 0
A79: ISS Trimestral | B79: =SUM(C79:N79) -> 3050.06 | C79: =382.16*4 -> 1528.64 | F79: =507.14*3 -> 1521.42 | O79: =C79+D79+E79+F79+G79+H79+I79+J79+K79+L79+M79+N79 -> 3050.06
A80: Participação/comissão - Arbitragem | B80: =SUM(C80:N80) -> 0 | O80: =C80+D80+E80+F80+G80+H80+I80+J80+K80+L80+M80+N80 -> 0
A81: Repasse - Arbitragem | B81: =SUM(C81:N81) -> 0 | O81: =C81+D81+E81+F81+G81+H81+I81+J81+K81+L81+M81+N81 -> 0
A82: Despesas para Clientes | B82: =SUM(C82:N82) -> 10923.3 | C82: =SUM(C83:C84) -> 8549.81 | D82: =SUM(D83:D84) -> 1212.73 | E82: =SUM(E83:E84) -> 0 | F82: =SUM(F83:F84) -> 1105.16 | G82: =SUM(G83:G84) -> 55.6 | H82: =SUM(H83:H84) -> 0 | I82: =SUM(I83:I84) -> 0 | J82: =SUM(J83:J84) -> 0 | ... N82: =SUM(N83:N84) -> 0 | O82: =C82+D82+E82+F82+G82+H82+I82+J82+K82+L82+M82+N82 -> 10923.3
A83: Não Reembolsáveis | B83: =SUM(C83:N83) -> 1029.08 | F83: =111.06+115.26+691.56+55.6 -> 973.48 | G83: 55.6 | O83: =C83+D83+E83+F83+G83+H83+I83+J83+K83+L83+M83+N83 -> 1029.08
A84: Reembolsáveis | B84: =SUM(C84:N84) -> 9894.22 | C84: =86.06+3916.04+250.06+3947.65+350 -> 8549.81 | D84: =374.31+800+38.42 -> 1212.73 | F84: 131.68 | O84: =C84+D84+E84+F84+G84+H84+I84+J84+K84+L84+M84+N84 -> 9894.22
A85: Ocupação | B85: =SUM(C85:N85) -> 172052.01 | C85: =SUM(C86:C91) -> 27660.2 | D85: =SUM(D86:D91) -> 34729.91 | E85: =SUM(E86:E91) -> 36273.05 | F85: =SUM(F86:F91) -> 36198.98 | G85: =SUM(G86:G91) -> 37189.87 | H85: =SUM(H86:H91) -> 0 | I85: =SUM(I86:I91) -> 0 | J85: =SUM(J86:J91) -> 0 | ... N85: =SUM(N86:N91) -> 0 | O85: =C85+D85+E85+F85+G85+H85+I85+J85+K85+L85+M85+N85 -> 172052.01
A86: Aluguel | B86: =SUM(C86:N86) -> 114050.45 | C86: =26384.63-4676.85 -> 21707.78 | D86: =26384.63-4676.85 -> 21707.78 | E86: =26384.63-3117.9 -> 23266.73 | F86: =26384.63-3247.07 -> 23137.56 | G86: =27477.67-3247.07 -> 24230.6 | O86: =C86+D86+E86+F86+G86+H86+I86+J86+K86+L86+M86+N86 -> 114050.45
A87: Condomínio | B87: =SUM(C87:N87) -> 24980 | C87: 4996 | D87: 4996 | E87: 4996 | F87: 4996 | G87: 4996 | O87: =C87+D87+E87+F87+G87+H87+I87+J87+K87+L87+M87+N87 -> 24980
A88: Camera Ed. Lacerda | B88: =SUM(C88:N88) -> 0 | O88: =C88+D88+E88+F88+G88+H88+I88+J88+K88+L88+M88+N88 -> 0
A89: Energia | B89: =SUM(C89:N89) -> 4439.84 | C89: 773.71 | D89: 926.16 | E89: 910.64 | F89: 965.74 | G89: 863.59 | O89: =C89+D89+E89+F89+G89+H89+I89+J89+K89+L89+M89+N89 -> 4439.84
A90: IPTU | B90: =SUM(C90:N90) -> 27667.88 | D90: 6916.97 | E90: 6916.97 | F90: 6916.97 | G90: 6916.97 | O90: =C90+D90+E90+F90+G90+H90+I90+J90+K90+L90+M90+N90 -> 27667.88
A91: Seguro Locação | B91: =SUM(C91:N91) -> 913.84 | C91: 182.71 | D91: 183 | E91: 182.71 | F91: 182.71 | G91: 182.71 | O91: =C91+D91+E91+F91+G91+H91+I91+J91+K91+L91+M91+N91 -> 913.84
A92: Telecomunicações | B92: =SUM(C92:N92) -> 4071.3 | C92: =SUM(C93:C94) -> 807.16 | D92: =SUM(D93:D94) -> 807.16 | E92: =SUM(E93:E94) -> 807.16 | F92: =SUM(F93:F94) -> 824.81 | G92: =SUM(G93:G94) -> 825.01 | H92: =SUM(H93:H94) -> 0 | I92: =SUM(I93:I94) -> 0 | J92: =SUM(J93:J94) -> 0 | ... N92: =SUM(N93:N94) -> 0 | O92: =C92+D92+E92+F92+G92+H92+I92+J92+K92+L92+M92+N92 -> 4071.3
A93: Internet | B93: =SUM(C93:N93) -> 3744.85 | C93: =399.9+184.92+157.05 -> 741.87 | D93: =399.9+184.92+157.05 -> 741.87 | E93: =399.9+157.05+184.92 -> 741.87 | F93: =399.9+184.92+174.7 -> 759.52 | G93: =399.9+184.92+174.9 -> 759.72 | O93: =C93+D93+E93+F93+G93+H93+I93+J93+K93+L93+M93+N93 -> 3744.85
A94: Telefonia Fixa | B94: =SUM(C94:N94) -> 326.45 | C94: 65.29 | D94: 65.29 | E94: 65.29 | F94: 65.29 | G94: 65.29 | O94: =C94+D94+E94+F94+G94+H94+I94+J94+K94+L94+M94+N94 -> 326.45
A95: Despesas Gerais | B95: =SUM(C95:N95) -> 30500.48 | C95: =SUM(C96:C109) -> 6773.44 | D95: =SUM(D96:D109) -> 5243.68 | E95: =SUM(E96:E109) -> 6492.79 | F95: =SUM(F96:F109) -> 5820.18 | G95: =SUM(G96:G109) -> 6170.39 | H95: =SUM(H96:H109) -> 0 | I95: =SUM(I96:I109) -> 0 | J95: =SUM(J96:J109) -> 0 | ... N95: =SUM(N96:N109) -> 0 | O95: =C95+D95+E95+F95+G95+H95+I95+J95+K95+L95+M95+N95 -> 30500.48
A96: Alteração Contrato Social | B96: =SUM(C96:N96) -> 0 | O96: =C96+D96+E96+F96+G96+H96+I96+J96+K96+L96+M96+N96 -> 0
A97: Cartório | B97: =SUM(C97:N97) -> 0 | O97: =C97+D97+E97+F97+G97+H97+I97+J97+K97+L97+M97+N97 -> 0
A98: Cópias / Gráfica | B98: =SUM(C98:N98) -> 0 | O98: =C98+D98+E98+F98+G98+H98+I98+J98+K98+L98+M98+N98 -> 0
A99: Correio | B99: =SUM(C99:N99) -> 0 | O99: =C99+D99+E99+F99+G99+H99+I99+J99+K99+L99+M99+N99 -> 0
A100: Estacionamento (clientes) | B100: =SUM(C100:N100) -> 0 | O100: =C100+D100+E100+F100+G100+H100+I100+J100+K100+L100+M100+N100 -> 0
A101: Limpeza e Copeira - Serviço Terceirizado | B101: =SUM(C101:N101) -> 16138.5 | C101: 3049.23 | D101: 3049.23 | E101: 3346.68 | F101: 3346.68 | G101: 3346.68 | O101: =C101+D101+E101+F101+G101+H101+I101+J101+K101+L101+M101+N101 -> 16138.5
...

Sheet Areas Sintetico atualizado
A1: DRE 2026 | B1: Janeiro | F1: Fevereiro | J1: Março | N1: Abril | R1: Maio | AA1: 7 | AC1: CHECK
A2: Resultado Institucional | B2: Orçado | C2: Realizado | D2: Variação Mensal | E2: Desvio% | F2: Orçado | G2: Realizado | H2: Variação Mensal | I2: Desvio% | J2: Orçado | K2: Realizado | L2: Variação Mensal | M2: Desvio% | N2: Orçado | O2: Realizado | P2: Variação Mensal | Q2: Desvio% | R2: Orçado | S2: Realizado | T2: Variação Mensal | U2: Desvio% | V2: Orçado YTG | W2: Orçado YTD | X2: Realizado | Y2: Variação | Z2: Variação Mensal | AA2: YTG
A3: Faturamento | B3: ='DRE 2026'!C3 -> 671666.67 | C3: 444545.69 | D3: =+C3-B3 -> -227120.98 | E3: =C3/B3 -> 0.66185462 | F3: ='DRE 2026'!D3 -> 671666.67 | G3: 534752.84 | H3: =+G3-F3 -> -136913.83 | I3: =G3/F3 -> 0.79615807 | J3: ='DRE 2026'!H3 -> 671666.67 | K3: 391005.89 | L3: =+K3-J3 -> -280660.78 | M3: =K3/J3 -> 0.58214276 | N3: ='DRE 2026'!F3 -> 671666.67 | O3: 282214.17 | P3: =+O3-N3 -> -389452.5 | Q3: =O3/N3 -> 0.42016998 | R3: ='DRE 2026'!J3 -> 671666.67 | S3: 719988.05 | T3: =+S3-R3 -> 48321.38 | U3: =S3/R3 -> 1.0719425 | V3: ='DRE 2026'!B3 -> 8060000 | W3: ='DRE 2026'!C3+'DRE 2026'!D3+'DRE 2026'!E3+'DRE 2026'!F3+'DRE 2026'!G3 -> 3358333.4 | X3: =C3+G3+K3+O3+S3 -> 2372506.6 | Y3: =X3-W3 -> -985826.71 | Z3: =X3/W3 -> 0.70645359 | AA3: =V3-X3 -> 5687493.4 | AC3: =C3+G3+K3+O3+S3 -> 2372506.6 | AD3: =X3-AC3 -> 0
A4: Receita | C4: ='Base_Resultado Mensal_V2'!C4 -> 279821.07 | G4: ='Base_Resultado Mensal_V2'!D4 -> 319233.58 | H4: =+G4-F3 -> -352433.09 | K4: ='Base_Resultado Mensal_V2'!E4 -> 612501.76 | L4: =+K4-J3 -> -59164.91 | O4: 238327.46 | P4: =+O4-N3 -> -433339.21 | S4: ='Base_Resultado Mensal_V2'!G4 -> 415928 | T4: =+S4-R3 -> -255738.67 | W4: ='DRE 2026'!C3+'DRE 2026'!D3+'DRE 2026'!E3+'DRE 2026'!F3 -> 2686666.7 | X4: ='Base_Resultado Mensal_V2'!B4 -> 1865811.9 | Y4: =X4-W3 -> -1492521.5 | Z4: =X4/W4 -> 0.69447092 | AC4: =C4+G4+K4+O4+S4 -> 1865811.9 | AD4: =X4-AC4 -> 0
A5: Despesas | B5: Orçado | C5: Realizado | D5: Variação Mensal | E5: Variação Mensal | F5: Orçado | G5: Realizado | H5: Variação Mensal | I5: Variação Mensal | J5: Orçado | K5: Realizado | L5: Variação Mensal | M5: Variação Mensal | N5: Orçado | O5: Realizado | P5: Variação Mensal | Q5: Variação Mensal | R5: Orçado | S5: Realizado | T5: Variação Mensal | U5: Variação Mensal | Z5: Variação Mensal
A6: Custos Diretos | B6: =SUM(B7:B11) -> 215786.59 | C6: =SUM(C7:C12) -> 211242.68 | D6: =+B6-C6 -> 4543.91 | F6: =SUM(F7:F11) -> 211686.59 | G6: =SUM(G7:G12) -> 218453.74 | H6: =+F6-G6 -> -6767.15 | J6: =SUM(J7:J11) -> 199069.61 | K6: =SUM(K7:K12) -> 198079.41 | L6: =+J6-K6 -> 990.2 | N6: =SUM(N7:N11) -> 203869.61 | O6: =SUM(O7:O12) -> 209572.83 | P6: =+N6-O6 -> -5703.22 | R6: =SUM(R7:R11) -> 199069.61 | S6: =SUM(S7:S12) -> 210089.46 | T6: =+R6-S6 -> -11019.85 | V6: =SUM(V7:V11) -> 2438910.6 | W6: =SUM(W7:W11) -> 1029482 | X6: =X7+X8+X9+X10+X11+X12 -> 1047438.1 | Y6: =W6-X6 -> -17956.11 | Z6: =X6/W6 -> 1.0174419 | AA6: =V6-X6 -> 1391472.5 | AC6: =C6+G6+K6+O6+S6 -> 1047438.1 | AD6: =X6-AC6 -> 0
A7: =+'Base_Resultado Mensal_V2'!A5 -> Custo equipe - Contencioso | B7: ='DRE 2026'!C6 -> 75454.065 | C7: ='Base_Resultado Mensal_V2'!C5 -> 73576.315 | D7: =+B7-C7 -> 1877.75 | E7: =C7/B7 -> 0.975114 | F7: ='DRE 2026'!D6 -> 74454.065 | G7: ='Base_Resultado Mensal_V2'!D5 -> 76342.345 | H7: =+F7-G7 -> -1888.28 | I7: =G7/F7 -> 1.0253617 | J7: ='DRE 2026'!H6 -> 74454.065 | K7: ='Base_Resultado Mensal_V2'!E5 -> 72845.495 | L7: =+J7-K7 -> 1608.57 | M7: =K7/J7 -> 0.97839514 | N7: ='DRE 2026'!F6 -> 76054.065 | O7: ='Base_Resultado Mensal_V2'!F5 -> 75374.055 | P7: =+N7-O7 -> 680.01 | Q7: =O7/N7 -> 0.99105886 | R7: ='DRE 2026'!J6 -> 74454.065 | S7: ='Base_Resultado Mensal_V2'!G5 -> 74141.215 | T7: =+R7-S7 -> 312.85 | U7: =S7/R7 -> 0.99579808 | V7: ='DRE 2026'!B6 -> 901597.73 | W7: ='DRE 2026'!C6+'DRE 2026'!D6+'DRE 2026'!E6+'DRE 2026'!F6+'DRE 2026'!G6 -> 374870.33 | X7: ='Base_Resultado Mensal_V2'!B5 -> 372279.42 | Y7: =W7-X7 -> 2590.9 | Z7: =X7/W7 -> 0.99308854 | AA7: =V7-X7 -> 529318.31 | AC7: =C7+G7+K7+O7+S7 -> 372279.42 | AD7: =X7-AC7 -> 0
A8: ='Base_Resultado Mensal_V2'!A28 -> Participação/Comissão - Contencioso | C8: ='Base_Resultado Mensal_V2'!C28+'Base_Resultado Mensal_V2'!C29 -> 0 | G8: ='Base_Resultado Mensal_V2'!D28+'Base_Resultado Mensal_V2'!D29 -> 0 | K8: ='Base_Resultado Mensal_V2'!E28+'Base_Resultado Mensal_V2'!E29 -> 0 | O8: ='Base_Resultado Mensal_V2'!F28+'Base_Resultado Mensal_V2'!F29 -> 0 | S8: ='Base_Resultado Mensal_V2'!G28 -> 0 | X8: ='Base_Resultado Mensal_V2'!B28+'Base_Resultado Mensal_V2'!B29 -> 0 | Y8: =W8-X8 -> 0 | AC8: =C8+G8+K8+O8+S8 -> 0 | AD8: =X8-AC8 -> 0
A9: =+'Base_Resultado Mensal_V2'!A30 -> Custo equipe - Econômico | B9: ='DRE 2026'!C7 -> 76879.165 | C9: ='Base_Resultado Mensal_V2'!C30 -> 75653.195 | D9: =+B9-C9 -> 1225.97 | E9: =C9/B9 -> 0.98405329 | F9: ='DRE 2026'!D7 -> 75379.165 | G9: ='Base_Resultado Mensal_V2'!D30 -> 78817.055 | H9: =+F9-G9 -> -3437.89 | I9: =G9/F9 -> 1.045608 | J9: ='DRE 2026'!H7 -> 75379.165 | K9: ='Base_Resultado Mensal_V2'!E30 -> 76049.975 | L9: =+J9-K9 -> -670.81 | M9: =K9/J9 -> 1.0088991 | N9: ='DRE 2026'!F7 -> 76979.165 | O9: ='Base_Resultado Mensal_V2'!F30 -> 79160.085 | P9: =+N9-O9 -> -2180.92 | Q9: =O9/N9 -> 1.0283313 | R9: ='DRE 2026'!J7 -> 75379.165 | S9: ='Base_Resultado Mensal_V2'!G30 -> 79436.245 | T9: =+R9-S9 -> -4057.08 | U9: =S9/R9 -> 1.0538223 | V9: ='DRE 2026'!B7 -> 914114.75 | W9: ='DRE 2026'!C7+'DRE 2026'!D7+'DRE 2026'!E7+'DRE 2026'!F7+'DRE 2026'!G7 -> 379995.83 | X9: ='Base_Resultado Mensal_V2'!B30 -> 389116.56 | Y9: =W9-X9 -> -9120.73 | Z9: =X9/W9 -> 1.0240022 | AA9: =V9-X9 -> 524998.2 | AC9: =C9+G9+K9+O9+S9 -> 389116.55 | AD9: =X9-AC9 -> 0
A10: ='Base_Resultado Mensal_V2'!A58 -> Participação/comissão - Economico | C10: ='Base_Resultado Mensal_V2'!C28+'Base_Resultado Mensal_V2'!C29 -> 0 | G10: ='Base_Resultado Mensal_V2'!D58+'Base_Resultado Mensal_V2'!D59 -> 1500 | K10: ='Base_Resultado Mensal_V2'!E58+'Base_Resultado Mensal_V2'!E59 -> 0 | O10: ='Base_Resultado Mensal_V2'!F58+'Base_Resultado Mensal_V2'!F59 -> 0 | S10: ='Base_Resultado Mensal_V2'!G58 -> 2128.06 | X10: ='Base_Resultado Mensal_V2'!B58+'Base_Resultado Mensal_V2'!B59 -> 3628.06 | Y10: =W10-X10 -> -3628.06 | AC10: =C10+G10+K10+O10+S10 -> 3628.06 | AD10: =X10-AC10 -> 0
A11: =+'Base_Resultado Mensal_V2'!A60 -> Custo equipe - Arbitragem e Compliance | B11: ='DRE 2026'!C8 -> 63453.36 | C11: ='Base_Resultado Mensal_V2'!C60 -> 62013.17 | D11: =+B11-C11 -> 1440.19 | E11: =C11/B11 -> 0.97730317 | F11: ='DRE 2026'!D8 -> 61853.36 | G11: ='Base_Resultado Mensal_V2'!D60 -> 61794.34 | H11: =+F11-G11 -> 59.02 | I11: =G11/F11 -> 0.99904581 | J11: ='DRE 2026'!H8 -> 49236.38 | K11: ='Base_Resultado Mensal_V2'!E60 -> 49183.94 | L11: =+J11-K11 -> 52.44 | M11: =K11/J11 -> 0.99893493 | N11: ='DRE 2026'!F8 -> 50836.38 | O11: ='Base_Resultado Mensal_V2'!F60 -> 55038.69 | P11: =+N11-O11 -> -4202.31 | Q11: =O11/N11 -> 1.0826634 | R11: ='DRE 2026'!J8 -> 49236.38 | S11: ='Base_Resultado Mensal_V2'!G60 -> 54383.94 | T11: =+R11-S11 -> -5147.56 | U11: =S11/R11 -> 1.1045479 | V11: ='DRE 2026'!B8 -> 623198.16 | W11: ='DRE 2026'!C8+'DRE 2026'!D8+'DRE 2026'!E8+'DRE 2026'!F8+'DRE 2026'!G8 -> 274615.86 | X11: ='Base_Resultado Mensal_V2'!B60 -> 282414.08 | Y11: =W11-X11 -> -7798.22 | Z11: =X11/W11 -> 1.0283968 | AA11: =V11-X11 -> 340784.08 | AC11: =C11+G11+K11+O11+S11 -> 282414.08 | AD11: =X11-AC11 -> 0
A12: ='Base_Resultado Mensal_V2'!A80 -> Participação/comissão - Arbitragem | C12: ='Base_Resultado Mensal_V2'!C80+'Base_Resultado Mensal_V2'!C81 -> 0 | G12: ='Base_Resultado Mensal_V2'!D80+'Base_Resultado Mensal_V2'!D81 -> 0 | K12: ='Base_Resultado Mensal_V2'!E80+'Base_Resultado Mensal_V2'!E81 -> 0 | O12: ='Base_Resultado Mensal_V2'!F80+'Base_Resultado Mensal_V2'!F81 -> 0 | S12: ='Base_Resultado Mensal_V2'!G80 -> 0 | X12: ='Base_Resultado Mensal_V2'!B80+'Base_Resultado Mensal_V2'!B81 -> 0 | Y12: =W12-X12 -> 0
A13: Despesas Indiretas | B13: =SUM(B14:B24) -> 102906.66 | C13: =SUM(C14:C24) -> 100181.41 | D13: =(B13-C13) -> 2725.2533 | F13: =SUM(F14:F24) -> 112483.91 | G13: =SUM(G14:G24) -> 95047.39 | H13: =(F13-G13) -> 17436.52 | J13: =SUM(J14:J24) -> 129851.12 | K13: =SUM(K14:K24) -> 101968.9 | L13: =(J13-K13) -> 27882.215 | N13: =SUM(N14:N24) -> 124351.12 | O13: =SUM(O14:O24) -> 110156.11 | P13: =(N13-O13) -> 14195.005 | R13: =SUM(R14:R24) -> 103162.07 | S13: =SUM(S14:S24) -> 105511.43 | T13: =(R13-S13) -> -2349.3645 | V13: =SUM(V14:V24) -> 1386633.4 | W13: =SUM(W14:W24) -> 572754.87 | X13: =SUM(X14:X24) -> 512865.24 | Y13: =W13-X13 -> 59889.63 | Z13: =X13/W13 -> 0.89543584 | AA13: =V13-X13 -> 873768.15 | AC13: =C13+G13+K13+O13+S13 -> 512865.24 | AD13: =X13-AC13 -> 0
A14: =+'Base_Resultado Mensal_V2'!A85 -> Ocupação | B14: ='DRE 2026'!C10 -> 27197.48 | C14: ='Base_Resultado Mensal_V2'!C85 -> 27660.2 | D14: =+B14-C14 -> -462.72 | E14: =(C14/B14) -> 1.0170133 | F14: ='DRE 2026'!D10 -> 34236.38 | G14: ='Base_Resultado Mensal_V2'!D85 -> 34729.91 | H14: =+F14-G14 -> -493.53 | I14: =(G14/F14) -> 1.0144154 | J14: ='DRE 2026'!E10 -> 34236.38 | K14: ='Base_Resultado Mensal_V2'!E85 -> 36273.05 | L14: =+J14-K14 -> -2036.67 | M14: =(K14/J14) -> 1.0594885 | N14: ='DRE 2026'!F10 -> 34236.38 | O14: ='Base_Resultado Mensal_V2'!F85 -> 36198.98 | P14: =+N14-O14 -> -1962.6 | Q14: =(O14/N14) -> 1.057325 | R14: ='DRE 2026'!G10 -> 34236.38 | S14: ='Base_Resultado Mensal_V2'!G85 -> 37189.87 | T14: =+R14-S14 -> -2953.49 | U14: =(S14/R14) -> 1.0862676 | V14: ='DRE 2026'!B10 -> 410635.68 | W14: ='DRE 2026'!C10+'DRE 2026'!D10+'DRE 2026'!E10+'DRE 2026'!F10+'DRE 2026'!G10 -> 164143 | X14: ='Base_Resultado Mensal_V2'!B85 -> 172052.01 | Y14: =W14-X14 -> -7909.01 | Z14: =X14/W14 -> 1.0481837 | AA14: =V14-X14 -> 238583.67 | AC14: =C14+G14+K14+O14+S14 -> 172052.01 | AD14: =X14-AC14 -> 0
A15: =+'Base_Resultado Mensal_V2'!A92 -> Telecomunicações | B15: ='DRE 2026'!C11 -> 890 | C15: ='Base_Resultado Mensal_V2'!C92 -> 807.16 | D15: =+B15-C15 -> 82.84 | E15: =(C15/B15) -> 0.90692135 | F15: ='DRE 2026'!D11 -> 839.7638 | G15: ='Base_Resultado Mensal_V2'!D92 -> 807.16 | H15: =+F15-G15 -> 32.6038 | I15: =(G15/F15) -> 0.96117504 | J15: ='DRE 2026'!E11 -> 839.7638 | K15: ='Base_Resultado Mensal_V2'!E92 -> 807.16 | L15: =+J15-K15 -> 32.6038 | M15: =(K15/J15) -> 0.96117504 | N15: ='DRE 2026'!F11 -> 839.7638 | O15: ='Base_Resultado Mensal_V2'!F92 -> 824.81 | P15: =+N15-O15 -> 14.9538 | Q15: =(O15/N15) -> 0.98219285 | R15: ='DRE 2026'!G11 -> 839.7638 | S15: ='Base_Resultado Mensal_V2'!G92 -> 825.01 | T15: =+R15-S15 -> 14.7538 | U15: =(S15/R15) -> 0.98243101 | V15: ='DRE 2026'!B11 -> 10127.402 | W15: ='DRE 2026'!C11+'DRE 2026'!D11+'DRE 2026'!E11+'DRE 2026'!F11+'DRE 2026'!G11 -> 4249.0552 | X15: ='Base_Resultado Mensal_V2'!B92 -> 4071.3 | Y15: =W15-X15 -> 177.7552 | Z15: =X15/W15 -> 0.95816595 | AA15: =V15-X15 -> 6056.1018 | AC15: =C15+G15+K15+O15+S15 -> 4071.3 | AD15: =X15-AC15 -> 0
A16: =+'Base_Resultado Mensal_V2'!A95 -> Despesas Gerais | B16: ='DRE 2026'!C12 -> 7255 | C16: ='Base_Resultado Mensal_V2'!C95 -> 6773.44 | D16: =+B16-C16 -> 481.56 | E16: =(C16/B16) -> 0.93362371 | F16: ='DRE 2026'!D12 -> 5505 | G16: ='Base_Resultado Mensal_V2'!D95 -> 5243.68 | H16: =+F16-G16 -> 261.32 | I16: =(G16/F16) -> 0.95253043 | J16: ='DRE 2026'!E12 -> 5742.205 | K16: ='Base_Resultado Mensal_V2'!E95 -> 6492.79 | L16: =+J16-K16 -> -750.585 | M16: =(K16/J16) -> 1.1307137 | N16: ='DRE 2026'!F12 -> 7292.205 | O16: ='Base_Resultado Mensal_V2'!F95 -> 5820.18 | P16: =+N16-O16 -> 1472.025 | Q16: =(O16/N16) -> 0.79813719 | R16: ='DRE 2026'!G12 -> 5742.205 | S16: ='Base_Resultado Mensal_V2'!G95 -> 6170.39 | T16: =+R16-S16 -> -428.185 | U16: =(S16/R16) -> 1.074568 | V16: ='DRE 2026'!B12 -> 74921.85 | W16: ='DRE 2026'!C12+'DRE 2026'!D12+'DRE 2026'!E12+'DRE 2026'!F12+'DRE 2026'!G12 -> 31536.615 | X16: ='Base_Resultado Mensal_V2'!B95 -> 30500.48 | Y16: =W16-X16 -> 1036.135 | Z16: =X16/W16 -> 0.96714502 | AA16: =V16-X16 -> 44421.37 | AC16: =C16+G16+K16+O16+S16 -> 30500.48 | AD16: =X16-AC16 -> 0
A17: =+'Base_Resultado Mensal_V2'!A110 -> Consultoria | B17: ='DRE 2026'!C13 -> 23240.8 | C17: ='Base_Resultado Mensal_V2'!C110 -> 30035.14 | D17: =+B17-C17 -> -6794.34 | E17: =(C17/B17) -> 1.2923454 | F17: ='DRE 2026'!D13 -> 23035.8 | G17: ='Base_Resultado Mensal_V2'!D110 -> 22509.85 | H17: =+F17-G17 -> 525.95 | I17: =(G17/F17) -> 0.97716815 | J17: ='DRE 2026'!E13 -> 22815.8 | K17: ='Base_Resultado Mensal_V2'!E110 -> 22457.81 | L17: =+J17-K17 -> 357.99 | M17: =(K17/J17) -> 0.98430956 | N17: ='DRE 2026'!F13 -> 23115.8 | O17: ='Base_Resultado Mensal_V2'!F110 -> 22343.08 | P17: =+N17-O17 -> 772.72 | Q17: =(O17/N17) -> 0.96657178 | R17: ='DRE 2026'!G13 -> 22815.8 | S17: ='Base_Resultado Mensal_V2'!G110 -> 22748.74 | T17: =+R17-S17 -> 67.06 | U17: =(S17/R17) -> 0.99706081 | V17: ='DRE 2026'!B13 -> 287104.88 | W17: ='DRE 2026'!C13+'DRE 2026'!D13+'DRE 2026'!E13+'DRE 2026'!F13+'DRE 2026'!G13 -> 115024 | X17: ='Base_Resultado Mensal_V2'!B110 -> 120094.62 | Y17: =W17-X17 -> -5070.62 | Z17: =X17/W17 -> 1.0440831 | AA17: =V17-X17 -> 167010.26 | AC17: =C17+G17+K17+O17+S17 -> 120094.62 | AD17: =X17-AC17 -> 0
A18: =+'Base_Resultado Mensal_V2'!A116 -> Salários Administração | B18: ='DRE 2026'!C14 -> 6426.58 | C18: ='Base_Resultado Mensal_V2'!C116 -> 6408.59 | D18: =+B18-C18 -> 17.99 | E18: =(C18/B18) -> 0.99720069 | F18: ='DRE 2026'!D14 -> 6776.58 | G18: ='Base_Resultado Mensal_V2'!D116 -> 6076.76 | H18: =+F18-G18 -> 699.82 | I18: =(G18/F18) -> 0.89672962 | J18: ='DRE 2026'!E14 -> 7626.58 | K18: ='Base_Resultado Mensal_V2'!E116 -> 9751.18 | L18: =+J18-K18 -> -2124.6 | M18: =(K18/J18) -> 1.2785783 | N18: ='DRE 2026'!F14 -> 7626.58 | O18: ='Base_Resultado Mensal_V2'!F116 -> 9189.32 | P18: =+N18-O18 -> -1562.74 | Q18: =(O18/N18) -> 1.204907 | R18: ='DRE 2026'!G14 -> 7626.58 | S18: ='Base_Resultado Mensal_V2'!G116 -> 12344.91 | T18: =+R18-S18 -> -4718.33 | U18: =(S18/R18) -> 1.6186692 | V18: ='DRE 2026'!B14 -> 94659.531 | W18: ='DRE 2026'!C14+'DRE 2026'!D14+'DRE 2026'!E14+'DRE 2026'!F14+'DRE 2026'!G14 -> 36082.9 | X18: ='Base_Resultado Mensal_V2'!B116 -> 43770.76 | Y18: =W18-X18 -> -7687.86 | Z18: =X18/W18 -> 1.213061 | AA18: =V18-X18 -> 50888.771 | AC18: =C18+G18+K18+O18+S18 -> 43770.76 | AD18: =X18-AC18 -> 0
A19: =+'Base_Resultado Mensal_V2'!A124 -> Administrativas | B19: ='DRE 2026'!C15 -> 2996.8033 | C19: ='Base_Resultado Mensal_V2'!C124 -> 4300.03 | D19: =+B19-C19 -> -1303.2267 | E19: =(C19/B19) -> 1.4348723 | F19: ='DRE 2026'!D15 -> 14690.387 | G19: ='Base_Resultado Mensal_V2'!D124 -> 6892.33 | H19: =+F19-G19 -> 7798.0567 | I19: =(G19/F19) -> 0.46917281 | J19: ='DRE 2026'!E15 -> 14690.387 | K19: ='Base_Resultado Mensal_V2'!E124 -> 7109.73 | L19: =+J19-K19 -> 7580.6567 | M19: =(K19/J19) -> 0.4839716 | N19: ='DRE 2026'!F15 -> 14690.387 | O19: ='Base_Resultado Mensal_V2'!F124 -> 7304.73 | P19: =+N19-O19 -> 7385.6567 | Q19: =(O19/N19) -> 0.49724559 | R19: ='DRE 2026'!G15 -> 3001.3367 | S19: ='Base_Resultado Mensal_V2'!G124 -> 2822.06 | T19: =+R19-S19 -> 179.27667 | U19: =(S19/R19) -> 0.94026773 | V19: ='DRE 2026'!B15 -> 91084.049 | W19: ='DRE 2026'!C15+'DRE 2026'!D15+'DRE 2026'!E15+'DRE 2026'!F15+'DRE 2026'!G15 -> 50069.3 | X19: ='Base_Resultado Mensal_V2'!B124 -> 28428.88 | Y19: =W19-X19 -> 21640.42 | Z19: =X19/W19 -> 0.56779064 | AA19: =V19-X19 -> 62655.169 | AC19: =C19+G19+K19+O19+S19 -> 28428.88 | AD19: =X19-AC19 -> 0
A20: ='Base_Resultado Mensal_V2'!A134 -> Taxas / Despesas Financeiras | B20: ='DRE 2026'!C16 -> 0 | C20: ='Base_Resultado Mensal_V2'!C134 -> 0 | D20: =+B20-C20 -> 0 | F20: ='DRE 2026'!D16 -> 0 | G20: ='Base_Resultado Mensal_V2'!D134 -> 0 | H20: =+F20-G20 -> 0 | J20: ='DRE 2026'!E16 -> 0 | K20: ='Base_Resultado Mensal_V2'!E134 -> 0 | L20: =+J20-K20 -> 0 | N20: ='DRE 2026'!F16 -> 0 | O20: ='Base_Resultado Mensal_V2'!F134 -> 0 | P20: =+N20-O20 -> 0 | R20: ='DRE 2026'!G16 -> 0 | S20: ='Base_Resultado Mensal_V2'!G134 -> 0 | T20: =+R20-S20 -> 0 | V20: ='DRE 2026'!B16 -> 0 | W20: ='DRE 2026'!C16+'DRE 2026'!D16+'DRE 2026'!E16+'DRE 2026'!F16+'DRE 2026'!G16 -> 0 | X20: ='Base_Resultado Mensal_V2'!B134 -> 0 | Y20: =W20-X20 -> 0 | AA20: =V20-X20 -> 0 | AC20: =C20+G20+K20+O20+S20 -> 0 | AD20: =X20-AC20 -> 0
A21: =+'Base_Resultado Mensal_V2'!A137 -> Investimentos em Prospecção | B21: ='DRE 2026'!C17 -> 4500 | C21: ='Base_Resultado Mensal_V2'!C137 -> 1317.71 | D21: =+B21-C21 -> 3182.29 | E21: =(C21/B21) -> 0.29282444 | F21: ='DRE 2026'!D17 -> 4500 | G21: ='Base_Resultado Mensal_V2'!D137 -> 1166.75 | H21: =+F21-G21 -> 3333.25 | I21: =(G21/F21) -> 0.25927778 | J21: ='DRE 2026'!E17 -> 6000 | K21: ='Base_Resultado Mensal_V2'!E137 -> 811.14 | L21: =+J21-K21 -> 5188.86 | M21: =(K21/J21) -> 0.13519 | N21: ='DRE 2026'!F17 -> 6000 | O21: ='Base_Resultado Mensal_V2'!F137 -> 1826.5 | P21: =+N21-O21 -> 4173.5 | Q21: =(O21/N21) -> 0.30441667 | R21: ='DRE 2026'!G17 -> 6000 | S21: ='Base_Resultado Mensal_V2'!G137 -> 1426.72 | T21: =+R21-S21 -> 4573.28 | U21: =(S21/R21) -> 0.23778667 | V21: ='DRE 2026'!B17 -> 96000 | W21: ='DRE 2026'!C17+'DRE 2026'!D17+'DRE 2026'!E17+'DRE 2026'!F17+'DRE 2026'!G17 -> 27000 | X21: ='Base_Resultado Mensal_V2'!B137 -> 6548.82 | Y21: =W21-X21 -> 20451.18 | Z21: =X21/W21 -> 0.24254889 | AA21: =V21-X21 -> 89451.18 | AC21: =C21+G21+K21+O21+S21 -> 6548.82 | AD21: =X21-AC21 -> 0
A22: ='Base_Resultado Mensal_V2'!A164 -> Endomarketing | B22: ='DRE 2026'!C18 -> 100 | C22: ='Base_Resultado Mensal_V2'!C164 -> 0 | D22: =+B22-C22 -> 100 | E22: =(C22/B22) -> 0 | F22: ='DRE 2026'!D18 -> 100 | G22: ='Base_Resultado Mensal_V2'!D164 -> 0 | H22: =+F22-G22 -> 100 | I22: =(G22/F22) -> 0 | J22: ='DRE 2026'!E18 -> 100 | K22: ='Base_Resultado Mensal_V2'!E164 -> 64.98 | L22: =+J22-K22 -> 35.02 | M22: =(K22/J22) -> 0.6498 | N22: ='DRE 2026'!F18 -> 100 | O22: ='Base_Resultado Mensal_V2'!F164 -> 61.98 | P22: =+N22-O22 -> 38.02 | Q22: =(O22/N22) -> 0.6198 | R22: ='DRE 2026'!G18 -> 100 | S22: ='Base_Resultado Mensal_V2'!G164 -> 420.98 | T22: =+R22-S22 -> -320.98 | U22: =(S22/R22) -> 4.2098 | V22: ='DRE 2026'!B18 -> 1200 | W22: ='DRE 2026'!C18+'DRE 2026'!D18+'DRE 2026'!E18+'DRE 2026'!F18+'DRE 2026'!G18 -> 500 | X22: ='Base_Resultado Mensal_V2'!B164 -> 547.94 | Y22: =W22-X22 -> -47.94 | Z22: =X22/W22 -> 1.09588 | AA22: =V22-X22 -> 652.06 | AC22: =C22+G22+K22+O22+S22 -> 547.94 | AD22: =X22-AC22 -> 0
A23: ='Base_Resultado Mensal_V2'!A158 -> Gestão do Conhecimento | B23: ='DRE 2026'!C19 -> 0 | C23: ='Base_Resultado Mensal_V2'!C158 -> 692.37 | D23: =+B23-C23 -> -692.37 | F23: ='DRE 2026'!D19 -> 0 | G23: ='Base_Resultado Mensal_V2'!D158 -> 0 | H23: =+F23-G23 -> 0 | J23: ='DRE 2026'!E19 -> 0 | K23: ='Base_Resultado Mensal_V2'!E158 -> 1094.49 | L23: =+J23-K23 -> -1094.49 | N23: ='DRE 2026'!F19 -> 150 | O23: ='Base_Resultado Mensal_V2'!F158 -> 1450 | P23: =+N23-O23 -> -1300 | R23: ='DRE 2026'!G19 -> 0 | S23: ='Base_Resultado Mensal_V2'!G158 -> 1600 | T23: =+R23-S23 -> -1600 | V23: ='DRE 2026'!B19 -> 2300 | W23: ='DRE 2026'!C19+'DRE 2026'!D19+'DRE 2026'!E19+'DRE 2026'!F19+'DRE 2026'!G19 -> 150 | X23: ='Base_Resultado Mensal_V2'!B158 -> 4836.86 | Y23: =W23-X23 -> -4686.86 | Z23: =X23/W23 -> 32.245733 | AA23: =V23-X23 -> -2536.86 | AC23: =C23+G23+K23+O23+S23 -> 4836.86 | AD23: =X23-AC23 -> 0
A24: =+'Base_Resultado Mensal_V2'!A180 -> Informática | B24: ='DRE 2026'!C20 -> 30300 | C24: ='Base_Resultado Mensal_V2'!C180 -> 22186.77 | D24: =+B24-C24 -> 8113.23 | E24: =(C24/B24) -> 0.73223663 | F24: ='DRE 2026'!D20 -> 22800 | G24: ='Base_Resultado Mensal_V2'!D180 -> 17620.95 | H24: =+F24-G24 -> 5179.05 | I24: =(G24/F24) -> 0.77284868 | J24: ='DRE 2026'!E20 -> 37800 | K24: ='Base_Resultado Mensal_V2'!E180 -> 17106.57 | L24: =+J24-K24 -> 20693.43 | M24: =(K24/J24) -> 0.45255476 | N24: ='DRE 2026'!F20 -> 30300 | O24: ='Base_Resultado Mensal_V2'!F180 -> 25136.53 | P24: =+N24-O24 -> 5163.47 | Q24: =(O24/N24) -> 0.82958845 | R24: ='DRE 2026'!G20 -> 22800 | S24: ='Base_Resultado Mensal_V2'!G180 -> 19962.75 | T24: =+R24-S24 -> 2837.25 | U24: =(S24/R24) -> 0.87555921 | V24: ='DRE 2026'!B20 -> 318600 | W24: ='DRE 2026'!C20+'DRE 2026'!D20+'DRE 2026'!E20+'DRE 2026'!F20+'DRE 2026'!G20 -> 144000 | X24: ='Base_Resultado Mensal_V2'!B180 -> 102013.57 | Y24: =W24-X24 -> 41986.43 | Z24: =X24/W24 -> 0.70842757 | AA24: =V24-X24 -> 216586.43 | AC24: =C24+G24+K24+O24+S24 -> 102013.57 | AD24: =X24-AC24 -> 0
A25: Resultado Bruto | B25: =B3-B6-B13 -> 352973.42 | C25: =C4-C6-C13 -> -31603.02 | F25: =F3-F6-F13 -> 347496.17 | G25: =G4-G6-G13 -> 5732.45 | J25: =J3-J6-J13 -> 342745.94 | K25: =K4-K6-K13 -> 312453.45 | N25: =N3-N6-N13 -> 343445.94 | O25: =O4-O6-O13 -> -81401.48 | R25: =R3-R6-R13 -> 369434.99 | S25: =S4-S6-S13 -> 100327.11 | V25: =V3-V6-V13 -> 4234456 | W25: =W3-W6-W13 -> 1756096.5 | X25: =X4-X6-X13 -> 305508.51
A26: Margem de bruta | B26: =B25/B3 -> 0.52551873 | C26: =C25/C4 -> -0.1129401 | F26: =F25/F3 -> 0.51736402 | G26: =G25/G4 -> 0.017956914 | J26: =J25/J3 -> 0.51029173 | K26: =K25/K4 -> 0.51012662 | N26: =N25/N3 -> 0.51133391 | O26: =O25/O4 -> -0.34155309 | R26: =R25/R3 -> 0.55002728 | S26: =S25/S4 -> 0.24121269 | V26: =V25/V3 -> 0.52536675 | W26: =W25/W3 -> 0.52290713 | X26: =X25/X4 -> 0.16374025
A27: 0.15
A28: Impostos | B28: ='DRE 2026'!C23 -> 100750 | C28: =C4*$A$27 -> 41973.16 | F28: ='DRE 2026'!D23 -> 100750 | G28: =G4*$A$27 -> 47885.037 | J28: ='DRE 2026'!H23 -> 100750 | K28: =K4*$A$27 -> 91875.264 | N28: ='DRE 2026'!L23 -> 100750 | O28: =O4*$A$27 -> 35749.119 | R28: ='DRE 2026'!G23 -> 100750 | S28: =S4*$A$27 -> 62389.2 | V28: ='DRE 2026'!B23 -> 1209000 | W28: ='DRE 2026'!C23+'DRE 2026'!D23+'DRE 2026'!E23+'DRE 2026'!F23+'DRE 2026'!G23 -> 503750 | X28: =X4*A27 -> 279871.78 | AC28: =C28+G28+K28+O28+S28 -> 279871.78 | AD28: =X28-AC28 -> 0
A29: Investimento amortização | B29: ='DRE 2026'!C24 -> 8117 | C29: 8117 | F29: 8117 | G29: =F29 -> 8117 | J29: 8117 | K29: =J29 -> 8117 | N29: 8117 | O29: =N29 -> 8117 | R29: 8117 | S29: =R29 -> 8117 | V29: ='DRE 2026'!B24 -> 97404 | W29: ='DRE 2026'!C24+'DRE 2026'!D24+'DRE 2026'!E24+'DRE 2026'!F24+'DRE 2026'!G24 -> 40585 | X29: =C29+G29+K29+O29+S29 -> 40585 | AC29: =C29+G29+K29+O29+S29 -> 40585 | AD29: =X29-AC29 -> 0
A30: Resultado Liquido após impostos | B30: =B25-B28-B29 -> 244106.42 | C30: =C25-C28-C29 -> -81693.18 | F30: =F25-F28-F29 -> 238629.17 | G30: =G25-G28-G29 -> -50269.587 | J30: =J25-J28-J29 -> 233878.94 | K30: =K25-K28-K29 -> 212461.19 | N30: =N25-N28-N29 -> 234578.94 | O30: =O25-O28-O29 -> -125267.6 | R30: =R25-R28-R29 -> 260567.99 | S30: =S25-S28-S29 -> 29820.91 | V30: =V25-V28-V29 -> 2928052 | W30: =W25-W28-W29 -> 1211761.5 | X30: =X25-X28-X29 -> -14948.27
A31: Margem liquida | B31: =B30/B3 -> 0.36343387 | C31: =C30/C4 -> -0.29194792 | F31: =F30/F3 -> 0.35527916 | G31: =G30/G4 -> -0.15746961 | J31: =J30/J3 -> 0.34820686 | K31: =K30/K4 -> 0.34687441 | N31: =N30/N3 -> 0.34924905 | O31: =O30/O4 -> -0.52561127 | R31: =R30/R3 -> 0.38794242 | S31: =S30/S4 -> 0.071697289 | V31: =V30/V3 -> 0.36328188 | W31: =W30/W3 -> 0.36082227 | X31: =X30/X4 -> -0.0080116708
A32: Bonus | B32: =B30*10% -> 24410.642 | C32: =C30*10% -> -8169.318 | F32: =F30*10% -> 23862.917 | G32: =G30*10% -> -5026.9587 | J32: =J30*10% -> 23387.894 | K32: =K30*10% -> 21246.119 | N32: =N30*10% -> 23457.894 | O32: =O30*10% -> -12526.76 | R32: =R30*10% -> 26056.799 | S32: =S30*10% -> 2982.091 | V32: =V30*10% -> 292805.2 | W32: =W30*10% -> 121176.15 | X32: =X30*10% -> -1494.827
AC33: =C33+G33+K33+O33+S33 -> 0
A34: 0.15 | B34: Janeiro | F34: Fevereiro | J34: =J1 -> Março | N34: =N1 -> Abril | R34: =R1 -> Maio | AC34: =C34+G34+K34+O34+S34 -> 0
A35: Resultado Contencioso | B35: Orçado | C35: Realizado | D35: Variação Mensal | E35: Desvio% | F35: Orçado | G35: Realizado | H35: Variação Mensal | I35: Desvio% | J35: Orçado | K35: Realizado | L35: Variação Mensal | M35: Desvio% | N35: Orçado | O35: Realizado | P35: Variação Mensal | Q35: Desvio% | R35: Orçado | S35: Realizado | T35: Variação Mensal | U35: Desvio% | V35: Orçado YTG | W35: Orçado YTD | X35: Realizado | Y35: Variação | Z35: Desvio% | AA35: YTG
A36: Receita | B36: =($B$3-($B$3/4))/2 -> 251875 | C36: 38071 | D36: =C36-B36 -> -213804 | E36: =C36/B36 -> 0.15115037 | F36: =B36 -> 251875 | G36: 159539 | H36: =G36-F36 -> -92336.001 | I36: =G36/F36 -> 0.63340546 | J36: =F36 -> 251875 | K36: 159925 | L36: =K36-J36 -> -91950.001 | M36: =K36/J36 -> 0.63493796 | N36: =J36 -> 251875 | O36: 56461 | P36: =O36-N36 -> -195414 | Q36: =O36/N36 -> 0.22416278 | R36: =N36 -> 251875 | S36: 240445 | T36: =S36-R36 -> -11430.001 | U36: =S36/R36 -> 0.95462034 | V36: =($V$3-($V$3/4))/2 -> 3022500 | W36: =B36+F36+J36+N36+R36 -> 1259375 | X36: =C36+G36+K36+O36+S36 -> 654441 | Y36: =X36-W36 -> -604934.01 | Z36: =X36/W36 -> 0.51965538 | AA36: =V36-X36 -> 2368059 | AC36: =C36+G36+K36+O36+S36 -> 654441 | AD36: =X36-AC36 -> 0
AC37: =C37+G37+K37+O37+S37 -> 0
A38: Despesas | B38: Orçado | C38: Realizado | D38: Variação Mensal | E38: Desvio% | F38: Orçado | G38: Realizado | H38: Variação Mensal | I38: Desvio% | J38: Orçado | K38: Realizado | L38: Variação Mensal | M38: Desvio% | N38: Orçado | O38: Realizado | P38: Variação Mensal | Q38: Desvio% | R38: Orçado | S38: Realizado | T38: Variação Mensal | U38: Desvio% | V38: Orçado YTG | W38: Orçado YTD | X38: Realizado | Y38: Variação | Z38: Desvio% | AA38: YTG
A39: Custo Equipe | B39: =+B7 -> 75454.065 | C39: =+'Base_Resultado Mensal_V2'!C5 -> 73576.315 | D39: =+B39-C39 -> 1877.75 | E39: =C39/B39 -> 0.975114 | F39: =+F7 -> 74454.065 | G39: ='Base_Resultado Mensal_V2'!D5 -> 76342.345 | H39: =+F39-G39 -> -1888.28 | I39: =G39/F39 -> 1.0253617 | J39: =+J7 -> 74454.065 | K39: =K7 -> 72845.495 | L39: =+J39-K39 -> 1608.57 | M39: =K39/J39 -> 0.97839514 | N39: =+N7 -> 76054.065 | O39: =O7 -> 75374.055 | P39: =+N39-O39 -> 680.01 | Q39: =O39/N39 -> 0.99105886 | R39: =+R7 -> 74454.065 | S39: =S7 -> 74141.215 | T39: =+R39-S39 -> 312.85 | U39: =S39/R39 -> 0.99579808 | V39: =V7 -> 901597.73 | W39: =B39+F39+J39+N39+R39 -> 374870.33 | X39: =X7 -> 372279.42 | Y39: =W39-X39 -> 2590.9 | Z39: =X39/W39 -> 0.99308854 | AA39: =V39-X39 -> 529318.31 | AC39: =C39+G39+K39+O39+S39 -> 372279.42 | AD39: =X39-AC39 -> 0
A40: =A8 -> Participação/Comissão - Contencioso | C40: =C8 -> 0 | G40: ='Base_Resultado Mensal_V2'!D28 -> 0 | K40: =K8 -> 0 | O40: =O8 -> 0 | S40: =S8 -> 0 | X40: =X8+G40+K40+O40+S40 -> 0
A41: Despesas Equipe | B41: ='Orçamento 2026'!D192 -> 2110.49 | C41: =+'Base_Resultado Mensal_V2'!C204 -> 1060.095 | D41: =(B41-C41) -> 1050.395 | E41: =C41/B41 -> 0.50229804 | F41: ='Orçamento 2026'!E192 -> 6008.49 | G41: ='Base_Resultado Mensal_V2'!D204 -> 2129.3183 | H41: =(F41-G41) -> 3879.1717 | I41: =G41/F41 -> 0.35438493 | J41: ='Orçamento 2026'!F192 -> 6008.49 | K41: ='Base_Resultado Mensal_V2'!E204 -> 2346.7183 | L41: =(J41-K41) -> 3661.7717 | M41: =K41/J41 -> 0.39056707 | N41: ='Orçamento 2026'!G192 -> 7508.49 | O41: ='Base_Resultado Mensal_V2'!F204 -> 4183.9183 | P41: =(N41-O41) -> 3324.5717 | Q41: =O41/N41 -> 0.557225 | R41: ='Orçamento 2026'!H192 -> 2110.49 | S41: ='Base_Resultado Mensal_V2'!G204 -> 2276.215 | T41: =(R41-S41) -> -165.725 | U41: =S41/R41 -> 1.0785244 | V41: ='Orçamento 2026'!B192 -> 40110.215 | W41: =B41+F41+J41+N41+R41 -> 23746.45 | X41: =C41+G41+K41+O41+S41 -> 11996.265 | Y41: =W41-X41 -> 11750.185 | Z41: =X41/W41 -> 0.50518141 | AA41: =V41-X41 -> 28113.95 | AC41: =C41+G41+K41+O41+S41 -> 11996.265 | AD41: =X41-AC41 -> 0
A42: Despesas Institucional | B42: ='Orçamento 2026'!D196*'Rateio Mensal'!M2 -> 35384.982 | C42: ='Rateio Mensal'!I2 -> 33821.378 | D42: =B42-C42 -> 1563.6042 | E42: =C42/B42 -> 0.95581164 | F42: ='Orçamento 2026'!E196*'Rateio Mensal'!M2 -> 34602.631 | G42: ='Rateio Mensal'!I8 -> 30609.712 | H42: =F42-G42 -> 3992.9186 | I42: =G42/F42 -> 0.8846065 | J42: ='Orçamento 2026'!F196*'Rateio Mensal'!M2 -> 40468.297 | K42: ='Rateio Mensal'!I14 -> 34482.809 | L42: =J42-K42 -> 5985.4879 | M42: =K42/J42 -> 0.8520944 | N42: ='Orçamento 2026'!G196*'Rateio Mensal'!M2 -> 38435.1 | O42: ='Rateio Mensal'!I20 -> 36400.455 | P42: =N42-O42 -> 2034.6449 | Q42: =O42/N42 -> 0.94706284 | R42: ='Orçamento 2026'!H196*'Rateio Mensal'!M2 -> 34925.042 | S42: ='Rateio Mensal'!I26 -> 35555.404 | T42: =R42-S42 -> -630.36139 | U42: =S42/R42 -> 1.018049 | V42: ='Orçamento 2026'!B196*'Rateio Mensal'!M2 -> 463063.98 | W42: =B42+F42+J42+N42+R42 -> 183816.05 | X42: =C42+G42+K42+O42+S42 -> 170869.76 | Y42: =W42-X42 -> 12946.294 | Z42: =X42/W42 -> 0.92956929 | AA42: =V42-X42 -> 292194.22 | AC42: =C42+G42+K42+O42+S42 -> 170869.76 | AD42: =X42-AC42 -> 0
A43: Resultado Bruto | B43: =B36-B39-B41-B42 -> 138925.46 | C43: =C36-C39-C41-C42-C40 -> -70386.788 | F43: =F36-F39-F41-F42 -> 136809.82 | G43: =G36-G39-G41-G42-G40 -> 50457.624 | J43: =J36-J39-J41-J42 -> 130944.15 | K43: =K36-K39-K41-K42-K40 -> 50249.977 | N43: =N36-N39-N41-N42 -> 129877.35 | O43: =O36-O39-O41-O42-O40 -> -59497.428 | R43: =R36-R39-R41-R42 -> 140385.4 | S43: =S36-S39-S41-S42-S40 -> 128472.17 | V43: =+V36-(V39+V41+V42) -> 1617728.1 | W43: =+W36-(W39+W41+W42) -> 676942.18 | X43: =X36-X39-X41-X42-X40 -> 99295.552
A44: Margem de bruta | B44: =B43/B36 -> 0.55156512 | C44: =C43/C36 -> -1.8488295 | F44: =F43/F36 -> 0.54316552 | G44: =G43/G36 -> 0.31627141 | J44: =J43/J36 -> 0.51987751 | K44: =K43/K36 -> 0.31420964 | N44: =N43/N36 -> 0.51564207 | O44: =O43/O36 -> -1.0537792 | R44: =R43/R36 -> 0.5573614 | S44: =S43/S36 -> 0.53430999 | V44: =V43/V36 -> 0.53522848 | W44: =W43/W36 -> 0.53752232 | X44: =X43/X36 -> 0.15172575
A46: Impostos | B46: =B36*$A$34 -> 37781.25 | C46: =C36*$A$34 -> 5710.65 | D46: =(B46-C46) -> 32070.6 | E46: =C46/B46 -> 0.15115037 | F46: =F36*$A$34 -> 37781.25 | G46: =G36*$A$34 -> 23930.85 | J46: =J36*$A$34 -> 37781.25 | K46: =K36*$A$34 -> 23988.75 | N46: =N36*$A$34 -> 37781.25 | O46: =O36*$A$34 -> 8469.15 | R46: =R36*$A$34 -> 37781.25 | S46: =S36*$A$34 -> 36066.75 | V46: =V36*$A$34 -> 453375 | W46: =B46+F46+J46+N46+R46 -> 188906.25 | X46: =X36*$A$34 -> 98166.15 | AC46: =C46+G46+K46+O46+S46 -> 98166.15 | AD46: =X46-AC46 -> 0
A47: Investimento amortização | B47: =B29*'Rateio Mensal'!M2 -> 3000.6301 | C47: =C29*'Rateio Mensal'!C2 -> 2827.1699 | D47: =B47-C47 -> 173.46023 | E47: =C47/B47 -> 0.94219206 | F47: =F29*'Rateio Mensal'!M2 -> 3000.6301 | G47: =G29*'Rateio Mensal'!C8 -> 2856.2348 | J47: =J29*'Rateio Mensal'!M2 -> 3000.6301 | K47: =K29*'Rateio Mensal'!C8 -> 2856.2348 | N47: =N29*'Rateio Mensal'!M2 -> 3000.6301 | O47: =O29*'Rateio Mensal'!C8 -> 2856.2348 | R47: =R29*'Rateio Mensal'!M2 -> 3000.6301 | S47: =S29*'Rateio Mensal'!C8 -> 2856.2348 | V47: =V29*'Rateio Mensal'!M2 -> 36007.562 | W47: =B47+F47+J47+N47+R47 -> 15003.151 | X47: =C47+G47+K47+O47+S47 -> 14252.109 | AC47: =C47+G47+K47+O47+S47 -> 14252.109 | AD47: =X47-AC47 -> 0
A48: Resultado Liquido após impostos | B48: =B43-B46-B47 -> 98143.584 | C48: =C43-C46-C47 -> -78924.607 | F48: =F43-F46-F47 -> 96027.935 | G48: =G43-G46-G47 -> 23670.54 | J48: =J43-J46-J47 -> 90162.269 | K48: =K43-K46-K47 -> 23404.993 | N48: =N43-N46-N47 -> 89095.466 | O48: =O43-O46-O47 -> -70822.813 | R48: =R43-R46-R47 -> 99603.523 | S48: =S43-S46-S47 -> 89549.181 | V48: =V43-V46-V47 -> 1128345.5 | W48: =W43-W46-W47 -> 473032.78 | X48: =X43-X46-X47 -> -13122.707
A49: Margem liquida | B49: =B48/B36 -> 0.38965194 | C49: =C48/C36 -> -2.0730899 | F49: =F48/F36 -> 0.38125235 | G49: =G48/G36 -> 0.14836836 | J49: =J48/J36 -> 0.35796434 | K49: =K48/K36 -> 0.14634981 | N49: =N48/N36 -> 0.3537289 | O49: =O48/O36 -> -1.254367 | R49: =R48/R36 -> 0.39544823 | S49: =S48/S36 -> 0.37243104 | V49: =V48/V36 -> 0.37331531 | W49: =W48/W36 -> 0.37560915 | X49: =X48/X36 -> -0.02005178
A50: Reserva bônus | B50: =B48*10% -> 9814.3584 | C50: =C48*10% -> -7892.4607 | F50: =F48*10% -> 9602.7935 | G50: =G48*10% -> 2367.054 | J50: =J48*10% -> 9016.2269 | K50: =K48*10% -> 2340.4993 | N50: =N48*10% -> 8909.5466 | O50: =O48*10% -> -7082.2813 | R50: =R48*10% -> 9960.3523 | S50: =S48*10% -> 8954.9181 | V50: =V48*10% -> 112834.55 | W50: =W48*10% -> 47303.278 | X50: =X48*10% -> -1312.2707
B52: Janeiro | F52: Fevereiro | J52: =J1 -> Março | N52: =N1 -> Abril | R52: =R1 -> Maio
A53: Resultado Econômico | B53: Orçado | C53: Realizado | D53: Variação Mensal | E53: Desvio% | F53: Orçado | G53: Realizado | H53: Variação Mensal | I53: Desvio% | J53: Orçado | K53: Realizado | L53: Variação Mensal | M53: Desvio% | N53: Orçado | O53: Realizado | P53: Variação Mensal | Q53: Desvio% | R53: Orçado | S53: Realizado | T53: Variação Mensal | U53: Desvio% | V53: Orçado YTG | W53: Orçado YTD | X53: Realizado | Y53: Variação | Z53: Desvio% | AA53: YTG
A54: Receita | B54: =($B$3-($B$3/4))/2 -> 251875 | C54: 61844 | D54: =C54-B54 -> -190031 | E54: =C54/B54 -> 0.24553449 | F54: =B54 -> 251875 | G54: 119667 | H54: =G54-F54 -> -132208 | I54: =G54/F54 -> 0.47510471 | J54: =F54 -> 251875 | K54: 343893 | L54: =K54-J54 -> 92017.999 | M54: =K54/J54 -> 1.365332 | N54: =J54 -> 251875 | O54: 159921 | P54: =O54-N54 -> -91954.001 | Q54: =O54/N54 -> 0.63492208 | R54: =N54 -> 251875 | S54: 166876 | T54: =S54-R54 -> -84999.001 | U54: =S54/R54 -> 0.66253498 | V54: =($V$3-($V$3/4))/2 -> 3022500 | W54: =B54+F54+J54+N54+R54 -> 1259375 | X54: =C54+G54+K54+O54+S54 -> 852201 | Y54: =X54-W54 -> -407174.01 | Z54: =X54/W54 -> 0.67668565 | AA54: =V54-X54 -> 2170299 | AC54: =C54+G54+K54+O54+S54 -> 852201 | AD54: =X54-AC54 -> 0
AC55: =C55+G55+K55+O55+S55 -> 0
A56: Despesas | B56: Orçado | C56: Realizado | D56: Variação Mensal | E56: Desvio% | H56: Variação Mensal | I56: Desvio% | L56: Variação Mensal | M56: Desvio% | P56: Variação Mensal | Q56: Desvio% | T56: Variação Mensal | U56: Desvio% | V56: Orçado YTG | W56: Orçado YTD | X56: Realizado | Y56: Variação | Z56: Desvio% | AA56: YTG
A57: Custo Equipe | B57: =+B9 -> 76879.165 | C57: ='Base_Resultado Mensal_V2'!C30 -> 75653.195 | D57: =+B57-C57 -> 1225.97 | E57: =C57/B57 -> 0.98405329 | F57: =+F9 -> 75379.165 | G57: ='Base_Resultado Mensal_V2'!D30 -> 78817.055 | H57: =+F57-G57 -> -3437.89 | I57: =G57/F57 -> 1.045608 | J57: =+J9 -> 75379.165 | K57: =K9 -> 76049.975 | L57: =+J57-K57 -> -670.81 | M57: =K57/J57 -> 1.0088991 | N57: =+N9 -> 76979.165 | O57: =O9 -> 79160.085 | P57: =+N57-O57 -> -2180.92 | Q57: =O57/N57 -> 1.0283313 | R57: =+R9 -> 75379.165 | S57: =S9 -> 79436.245 | T57: =+R57-S57 -> -4057.08 | U57: =S57/R57 -> 1.0538223 | V57: =V9 -> 914114.75 | W57: =B57+F57+J57+N57+R57 -> 379995.83 | X57: =G57+C57+K57+O57+S57 -> 389116.55 | Y57: =W57-X57 -> -9120.73 | Z57: =X57/W57 -> 1.0240022 | AA57: =V57-X57 -> 524998.2 | AC57: =C57+G57+K57+O57+S57 -> 389116.55 | AD57: =X57-AC57 -> 0
A58: =A10 -> Participação/comissão - Economico | C58: =C10 -> 0 | G58: ='Base_Resultado Mensal_V2'!D58 -> 1500 | K58: =K10 -> 0 | O58: =O10 -> 0 | S58: =S10 -> 2128.06 | W58: =B58+F58+J58+N58+R58 -> 0 | X58: =G58+C58+K58+O58+S58 -> 3628.06 | AC58: =C58+G58+K58+O58+S58 -> 3628.06
A59: Despesas Equipe | B59: ='Orçamento 2026'!D193 -> 3174.8233 | C59: =+'Base_Resultado Mensal_V2'!C205 -> 1871.805 | D59: =+B59-C59 -> 1303.0183 | E59: =C59/B59 -> 0.58957769 | F59: ='Orçamento 2026'!E193 -> 7072.4067 | G59: ='Base_Resultado Mensal_V2'!D205 -> 3296.0683 | H59: =+F59-G59 -> 3776.3383 | I59: =G59/F59 -> 0.46604621 | J59: ='Orçamento 2026'!F193 -> 7072.4067 | K59: ='Base_Resultado Mensal_V2'!E205 -> 2129.3183 | L59: =+J59-K59 -> 4943.0883 | M59: =K59/J59 -> 0.30107408 | N59: ='Orçamento 2026'!G193 -> 7072.4067 | O59: ='Base_Resultado Mensal_V2'!F205 -> 2129.3183 | P59: =+N59-O59 -> 4943.0883 | Q59: =O59/N59 -> 0.30107408 | R59: ='Orçamento 2026'!H193 -> 4674.4067 | S59: ='Base_Resultado Mensal_V2'!G205 -> 2300.095 | T59: =+R59-S59 -> 2374.3117 | U59: =S59/R59 -> 0.49206138 | V59: ='Orçamento 2026'!B193 -> 54287.297 | W59: =B59+F59+J59+N59+R59 -> 29066.45 | X59: =G59+C59+K59+O59+S59 -> 11726.605 | Y59: =W59-X59 -> 17339.845 | Z59: =X59/W59 -> 0.40344125 | AA59: =V59-X59 -> 42560.692 | AC59: =C59+G59+K59+O59+S59 -> 11726.605 | AD59: =X59-AC59 -> 0
A60: Despesas Institucional | B60: ='Orçamento 2026'!D196*'Rateio Mensal'!M3 -> 35876.237 | C60: ='Rateio Mensal'!I3 -> 34776.073 | D60: =+B60-C60 -> 1100.1643 | E60: =C60/B60 -> 0.96933446 | F60: ='Orçamento 2026'!E196*'Rateio Mensal'!M3 -> 35083.024 | G60: ='Rateio Mensal'!I9 -> 31601.955 | H60: =+F60-G60 -> 3481.0691 | I60: =G60/F60 -> 0.90077625 | J60: ='Orçamento 2026'!F196*'Rateio Mensal'!M3 -> 41030.125 | K60: ='Rateio Mensal'!I15 -> 35999.711 | L60: =+J60-K60 -> 5030.4135 | M60: =K60/J60 -> 0.87739707 | N60: ='Orçamento 2026'!G196*'Rateio Mensal'!M3 -> 38968.7 | O60: ='Rateio Mensal'!I21 -> 38228.845 | P60: =+N60-O60 -> 739.85459 | Q60: =O60/N60 -> 0.98101413 | R60: ='Orçamento 2026'!H196*'Rateio Mensal'!M3 -> 35409.912 | S60: ='Rateio Mensal'!I27 -> 38094.706 | T60: =+R60-S60 -> -2684.7936 | U60: =S60/R60 -> 1.0758204 | V60: ='Orçamento 2026'!B196*'Rateio Mensal'!M3 -> 469492.77 | W60: =B60+F60+J60+N60+R60 -> 186368 | X60: =G60+C60+K60+O60+S60 -> 178701.29 | Y60: =W60-X60 -> 7666.7078 | Z60: =X60/W60 -> 0.95886253 | AA60: =V60-X60 -> 290791.48 | AC60: =C60+G60+K60+O60+S60 -> 178701.29 | AD60: =X60-AC60 -> 0
A61: Resultado Bruto | B61: =B54-B57-B59-B60 -> 135944.78 | C61: =C54-C57-C59-C60-C58 -> -50457.073 | F61: =F54-F57-F59-F60 -> 134340.41 | G61: =G54-G57-G59-G60-G58 -> 4451.9213 | J61: =J54-J57-J59-J60 -> 128393.3 | K61: =K54-K57-K59-K60-K58 -> 229714 | N61: =N54-N57-N59-N60 -> 128854.73 | O61: =O54-O57-O59-O60-O58 -> 40402.751 | R61: =R54-R57-R59-R60 -> 136411.52 | S61: =S54-S57-S59-S60-S58 -> 44916.894 | V61: =+V54-(V57+V59+V60) -> 1584605.2 | W61: =W54-W57-W59-W60-W58 -> 663944.73 | X61: =X54-X57-X59-X60-X58 -> 269028.49
A62: Margem de bruta | B62: =B61/B54 -> 0.53973112 | C62: =C61/C54 -> -0.8158766 | F62: =F61/F54 -> 0.53336141 | G62: =G61/G54 -> 0.037202581 | J62: =J61/J54 -> 0.50975009 | K62: =K61/K54 -> 0.66798102 | N62: =N61/N54 -> 0.51158205 | O62: =O61/O54 -> 0.25264194 | R62: =R61/R54 -> 0.54158419 | S62: =S61/S54 -> 0.2691633 | V62: =V61/V54 -> 0.52426971 | W62: =W61/W54 -> 0.52720177 | X62: =X61/X54 -> 0.31568666
A64: Impostos | B64: =B54*$A$34 -> 37781.25 | C64: =C54*$A$34 -> 9276.6 | D64: =(B64-C64) -> 28504.65 | E64: =C64/B64 -> 0.24553449 | F64: =F54*$A$34 -> 37781.25 | G64: =G54*$A$34 -> 17950.05 | J64: =J54*$A$34 -> 37781.25 | K64: =K54*$A$34 -> 51583.95 | N64: =N54*$A$34 -> 37781.25 | O64: =O54*$A$34 -> 23988.15 | R64: =R54*$A$34 -> 37781.25 | S64: =S54*$A$34 -> 25031.4 | V64: =V54*$A$34 -> 453375 | W64: =W54*A34 -> 188906.25 | X64: =X54*$A$34 -> 127830.15 | AC64: =C64+G64+K64+O64+S64 -> 127830.15
A65: Investimento amortização | B65: =B29*'Rateio Mensal'!M3 -> 3042.2883 | C65: =C29*'Rateio Mensal'!C3 -> 2906.974 | D65: =B65-C65 -> 135.31432 | E65: =C65/B65 -> 0.95552219 | F65: =F29*'Rateio Mensal'!M3 -> 3042.2883 | G65: =G29*'Rateio Mensal'!C9 -> 2948.8223 | J65: =J29*'Rateio Mensal'!M3 -> 3042.2883 | K65: =K29*'Rateio Mensal'!C9 -> 2948.8223 | N65: =N29*'Rateio Mensal'!M3 -> 3042.2883 | O65: =O29*'Rateio Mensal'!C9 -> 2948.8223 | R65: =R29*'Rateio Mensal'!M3 -> 3042.2883 | S65: =S29*'Rateio Mensal'!C9 -> 2948.8223 | V65: =V29*'Rateio Mensal'!M3 -> 36507.46 | W65: =B65+F65+J65+N65+R65 -> 15211.442 | X65: =C65+G65+K65+O65+S65 -> 14702.263 | AC65: =C65+G65+K65+O65+S65 -> 14702.263
A66: Resultado Liquido após impostos | B66: =B61-B64-B65 -> 95121.237 | C66: =C61-C64-C65 -> -62640.647 | F66: =F61-F64-F65 -> 93516.867 | G66: =G61-G64-G65 -> -16446.951 | J66: =J61-J64-J65 -> 87569.766 | K66: =K61-K64-K65 -> 175181.22 | N66: =N61-N64-N65 -> 88031.191 | O66: =O61-O64-O65 -> 13465.779 | R66: =R61-R64-R65 -> 95587.979 | S66: =S61-S64-S65 -> 16936.672 | V66: =V61-V64-V65 -> 1094722.7 | W66: =W61-W64-W65 -> 459827.04 | X66: =X61-X64-X65 -> 126496.08 | AC66: =C66+G66+K66+O66+S66 -> 126496.08
A67: Margem liquida | B67: =B66/B54 -> 0.37765255 | C67: =C66/C54 -> -1.0128816 | F67: =F66/F54 -> 0.37128284 | G67: =G66/G54 -> -0.13743932 | J67: =J66/J54 -> 0.34767153 | K67: =K66/K54 -> 0.50940619 | N67: =N66/N54 -> 0.34950349 | O67: =O66/O54 -> 0.084202694 | R67: =R66/R54 -> 0.37950562 | S67: =S66/S54 -> 0.10149256 | V67: =V66/V54 -> 0.36219114 | W67: =W66/W54 -> 0.36512321 | X67: =X66/X54 -> 0.14843456
A68: Reserva bônus | B68: =B66*10% -> 9512.1237 | C68: =C66*10% -> -6264.0647 | F68: =F66*10% -> 9351.6867 | G68: =G66*10% -> -1644.6951 | J68: =J66*10% -> 8756.9766 | K68: =K66*10% -> 17518.122 | N68: =N66*10% -> 8803.1191 | O68: =O66*10% -> 1346.5779 | R68: =R66*10% -> 9558.7979 | S68: =S66*10% -> 1693.6672 | V68: =V66*10% -> 109472.27 | W68: =W66*10% -> 45982.704 | X68: =X66*10% -> 12649.608
AC69: =C69+G69+K69+O69+S69 -> 0
B70: Janeiro | F70: Fevereiro | J70: =J1 -> Março | N70: =N1 -> Abril | R70: =R1 -> Maio | AC70: =C70+G70+K70+O70+S70 -> 0
A71: Resultado Arbitragem | B71: Orçado | C71: Realizado | D71: Variação Mensal | E71: Desvio% | F71: Orçado | G71: Realizado | H71: Variação Mensal | I71: Desvio% | J71: Orçado | K71: Realizado | L71: Variação Mensal | M71: Desvio% | N71: Orçado | O71: Realizado | P71: Variação Mensal | Q71: Desvio% | R71: Orçado | S71: Realizado | T71: Variação Mensal | U71: Desvio% | V71: Orçado YTG | W71: Orçado YTD | X71: Realizado | Y71: Variação | Z71: Desvio% | AA71: YTG
A72: Receita | B72: =($B$3/4) -> 167916.67 | C72: =133078+91 -> 133169 | D72: =C72-B72 -> -34747.668 | E72: =C72/B72 -> 0.793066 | F72: =B72 -> 167916.67 | G72: =62401+105 -> 62506 | H72: =G72-F72 -> -105410.67 | I72: =G72/F72 -> 0.37224417 | J72: =F72 -> 167916.67 | K72: =113442+2 -> 113444 | L72: =K72-J72 -> -54472.668 | M72: =K72/J72 -> 0.67559702 | N72: =J72 -> 167916.67 | O72: =3473+3 -> 3476 | P72: =O72-N72 -> -164440.67 | Q72: =O72/N72 -> 0.020700744 | R72: =N72 -> 167916.67 | S72: =41998-138 -> 41860 | T72: =S72-R72 -> -126056.67 | U72: =S72/R72 -> 0.24929032 | V72: =($V$3/4) -> 2015000 | W72: =B72+F72+J72+N72+R72 -> 839583.34 | X72: =C72+G72+K72+O72+S72 -> 354455 | Y72: =X72-W72 -> -485128.34 | Z72: =X72/W72 -> 0.42217965 | AA72: =V72-X72 -> 1660545 | AC72: =C72+G72+K72+O72+S72 -> 354455 | AD72: =X72-AC72 -> 0
AC73: =C73+G73+K73+O73+S73 -> 0
A74: Despesas | B74: Orçado | C74: Realizado | D74: Variação Mensal | E74: Desvio% | F74: Orçado | G74: Realizado | H74: Variação Mensal | I74: Desvio% | J74: Orçado | K74: Realizado | L74: Variação Mensal | M74: Desvio% | N74: Orçado | O74: Realizado | P74: Variação Mensal | Q74: Desvio% | R74: Orçado | S74: Realizado | T74: Variação Mensal | U74: Desvio% | V74: Orçado YTG | W74: Orçado YTD | X74: Realizado | Y74: Variação | Z74: Desvio% | AA74: YTG
A75: Custo Equipe | B75: =+B11 -> 63453.36 | C75: ='Base_Resultado Mensal_V2'!C60 -> 62013.17 | D75: =+B75-C75 -> 1440.19 | E75: =(C75/B75)-1 -> -0.022696828 | F75: =+F11 -> 61853.36 | G75: ='Base_Resultado Mensal_V2'!D60 -> 61794.34 | H75: =+F75-G75 -> 59.02 | I75: =(G75/F75)-1 -> -0.0009541923 | J75: =+J11 -> 49236.38 | K75: =K11 -> 49183.94 | L75: =+J75-K75 -> 52.44 | M75: =(K75/J75)-1 -> -0.0010650661 | N75: =+N11 -> 50836.38 | O75: =O11 -> 55038.69 | P75: =+N75-O75 -> -4202.31 | Q75: =(O75/N75)-1 -> 0.082663439 | R75: =+R11 -> 49236.38 | S75: =S11 -> 54383.94 | T75: =+R75-S75 -> -5147.56 | U75: =(S75/R75)-1 -> 0.1045479 | V75: =V11 -> 623198.16 | W75: =B75+F75+J75+N75+R75 -> 274615.86 | X75: =X11 -> 282414.08 | Y75: =W75-X75 -> -7798.22 | Z75: =X75/W75 -> 1.0283968 | AA75: =V75-X75 -> 340784.08 | AC75: =C75+G75+K75+O75+S75 -> 282414.08 | AD75: =X75-AC75 -> 0
A76: =A12 -> Participação/comissão - Arbitragem | C76: =C12 -> 0 | G76: =G12 -> 0 | K76: =K12 -> 0 | O76: =O12 -> 0 | S76: =S12 -> 0 | W76: =B76+F76+J76+N76+R76 -> 0 | X76: =X12 -> 0 | AC76: =C76+G76+K76+O76+S76 -> 0
A77: Despesas Equipe | B77: ='Orçamento 2026'!D194 -> 1901.49 | C77: =+'Base_Resultado Mensal_V2'!C206 -> 146 | D77: =+B77-C77 -> 1755.49 | E77: =(C77/B77)-1 -> -0.92321811 | F77: ='Orçamento 2026'!E194 -> 5799.49 | G77: ='Base_Resultado Mensal_V2'!D206 -> 2633.6933 | H77: =+F77-G77 -> 3165.7967 | I77: =(G77/F77)-1 -> -0.54587501 | J77: ='Orçamento 2026'!F194 -> 7299.49 | K77: ='Base_Resultado Mensal_V2'!E206 -> 3728.1833 | L77: =+J77-K77 -> 3571.3067 | M77: =(K77/J77)-1 -> -0.48925427 | N77: ='Orçamento 2026'!G194 -> 5799.49 | O77: ='Base_Resultado Mensal_V2'!F206 -> 2633.6933 | P77: =+N77-O77 -> 3165.7967 | Q77: =(O77/N77)-1 -> -0.54587501 | R77: ='Orçamento 2026'!H194 -> 1901.49 | S77: ='Base_Resultado Mensal_V2'!G206 -> 1204.47 | T77: =+R77-S77 -> 697.02 | U77: =(S77/R77)-1 -> -0.36656517 | V77: ='Orçamento 2026'!B194 -> 39602.215 | W77: =B77+F77+J77+N77+R77 -> 22701.45 | X77: =C77+G77+K77+O77+S77 -> 10346.04 | Y77: =W77-X77 -> 12355.41 | Z77: =X77/W77 -> 0.45574358 | AA77: =V77-X77 -> 29256.175 | AC77: =C77+G77+K77+O77+S77 -> 10346.04 | AD77: =X77-AC77 -> 0
A78: Despesas Institucional | B78: ='Orçamento 2026'!D196*'Rateio Mensal'!M4 -> 24458.641 | C78: ='Rateio Mensal'!I4 -> 28506.06 | D78: =+B78-C78 -> -4047.4185 | E78: =(C78/B78)-1 -> 0.1654801 | F78: ='Orçamento 2026'!E196*'Rateio Mensal'!M4 -> 23917.868 | G78: ='Rateio Mensal'!I10 -> 24776.642 | H78: =+F78-G78 -> -858.77387 | I78: =(G78/F78)-1 -> 0.035905117 | J78: ='Orçamento 2026'!F196*'Rateio Mensal'!M4 -> 27972.307 | K78: ='Rateio Mensal'!I16 -> 23282.159 | L78: =+J78-K78 -> 4690.1474 | M78: =(K78/J78)-1 -> -0.1676711 | N78: ='Orçamento 2026'!G196*'Rateio Mensal'!M4 -> 26566.929 | O78: ='Rateio Mensal'!I22 -> 26579.88 | P78: =+N78-O78 -> -12.950653 | Q78: =(O78/N78)-1 -> 0.00048747269 | R78: ='Orçamento 2026'!H196*'Rateio Mensal'!M4 -> 24140.724 | S78: ='Rateio Mensal'!I28 -> 26080.54 | T78: =+R78-S78 -> -1939.8162 | U78: =(S78/R78)-1 -> 0.080354514 | V78: ='Orçamento 2026'!B196*'Rateio Mensal'!M4 -> 320076.92 | W78: =B78+F78+J78+N78+R78 -> 127056.47 | X78: =C78+G78+K78+O78+S78 -> 129225.28 | Y78: =W78-X78 -> -2168.8118 | Z78: =X78/W78 -> 1.0170697 | AA78: =V78-X78 -> 190851.63 | AC78: =C78+G78+K78+O78+S78 -> 129225.28 | AD78: =X78-AC78 -> 0
A79: Resultado Bruto | B79: =B72-B75-B77-B78 -> 78103.176 | C79: =C72-C75-C77-C78-C76 -> 42503.77 | F79: =F72-F75-F77-F78 -> 76345.949 | G79: =G72-G75-G77-G78-G76 -> -26698.676 | J79: =J72-J75-J77-J78 -> 83408.491 | K79: =K72-K75-K77-K78-K76 -> 37249.717 | N79: =N72-N75-N77-N78 -> 84713.868 | O79: =O72-O75-O77-O78-O76 -> -80776.263 | R79: =R72-R75-R77-R78 -> 92638.073 | S79: =S72-S75-S77-S78-S76 -> -39808.95 | V79: =+V72-(V75+V77+V78) -> 1032122.7 | W79: =+W72-(W75+W77+W78) -> 415209.56 | X79: =X72-X75-X77-X78-X76 -> -67530.402
A80: Margem de bruta | B80: =B79/B72 -> 0.46513058 | C80: =C79/C72 -> 0.31917166 | F80: =F79/F72 -> 0.4546657 | G80: =G79/G72 -> -0.4271378 | J80: =J79/J72 -> 0.4967255 | K80: =K79/K72 -> 0.32835335 | N80: =N79/N72 -> 0.50449946 | O80: =O79/O72 -> -23.238281 | R80: =R79/R72 -> 0.55169076 | S80: =S79/S72 -> -0.95100216 | V80: =V79/V72 -> 0.51221971 | W80: =W79/W72 -> 0.4945424 | X80: =X79/X72 -> -0.19051897
AC81: =C81+G81+K81+O81+S81 -> 0
A82: Impostos | B82: =B72*$A$34 -> 25187.5 | C82: =C72*$A$34 -> 19975.35 | D82: =(B82-C82) -> 5212.1501 | E82: =C82/B82 -> 0.793066 | F82: =F72*$A$34 -> 25187.5 | G82: =G72*$A$34 -> 9375.9 | J82: =J72*$A$34 -> 25187.5 | K82: =K72*$A$34 -> 17016.6 | N82: =N72*$A$34 -> 25187.5 | O82: =O72*$A$34 -> 521.4 | R82: =R72*$A$34 -> 25187.5 | S82: =S72*$A$34 -> 6279 | V82: =V72*$A$34 -> 302250 | W82: =B82+F82+J82+N82+R82 -> 125937.5 | X82: =X72*$A$34 -> 53168.25 | AC82: =C82+G82+K82+O82+S82 -> 53168.25 | AD82: =X82-AC82 -> 0
A83: Investimento amortização | B83: =B29*'Rateio Mensal'!M4 -> 2074.0815 | C83: =C29*'Rateio Mensal'!C4 -> 2382.8561 | D83: =B83-C83 -> -308.77456 | E83: =C83/B83 -> 1.1488729 | F83: =F29*'Rateio Mensal'!M4 -> 2074.0815 | G83: =G29*'Rateio Mensal'!C10 -> 2311.9429 | J83: =J29*'Rateio Mensal'!M4 -> 2074.0815 | K83: =K29*'Rateio Mensal'!C10 -> 2311.9429 | N83: =N29*'Rateio Mensal'!M4 -> 2074.0815 | O83: =O29*'Rateio Mensal'!C10 -> 2311.9429 | R83: =R29*'Rateio Mensal'!M4 -> 2074.0815 | S83: =S29*'Rateio Mensal'!C10 -> 2311.9429 | V83: =V29*'Rateio Mensal'!M4 -> 24888.978 | W83: =B83+F83+J83+N83+R83 -> 10370.408 | X83: =C83+G83+K83+O83+S83 -> 11630.628 | AC83: =C83+G83+K83+O83+S83 -> 11630.628 | AD83: =X83-AC83 -> 0
A84: Resultado Liquido após impostos | B84: =B79-B82-B83 -> 50841.595 | C84: =C79-C82-C83 -> 20145.564 | F84: =F79-F82-F83 -> 49084.367 | G84: =G79-G82-G83 -> -38386.518 | J84: =J79-J82-J83 -> 56146.909 | K84: =K79-K82-K83 -> 17921.174 | N84: =N79-N82-N83 -> 57452.286 | O84: =O79-O82-O83 -> -83609.606 | R84: =R79-R82-R83 -> 65376.492 | S84: =S79-S82-S83 -> -48399.893 | V84: =V79-V82-V83 -> 704983.74 | W84: =W79-W82-W83 -> 278901.65 | X84: =X79-X82-X83 -> -132329.28
A85: Margem liquida | B85: =B84/B72 -> 0.30277873 | C85: =C84/C72 -> 0.15127818 | F85: =F84/F72 -> 0.29231385 | G85: =G84/G72 -> -0.61412534 | J85: =J84/J72 -> 0.33437365 | K85: =K84/K72 -> 0.15797375 | N85: =N84/N72 -> 0.34214761 | O85: =O84/O72 -> -24.053397 | R85: =R84/R72 -> 0.38933891 | S85: =S84/S72 -> -1.1562325 | V85: =V84/V72 -> 0.34986786 | W85: =W84/W72 -> 0.33219055 | X85: =X84/X72 -> -0.37333168
A86: Reserva bônus | B86: =B84*10% -> 5084.1595 | C86: =C84*10% -> 2014.5564 | F86: =F84*10% -> 4908.4367 | G86: =G84*10% -> -3838.6518 | J86: =J84*10% -> 5614.6909 | K86: =K84*10% -> 1792.1174 | N86: =N84*10% -> 5745.2286 | O86: =O84*10% -> -8360.9606 | R86: =R84*10% -> 6537.6492 | S86: =S84*10% -> -4839.9893 | V86: =V84*10% -> 70498.374 | W86: =W84*10% -> 27890.165 | X86: =X84*10% -> -13232.928
A88: NÃO ALOCADOS | C88: 46736 | G88: -22478 | K88: -4760 | O88: 18470 | S88: -33252
C89: =C4 -> 279821.07 | G89: =G4 -> 319233.58 | K89: =K4 -> 612501.76 | O89: =O4 -> 238327.46 | S89: =S4 -> 415928
C90: =C36+C54+C72 -> 233084 | G90: =G36+G54+G72 -> 341712 | K90: =K36+K54+K72 -> 617262 | O90: =O36+O54+O72 -> 219858 | S90: =S36+S54+S72 -> 449181 | AC90: =AC86+AC68+AC50 -> 0
C91: =C89-C90 -> 46737.07 | G91: =G89-G90 -> -22478.42 | K91: =K89-K90 -> -4760.24 | O91: =O89-O90 -> 18469.46 | S91: =S89-S90 -> -33253
C92: =C88-C91 -> -1.07 | G92: =G88-G91 -> 0.42 | K92: =K88-K91 -> 0.24 | O92: =O88-O91 -> 0.54 | S92: =S88-S91 -> 1
R93: =R86+R68+R50 -> 26056.799 | S93: =S86+S68+S50 -> 5808.596
R94: =R32 -> 26056.799 | S94: =S32 -> 2982.091 | V94: =V86+V68+V50 -> 292805.2 | W94: =W86+W68+W50 -> 121176.15 | X94: =X86+X68+X50 -> -1895.591 | Y94: =Y86+Y68+Y50 -> 0
R95: =R93-R94 -> 0 | S95: =S93-S94 -> 2826.505 | V95: =V94-V32 -> 0 | W95: =W94-W32 -> 0 | X95: =X94-X32 -> -400.76395 | Y95: =Y94-Y32 -> 0 | Z95: =X99-Y95 -> 0
T96: Check | V96: =V77+V78+V59+V41+V42+V60 -> 1386633.4 | W96: =W77+W78+W59+W41+W42+W60 -> 572754.87 | X96: =X77+X78+X59+X41+X42+X60 -> 512865.24 | Y96: =X46+X64+X82 -> 279164.55 | Z96: =X100-Y96 -> -279164.55
V97: =V13 -> 1386633.4 | W97: =W13 -> 572754.87 | X97: =X13 -> 512865.24
V98: =V96-V97 -> 0 | W98: =W96-W97 -> 0 | X98: =X96-X97 -> 0

Sheet Institucional
B1: Orçado | C1: Realizado
A2: Recebimento | B2: ='Areas Sintetico atualizado'!W3 -> 3358333.4 | C2: ='Areas Sintetico atualizado'!X4 -> 1865811.9
A3: Custo equipe | B3: ='[1]Areas Sintetico atualizado'!AI7 -> 1806527.7 | C3: ='Areas Sintetico atualizado'!X6 -> 1047438.1 | D3: =C3/$C$2 -> 0.56138464
A4: Despesas | B4: ='[1]Areas Sintetico atualizado'!AI11 -> 1228915.9 | C4: ='Areas Sintetico atualizado'!X13 -> 512865.24 | D4: =C4/$C$2 -> 0.27487511
A5: Resultado Bruto | B5: =B2-B3-B4 -> 322889.67 | C5: =C2-C3-C4 -> 305508.51 | D5: =C5/$C$2 -> 0.16374025
A6: Imposto | B6: =B2*14.53% -> 487965.84 | C6: ='Areas Sintetico atualizado'!X28 -> 279871.78
A7: Amortização | C7: ='Areas Sintetico atualizado'!X29 -> 40585
A8: Resultado Liquido | B8: =B5-B6 -> -165076.16 | C8: =C5-C6-C7 -> -14948.27
A11: Recebimento
A12: Custo equipe | C12: =D3 -> 0.56138464
A13: Despesas | C13: =D4 -> 0.27487511
A14: Resultado Bruto | C14: =D5 -> 0.16374025
A15: Imposto
A16: Resultado Liquido
A20: =A2 -> Recebimento | B20: =C2 -> 1865811.9
A21: ='Areas Sintetico atualizado'!A14 -> Ocupação | B21: ='Areas Sintetico atualizado'!X14 -> 172052.01 | C21: =B21/$B$20 -> 0.092212946
A22: ='Areas Sintetico atualizado'!A15 -> Telecomunicações | B22: ='Areas Sintetico atualizado'!X15 -> 4071.3 | C22: =B22/$B$20 -> 0.0021820528
A23: ='Areas Sintetico atualizado'!A16 -> Despesas Gerais | B23: ='Areas Sintetico atualizado'!X16 -> 30500.48 | C23: =B23/$B$20 -> 0.016347029
A24: ='Areas Sintetico atualizado'!A17 -> Consultoria | B24: ='Areas Sintetico atualizado'!X17 -> 120094.62 | C24: =B24/$B$20 -> 0.064365878
A25: ='Areas Sintetico atualizado'!A18 -> Salários Administração | B25: ='Areas Sintetico atualizado'!X18 -> 43770.76 | C25: =B25/$B$20 -> 0.023459364
A26: ='Areas Sintetico atualizado'!A19 -> Administrativas | B26: ='Areas Sintetico atualizado'!X19 -> 28428.88 | C26: =B26/$B$20 -> 0.015236734
A27: ='Areas Sintetico atualizado'!A21 -> Investimentos em Prospecção | B27: ='Areas Sintetico atualizado'!X21 -> 6548.82 | C27: =B27/$B$20 -> 0.0035099037
A28: ='Areas Sintetico atualizado'!A22 -> Endomarketing | B28: ='Areas Sintetico atualizado'!X22 -> 547.94 | C28: =B28/$B$20 -> 0.00029367377
A29: ='Areas Sintetico atualizado'!A23 -> Gestão do Conhecimento | B29: ='Areas Sintetico atualizado'!X23 -> 4836.86 | C29: =B29/$B$20 -> 0.0025923621
A30: ='Areas Sintetico atualizado'!A24 -> Informática | B30: ='Areas Sintetico atualizado'!X24 -> 102013.57 | C30: =B30/$B$20 -> 0.054675164
A31: ='Areas Sintetico atualizado'!A25 -> Resultado Bruto

Sheet Planilha1

Sheet Institucional ano
B1: Orçado
A2: Recebimento | B2: ='Areas Sintetico atualizado'!W3 -> 3358333.4
A3: Custo equipe | B3: ='[1]Areas Sintetico atualizado'!AI7 -> 1806527.7
A4: Despesas | B4: ='[1]Areas Sintetico atualizado'!AI11 -> 1228915.9
A5: Resultado Bruto | B5: =B2-B3-B4 -> 322889.67
A6: Imposto | B6: =B2*14.53% -> 487965.84
A7: Amortização
A8: Resultado Liquido | B8: =B5-B6 -> -165076.16
A11: Recebimento
A12: Custo equipe
A13: Despesas
A14: Resultado Bruto
A15: Imposto
A16: Resultado Liquido
A20: =A2 -> Recebimento | B20: ='DRE 2026'!B3 -> 8060000
A21: ='DRE 2026'!A5 -> Custos Diretos | B21: ='DRE 2026'!B5 -> 2438910.6 | C21: =B21/$B$32 -> 0.63753302
A22: ='DRE 2026'!A10 -> Ocupação | B22: ='DRE 2026'!B10 -> 410635.68 | C22: =B22/$B$32 -> 0.10734047
A23: ='DRE 2026'!A11 -> Telecomunicações | B23: ='DRE 2026'!B11 -> 10127.402 | C23: =B23/$B$32 -> 0.0026473102
A24: ='DRE 2026'!A12 -> Despesas Gerais | B24: ='DRE 2026'!B12 -> 74921.85 | C24: =B24/$B$32 -> 0.019584626
A25: ='DRE 2026'!A13 -> Consultoria | B25: ='DRE 2026'!B13 -> 287104.88 | C25: =B25/$B$32 -> 0.075049426
A26: ='DRE 2026'!A14 -> Salários Administração | B26: ='DRE 2026'!B14 -> 94659.531 | C26: =B26/$B$32 -> 0.02474407
A27: ='DRE 2026'!A15 -> Administrativas | B27: ='DRE 2026'!B15 -> 91084.049 | C27: =B27/$B$32 -> 0.023809437
A28: Prospecção | B28: ='DRE 2026'!B17 -> 96000 | C28: =B28/$B$32 -> 0.02509447
A29: ='DRE 2026'!A18 -> Endomarketing | B29: ='DRE 2026'!B18 -> 1200 | C29: =B29/$B$32 -> 0.00031368087
A30: ='DRE 2026'!A19 -> Gestão do Conhecimento | B30: ='DRE 2026'!B19 -> 2300 | C30: =B30/$B$32 -> 0.00060122168
A31: ='DRE 2026'!A20 -> Informática | B31: ='DRE 2026'!B20 -> 318600 | C31: =B31/$B$32 -> 0.083282272
B32: =SUM(B21:B31) -> 3825544
A35: =A21 -> Custos Diretos | B35: =C21 -> 0.63753302
A36: =A22 -> Ocupação | B36: =C22 -> 0.10734047
A37: =A25 -> Consultoria | B37: =C25 -> 0.075049426
A38: =A27 -> Administrativas | B38: =C24+C29+C30+C27 -> 0.044308965
A39: Pessoal | B39: =C26 -> 0.02474407
A40: TI | B40: =C31+C23 -> 0.085929582
A41: =A28 -> Prospecção | B41: =C28 -> 0.02509447

Sheet Contencioso
B1: Orçado | C1: Realizado
A2: Recebimento | B2: ='Areas Sintetico atualizado'!W36 -> 1259375 | C2: ='Areas Sintetico atualizado'!X36 -> 654441
A3: Custo equipe | B3: ='Areas Sintetico atualizado'!W39 -> 374870.33 | C3: ='Areas Sintetico atualizado'!X39 -> 372279.42 | D3: =C3/$C$2 -> 0.56885101
A5: Despesas Equipe | B5: ='Areas Sintetico atualizado'!W41 -> 23746.45 | C5: ='Areas Sintetico atualizado'!X41 -> 11996.265 | D5: =C5/$C$2 -> 0.018330552
A6: Despesa Institucional | B6: ='Areas Sintetico atualizado'!W42 -> 183816.05 | C6: ='Areas Sintetico atualizado'!X42 -> 170869.76 | D6: =C6/$C$2 -> 0.26109268
A7: Resultado Bruto | B7: =B2-B3-B5-B6 -> 676942.18 | C7: =C2-C3-C5-C6-C4 -> 99295.552 | D7: =C7/$C$2 -> 0.15172575
A13: Recebimento
A14: Custo equipe | B14: =D3 -> 0.56885101
A16: Despesas Equipe | B16: =D5 -> 0.018330552
A17: Despesa Institucional | B17: =D6 -> 0.26109268
A18: =A7 -> Resultado Bruto | B18: =D7 -> 0.15172575

Sheet Econômico
B1: Orçado | C1: Realizado
A2: Recebimento | B2: ='Areas Sintetico atualizado'!W54 -> 1259375 | C2: ='Areas Sintetico atualizado'!X54 -> 852201
A3: Custo equipe | B3: ='Areas Sintetico atualizado'!W57 -> 379995.83 | C3: ='Areas Sintetico atualizado'!X57 -> 389116.55 | D3: =C3/$C$2 -> 0.45660185
A4: ='Areas Sintetico atualizado'!A40 -> Participação/Comissão - Contencioso | C4: ='Areas Sintetico atualizado'!X10 -> 3628.06 | D4: =C4/$C$2 -> 0.004257282
A5: Despesas Equipe | B5: ='Areas Sintetico atualizado'!W59 -> 29066.45 | C5: ='Areas Sintetico atualizado'!X59 -> 11726.605 | D5: =C5/$C$2 -> 0.013760375
A6: Despesa Institucional | B6: ='Areas Sintetico atualizado'!W60 -> 186368 | C6: ='Areas Sintetico atualizado'!X60 -> 178701.29 | D6: =C6/$C$2 -> 0.20969383
A7: Resultado Bruto | B7: =B2-B3-B5-B6 -> 663944.73 | C7: =C2-C3-C5-C6-C4 -> 269028.49 | D7: =C7/$C$2 -> 0.31568666
A13: Recebimento
A14: Custo equipe | B14: =D3 -> 0.45660185
A15: =A4 -> Participação/Comissão - Contencioso | B15: =D4 -> 0.004257282
A16: Despesas Equipe | B16: =D5 -> 0.013760375
A17: Despesa Institucional | B17: =D6 -> 0.20969383
A18: Resultado Bruto | B18: =D7 -> 0.31568666

Sheet Arbitragem
B1: Orçado | C1: Realizado
A2: Recebimento | B2: ='Areas Sintetico atualizado'!W72 -> 839583.34 | C2: ='Areas Sintetico atualizado'!X72 -> 354455
A3: Custo equipe | B3: ='Areas Sintetico atualizado'!W75 -> 274615.86 | C3: ='Areas Sintetico atualizado'!X75 -> 282414.08 | D3: =C3/$C$2 -> 0.79675581
A4: =Econômico!A4 -> Participação/Comissão - Contencioso | C4: ='Areas Sintetico atualizado'!X76 -> 0 | D4: =C4/$C$2 -> 0
A5: Despesas Equipe | B5: ='Areas Sintetico atualizado'!W77 -> 22701.45 | C5: ='Areas Sintetico atualizado'!X77 -> 10346.04 | D5: =C5/$C$2 -> 0.029188585
A6: Despesa Institucional | B6: ='Areas Sintetico atualizado'!W78 -> 127056.47 | C6: ='Areas Sintetico atualizado'!X78 -> 129225.28 | D6: =C6/$C$2 -> 0.36457458
A7: Resultado Bruto | B7: =B2-B3-B5-B6 -> 415209.56 | C7: =C2-C3-C5-C6-C4 -> -67530.402 | D7: =C7/$C$2 -> -0.19051897
A13: Recebimento
A14: Custo equipe | B14: =D3 -> 0.79675581
A15: Despesas Equipe | B15: =D5 -> 0.029188585
A16: Despesa Institucional | B16: =D6 -> 0.36457458
A17: Resultado Bruto | B17: =D7 -> -0.19051897

Sheet Nacional
A1: Docto | B1: Cliente | C1: Razão Social Fatura | D1: Histórico | E1: Fatura | F1: Número Nota Fiscal | G1: Data Emissão | H1: Vencimento | I1: Data Recebimento | J1: Moeda | K1: Valor Honorários | L1: Valor Despesas | M1: Valor Total Fatura | N1: Valor Total | O1: Valor Recebido | P1: Honorários
A2: 11754 | B2: 114 | C2: Companhia Ultragaz S.A. | D2: Fatura: 3952 - Cliente: 114 - Companhia Ultragaz S.A. - Caso: 1 - Trustee AC Ultragaz Supergasbras | E2: 3952 | F2: 00002950 | G2: 46003 | H2: 46034 | I2: 46027 | J2: R | K2: 6285.49 | L2: 0 | M2: 6285.49 | N2: 5898.93 | O2: 5898.93 | P2: 6285.49
A3: 11609 | B3: 2 | C3: VLI Multimodal S.A | D3: Fatura: 3919 - Cliente: 2 - VLI Multimodal S.A - Caso: 8 - (Contrato Fixo) - Ação Ordinária ANTAQ | E3: 3919 | F3: 00002932 | G3: 45982 | H3: 46027 | I3: 46027 | J3: R | K3: 1332.56 | L3: 0 | M3: 1332.56 | N3: 1250.61 | O3: 1250.61 | P3: 1332.56
A4: 11740 | B4: 6 | C4: Sherwin-Williams do Brasil Indústria e Comércio Ltda. Sherwin-Williams do Brasil Indústria e Comérc | D4: Fatura: 3944 - Cliente: 6 - Sherwin-Williams do Brasil Indústria e Comércio Ltda. - Caso: 7 - (Contrato Fixo) - Ação de Cobrança - ARG Representações - Acompanhamento Processual | E4: 3944 | G4: 46002 | H4: 46034 | I4: 46029 | J4: R | K4: 0 | L4: 477.87 | M4: 477.87 | N4: 477.87 | O4: 477.87 | P4: 0
A5: 11711 | B5: 139 | C5: Zetta | D5: Fatura: 3932 - Cliente: 139 - Zetta - Caso: 2 - Assessoria e Monitoramento (Etapa 3) - Cade | E5: 3932 | F5: 00002934 | G5: 45999 | H5: 46029 | I5: 46029 | J5: R | K5: 10000 | L5: 0 | M5: 10000 | N5: 9385 | O5: 9385 | P5: 10000
A6: 11696 | B6: 132 | C6: Eólica Serra Das Vacas Vii S.A. | D6: Fatura: 3929 - Cliente: 132 - Eólica Serra Das Vacas Vii S.A. - Caso: 1 - Ação Indenizatória Neo Energia | E6: 3929 | F6: 00002935 | G6: 45994 | H6: 46031 | I6: 46030 | J6: R | K6: 2318.18 | L6: 0 | M6: 2318.18 | N6: 2175.63 | O6: 2175.63 | P6: 2318.18
A7: 11729 | B7: 6 | C7: Sherwin-Williams do Brasil Indústria e Comércio Ltda. Sherwin-Williams do Brasil Indústria e Comérc | D7: Fatura: 3933 - Cliente: 6 - Sherwin-Williams do Brasil Indústria e Comércio Ltda. - Caso: 4 - (Contrato Fixo) - Ação de Cobrança - Renato Vaz de Mello - Acompanhamento Processual | E7: 3933 | F7: 00002943 | G7: 46001 | H7: 46034 | I7: 46030 | J7: R | K7: 4068 | L7: 0 | M7: 4068 | N7: 3817.82 | O7: 3817.82 | P7: 4068
A8: 11741 | B8: 7 | C8: John Deere Brasil Ltda. | D8: Fatura: 3945 - Cliente: 7 - John Deere Brasil Ltda. - Caso: 1 - Consultas Diversas | E8: 3945 | F8: 00002944 | G8: 46002 | H8: 46034 | I8: 46034 | J8: R | K8: 10064.34 | L8: 0 | M8: 10064.34 | N8: 9445.38 | O8: 9445.38 | P8: 10064.34
A9: 11742 | B9: 7 | C9: John Deere Brasil Ltda. | D9: Fatura: 3946 - Cliente: 7 - John Deere Brasil Ltda. - Caso: 17 - Consulta - Programa Protect | E9: 3946 | F9: 00002945 | G9: 46002 | H9: 46034 | I9: 46034 | J9: R | K9: 4860.5 | L9: 0 | M9: 4860.5 | N9: 4561.59 | O9: 4561.59 | P9: 4860.5
A10: 11690 | B10: 115 | C10: Maristela Haddad Andraus De Oliveira | D10: Fatura: 3923 - Cliente: 115 - Cansford Associates Limited - Caso: 1 - AMCHAM 156 | E10: 3923 | F10: 00002927 | G10: 45993 | H10: 46013 | I10: 46034 | J10: R | K10: 466.68 | L10: 0 | M10: 466.68 | N10: 466.68 | O10: 466.68 | P10: 466.68
A11: 11730 | B11: 61 | C11: Navemazônia Navegação Ltda | D11: Fatura: 3934 - Cliente: 61 - Atem's Distribuidora De Petróleo S.A. - Caso: 17 - Notificação de Operação ao CADE | Operação WPL | E11: 3934 | F11: 00002948 | G11: 46002 | H11: 46034 | I11: 46034 | J11: R | K11: 15000 | L11: 0 | M11: 15000 | N11: 14077.5 | O11: 14077.5 | P11: 15000
A12: 11749 | B12: 61 | C12: REFINARIA DE MANAUS S.A | D12: Fatura: 3947 - Cliente: 61 - Atem's Distribuidora De Petróleo S.A. - Caso: 10 - Ream - Trabalhos Adicionais | E12: 3947 | F12: 00002946 | G12: 46003 | H12: 46034 | I12: 46034 | J12: R | K12: 23419.69 | L12: 0 | M12: 23419.69 | N12: 21979.4 | O12: 21979.4 | P12: 23419.69
A13: 11750 | B13: 61 | C13: REFINARIA DE MANAUS S.A | D13: Fatura: 3948 - Cliente: 61 - Atem's Distribuidora De Petróleo S.A. - Caso: 9 - Cade - Cumprimento ACC | E13: 3948 | F13: 00002947 | G13: 46003 | H13: 46034 | I13: 46034 | J13: R | K13: 24923.14 | L13: 0 | M13: 24923.14 | N13: 23390.37 | O13: 23390.37 | P13: 24923.14
A14: 11755 | B14: 114 | C14: Supergasbras Energia Ltda | D14: Fatura: 3953 - Cliente: 114 - Companhia Ultragaz S.A. - Caso: 1 - Trustee AC Ultragaz Supergasbras | E14: 3953 | F14: 00002951 | G14: 46003 | H14: 46037 | I14: 46036 | J14: R | K14: 6285.49 | L14: 0 | M14: 6285.49 | N14: 5898.94 | O14: 5898.94 | P14: 6285.49
A15: 11849 | B15: 5 | C15: White Martins Gases Industriais Ltda. | D15: Fatura: 3963 - Cliente: 5 - White Martins Gases Industriais Ltda. - Caso: 11 - Avaliação de Risco Concorrencial | E15: 3963 | F15: 00002963 | G15: 46021 | H15: 46031 | I15: 46036 | J15: R | K15: 4930 | L15: 0 | M15: 4930 | N15: 4626.8 | O15: 4626.8 | P15: 4930
A16: 11970 | B16: 146 | C16: Hunter Douglas do Brasil LTDA | D16: Fatura: 4008 - Cliente: 146 - Hunter Douglas do Brasil LTDA - Caso: 2 - Contrato Montasul | E16: 4008 | F16: 00003024 | G16: 46037 | H16: 46056 | I16: 46037 | J16: R | K16: 18367.08 | L16: 0 | M16: 18367.08 | N16: 17237.5 | O16: 17237.5 | P16: 18367.08
A17: 11732 | B17: 61 | C17: Navemazônia Navegação Ltda | D17: Fatura: 3936 - Cliente: 61 - Atem's Distribuidora De Petróleo S.A. - Caso: 17 - Notificação de Operação ao CADE | Operação WPL | E17: 3936 | G17: 46002 | H17: 46034 | I17: 46037 | J17: R | K17: 0 | L17: 16644.03 | M17: 16644.03 | N17: 16644.03 | O17: 16644.03 | P17: 0
A18: 11793 | B18: 130 | C18: Sottopelle Brasil S.A | D18: Fatura: 3959 - Cliente: 130 - Renewal Pharma Brasil Royalties Ltda. - Caso: 1 - Farmacia Artesanal - Injunction and Arbitration | E18: 3959 | F18: 00002959 | G18: 46009 | H18: 46037 | I18: 46037 | J18: R | K18: 19558.33 | L18: 0 | M18: 19558.33 | N18: 18355.52 | O18: 18355.52 | P18: 19558.33
A19: 11792 | B19: 130 | C19: Renewal Pharma Brasil Royalties Ltda. | D19: Fatura: 3958 - Cliente: 130 - Renewal Pharma Brasil Royalties Ltda. - Caso: 1 - Farmacia Artesanal - Injunction and Arbitration | E19: 3958 | F19: 00002958 | G19: 46009 | H19: 46037 | I19: 46038 | J19: R | K19: 19558.33 | L19: 0 | M19: 19558.33 | N19: 18355.52 | O19: 18355.52 | P19: 19558.33
A20: 11631 | B20: 115 | C20: Maristela Haddad Andraus De Oliveira | D20: Fatura: 3833 - Cliente: 115 - Cansford Associates Limited - Caso: 1 - AMCHAM 156 | E20: 3833 | F20: 00002856 | G20: 45931 | H20: 46046 | I20: 46041 | J20: R | K20: 555 | L20: 0 | M20: 3333.4 | N20: 555 | O20: 555 | P20: 555
A21: 11935 | B21: 92 | C21: Agropecuária Sol da Costa S.A | D21: Fatura: 3998 - Cliente: 92 - Agropecuária Sol da Costa S.A - Caso: 1 - Contratos Grune - Eucaliptos | E21: 3998 | F21: 00002993 | G21: 46041 | H21: 46051 | I21: 46042 | J21: R | K21: 13505 | L21: 0 | M21: 13505 | N21: 12674.45 | O21: 12674.45 | P21: 13505
A22: 11936 | B22: 92 | C22: Agropecuária Sol da Costa S.A | D22: Fatura: 3999 - Cliente: 92 - Agropecuária Sol da Costa S.A - Caso: 3 - Parceria SJC | E22: 3999 | F22: 00002994 | G22: 46041 | H22: 46051 | I22: 46042 | J22: R | K22: 185 | L22: 0 | M22: 185 | N22: 182.22 | O22: 182.22 | P22: 185
A23: 11937 | B23: 101 | C23: Antonio Jose Pereira Lyra | D23: Fatura: 4000 - Cliente: 101 - Antonio Jose Pereira Lyra - Caso: 1 - Assuntos pessoais Antonio Lyra | E23: 4000 | F23: 00002995 | G23: 46041 | H23: 46051 | I23: 46042 | J23: R | K23: 145 | L23: 0 | M23: 145 | N23: 145 | O23: 145 | P23: 145
A24: 11871 | B24: 115 | C24: Cristina Pisaneschi Azevedo | D24: Fatura: 3966 - Cliente: 115 - Cansford Associates Limited - Caso: 1 - AMCHAM 156 | E24: 3966 | F24: 00002971 | G24: 46027 | H24: 46042 | I24: 46042 | J24: R | K24: 466.66 | L24: 0 | M24: 466.66 | N24: 466.66 | O24: 466.66 | P24: 466.66
A25: 11934 | B25: 68 | C25: Nova Mata Agropecuária e Imobiliária Ltda. | D25: Fatura: 3997 - Cliente: 68 - Casa Blanca Agropecuária e Imobiliária Ltda - Caso: 1 - [Casa Blanca] Ação judicial - Corretores de Imóvel | E25: 3997 | F25: 00002992 | G25: 46041 | H25: 46052 | I25: 46042 | J25: R | K25: 290 | L25: 0 | M25: 290 | N25: 272.17 | O25: 272.17 | P25: 290
A26: 11933 | B26: 64 | C26: Nova Mata Agropecuária e Imobiliária Ltda. | D26: Fatura: 3996 - Cliente: 64 - Nova Mata Agropecuária e Imobiliária Ltda - Caso: 3 - Consultas Gerais | E26: 3996 | F26: 00002991 | G26: 46041 | H26: 46052 | I26: 46042 | J26: R | K26: 870 | L26: 0 | M26: 870 | N26: 816.5 | O26: 816.5 | P26: 870
A27: 11932 | B27: 28 | C27: Solange Queiroz Ramiro Costa | D27: Fatura: 3995 - Cliente: 28 - Solange Queiroz Ramiro Costa - Caso: 12 - Falência/Inventário - Providências | E27: 3995 | F27: 00002990 | G27: 46041 | H27: 46052 | I27: 46042 | J27: R | K27: 4440 | L27: 0 | M27: 4440 | N27: 4440 | O27: 4440 | P27: 4440
A28: 11931 | B28: 28 | C28: Solange Queiroz Ramiro Costa | D28: Fatura: 3994 - Cliente: 28 - Solange Queiroz Ramiro Costa - Caso: 10 - Dionatan Meira | E28: 3994 | F28: 00002989 | G28: 46041 | H28: 46052 | I28: 46042 | J28: R | K28: 290 | L28: 0 | M28: 290 | N28: 290 | O28: 290 | P28: 290
A29: 11893 | B29: 12 | C29: Abril Comunicações S.A. | D29: Fatura: 3975 - Cliente: 12 - Abril Comunicações S.A - Caso: 15 - Ação de Obrigação de Fazer - Gaia | E29: 3975 | F29: 00002975 | G29: 46029 | H29: 46062 | I29: 46048 | J29: R | K29: 15000 | L29: 0 | M29: 15000 | N29: 14077.5 | O29: 14077.5 | P29: 15000
... A32: 11901 | B32: 5 | C32: White Martins Gases Industriais Ltda. | D32: Fatura: 3983 - Cliente: 5 - White Martins Gases Industriais Ltda. - Caso: 1 - Ato de Concentração - Projeto CSA | E32: 3983 | F32: 00002976 | G32: 46031 | H32: 46041 | I32: 46052 | J32: R | K32: 7665 | L32: 0 | M32: 7665 | N32: 7193.6 | O32: 7193.6 | P32: 7665
A33: 11874 | B33: 115 | C33: Cansford Associates Limited | D33: Fatura: 3969 - Cliente: 115 - Cansford Associates Limited - Caso: 1 - AMCHAM 156 | E33: 3969 | G33: 46027 | H33: 46058 | I33: 46056 | J33: R | K33: 1400 | L33: 0 | M33: 1400 | N33: 1400 | O33: 1367.64 | P33: 1400
A34: 11900 | B34: 132 | C34: Eólica Serra Das Vacas Vii S.A. | D34: Fatura: 3982 - Cliente: 132 - Eólica Serra Das Vacas Vii S.A. - Caso: 1 - Ação Indenizatória Neo Energia | E34: 3982 | F34: 00003051 | G34: 46031 | H34: 46062 | I34: 46058 | J34: R | K34: 1500 | L34: 0 | M34: 1500 | N34: 1407.75 | O34: 1407.75 | P34: 1500
A35: 11869 | B35: 2 | C35: VLI Multimodal S.A | D35: Fatura: 3964 - Cliente: 2 - VLI Multimodal S.A - Caso: 8 - (Contrato Fixo) - Ação Ordinária ANTAQ | E35: 3964 | F35: 00002966 | G35: 46027 | H35: 46058 | I35: 46058 | J35: R | K35: 1368.51 | L35: 0 | M35: 1368.51 | N35: 1284.34 | O35: 1284.34 | P35: 1368.51
A36: 11896 | B36: 81 | C36: KCI Brazil Holdings LLC | D36: Fatura: 3978 - Cliente: 81 - KCI Brazil Holdings LLC - Caso: 1 - PA Mercado de Trabalho - Ferreira | E36: 3978 | F36: 00002985 | G36: 46030 | H36: 46069 | I36: 46062 | J36: R | K36: 1059.99 | L36: 0 | M36: 1059.99 | N36: 994.84 | O36: 994.84 | P36: 1059.99
A37: 11789 | B37: 135 | C37: Companhia Brasileira de Distribuição | D37: Fatura: 3955 - Cliente: 135 - Companhia Brasileira de Distribuição - GPA - Caso: 1 - Secondment GPA - Compliance | E37: 3955 | F37: 00002977 | G37: 46008 | H37: 46077 | I37: 46063 | J37: R | K37: 8666.66 | L37: 0 | M37: 8666.66 | N37: 8133.66 | O37: 8133.66 | P37: 8666.66
A38: 11894 | B38: 135 | C38: Companhia Brasileira de Distribuição | D38: Fatura: 3976 - Cliente: 135 - Companhia Brasileira de Distribuição - GPA - Caso: 1 - Secondment GPA - Compliance | E38: 3976 | F38: 00002978 | G38: 46029 | H38: 46077 | I38: 46063 | J38: R | K38: 13000 | L38: 0 | M38: 13000 | N38: 12200.5 | O38: 12200.5 | P38: 13000
A39: 11872 | B39: 115 | C39: Maristela Haddad Andraus De Oliveira | D39: Fatura: 3967 - Cliente: 115 - Cansford Associates Limited - Caso: 1 - AMCHAM 156 | E39: 3967 | F39: 00002970 | G39: 46027 | H39: 46042 | I39: 46063 | J39: R | K39: 466.68 | L39: 0 | M39: 466.68 | N39: 466.68 | O39: 466.68 | P39: 466.68
A40: 11912 | B40: 130 | C40: Renewal Pharma Brasil Royalties Ltda. | D40: Fatura: 3989 - Cliente: 130 - Renewal Pharma Brasil Royalties Ltda. - Caso: 1 - Farmacia Artesanal - Injunction and Arbitration | E40: 3989 | F40: 00002981 | G40: 46034 | H40: 46066 | I40: 46066 | J40: R | K40: 6875 | L40: 0 | M40: 6875 | N40: 6452.2 | O40: 6452.2 | P40: 6875
A41: 11913 | B41: 130 | C41: Sottopelle Brasil S.A | D41: Fatura: 3990 - Cliente: 130 - Renewal Pharma Brasil Royalties Ltda. - Caso: 1 - Farmacia Artesanal - Injunction and Arbitration | E41: 3990 | F41: 00002982 | G41: 46034 | H41: 46066 | I41: 46066 | J41: R | K41: 6875 | L41: 0 | M41: 6875 | N41: 6452.19 | O41: 6452.19 | P41: 6875
A42: 11930 | B42: 61 | C42: REFINARIA DE MANAUS S.A | D42: Fatura: 3993 - Cliente: 61 - Atem's Distribuidora De Petróleo S.A. - Caso: 10 - Ream - Trabalhos Adicionais | E42: 3993 | F42: 00002987 | G42: 46041 | H42: 46071 | I42: 46071 | J42: R | K42: 4551.17 | L42: 0 | M42: 4551.17 | N42: 4271.28 | O42: 4271.28 | P42: 4551.17
A43: 11929 | B43: 61 | C43: REFINARIA DE MANAUS S.A | D43: Fatura: 3992 - Cliente: 61 - Atem's Distribuidora De Petróleo S.A. - Caso: 9 - Cade - Cumprimento ACC | E43: 3992 | F43: 00002986 | G43: 46041 | H43: 46071 | I43: 46071 | J43: R | K43: 34418.38 | L43: 0 | M43: 34418.38 | N43: 32301.67 | O43: 32301.67 | P43: 34418.38
A44: 11910 | B44: 124 | C44: Sottopelle Brasil S.A | D44: Fatura: 3987 - Cliente: 124 - Sottopelle Brasil S.A - Caso: 4 - Arbitragem CMA 918-P | E44: 3987 | F44: 00002979 | G44: 46034 | H44: 46066 | I44: 46071 | J44: R | K44: 7933.33 | L44: 0 | M44: 7933.33 | N44: 7445.46 | O44: 7445.46 | P44: 7933.33
A45: 11898 | B45: 114 | C45: Supergasbras Energia Ltda | D45: Fatura: 3980 - Cliente: 114 - Companhia Ultragaz S.A. - Caso: 1 - Trustee AC Ultragaz Supergasbras | E45: 3980 | F45: 00002996 | G45: 46030 | H45: 46072 | I45: 46071 | J45: R | K45: 6873.91 | L45: 0 | M45: 6873.91 | N45: 6451.17 | O45: 6451.17 | P45: 6873.91
... A51: 12074 | B51: 68 | C51: Nova Mata Agropecuária e Imobiliária Ltda. | D51: Fatura: 4045 - Cliente: 68 - Casa Blanca Agropecuária e Imobiliária Ltda - Caso: 1 - [Casa Blanca] Ação judicial - Corretores de Imóvel | E51: 4045 | F51: 00003046 | G51: 46072 | H51: 46083 | I51: 46076 | J51: R | K51: 4868.2 | L51: 0 | M51: 4868.2 | N51: 4568.82 | O51: 4568.82 | P51: 4868.2
A52: 12019 | B52: 28 | C52: Solange Queiroz Ramiro Costa | D52: Fatura: 4027 - Cliente: 28 - Solange Queiroz Ramiro Costa - Caso: 12 - Falência/Inventário - Providências | E52: 4027 | G52: 46063 | H52: 46084 | I52: 46076 | J52: R | K52: 0 | L52: 3916.04 | M52: 3916.04 | N52: 3916.04 | O52: 3916.04 | P52: 0
A53: 12078 | B53: 28 | C53: Solange Queiroz Ramiro Costa | D53: Fatura: 4049 - Cliente: 28 - Solange Queiroz Ramiro Costa - Caso: 10 - Dionatan Meira | E53: 4049 | F53: 00003050 | G53: 46072 | H53: 46083 | I53: 46076 | J53: R | K53: 303 | L53: 0 | M53: 303 | N53: 303 | O53: 303 | P53: 303
A54: 12076 | B54: 28 | C54: Solange Queiroz Ramiro Costa | D54: Fatura: 4047 - Cliente: 28 - Solange Queiroz Ramiro Costa - Caso: 5 - Consultas Gerais | E54: 4047 | F54: 00003048 | G54: 46072 | H54: 46083 | I54: 46076 | J54: R | K54: 303 | L54: 0 | M54: 303 | N54: 303 | O54: 303 | P54: 303
A55: 12077 | B55: 28 | C55: Solange Queiroz Ramiro Costa | D55: Fatura: 4048 - Cliente: 28 - Solange Queiroz Ramiro Costa - Caso: 12 - Falência/Inventário - Providências | E55: 4048 | F55: 00003049 | G55: 46072 | H55: 46083 | I55: 46076 | J55: R | K55: 105000 | L55: 0 | M55: 105000 | N55: 105000 | O55: 105000 | P55: 105000
A56: 12050 | B56: 147 | C56: Crescera Growth Master V Fundo de Investimento em Participações Multiestratégia | D56: Fatura: 4039 - Cliente: 147 - Mapa Capital Participações e Consultoria Ltda - Caso: 1 - Notificação de operação ao CADE | Plural Care | E56: 4039 | G56: 46066 | H56: 46094 | I56: 46080 | J56: R | K56: 15000 | L56: 0 | M56: 15000 | N56: 14077.5 | O56: 14077.5 | P56: 15000
A57: 11949 | B57: 7 | C57: John Deere Brasil Ltda. | D57: Fatura: 4004 - Cliente: 7 - John Deere Brasil Ltda. - Caso: 1 - Consultas Diversas | E57: 4004 | F57: 00003016 | G57: 46050 | H57: 46080 | I57: 46080 | J57: R | K57: 6494.21 | L57: 0 | M57: 6494.21 | N57: 6094.81 | O57: 6094.81 | P57: 6494.21
A58: 11950 | B58: 7 | C58: John Deere Brasil Ltda. | D58: Fatura: 4005 - Cliente: 7 - John Deere Brasil Ltda. - Caso: 18 - Consulta Econômico e Lei Ferrari - Parceria MWM – Tupy do Brasil Ltda. | E58: 4005 | F58: 00003017 | G58: 46050 | H58: 46080 | I58: 46080 | J58: R | K58: 16246.55 | L58: 0 | M58: 16246.55 | N58: 15247.39 | O58: 15247.39 | P58: 16246.55
A59: 11951 | B59: 7 | C59: John Deere Brasil Ltda. | D59: Fatura: 4006 - Cliente: 7 - John Deere Brasil Ltda. - Caso: 19 - Investigação antidumping - Pneus Agrícolas | E59: 4006 | F59: 00003018 | G59: 46050 | H59: 46080 | I59: 46080 | J59: R | K59: 34229.06 | L59: 0 | M59: 34229.06 | N59: 32123.99 | O59: 32123.99 | P59: 34229.06
A60: 11809 | B60: 3 | C60: Ambev S.A. | D60: Fatura: 3961 - Cliente: 3 - Ambev S.A. - Caso: 30 - Incidente Notas Fiscais | E60: 3961 | F60: 00002960 | G60: 46010 | H60: 46132 | I60: 46083 | J60: R | K60: 10533.34 | L60: 0 | M60: 10533.34 | N60: 9885.54 | O60: 9885.54 | P60: 10533.34
A61: 11895 | B61: 6 | C61: Sherwin-Williams do Brasil Indústria e Comércio Ltda. Sherwin-Williams do Brasil Indústria e Comérc | D61: Fatura: 3977 - Cliente: 6 - Sherwin-Williams do Brasil Indústria e Comércio Ltda. - Caso: 4 - (Contrato Fixo) - Ação de Cobrança - Renato Vaz de Mello - Acompanhamento Processual | E61: 3977 | G61: 46029 | H61: 46083 | I61: 46083 | J61: R | K61: 4068 | L61: 0 | M61: 4068 | N61: 3817.82 | O61: 3817.82 | P61: 4068
A62: 12014 | B62: 114 | C62: Companhia Ultragaz S.A. | D62: Fatura: 4022 - Cliente: 114 - Companhia Ultragaz S.A. - Caso: 1 - Trustee AC Ultragaz Supergasbras | E62: 4022 | F62: 00003033 | G62: 46062 | H62: 46091 | I62: 46086 | J62: R | K62: 6579.7 | L62: 0 | M62: 6579.7 | N62: 6175.07 | O62: 6175.07 | P62: 6579.7
A63: 11897 | B63: 114 | C63: Companhia Ultragaz S.A. | D63: Fatura: 3979 - Cliente: 114 - Companhia Ultragaz S.A. - Caso: 1 - Trustee AC Ultragaz Supergasbras | E63: 3979 | F63: 00002974 | G63: 46030 | H63: 46063 | I63: 46086 | J63: R | K63: 6873.91 | L63: 0 | M63: 6873.91 | N63: 6451.13 | O63: 6451.13 | P63: 6873.91
A64: 11994 | B64: 123 | C64: Paulo Kopenhagen Goldfinger | D64: Fatura: 4014 - Cliente: 123 - Paulo Kopenhagen Goldfinger - Caso: 1 - Contrato Padrão Judicial - Fixo acompanhamento mensal (Brascan Allpark) | E64: 4014 | F64: 00003027 | G64: 46059 | H64: 46079 | I64: 46087 | J64: R | K64: 1000 | L64: 0 | M64: 1000 | N64: 1000 | O64: 1000 | P64: 1000
A65: 11990 | B65: 97 | C65: Transocean Brasil Ltda. | D65: Fatura: 4010 - Cliente: 97 - Transocean Brasil Ltda. - Caso: 1 - Ação Civil Pública FUP | E65: 4010 | F65: 00003025 | G65: 46058 | H65: 46086 | I65: 46087 | J65: R | K65: 1280 | L65: 0 | M65: 1280 | N65: 1201.28 | O65: 1201.28 | P65: 1280
A66: 12130 | B66: 145 | C66: Silvia Figueiredo de Mello Barros e Outros | D66: Fatura: 4057 - Cliente: 145 - Marina Figueiredo de Mello Barros Castellani - Caso: 1 - Ação Civil Pública - Reserva Legal e APP | E66: 4057 | F66: 00003067 | G66: 46086 | H66: 46118 | I66: 46090 | J66: R | K66: 1000 | L66: 0 | M66: 1000 | N66: 938.5 | O66: 938.5 | P66: 1000
A67: 12010 | B67: 115 | C67: Maristela Haddad Andraus De Oliveira | D67: Fatura: 4018 - Cliente: 115 - Cansford Associates Limited - Caso: 1 - AMCHAM 156 | E67: 4018 | F67: 00003030 | G67: 46062 | H67: 46073 | I67: 46091 | J67: R | K67: 466.68 | L67: 0 | M67: 466.68 | N67: 466.68 | O67: 466.68 | P67: 466.68
A68: 12013 | B68: 22 | C68: S.A. O Estado de S. Paulo | D68: Fatura: 4021 - Cliente: 22 - O Estado de S. Paulo S.A - Caso: 5 - Portal Agro - Pyxys | E68: 4021 | F68: 00003031 | G68: 46062 | H68: 46091 | I68: 46091 | J68: R | K68: 5893.33 | L68: 0 | M68: 5893.33 | N68: 5530.89 | O68: 5530.89 | P68: 5893.33
A69: 11132 | B69: 109 | C69: Antonio Cleidenir Tonico Ramos | D69: Fatura: 3771 - Cliente: 109 - Antonio Cleidenir Tonico Ramos - Caso: 1 - Representação MPSP - Fundacao Arnaldo Vieira de Carvalho | E69: 3771 | F69: 00002791 | G69: 45883 | H69: 45952 | I69: 46093 | J69: R | K69: 8700 | L69: 0 | M69: 8700 | N69: 8700 | O69: 8700 | P69: 8700
A70: 11570 | B70: 109 | C70: Antonio Cleidenir Tonico Ramos | D70: Fatura: 3909 - Cliente: 109 - Antonio Cleidenir Tonico Ramos - Caso: 1 - Representação MPSP - Fundacao Arnaldo Vieira de Carvalho | E70: 3909 | F70: 00002912 | G70: 45974 | H70: 46034 | I70: 46093 | J70: R | K70: 15300 | L70: 0 | M70: 15300 | N70: 15300 | O70: 15300 | P70: 15300
A71: 12016 | B71: 7 | C71: John Deere Brasil Ltda. | D71: Fatura: 4024 - Cliente: 7 - John Deere Brasil Ltda. - Caso: 19 - Investigação antidumping - Pneus Agrícolas | E71: 4024 | G71: 46063 | H71: 46101 | I71: 46093 | J71: R | K71: 0 | L71: 4197.71 | M71: 4197.71 | N71: 4197.71 | O71: 4197.71 | P71: 0
A72: 12017 | B72: 81 | C72: KCI Brazil Holdings LLC | D72: Fatura: 4025 - Cliente: 81 - KCI Brazil Holdings LLC - Caso: 1 - PA Mercado de Trabalho - Ferreira | E72: 4025 | F72: 00003038 | G72: 46063 | H72: 46094 | I72: 46093 | J72: R | K72: 5464.99 | L72: 0 | M72: 5464.99 | N72: 5128.92 | O72: 5128.92 | P72: 5464.99
A73: 12011 | B73: 115 | C73: Myriam Clara Salvadori | D73: Fatura: 4019 - Cliente: 115 - Cansford Associates Limited - Caso: 1 - AMCHAM 156 | E73: 4019 | F73: 00003029 | G73: 46062 | H73: 46073 | I73: 46093 | J73: R | K73: 466.66 | L73: 0 | M73: 466.66 | N73: 466.66 | O73: 466.68 | P73: 466.66
A74: 12023 | B74: 139 | C74: Zetta | D74: Fatura: 4031 - Cliente: 139 - Zetta - Caso: 2 - Assessoria e Monitoramento (Etapa 3) - Cade | E74: 4031 | F74: 00003036 | G74: 46065 | H74: 46093 | I74: 46093 | J74: R | K74: 17983.33 | L74: 0 | M74: 17983.33 | N74: 16877.38 | O74: 16877.38 | P74: 17983.33
A75: 11993 | B75: 6 | C75: Sherwin-Williams do Brasil Indústria e Comércio Ltda. Sherwin-Williams do Brasil Indústria e Comérc | D75: Fatura: 4013 - Cliente: 6 - Sherwin-Williams do Brasil Indústria e Comércio Ltda. - Caso: 4 - (Contrato Fixo) - Ação de Cobrança - Renato Vaz de Mello - Acompanhamento Processual | E75: 4013 | F75: 00003037 | G75: 46059 | H75: 46094 | I75: 46094 | J75: R | K75: 4068 | L75: 0 | M75: 4068 | N75: 3817.82 | O75: 3817.82 | P75: 4068
A76: 11889 | B76: 61 | C76: Atem's Distribuidora De Petróleo S.A. | D76: Fatura: 3971 - Cliente: 61 - Atem's Distribuidora De Petróleo S.A. - Caso: 23 - Execução - Grupo Cariocão | E76: 3971 | G76: 46029 | H76: 46107 | I76: 46097 | J76: R | K76: 0 | L76: 75.1 | M76: 75.1 | N76: 75.1 | O76: 75.1 | P76: 0
A77: 12009 | B77: 115 | C77: Cristina Pisaneschi Azevedo | D77: Fatura: 4017 - Cliente: 115 - Cansford Associates Limited - Caso: 1 - AMCHAM 156 | E77: 4017 | F77: 00003028 | G77: 46062 | H77: 46073 | I77: 46097 | J77: R | K77: 466.66 | L77: 0 | M77: 466.66 | N77: 466.66 | O77: 466.66 | P77: 466.66
A78: 12012 | B78: 115 | C78: Cansford Associates Limited | D78: Fatura: 4020 - Cliente: 115 - Cansford Associates Limited - Caso: 1 - AMCHAM 156 | E78: 4020 | G78: 46062 | H78: 46090 | I78: 46099 | J78: R | K78: 1400 | L78: 0 | M78: 1400 | N78: 1400 | O78: 1383.62 | P78: 1400
A79: 12015 | B79: 114 | C79: Supergasbras Energia Ltda | D79: Fatura: 4023 - Cliente: 114 - Companhia Ultragaz S.A. - Caso: 1 - Trustee AC Ultragaz Supergasbras | E79: 4023 | F79: 00003035 | G79: 46062 | H79: 46093 | I79: 46099 | J79: R | K79: 6579.7 | L79: 0 | M79: 6579.7 | N79: 6175.06 | O79: 6175.06 | P79: 6579.7
A80: 11991 | B80: 125 | C80: CanadaHRT Brasil Royalties Ltda. | D80: Fatura: 4011 - Cliente: 125 - CanadaHRT Brasil Royalties Ltda. - Caso: 3 - CAMES: Anulatória Sentença Arbitral | E80: 4011 | F80: 00003026 | G80: 46058 | H80: 46087 | I80: 46100 | J80: R | K80: 6052.19 | L80: 0 | M80: 6052.19 | N80: 5680 | O80: 5680 | P80: 6052.19
A81: 12028 | B81: 61 | C81: Navemazônia Navegação Ltda | D81: Fatura: 4036 - Cliente: 61 - Atem's Distribuidora De Petróleo S.A. - Caso: 17 - Notificação de Operação ao CADE | Operação WPL | E81: 4036 | F81: 00003053 | G81: 46065 | H81: 46105 | I81: 46100 | J81: R | K81: 15000 | L81: 0 | M81: 15000 | N81: 14077.5 | O81: 14077.5 | P81: 15000
A82: 12081 | B82: 61 | C82: REFINARIA DE MANAUS S.A | D82: Fatura: 4052 - Cliente: 61 - Atem's Distribuidora De Petróleo S.A. - Caso: 24 - Reavaliação Contingências WPL | E82: 4052 | F82: 00003057 | G82: 46072 | H82: 46104 | I82: 46100 | J82: R | K82: 56080 | L82: 0 | M82: 56080 | N82: 52631.08 | O82: 52631.08 | P82: 56080
A83: 12131 | B83: 115 | C83: Cristina Pisaneschi Azevedo | D83: Fatura: 4058 - Cliente: 115 - Cansford Associates Limited - Caso: 1 - AMCHAM 156 | E83: 4058 | F83: 00003070 | G83: 46086 | H83: 46101 | I83: 46101 | J83: R | K83: 466.66 | L83: 0 | M83: 466.66 | N83: 466.66 | O83: 466.66 | P83: 466.66
A84: 12069 | B84: 7 | C84: John Deere Brasil Ltda. | D84: Fatura: 4040 - Cliente: 7 - John Deere Brasil Ltda. - Caso: 18 - Consulta Econômico e Lei Ferrari - Parceria MWM – Tupy do Brasil Ltda. | E84: 4040 | F84: 00003040 | G84: 46071 | H84: 46101 | I84: 46101 | J84: R | K84: 941.25 | L84: 0 | M84: 941.25 | N84: 883.39 | O84: 883.39 | P84: 941.25
A85: 12070 | B85: 7 | C85: John Deere Brasil Ltda. | D85: Fatura: 4041 - Cliente: 7 - John Deere Brasil Ltda. - Caso: 19 - Investigação antidumping - Pneus Agrícolas | E85: 4041 | F85: 00003041 | G85: 46071 | H85: 46101 | I85: 46101 | J85: R | K85: 42383.93 | L85: 0 | M85: 42383.93 | N85: 39784.34 | O85: 39784.34 | P85: 42383.93
A86: 12071 | B86: 7 | C86: John Deere Brasil Ltda. | D86: Fatura: 4042 - Cliente: 7 - John Deere Brasil Ltda. - Caso: 17 - Consulta - Programa Protect | E86: 4042 | F86: 00003042 | G86: 46071 | H86: 46101 | I86: 46101 | J86: R | K86: 470.63 | L86: 0 | M86: 470.63 | N86: 441.71 | O86: 441.71 | P86: 470.63
A87: 11633 | B87: 115 | C87: Maristela Haddad Andraus De Oliveira | D87: Fatura: 3833 - Cliente: 115 - Cansford Associates Limited - Caso: 1 - AMCHAM 156 | E87: 3833 | F87: 00002856 | G87: 45931 | H87: 46105 | I87: 46101 | J87: R | K87: 555 | L87: 0 | M87: 3333.4 | N87: 555 | O87: 555 | P87: 555
A88: 12080 | B88: 61 | C88: REFINARIA DE MANAUS S.A | D88: Fatura: 4051 - Cliente: 61 - Atem's Distribuidora De Petróleo S.A. - Caso: 10 - Ream - Trabalhos Adicionais | E88: 4051 | F88: 00003054 | G88: 46072 | H88: 46104 | I88: 46104 | J88: R | K88: 13511.29 | L88: 0 | M88: 13511.29 | N88: 12680.37 | O88: 12680.37 | P88: 13511.29
A89: 12082 | B89: 61 | C89: REFINARIA DE MANAUS S.A | D89: Fatura: 4053 - Cliente: 61 - Atem's Distribuidora De Petróleo S.A. - Caso: 9 - Cade - Cumprimento ACC | E89: 4053 | F89: 00003056 | G89: 46072 | H89: 46104 | I89: 46104 | J89: R | K89: 26690.69 | L89: 0 | M89: 26690.69 | N89: 25049.25 | O89: 25049.25 | P89: 26690.69
A90: 12079 | B90: 132 | C90: Eólica Serra Das Vacas Vii S.A. | D90: Fatura: 4050 - Cliente: 132 - Eólica Serra Das Vacas Vii S.A. - Caso: 1 - Ação Indenizatória Neo Energia | E90: 4050 | G90: 46072 | H90: 46105 | I90: 46105 | J90: R | K90: 1500 | L90: 0 | M90: 1500 | N90: 1407.75 | O90: 1407.75 | P90: 1500
A91: 11940 | B91: 22 | C91: O Estado de S. Paulo S.A | D91: Fatura: 4003 - Cliente: 22 - O Estado de S. Paulo S.A - Caso: 5 - Portal Agro - Pyxys | E91: 4003 | F91: 00002998 | G91: 46045 | H91: 46105 | I91: 46105 | J91: R | K91: 19106.67 | L91: 0 | M91: 19106.67 | N91: 17931.61 | O91: 17931.61 | P91: 19106.67
A92: 11995 | B92: 12 | C92: Abril Comunicações S.A. | D92: Fatura: 4015 - Cliente: 12 - Abril Comunicações S.A - Caso: 15 - Ação de Obrigação de Fazer - Gaia | E92: 4015 | F92: 00003061 | G92: 46059 | H92: 46106 | I92: 46106 | J92: R | K92: 600 | L92: 0 | M92: 600 | N92: 572.1 | O92: 572.1 | P92: 600
A93: 12150 | B93: 12 | C93: Abril Comunicações S.A. | D93: Fatura: 4063 - Cliente: 12 - Abril Comunicações S.A - Caso: 15 - Ação de Obrigação de Fazer - Gaia | E93: 4063 | F93: 00003071 | G93: 46090 | H93: 46121 | I93: 46106 | J93: R | K93: 600 | L93: 0 | M93: 600 | N93: 572.1 | O93: 572.1 | P93: 600
A94: 12214 | B94: 92 | C94: Agropecuária Sol da Costa S.A | D94: Fatura: 4085 - Cliente: 92 - Agropecuária Sol da Costa S.A - Caso: 1 - Contratos Grune - Eucaliptos | E94: 4085 | F94: 00003092 | G94: 46101 | H94: 46111 | I94: 46106 | J94: R | K94: 773.07 | L94: 0 | M94: 773.07 | N94: 725.54 | O94: 725.54 | P94: 773.07
A95: 12215 | B95: 101 | C95: Antonio Jose Pereira Lyra | D95: Fatura: 4086 - Cliente: 101 - Antonio Jose Pereira Lyra - Caso: 1 - Assuntos pessoais Antonio Lyra | E95: 4086 | F95: 00003093 | G95: 46101 | H95: 46111 | I95: 46106 | J95: R | K95: 151.5 | L95: 0 | M95: 151.5 | N95: 151.5 | O95: 151.5 | P95: 151.5
A96: 12191 | B96: 94 | C96: Guaçu Geração De Energia S/A | D96: Fatura: 4078 - Cliente: 94 - Gordilho Napolitano Advogados Associados - Caso: 2 - Procedimento Arbitral - Guaçu | E96: 4078 | F96: 00003081 | G96: 46098 | H96: 46108 | I96: 46106 | J96: R | K96: 36000 | L96: 0 | M96: 36000 | N96: 33786 | O96: 33786 | P96: 36000
A97: 12212 | B97: 64 | C97: Nova Mata Agropecuária e Imobiliária Ltda. | D97: Fatura: 4083 - Cliente: 64 - Nova Mata Agropecuária e Imobiliária Ltda - Caso: 3 - Consultas Gerais | E97: 4083 | F97: 00003090 | G97: 46101 | H97: 46111 | I97: 46106 | J97: R | K97: 606 | L97: 0 | M97: 606 | N97: 568.74 | O97: 568.74 | P97: 606
A98: 12213 | B98: 68 | C98: Nova Mata Agropecuária e Imobiliária Ltda. | D98: Fatura: 4084 - Cliente: 68 - Casa Blanca Agropecuária e Imobiliária Ltda - Caso: 1 - [Casa Blanca] Ação judicial - Corretores de Imóvel | E98: 4084 | F98: 00003091 | G98: 46101 | H98: 46111 | I98: 46106 | J98: R | K98: 606 | L98: 0 | M98: 606 | N98: 568.74 | O98: 568.74 | P98: 606
A99: 12049 | B99: 147 | C99: Mapa Capital Participações e Consultoria Ltda | D99: Fatura: 4038 - Cliente: 147 - Mapa Capital Participações e Consultoria Ltda - Caso: 1 - Notificação de operação ao CADE | Plural Care | E99: 4038 | G99: 46066 | H99: 46107 | I99: 46107 | J99: R | K99: 15000 | L99: 0 | M99: 15000 | N99: 14077.5 | O99: 14077.5 | P99: 15000
A100: 12250 | B100: 28 | C100: Solange Queiroz Ramiro Costa | D100: Fatura: 4089 - Cliente: 28 - Solange Queiroz Ramiro Costa - Caso: 12 - Falência/Inventário - Providências | E100: 4089 | F100: 00003095 | G100: 46107 | H100: 46118 | I100: 46108 | J100: R | K100: 28004.34 | L100: 0 | M100: 28004.34 | N100: 28004.34 | O100: 28004.34 | P100: 28004.34
A101: 12251 | B101: 28 | C101: Solange Queiroz Ramiro Costa | D101: Fatura: 4090 - Cliente: 28 - Solange Queiroz Ramiro Costa - Caso: 10 - Dionatan Meira | E101: 4090 | F101: 00003094 | G101: 46108 | H101: 46118 | I101: 46108 | J101: R | K101: 303 | L101: 0 | M101: 303 | N101: 303 | O101: 303 | P101: 303
A102: 12289 | B102: 147 | C102: Mapa Capital Participações e Consultoria LTDA | D102: Fatura: 4092 - Cliente: 147 - Mapa Capital Participações e Consultoria Ltda - Caso: 1 - Notificação de operação ao CADE | Plural Care | E102: 4092 | G102: 46114 | H102: 46114 | I102: 46114 | J102: R | K102: 922.5 | L102: 0 | M102: 922.5 | N102: 922.5 | O102: 922.5 | P102: 922.5
A103: 12072 | B103: 6 | C103: Sherwin-Williams do Brasil Indústria e Comércio Ltda. Sherwin-Williams do Brasil Indústria e Comérc | D103: Fatura: 4043 - Cliente: 6 - Sherwin-Williams do Brasil Indústria e Comércio Ltda. - Caso: 19 - Renato Vaz x SWB - Reclamação | E103: 4043 | F103: 00003065 | G103: 46071 | H103: 46115 | I103: 46114 | J103: R | K103: 15000 | L103: 0 | M103: 15000 | N103: 14077.5 | O103: 14077.5 | P103: 15000
A104: 11996 | B104: 135 | C104: Companhia Brasileira de Distribuição | D104: Fatura: 4016 - Cliente: 135 - Companhia Brasileira de Distribuição - GPA - Caso: 4 - Consultoria em Compliance | E104: 4016 | F104: 00003032 | G104: 46059 | H104: 46090 | I104: 46118 | J104: R | K104: 13000 | L104: 0 | M104: 13000 | N104: 12200.5 | O104: 12200.5 | P104: 13000
A105: 12109 | B105: 2 | C105: VLI Multimodal S.A | D105: Fatura: 4055 - Cliente: 2 - VLI Multimodal S.A - Caso: 8 - (Contrato Fixo) - Ação Ordinária ANTAQ | E105: 4055 | F105: 00003064 | G105: 46079 | H105: 46117 | I105: 46118 | J105: R | K105: 1368.51 | L105: 0 | M105: 1368.51 | N105: 1284.34 | O105: 1284.34 | P105: 1368.51
A106: 12316 | B106: 145 | C106: Silvia Figueiredo de Mello Barros e Outros | D106: Fatura: 4099 - Cliente: 145 - Marina Figueiredo de Mello Barros Castellani - Caso: 1 - Ação Civil Pública - Reserva Legal e APP | E106: 4099 | G106: 46120 | H106: 46150 | I106: 46121 | J106: R | K106: 1000 | L106: 0 | M106: 1000 | N106: 938.5 | O106: 938.5 | P106: 1000
A107: 12317 | B107: 145 | C107: Silvia Figueiredo de Mello Barros e Outros | D107: Fatura: 4100 - Cliente: 145 - Marina Figueiredo de Mello Barros Castellani - Caso: 1 - Ação Civil Pública - Reserva Legal e APP | E107: 4100 | G107: 46120 | H107: 46181 | I107: 46121 | J107: R | K107: 0 | L107: 576.3 | M107: 576.3 | N107: 576.3 | O107: 576.3 | P107: 0
...

Sheet Moedas
A1: Docto | B1: Cliente | C1: Razão Social Fatura | D1: Histórico | E1: Fatura | F1: Número Nota Fiscal | G1: Data Emissão | H1: Vencimento | I1: Data Recebimento | J1: Moeda | K1: Valor Honorários | L1: Valor Despesas | M1: Valor Total Fatura | N1: Valor Total | O1: Valor Recebido | P1: Honorários
A2: 11899 | B2: 20 | C2: Dachser SE | D2: Fatura: 3981 - Cliente: 20 - Dachser SE - Caso: 2 - Appeal Brazilian Court | E2: 3981 | G2: 46031 | H2: 46041 | I2: 46050 | J2: E | K2: 820 | L2: 0 | M2: 820 | N2: 820 | O2: 820 | P2: 4893.84
A3: 12192 | B3: 20 | C3: Dachser SE | D3: Fatura: 4079 - Cliente: 20 - Dachser SE - Caso: 2 - Appeal Brazilian Court | E3: 4079 | F3: 00003096 | G3: 46098 | H3: 46098 | I3: 46098 | J3: E | K3: 50 | L3: 0 | M3: 50 | N3: 50 | O3: 50 | P3: 285.9
A4: 11791 | B4: 136 | C4: Deere & Company | D4: Fatura: 3957 - Cliente: 136 - Deere & Company - Caso: 3 - Project North | E4: 3957 | G4: 46009 | H4: 46038 | I4: 46030 | J4: U | K4: 3316.66 | L4: 0 | M4: 3316.66 | N4: 3316.66 | O4: 3316.66 | P4: 17121.92
A5: 11903 | B5: 136 | C5: Deere & Company | D5: Fatura: 3985 - Cliente: 136 - Deere & Company - Caso: 3 - Project North | E5: 3985 | G5: 46031 | H5: 46062 | I5: 46050 | J5: U | K5: 4891.66 | L5: 0 | M5: 4891.66 | N5: 4891.66 | O5: 4891.66 | P5: 24455.85
A6: 11989 | B6: 136 | C6: Deere & Company | D6: Fatura: 4009 - Cliente: 136 - Deere & Company - Caso: 3 - Project North | E6: 4009 | F6: 00003034 | G6: 46058 | H6: 46093 | I6: 46063 | J6: U | K6: 5025 | L6: 0 | M6: 5025 | N6: 5025 | O6: 5025 | P6: 25054.14
A7: 12155 | B7: 136 | C7: Deere & Company | D7: Fatura: 4068 - Cliente: 136 - Deere & Company - Caso: 3 - Project North | E7: 4068 | F7: 00003099 | G7: 46091 | H7: 46122 | I7: 46101 | J7: U | K7: 6258.33 | L7: 0 | M7: 6258.33 | N7: 6258.33 | O7: 6258.33 | P7: 31515.7
A8: 12018 | B8: 87 | C8: Spotify A.B | D8: Fatura: 4026 - Cliente: 87 - Spotify Technology S.A - Caso: 2 - CADE – Mercado Livre Complaint | E8: 4026 | F8: 00003097 | G8: 46063 | H8: 46093 | I8: 46106 | J8: U | K8: 18833.34 | L8: 0 | M8: 18833.34 | N8: 18833.34 | O8: 18833.34 | P8: 94484.98
A9: 12021 | B9: 87 | C9: Spotify A.B | D9: Fatura: 4029 - Cliente: 87 - Spotify Technology S.A - Caso: 2 - CADE – Mercado Livre Complaint | E9: 4029 | F9: 00003098 | G9: 46065 | H9: 46093 | I9: 46106 | J9: U | K9: 24458.34 | L9: 0 | M9: 24458.34 | N9: 24458.34 | O9: 24458.34 | P9: 122705.05
A10: 12157 | B10: 87 | C10: Spotify A.B | D10: Fatura: 4070 - Cliente: 87 - Spotify Technology S.A - Caso: 2 - CADE – Mercado Livre Complaint | E10: 4070 | G10: 46091 | H10: 46121 | I10: 46121 | J10: U | K10: 17133.33 | L10: 0 | M10: 17133.33 | N10: 17133.33 | O10: 17133.33 | P10: 83405.05

Sheet Amortização
A1: 44682 | D1: Acumulado Maio
A2: Total | B2: 78409
A3: Mensal | B3: =B2/60 -> 1306.8167 | C3: parcela 1/60 | D3: =B3 -> 1306.8167
A5: 44713 | D5: Acumulado Junho
A6: Total | B6: ='[4]Orçamento 2022'!R189 -> 154730.96
A7: Mensal | B7: =B6/60 -> 2578.8493 | C7: parcela 2/60 | D7: =B3+B7 -> 3885.666
A9: 44743 | D9: Acumulado Julho
A10: Total | B10: 116368.83
A11: Mensal | B11: =B10/60 -> 1939.4805 | C11: parcela 3/60 | D11: =D7+B11 -> 5825.1465
A13: 44774 | D13: Acumulado Agosto
A14: Total | B14: ='[4]Orçamento 2022'!X189 -> 43795.59
A15: Mensal | B15: =B14/60 -> 729.9265 | C15: parcela 4/60 | D15: =D11+B15 -> 6555.073
A17: 44805 | D17: Acumulado Setembro
A18: Total | B18: ='[4]Orçamento 2022'!AA186 -> 20140
A19: Mensal | B19: =B18/60 -> 335.66667 | C19: parcela 5/60 | D19: =D15+B19 -> 6890.7397
A21: 44835 | D21: Acumulado Outubro
A22: Total | B22: ='[4]Orçamento 2022'!AD189 -> 41551
A23: Mensal | B23: =B22/60 -> 692.51667 | C23: parcela 6/60 | D23: =D19+B23 -> 7583.2563
A25: 44866 | D25: Acumulado Novembro
A26: Total | B26: ='[4]Orçamento 2022'!AG189 -> 21722
A27: Mensal | B27: =B26/60 -> 362.03333 | C27: parcela 7/60 | D27: =D23+B27 -> 7945.2897
A29: 44896 | D29: Acumulado Dezembro
A30: Total | B30: ='[4]Orçamento 2022'!AJ189 -> 10321
A31: Mensal | B31: =B30/60 -> 172.01667 | C31: parcela 8/60 | D31: =D27+B31 -> 8117.3063
A33: 44927 | D33: Acumulado Janeiro
A34: Total | B34: -
A35: Mensal | B35: - | C35: parcela 09/60 | D35: 8117.31
A37: Mês | B37: Parcela | C37: Valor Institucional
A38: 44682 | B38: 1 | C38: 1306.82
A39: 44713 | B39: 2 | C39: 3885.67
A40: 44743 | B40: 3 | C40: 5825.15
A41: 44774 | B41: 4 | C41: 6555.07
A42: 44805 | B42: 5 | C42: 6890.74
A43: 44835 | B43: 6 | C43: 7583.26
A44: 44866 | B44: 7 | C44: 7945.29
A45: 44896 | B45: 8 | C45: 8117.31
A46: 44927 | B46: 9 | C46: 8117.31
A47: 44958 | B47: 10 | C47: 8117.31
A48: 44986 | B48: 11 | C48: 8117.31
A49: 45017 | B49: 12 | C49: 8117.31
... A93: 46357 | B93: 56 | C93: 8117.31
A94: 46388 | B94: 57
A95: 46419 | B95: 58
A96: 46447 | B96: 59
A97: 46478 | B97: 60
B98: Total | C98: =SUM(C38:C97) -> 437740.19
